Workbook

Sheet USE OF DATA
C1: WHAT DO USERS WANT?
C2: MAIN USE OF DATA | D2: WHAT DATA SHOULD I USE? | E2: WORKSHEET
B3: 1 | C3: Policy Formulations | D3: The original unadjusted series and all components | E3: Original_VA
B4: 2 | C4: Macro-economic model building | D4: Could be Unadjusted, adjusted, trend-cycle or all components depending on the main purpose of the model | E4: Original_VA, Deseason_VA, Trend_VA
B5: 3 | C5: To determine what actually happened | D5: The original unadjusted series | E5: Original_VA
B6: 4 | C6: Analysis of the effect of particular events such as a strike | D6: The irregular component | E6: Deseason_VA and Trend_VA
B7: 5 | C7: Business Cycle analysis & detection of turning points | D7: Trend-cycle and irregular component | E7: Trend_VA
B8: 6 | C8: Short-term and medium term forecasting | D8: Original unadjusted series and all its components | E8: Original_VA
B9: 7 | C9: Long-term forecasting | D9: The trend cycle component | E9: Trend_VA
C12: Notes:
B13: a | C13: Original (Unadjusted) estimates have been benchmarked to the 2024/25 Annual GDP estimates (October release 2025) due to quarterly differences in source data for selected economic activities. The Denton benchmarking method revises quarterly estimates whenever new annual benchmarks are produced.
B14: b | C14: Therefore, there were no revisions in series because the benchmarks and input data have not been revised over the period. Quarterly input data includes Government Finance statistics (GFS), Customs data, Sales data, Electricity, water and Central bank data among others.
B15: c | C15: Seasonally adjusted data are subject to revisions as future data become available, even when the original data are not revised.
B16: d | C16: Seasonally adjusted and Trend-cycle estimates represent an analytical elaboration of the data designed to show the underlying movements that may be hidden by the seasonal variations.
B17: e | C17: Seasonally adjusted data is the sum of the Trend-cycle component and the Irregular component. When the Irregular component is strong, the Seasonally adjusted series may not present a smooth pattern.
B18: f | C18: Original (Unadjusted) data are useful in their own right. They show the actual economic events that have occurred and therefore Seasonally adjusted data should not replace the unadjusted data.
B19: h | C19: In terms of interpretation, original series consider year on year similar quarter changes due to seasonal effects while adjusted series consider quarter to quarter changes.

Sheet Summary
A2: TABLE 1: SUMMARY OF QGDP AT CONSTANT 2016/17 PRICES, BILLION SHILLINGS, 2016/17-2025/26
A3: Year | B3: 2016/17 | F3: 2017/18 | G3: 2017/18 | J3: 2018/19 | N3: 2019/20 | R3: 2020/21 | V3: 2021/22 | Z3: 2022/23 | AD3: 2023/24 | AH3: 2024/25 | AL3: 2025/26
A4: Period | B4: Q1 | C4: Q2 | D4: Q3 | E4: Q4 | F4: Q1 | G4: Q2 | H4: Q3 | I4: Q4 | J4: Q1 | K4: Q2 | L4: Q3 | M4: Q4 | N4: Q1 | O4: Q2 | P4: Q3 | Q4: Q4 | R4: Q1 | S4: Q2 | T4: Q3 | U4: Q4 | V4: Q1 | W4: Q2 | X4: Q3 | Y4: Q4 | Z4: Q1 | AA4: Q2 | AB4: Q3 | AC4: Q4 | AD4: Q1 | AE4: Q2 | AF4: Q3 | AG4: Q4 | AH4: Q1 | AI4: Q2 | AJ4: Q3 | AK4: Q4 | AL4: Q1 | AM4: Q2
A5: ORIGINAL ESTIMATES
A6: GDP at market prices | B6: 28577.247 | C6: 26610.18 | D6: 26240.178 | E6: 27090.435 | F6: 30772.237 | G6: 28335.28 | H6: 27653.331 | I6: 28598.087 | J6: 32487.642 | K6: 29958.631 | L6: 29773.235 | M6: 30567.095 | N6: 34943.779 | O6: 32466.458 | P6: 30130.072 | Q6: 28870.102 | R6: 34802.923 | S6: 32477.008 | T6: 30975.024 | U6: 32626.063 | V6: 35622.436 | W6: 34024.49 | X6: 32716.662 | Y6: 34522.28 | Z6: 38746.737 | AA6: 35492.013 | AB6: 33446.228 | AC6: 36506.452 | AD6: 41068.072 | AE6: 37544.31 | AF6: 35728.791 | AG6: 38581.884 | AH6: 43605.836 | AI6: 39557.991 | AJ6: 38727.987 | AK6: 40714.044 | AL6: 45718.884 | AM6: 42903.876
A7: Agriculture, Forestry & Fishing | B7: 8012.3898 | C7: 6110.5575 | D7: 5359.3298 | E7: 5974.7915 | F7: 8783.7536 | G7: 6199.5724 | H7: 5495.0897 | I7: 6096.0101 | J7: 8974.6097 | K7: 6448.4413 | L7: 5935.2774 | M7: 6628.7289 | N7: 9517.4185 | O7: 6941.2508 | P7: 5858.4835 | Q7: 7019.6669 | R7: 10178.838 | S7: 7480.0514 | T7: 5874.7257 | U7: 7070.5839 | V7: 10624.95 | W7: 7330.892 | X7: 6120.4467 | Y7: 7804.9868 | Z7: 11088.263 | AA7: 8197.4364 | AB7: 6452.1008 | AC7: 7589.8403 | AD7: 11715.27 | AE7: 8365.8311 | AF7: 6712.9791 | AG7: 8392.5624 | AH7: 12457.04 | AI7: 9018.0558 | AJ7: 7404.8569 | AK7: 8683.3829 | AL7: 12839.64 | AM7: 9809.0589
A8: Industry | B8: 6768.7131 | C8: 7106.8656 | D8: 7305.421 | E8: 7067.3259 | F8: 7134.9059 | G8: 7312.6318 | H8: 7537.2021 | I8: 7631.5343 | J8: 7779.6918 | K8: 8068.1838 | L8: 8243.5123 | M8: 8201.8824 | N8: 8570.2406 | O8: 8886.3356 | P8: 8486.7958 | Q8: 7398.8511 | R8: 8381.1058 | S8: 8755.7883 | T8: 8669.0779 | U8: 8693.4802 | V8: 8370.9467 | W8: 9440.8925 | X8: 9148.3498 | Y8: 9308.0376 | Z8: 9399.6503 | AA8: 9216.6242 | AB8: 9213.4013 | AC8: 9899.9765 | AD8: 10329.779 | AE8: 9629.9206 | AF8: 9832.8272 | AG8: 10008.679 | AH8: 10858.986 | AI8: 10366.745 | AJ8: 10560.436 | AK8: 10766.195 | AL8: 11507.782 | AM8: 11637.499
A9: Services | B9: 11937.718 | C9: 11574.904 | D9: 11626.766 | E9: 12042.627 | F9: 12862.303 | G9: 12815.187 | H9: 12685.299 | I9: 12837.368 | J9: 13754.229 | K9: 13368.754 | L9: 13465.069 | M9: 13600.746 | N9: 14658.784 | O9: 14367.919 | P9: 13669.805 | Q9: 12849.732 | R9: 14119.436 | S9: 14074.464 | T9: 14391.411 | U9: 14495.401 | V9: 14539.216 | W9: 14902.836 | X9: 14962.971 | Y9: 14980.554 | Z9: 15799.82 | AA9: 15607.29 | AB9: 15193.7 | AC9: 16317.733 | AD9: 16221.882 | AE9: 16906.179 | AF9: 16418.929 | AG9: 17379.216 | AH9: 17192.953 | AI9: 17283.665 | AJ9: 17847.735 | AK9: 18239.581 | AL9: 18170.905 | AM9: 18361.432
A10: Adjustments
A11: Taxes on products | B11: 1858.4261 | C11: 1817.8528 | D11: 1948.6611 | E11: 2005.691 | F11: 1991.2744 | G11: 2007.8887 | H11: 1935.7403 | I11: 2033.1747 | J11: 1979.1119 | K11: 2073.2514 | L11: 2129.377 | M11: 2135.7379 | N11: 2197.3365 | O11: 2270.9524 | P11: 2114.9878 | Q11: 1601.8521 | R11: 2123.5437 | S11: 2166.7043 | T11: 2039.8093 | U11: 2366.598 | V11: 2087.3237 | W11: 2349.8691 | X11: 2484.895 | Y11: 2428.7012 | Z11: 2459.0041 | AA11: 2470.6617 | AB11: 2587.0261 | AC11: 2698.9015 | AD11: 2801.1416 | AE11: 2642.3794 | AF11: 2764.0558 | AG11: 2801.4262 | AH11: 3096.8575 | AI11: 2889.5255 | AJ11: 2914.9594 | AK11: 3024.8849 | AL11: 3200.5564 | AM11: 3095.8858
A13: SEASONALLY ADJUSTED ESTIMATES
A14: GDP at market prices | B14: 26418.33 | C14: 26820.341 | D14: 27619.794 | E14: 27877.519 | F14: 28291.339 | G14: 28562.977 | H14: 29225.636 | I14: 29425.25 | J14: 29958.925 | K14: 30153.094 | L14: 31561.031 | M14: 31371.83 | N14: 32311.887 | O14: 32681.047 | P14: 31941.991 | Q14: 29638.437 | R14: 31936.886 | S14: 32665.96 | T14: 32913.148 | U14: 33266.263 | V14: 32690.007 | W14: 34248.282 | X14: 35004.411 | Y14: 35114.23 | Z14: 35517.737 | AA14: 35836.545 | AB14: 35798.781 | AC14: 36969.932 | AD14: 37483.15 | AE14: 38034.023 | AF14: 38330.506 | AG14: 38995.258 | AH14: 39825.16 | AI14: 40146.528 | AJ14: 41458.228 | AK14: 41147.854 | AL14: 41936.505 | AM14: 43598.4
A15: Agriculture, Forestry & Fishing | B15: 6113.5807 | C15: 6365.3902 | D15: 6582.613 | E15: 6545.5468 | F15: 6624.4085 | G15: 6533.6463 | H15: 6886.5598 | I15: 6658.9337 | J15: 6779.4574 | K15: 6777.7826 | L15: 7530.1008 | M15: 7187.1377 | N15: 7185.5965 | O15: 7287.0483 | P15: 7449.7978 | Q15: 7591.413 | R15: 7576.6284 | S15: 7813.6823 | T15: 7522.4789 | U15: 7637.3368 | V15: 7927.1369 | W15: 7630.167 | X15: 8035.5081 | Y15: 8447.1775 | Z15: 8159.0795 | AA15: 8513.0207 | AB15: 8383.2101 | AC15: 8246.0464 | AD15: 8605.2413 | AE15: 8671.4432 | AF15: 8843.9697 | AG15: 9113.9734 | AH15: 9189.0095 | AI15: 9308.9636 | AJ15: 9634.1005 | AK15: 9429.3307 | AL15: 9593.9998 | AM15: 10108.554
A16: Industry | B16: 6810.6034 | C16: 7063.7601 | D16: 7254.0027 | E16: 7141.0369 | F16: 7166.4739 | G16: 7225.7595 | H16: 7502.9433 | I16: 7726.2775 | J16: 7801.3782 | K16: 7960.7061 | L16: 8233.1105 | M16: 8293.8714 | N16: 8575.638 | O16: 8793.2643 | P16: 8516.0149 | Q16: 7475.9913 | R16: 8344.0458 | S16: 8664.3391 | T16: 8746.7761 | U16: 8744.402 | V16: 8320.4574 | W16: 9400.4202 | X16: 9287.252 | Y16: 9327.8918 | Z16: 9270.1095 | AA16: 9216.431 | AB16: 9362.2701 | AC16: 9903.2747 | AD16: 10051.235 | AE16: 9693.1081 | AF16: 10001.426 | AG16: 9991.0365 | AH16: 10553.501 | AI16: 10470.413 | AJ16: 10737.855 | AK16: 10743.283 | AL16: 11200.126 | AM16: 11777.905
A17: Services | B17: 11610.862 | C17: 11586.137 | D17: 11813.858 | E17: 12212.573 | F17: 12489.013 | G17: 12814.711 | H17: 12875.605 | I17: 13027.644 | J17: 13383.12 | K17: 13363.712 | L17: 13643.786 | M17: 13769.895 | N17: 14342.035 | O17: 14348.651 | P17: 13842.032 | Q17: 12976.614 | R17: 13891.505 | S17: 14030.582 | T17: 14588.772 | U17: 14518.594 | V17: 14373.181 | W17: 14859.667 | X17: 15183.909 | Y17: 14904.481 | Z17: 15673.293 | AA17: 15606.616 | AB17: 15455.052 | AC17: 16110.687 | AD17: 16092.728 | AE17: 16979.164 | AF17: 16709.108 | AG17: 17074.679 | AH17: 17070.877 | AI17: 17417.405 | AJ17: 18157.649 | AK17: 17935.607 | AL17: 18035.152 | AM17: 18549.363
A18: Adjustments
A19: Taxes on products | B19: 1883.2834 | C19: 1805.0535 | D19: 1969.3194 | E19: 1978.3628 | F19: 2011.4434 | G19: 1988.86 | H19: 1960.5283 | I19: 2012.3942 | J19: 1994.9695 | K19: 2050.8934 | L19: 2154.0345 | M19: 2120.9253 | N19: 2208.6176 | O19: 2252.0829 | P19: 2134.1464 | Q19: 1594.4186 | R19: 2124.7071 | S19: 2157.3562 | T19: 2055.1209 | U19: 2365.9306 | V19: 2069.2315 | W19: 2358.027 | X19: 2497.7416 | Y19: 2434.6792 | Z19: 2415.2547 | AA19: 2500.4775 | AB19: 2598.2494 | AC19: 2709.924 | AD19: 2733.946 | AE19: 2690.3075 | AF19: 2776.001 | AG19: 2815.5688 | AH19: 3011.7728 | AI19: 2949.7457 | AJ19: 2928.624 | AK19: 3039.6326 | AL19: 3107.2263 | AM19: 3162.5776
A21: TREND CYCLE ESTIMATES
A22: GDP at market prices | B22: 26462.729 | C22: 26896.395 | D22: 27382.403 | E22: 27823.292 | F22: 28161.943 | G22: 28513.962 | H22: 28957.26 | I22: 29462.114 | J22: 29881.613 | K22: 30348.906 | L22: 30850.88 | M22: 31471.349 | N22: 32206.382 | O22: 32534.765 | P22: 32175.212 | Q22: 32026.06 | R22: 32219.26 | S22: 32509.801 | T22: 32839.663 | U22: 32898.971 | V22: 33160.329 | W22: 34069.828 | X22: 34839.343 | Y22: 35033.552 | Z22: 35348.49 | AA22: 35585.28 | AB22: 36078.587 | AC22: 36779.913 | AD22: 37191.742 | AE22: 37418.391 | AF22: 38268.834 | AG22: 39291.159 | AH22: 39872.71 | AI22: 40241.212 | AJ22: 40656.363 | AK22: 41347.988 | AL22: 42239.942 | AM22: 43273.383
A23: Agriculture, Forestry & Fishing | B23: 6219.3427 | C23: 6294.9669 | D23: 6407.4385 | E23: 6477.3375 | F23: 6492.3673 | G23: 6510.6472 | H23: 6592.6195 | I23: 6679.9926 | J23: 6762.4404 | K23: 6851.8703 | L23: 6974.0034 | M23: 7093.5297 | N23: 7177.9759 | O23: 7247.1952 | P23: 7351.7641 | Q23: 7498.5506 | R23: 7601.7848 | S23: 7595.9446 | T23: 7545.8478 | U23: 7498.9166 | V23: 7553.2979 | W23: 7784.6192 | X23: 8052.5733 | Y23: 8303.0837 | Z23: 8440.4735 | AA23: 8395.4301 | AB23: 8324.0587 | AC23: 8334.4393 | AD23: 8415.4908 | AE23: 8575.3602 | AF23: 8756.8475 | AG23: 8934.4361 | AH23: 9086.7845 | AI23: 9205.3115 | AJ23: 9283.9208 | AK23: 9390.2858 | AL23: 9596.0021 | AM23: 9897.4766
A24: Industry | B24: 6791.0364 | C24: 7077.731 | D24: 7200.174 | E24: 7178.8762 | F24: 7145.538 | G24: 7259.2795 | H24: 7489.921 | I24: 7702.2802 | J24: 7816.3296 | K24: 7986.6672 | L24: 8177.1601 | M24: 8347.9343 | N24: 8583.36 | O24: 8719.0967 | P24: 8659.4439 | Q24: 8631.8724 | R24: 8675.9397 | S24: 8693.6963 | T24: 8724.2683 | U24: 8713.2737 | V24: 8889.5175 | W24: 9198.4026 | X24: 9353.5156 | Y24: 9306.4883 | Z24: 9263.289 | AA24: 9216.4138 | AB24: 9447.5444 | AC24: 9800.8344 | AD24: 9860.4728 | AE24: 9788.7521 | AF24: 9945.4833 | AG24: 10259.871 | AH24: 10474.648 | AI24: 10592.303 | AJ24: 10632.774 | AK24: 10784.478 | AL24: 11190.244 | AM24: 11740.477
A25: Services | B25: 11589.542 | C25: 11612.456 | D25: 11823.783 | E25: 12175.714 | F25: 12522.111 | G25: 12757.821 | H25: 12896.904 | I25: 13088.897 | J25: 13295.481 | K25: 13447.922 | L25: 13578.028 | M25: 13877.968 | N25: 14239.943 | O25: 14349.331 | P25: 13984.686 | Q25: 13745.471 | R25: 13790.337 | S25: 14083.848 | T25: 14424.047 | U25: 14513.376 | V25: 14468.768 | W25: 14713.635 | X25: 14970.425 | Y25: 14975.687 | Z25: 15218.231 | AA25: 15479.82 | AB25: 15701.178 | AC25: 15943.64 | AD25: 16194.829 | AE25: 16336.623 | AF25: 16815.867 | AG25: 17245.556 | AH25: 17370.262 | AI25: 17488.209 | AJ25: 17789.05 | AK25: 18148.771 | AL25: 18347.572 | AM25: 18470.604
A26: Adjustments
A27: Taxes on products | B27: 1862.8078 | C27: 1911.2419 | D27: 1951.0075 | E27: 1991.364 | F27: 2001.9261 | G27: 1986.2144 | H27: 1977.8154 | I27: 1990.9443 | J27: 2007.3618 | K27: 2062.4461 | L27: 2121.6887 | M27: 2151.9172 | N27: 2205.1039 | O27: 2219.1416 | P27: 2179.3171 | Q27: 2150.1665 | R27: 2151.1983 | S27: 2136.3114 | T27: 2145.5 | U27: 2173.405 | V27: 2248.7455 | W27: 2373.1712 | X27: 2462.8291 | Y27: 2448.2929 | Z27: 2426.4969 | AA27: 2493.6157 | AB27: 2605.8057 | AC27: 2700.9992 | AD27: 2720.9495 | AE27: 2717.6552 | AF27: 2750.6356 | AG27: 2851.2955 | AH27: 2941.015 | AI27: 2955.3882 | AJ27: 2950.618 | AK27: 3024.4541 | AL27: 3106.1235 | AM27: 3164.8249
A29: Source: Uganda Bureau of Statistics
A31: TABLE 2: SUMMARY OF QGDP AT CONSTANT 2016/17 PRICES, PERCENTAGE CHANGE, 2016/17-2025/26
A32: Year | B32: 2016/17 | F32: 2017/18 | G32: 2017/18 | J32: 2018/19 | N32: 2019/20 | R32: 2020/21 | V32: 2021/22 | Z32: 2022/23 | AD32: 2023/24 | AH32: 2024/25 | AL32: 2025/26
A33: Period | B33: Q1 | C33: Q2 | D33: Q3 | E33: Q4 | F33: Q1 | G33: Q2 | H33: Q3 | I33: Q4 | J33: Q1 | K33: Q2 | L33: Q3 | M33: Q4 | N33: Q1 | O33: Q2 | P33: Q3 | Q33: Q4 | R33: Q1 | S33: Q2 | T33: Q3 | U33: Q4 | V33: Q1 | W33: Q2 | X33: Q3 | Y33: Q4 | Z33: Q1 | AA33: Q2 | AB33: Q3 | AC33: Q4 | AD33: Q1 | AE33: Q2 | AF33: Q3 | AG33: Q4 | AH33: Q1 | AI33: Q2 | AJ33: Q3 | AK33: Q4 | AL33: Q1 | AM33: Q2
A34: ORIGINAL ESTIMATES
A35: GDP at market prices | B35: -0.26122599 | C35: 0.50756396 | D35: 6.7464548 | E35: 6.1811727 | F35: 7.6808998 | G35: 6.4828574 | H35: 5.3854549 | I35: 5.5652552 | J35: 5.5745218 | K35: 5.7290794 | L35: 7.6659989 | M35: 6.8851035 | N35: 7.5602194 | O35: 8.3709675 | P35: 1.1985158 | Q35: -5.5516965 | R35: -0.40309239 | S35: 0.032495737 | T35: 2.804345 | U35: 13.009861 | V35: 2.354724 | W35: 4.7648514 | X35: 5.6227189 | Y35: 5.811971 | Z35: 8.7705981 | AA35: 4.3131379 | AB35: 2.2299523 | AC35: 5.7475112 | AD35: 5.9910476 | AE35: 5.7824205 | AF35: 6.8245768 | AG35: 5.6851104 | AH35: 6.1794064 | AI35: 5.3634777 | AJ35: 8.394339 | AK35: 5.5263248 | AL35: 4.8457919 | AM35: 8.4581777
A36: Agriculture, Forestry & Fishing | B36: 1.1733408 | C36: 3.2296506 | D36: 1.0636812 | E36: 6.0861995 | F36: 9.6271373 | G36: 1.4567401 | H36: 2.5331515 | I36: 2.0288347 | J36: 2.172831 | K36: 4.0142917 | L36: 8.010565 | M36: 8.7388102 | N36: 6.0482714 | O36: 7.6423041 | P36: -1.2938559 | Q36: 5.8976315 | R36: 6.9495696 | S36: 7.7622984 | T36: 0.27724211 | U36: 0.72534795 | V36: 4.382736 | W36: -1.9940967 | X36: 4.1826802 | Y36: 10.386736 | Z36: 4.3606145 | AA36: 11.82045 | AB36: 5.4187897 | AC36: -2.7565253 | AD36: 5.654692 | AE36: 2.0542364 | AF36: 4.0433085 | AG36: 10.57627 | AH36: 6.331648 | AI36: 7.796292 | AJ36: 10.306569 | AK36: 3.4652179 | AL36: 3.0713611 | AM36: 8.7713266
A37: Industry | B37: -0.60233732 | C37: 4.5995317 | D37: 16.225662 | E37: 7.9277803 | F37: 5.4100804 | G37: 2.8953153 | H37: 3.1727275 | I37: 7.983336 | J37: 9.0370626 | K37: 10.33215 | L37: 9.3709856 | M37: 7.4735698 | N37: 10.161699 | O37: 10.14047 | P37: 2.9512124 | Q37: -9.7908167 | R37: -2.2068791 | S37: -1.4690787 | T37: 2.1478318 | U37: 17.497705 | V37: -0.121214 | W37: 7.8245859 | X37: 5.5285218 | Y37: 7.0691761 | Z37: 12.288976 | AA37: -2.3754988 | AB37: 0.71107424 | AC37: 6.3594382 | AD37: 9.8953589 | AE37: 4.4842493 | AF37: 6.7230965 | AG37: 1.0980079 | AH37: 5.1231152 | AI37: 7.6514026 | AJ37: 7.3997957 | AK37: 7.5685941 | AL37: 5.9747366 | AM37: 12.257991
A38: Services | B38: -2.4907341 | C38: -3.736009 | D38: 2.5175007 | E38: 4.5088343 | F38: 7.7450719 | G38: 10.715277 | H38: 9.1042744 | I38: 6.5993997 | J38: 6.9344151 | K38: 4.3196164 | L38: 6.1470326 | M38: 5.9465301 | N38: 6.576558 | O38: 7.4738828 | P38: 1.5205013 | Q38: -5.5218535 | R38: -3.6793477 | S38: -2.042432 | T38: 5.2788271 | U38: 12.807022 | V38: 2.9730667 | W38: 5.8856353 | X38: 3.9715352 | Y38: 3.3469497 | Z38: 8.6703688 | AA38: 4.7269825 | AB38: 1.5420013 | AC38: 8.9260995 | AD38: 2.6713069 | AE38: 8.3223194 | AF38: 8.0640636 | AG38: 6.505087 | AH38: 5.9861799 | AI38: 2.2328288 | AJ38: 8.7021833 | AK38: 4.9505378 | AL38: 5.6881024 | AM38: 6.2357551
A39: Adjustments
A40: Taxes on products | B40: 10.604422 | C40: 4.5985732 | D40: 17.953651 | E40: 10.804192 | F40: 7.14843 | G40: 10.453864 | H40: -0.66306097 | I40: 1.3702884 | J40: -0.61078727 | K40: 3.2552983 | L40: 10.00324 | M40: 5.0444829 | N40: 11.026391 | O40: 9.535794 | P40: -0.67574802 | Q40: -24.997721 | R40: -3.3582876 | S40: -4.5905031 | T40: -3.5545582 | U40: 47.741356 | V40: -1.7056382 | W40: 8.453615 | X40: 21.819967 | Y40: 2.6241571 | Z40: 17.806552 | AA40: 5.1403958 | AB40: 4.1100754 | AC40: 11.125298 | AD40: 13.913662 | AE40: 6.9502737 | AF40: 6.8429801 | AG40: 3.7987589 | AH40: 10.556979 | AI40: 9.3531628 | AJ40: 5.4594994 | AK40: 7.9766044 | AL40: 3.3485178 | AM40: 7.1416697
A42: SEASONALLY ADJUSTED ESTIMATES
A43: GDP at market prices | B43: 0.86546068 | C43: 1.5217117 | D43: 2.9807704 | E43: 0.93312038 | F43: 1.4844207 | G43: 0.96014433 | H43: 2.3199933 | I43: 0.68300934 | J43: 1.8136644 | K43: 0.64811638 | L43: 4.6692978 | M43: -0.5994792 | N43: 2.996502 | O43: 1.1424887 | P43: -2.2614196 | Q43: -7.2116804 | R43: 7.7549618 | S43: 2.2828561 | T43: 0.75671459 | U43: 1.0728699 | V43: -1.7322538 | W43: 4.766823 | X43: 2.2077868 | Y43: 0.31372912 | Z43: 1.149128 | AA43: 0.89760246 | AB43: -0.10537823 | AC43: 3.2714827 | AD43: 1.3882041 | AE43: 1.4696532 | AF43: 0.77952016 | AG43: 1.7342644 | AH43: 2.1282137 | AI43: 0.80694549 | AJ43: 3.2672815 | AK43: -0.74864265 | AL43: 1.9166271 | AM43: 3.9628848
A44: Agriculture, Forestry & Fishing | B44: -0.95264124 | C44: 4.1188552 | D44: 3.4125598 | E44: -0.56309295 | F44: 1.2048157 | G44: -1.3701187 | H44: 5.4014788 | I44: -3.3053667 | J44: 1.809954 | K44: -0.024703168 | L44: 11.099768 | M44: -4.554562 | N44: -0.02144354 | O44: 1.4118782 | P44: 2.2334067 | Q44: 1.9009271 | R44: -0.19475384 | S44: 3.1287517 | T44: -3.7268402 | U44: 1.5268624 | V44: 3.7945184 | W44: -3.7462449 | X44: 5.3123497 | Y44: 5.1231289 | Z44: -3.4105828 | AA44: 4.3380037 | AB44: -1.5248479 | AC44: -1.6361716 | AD44: 4.3559656 | AE44: 0.76931957 | AF44: 1.9895942 | AG44: 3.0529694 | AH44: 0.82330881 | AI44: 1.3054081 | AJ44: 3.492729 | AK44: -2.1254685 | AL44: 1.7463496 | AM44: 5.3632931
A45: Industry | B45: 3.1670471 | C45: 3.717097 | D45: 2.6932197 | E45: -1.5572898 | F45: 0.35620939 | G45: 0.82726373 | H45: 3.8360498 | I45: 2.9766219 | J45: 0.97201608 | K45: 2.042305 | L45: 3.4218618 | M45: 0.73800683 | N45: 3.3972867 | O45: 2.5377276 | P45: -3.1529752 | Q45: -12.212562 | R45: 11.61123 | S45: 3.8385845 | T45: 0.95145188 | U45: -0.027142845 | V45: -4.8481825 | W45: 12.979608 | X45: -1.2038631 | Y45: 0.43758695 | Z45: -0.61945777 | AA45: -0.57904912 | AB45: 1.582382 | AC45: 5.778562 | AD45: 1.4940567 | AE45: -3.5630162 | AF45: 3.1808 | AG45: -0.10388497 | AH45: 5.6296866 | AI45: -0.78729527 | AJ45: 2.5542563 | AK45: 0.050557372 | AL45: 4.2523591 | AM45: 5.15868
A46: Services | B46: -0.23506787 | C46: -0.21295183 | D46: 1.9654659 | E46: 3.3749736 | F46: 2.2635705 | G46: 2.6078739 | H46: 0.47518546 | I46: 1.1808353 | J46: 2.7286258 | K46: -0.14502166 | L46: 2.0957819 | M46: 0.92429978 | N46: 4.1550047 | O46: 0.046131214 | P46: -3.5307782 | Q46: -6.2521035 | R46: 7.0503066 | S46: 1.0011646 | T46: 3.9783803 | U46: -0.48104309 | V46: -1.0015607 | W46: 3.3846817 | X46: 2.1820235 | Y46: -1.8402888 | Z46: 5.1582627 | AA46: -0.42542075 | AB46: -0.97115419 | AC46: 4.2422081 | AD46: -0.11147455 | AE46: 5.5083025 | AF46: -1.5905116 | AG46: 2.1878533 | AH46: -0.022265295 | AI46: 2.0299339 | AJ46: 4.250023 | AK46: -1.2228544 | AL46: 0.55501444 | AM46: 2.8511598
A47: Adjustments
A48: Taxes on products | B48: 5.8309683 | C48: -4.1539103 | D48: 9.1003326 | E48: 0.45921373 | F48: 1.6721228 | G48: -1.1227465 | H48: -1.4245218 | I48: 2.6455086 | J48: -0.86586866 | K48: 2.8032472 | L48: 5.0290772 | M48: -1.5370745 | N48: 4.134624 | O48: 1.9679872 | P48: -5.2367755 | Q48: -25.290101 | R48: 33.259047 | S48: 1.5366438 | T48: -4.7389196 | U48: 15.123673 | V48: -12.540484 | W48: 13.956656 | X48: 5.9250661 | Y48: -2.5247783 | Z48: -0.79782628 | AA48: 3.5285237 | AB48: 3.9101277 | AC48: 4.2980714 | AD48: 0.88644397 | AE48: -1.5961719 | AF48: 3.1852689 | AG48: 1.4253527 | AH48: 6.9685372 | AI48: -2.0594866 | AJ48: -0.71605213 | AK48: 3.7904706 | AL48: 2.2237433 | AM48: 1.7813745
A50: TREND CYCLE ESTIMATES
A51: GDP at market prices | B51: 1.1600043 | C51: 1.6387808 | D51: 1.8069627 | E51: 1.6101159 | F51: 1.2171498 | G51: 1.249981 | H51: 1.5546698 | I51: 1.743448 | J51: 1.4238561 | K51: 1.5638156 | L51: 1.6540111 | M51: 2.0111873 | N51: 2.3355632 | O51: 1.0196182 | P51: -1.1051348 | Q51: -0.46355991 | R51: 0.60325829 | S51: 0.90176095 | T51: 1.0146551 | U51: 0.18059848 | V51: 0.79442676 | W51: 2.742732 | X51: 2.2586389 | Y51: 0.55744241 | Z51: 0.89896211 | AA51: 0.66987123 | AB51: 1.386268 | AC51: 1.9438837 | AD51: 1.1197133 | AE51: 0.6094055 | AF51: 2.2727936 | AG51: 2.6714297 | AH51: 1.4801069 | AI51: 0.9241967 | AJ51: 1.031655 | AK51: 1.7011504 | AL51: 2.1571877 | AM51: 2.4465953
A52: Agriculture, Forestry & Fishing | B52: -0.32447705 | C52: 1.2159518 | D52: 1.7866906 | E52: 1.0909037 | F52: 0.23203631 | G52: 0.28155949 | H52: 1.2590512 | I52: 1.3253156 | J52: 1.2342505 | K52: 1.3224506 | L52: 1.7824778 | M52: 1.713884 | N52: 1.1904674 | O52: 0.96432903 | P52: 1.4428886 | Q52: 1.9966159 | R52: 1.3767221 | S52: -0.07682714 | T52: -0.65951993 | U52: -0.62194756 | V52: 0.72518788 | W52: 3.0625205 | X52: 3.4420974 | Y52: 3.1109351 | Z52: 1.6546843 | AA52: -0.53365901 | AB52: -0.85012281 | AC52: 0.12470577 | AD52: 0.97248991 | AE52: 1.8997033 | AF52: 2.116381 | AG52: 2.0279976 | AH52: 1.7051817 | AI52: 1.3043889 | AJ52: 0.85395584 | AK52: 1.1456899 | AL52: 2.1907354 | AM52: 3.1416674
A53: Industry | B53: 3.8740071 | C53: 4.2216624 | D53: 1.7299746 | E53: -0.29579554 | F53: -0.46439365 | G53: 1.5917849 | H53: 3.177195 | I53: 2.8352659 | J53: 1.480723 | K53: 2.1792533 | L53: 2.3851353 | M53: 2.0884291 | N53: 2.8201673 | O53: 1.5813933 | P53: -0.68416167 | Q53: -0.31839831 | R53: 0.5105181 | S53: 0.20466531 | T53: 0.35165734 | U53: -0.12602364 | V53: 2.022705 | W53: 3.4747112 | X53: 1.6863042 | Y53: -0.50277734 | Z53: -0.46418428 | AA53: -0.5060324 | AB53: 2.5078151 | AC53: 3.7394904 | AD53: 0.60850301 | AE53: -0.72735566 | AF53: 1.6011356 | AG53: 3.1611068 | AH53: 2.0933719 | AI53: 1.1232365 | AJ53: 0.38207511 | AK53: 1.4267595 | AL53: 3.762507 | AM53: 4.9170773
A54: Services | B54: -0.15071624 | C54: 0.19770636 | D54: 1.8198359 | E54: 2.9764652 | F54: 2.8449873 | G54: 1.8823433 | H54: 1.0901795 | I54: 1.4886805 | J54: 1.5783097 | K54: 1.1465662 | L54: 0.96747859 | M54: 2.2090095 | N54: 2.6082687 | O54: 0.76818082 | P54: -2.5411975 | Q54: -1.7105547 | R54: 0.32641018 | S54: 2.128383 | T54: 2.4155222 | U54: 0.6193047 | V54: -0.30735351 | W54: 1.6923828 | X54: 1.7452468 | Y54: 0.035152744 | Z54: 1.6195839 | AA54: 1.7189196 | AB54: 1.4299791 | AC54: 1.5442258 | AD54: 1.575483 | AE54: 0.8755516 | AF54: 2.9335558 | AG54: 2.5552597 | AH54: 0.72311941 | AI54: 0.67901688 | AJ54: 1.7202497 | AK54: 2.0221472 | AL54: 1.095398 | AM54: 0.67056052
A55: Adjustments
A56: Taxes on products | B56: 4.9532628 | C56: 2.6000544 | D56: 2.0806191 | E56: 2.0684931 | F56: 0.53039555 | G56: -0.78482691 | H56: -0.42286606 | I56: 0.66380713 | J56: 0.82460852 | K56: 2.7441136 | L56: 2.8724442 | M56: 1.4247401 | N56: 2.4715954 | O56: 0.63659811 | P56: -1.7945864 | Q56: -1.3376045 | R56: 0.047985802 | S56: -0.69202804 | T56: 0.43011652 | U56: 1.3006287 | V56: 3.4664753 | W56: 5.5331139 | X56: 3.7779798 | Y56: -0.59022444 | Z56: -0.89025433 | AA56: 2.766078 | AB56: 4.4990892 | AC56: 3.6531322 | AD56: 0.73862534 | AE56: -0.12106867 | AF56: 1.2135592 | AG56: 3.6595137 | AH56: 3.1466241 | AI56: 0.48871519 | AJ56: -0.16140776 | AK56: 2.5023932 | AL56: 2.7003025 | AM56: 1.8898611
A57: Source: Uganda Bureau of Statistics

Sheet Summary IPD
X2: Table 3: Summary of QGDP at constant 2009/10 prices, IMPLICIT PRICE DEFLATORS, 2013/14-2017/18
B3: 2007/08 | D3: 2008/09 | H3: 2009/10 | L3: 2010/11 | P3: 2011/12 | U3: 2012/13 | X3: 2013/14 | AB3: 2014/15 | AF3: 2015/16 | AJ3: 2016/17 | AN3: 2017/18
A4: ACTIVITY | B4: Q3 | C4: Q4 | D4: Q1 | E4: Q2 | F4: Q3 | G4: Q4 | H4: Q1 | I4: Q2 | J4: Q3 | K4: Q4 | L4: Q1 | M4: Q2 | N4: Q3 | O4: Q4 | P4: Q1 | Q4: Q2 | R4: Q3 | S4: Q4 | T4: Q1 | U4: Q2 | V4: Q3 | W4: Q4 | X4: Q1 | Y4: Q2 | Z4: Q3 | AA4: Q4 | AB4: Q1 | AC4: Q2 | AD4: Q3 | AE4: Q4 | AF4: Q1 | AG4: Q2 | AH4: Q3 | AI4: Q4 | AJ4: Q1 | AK4: Q2 | AL4: Q3 | AM4: Q4 | AN4: Q1 | AO4: Q2 | AP4: Q3 | AQ4: Q4
A5: ORIGINAL ESTIMATES
A6: GDP at market prices | B6: =#REF!/Summary!#REF!*100 -> #REF! | C6: =#REF!/Summary!#REF!*100 -> #REF! | D6: =#REF!/Summary!#REF!*100 -> #REF! | E6: =#REF!/Summary!#REF!*100 -> #REF! | F6: =#REF!/Summary!#REF!*100 -> #REF! | G6: =#REF!/Summary!#REF!*100 -> #REF! | H6: =#REF!/Summary!#REF!*100 -> #REF! | I6: =#REF!/Summary!#REF!*100 -> #REF! | ... AI6: =#REF!/Summary!#REF!*100 -> #REF! | AJ6: =#REF!/Summary!B6*100 -> #REF! | AK6: =#REF!/Summary!C6*100 -> #REF! | AL6: =#REF!/Summary!D6*100 -> #REF! | AM6: =#REF!/Summary!E6*100 -> #REF! | AN6: =#REF!/Summary!F6*100 -> #REF! | AO6: =#REF!/Summary!G6*100 -> #REF! | AP6: =#REF!/Summary!H6*100 -> #REF! | AQ6: =#REF!/Summary!I6*100 -> #REF!
A7: Agriculture, Forestry & Fishing | B7: =#REF!/Summary!#REF!*100 -> #REF! | C7: =#REF!/Summary!#REF!*100 -> #REF! | D7: =#REF!/Summary!#REF!*100 -> #REF! | E7: =#REF!/Summary!#REF!*100 -> #REF! | F7: =#REF!/Summary!#REF!*100 -> #REF! | G7: =#REF!/Summary!#REF!*100 -> #REF! | H7: =#REF!/Summary!#REF!*100 -> #REF! | I7: =#REF!/Summary!#REF!*100 -> #REF! | ... AI7: =#REF!/Summary!#REF!*100 -> #REF! | AJ7: =#REF!/Summary!B7*100 -> #REF! | AK7: =#REF!/Summary!C7*100 -> #REF! | AL7: =#REF!/Summary!D7*100 -> #REF! | AM7: =#REF!/Summary!E7*100 -> #REF! | AN7: =#REF!/Summary!F7*100 -> #REF! | AO7: =#REF!/Summary!G7*100 -> #REF! | AP7: =#REF!/Summary!H7*100 -> #REF! | AQ7: =#REF!/Summary!I7*100 -> #REF!
A8: Industry | B8: =#REF!/Summary!#REF!*100 -> #REF! | C8: =#REF!/Summary!#REF!*100 -> #REF! | D8: =#REF!/Summary!#REF!*100 -> #REF! | E8: =#REF!/Summary!#REF!*100 -> #REF! | F8: =#REF!/Summary!#REF!*100 -> #REF! | G8: =#REF!/Summary!#REF!*100 -> #REF! | H8: =#REF!/Summary!#REF!*100 -> #REF! | I8: =#REF!/Summary!#REF!*100 -> #REF! | ... AI8: =#REF!/Summary!#REF!*100 -> #REF! | AJ8: =#REF!/Summary!B8*100 -> #REF! | AK8: =#REF!/Summary!C8*100 -> #REF! | AL8: =#REF!/Summary!D8*100 -> #REF! | AM8: =#REF!/Summary!E8*100 -> #REF! | AN8: =#REF!/Summary!F8*100 -> #REF! | AO8: =#REF!/Summary!G8*100 -> #REF! | AP8: =#REF!/Summary!H8*100 -> #REF! | AQ8: =#REF!/Summary!I8*100 -> #REF!
A9: Services | B9: =#REF!/Summary!#REF!*100 -> #REF! | C9: =#REF!/Summary!#REF!*100 -> #REF! | D9: =#REF!/Summary!#REF!*100 -> #REF! | E9: =#REF!/Summary!#REF!*100 -> #REF! | F9: =#REF!/Summary!#REF!*100 -> #REF! | G9: =#REF!/Summary!#REF!*100 -> #REF! | H9: =#REF!/Summary!#REF!*100 -> #REF! | I9: =#REF!/Summary!#REF!*100 -> #REF! | ... AI9: =#REF!/Summary!#REF!*100 -> #REF! | AJ9: =#REF!/Summary!B9*100 -> #REF! | AK9: =#REF!/Summary!C9*100 -> #REF! | AL9: =#REF!/Summary!D9*100 -> #REF! | AM9: =#REF!/Summary!E9*100 -> #REF! | AN9: =#REF!/Summary!F9*100 -> #REF! | AO9: =#REF!/Summary!G9*100 -> #REF! | AP9: =#REF!/Summary!H9*100 -> #REF! | AQ9: =#REF!/Summary!I9*100 -> #REF!
A10: Adjustments
A11: Taxes on products | B11: =#REF!/Summary!#REF!*100 -> #REF! | C11: =#REF!/Summary!#REF!*100 -> #REF! | D11: =#REF!/Summary!#REF!*100 -> #REF! | E11: =#REF!/Summary!#REF!*100 -> #REF! | F11: =#REF!/Summary!#REF!*100 -> #REF! | G11: =#REF!/Summary!#REF!*100 -> #REF! | H11: =#REF!/Summary!#REF!*100 -> #REF! | I11: =#REF!/Summary!#REF!*100 -> #REF! | ... AI11: =#REF!/Summary!#REF!*100 -> #REF! | AJ11: =#REF!/Summary!B11*100 -> #REF! | AK11: =#REF!/Summary!C11*100 -> #REF! | AL11: =#REF!/Summary!D11*100 -> #REF! | AM11: =#REF!/Summary!E11*100 -> #REF! | AN11: =#REF!/Summary!F11*100 -> #REF! | AO11: =#REF!/Summary!G11*100 -> #REF! | AP11: =#REF!/Summary!H11*100 -> #REF! | AQ11: =#REF!/Summary!I11*100 -> #REF!
A13: SEASONALLY ADJUSTED ESTIMATES
A14: GDP at market prices | B14: =#REF!/Summary!#REF!*100 -> #REF! | C14: =#REF!/Summary!#REF!*100 -> #REF! | D14: =#REF!/Summary!#REF!*100 -> #REF! | E14: =#REF!/Summary!#REF!*100 -> #REF! | F14: =#REF!/Summary!#REF!*100 -> #REF! | G14: =#REF!/Summary!#REF!*100 -> #REF! | H14: =#REF!/Summary!#REF!*100 -> #REF! | I14: =#REF!/Summary!#REF!*100 -> #REF! | ... AI14: =#REF!/Summary!#REF!*100 -> #REF! | AJ14: =#REF!/Summary!B14*100 -> #REF! | AK14: =#REF!/Summary!C14*100 -> #REF! | AL14: =#REF!/Summary!D14*100 -> #REF! | AM14: =#REF!/Summary!E14*100 -> #REF! | AN14: =#REF!/Summary!F14*100 -> #REF! | AO14: =#REF!/Summary!G14*100 -> #REF! | AP14: =#REF!/Summary!H14*100 -> #REF! | AQ14: =#REF!/Summary!I14*100 -> #REF!
A15: Agriculture, Forestry & Fishing | B15: =#REF!/Summary!#REF!*100 -> #REF! | C15: =#REF!/Summary!#REF!*100 -> #REF! | D15: =#REF!/Summary!#REF!*100 -> #REF! | E15: =#REF!/Summary!#REF!*100 -> #REF! | F15: =#REF!/Summary!#REF!*100 -> #REF! | G15: =#REF!/Summary!#REF!*100 -> #REF! | H15: =#REF!/Summary!#REF!*100 -> #REF! | I15: =#REF!/Summary!#REF!*100 -> #REF! | ... AI15: =#REF!/Summary!#REF!*100 -> #REF! | AJ15: =#REF!/Summary!B15*100 -> #REF! | AK15: =#REF!/Summary!C15*100 -> #REF! | AL15: =#REF!/Summary!D15*100 -> #REF! | AM15: =#REF!/Summary!E15*100 -> #REF! | AN15: =#REF!/Summary!F15*100 -> #REF! | AO15: =#REF!/Summary!G15*100 -> #REF! | AP15: =#REF!/Summary!H15*100 -> #REF! | AQ15: =#REF!/Summary!I15*100 -> #REF!
A16: Industry | B16: =#REF!/Summary!#REF!*100 -> #REF! | C16: =#REF!/Summary!#REF!*100 -> #REF! | D16: =#REF!/Summary!#REF!*100 -> #REF! | E16: =#REF!/Summary!#REF!*100 -> #REF! | F16: =#REF!/Summary!#REF!*100 -> #REF! | G16: =#REF!/Summary!#REF!*100 -> #REF! | H16: =#REF!/Summary!#REF!*100 -> #REF! | I16: =#REF!/Summary!#REF!*100 -> #REF! | ... AI16: =#REF!/Summary!#REF!*100 -> #REF! | AJ16: =#REF!/Summary!B16*100 -> #REF! | AK16: =#REF!/Summary!C16*100 -> #REF! | AL16: =#REF!/Summary!D16*100 -> #REF! | AM16: =#REF!/Summary!E16*100 -> #REF! | AN16: =#REF!/Summary!F16*100 -> #REF! | AO16: =#REF!/Summary!G16*100 -> #REF! | AP16: =#REF!/Summary!H16*100 -> #REF! | AQ16: =#REF!/Summary!I16*100 -> #REF!
A17: Services | B17: =#REF!/Summary!#REF!*100 -> #REF! | C17: =#REF!/Summary!#REF!*100 -> #REF! | D17: =#REF!/Summary!#REF!*100 -> #REF! | E17: =#REF!/Summary!#REF!*100 -> #REF! | F17: =#REF!/Summary!#REF!*100 -> #REF! | G17: =#REF!/Summary!#REF!*100 -> #REF! | H17: =#REF!/Summary!#REF!*100 -> #REF! | I17: =#REF!/Summary!#REF!*100 -> #REF! | ... AI17: =#REF!/Summary!#REF!*100 -> #REF! | AJ17: =#REF!/Summary!B17*100 -> #REF! | AK17: =#REF!/Summary!C17*100 -> #REF! | AL17: =#REF!/Summary!D17*100 -> #REF! | AM17: =#REF!/Summary!E17*100 -> #REF! | AN17: =#REF!/Summary!F17*100 -> #REF! | AO17: =#REF!/Summary!G17*100 -> #REF! | AP17: =#REF!/Summary!H17*100 -> #REF! | AQ17: =#REF!/Summary!I17*100 -> #REF!
A18: Adjustments
A19: Taxes on products | B19: =#REF!/Summary!#REF!*100 -> #REF! | C19: =#REF!/Summary!#REF!*100 -> #REF! | D19: =#REF!/Summary!#REF!*100 -> #REF! | E19: =#REF!/Summary!#REF!*100 -> #REF! | F19: =#REF!/Summary!#REF!*100 -> #REF! | G19: =#REF!/Summary!#REF!*100 -> #REF! | H19: =#REF!/Summary!#REF!*100 -> #REF! | I19: =#REF!/Summary!#REF!*100 -> #REF! | ... AI19: =#REF!/Summary!#REF!*100 -> #REF! | AJ19: =#REF!/Summary!B19*100 -> #REF! | AK19: =#REF!/Summary!C19*100 -> #REF! | AL19: =#REF!/Summary!D19*100 -> #REF! | AM19: =#REF!/Summary!E19*100 -> #REF! | AN19: =#REF!/Summary!F19*100 -> #REF! | AO19: =#REF!/Summary!G19*100 -> #REF! | AP19: =#REF!/Summary!H19*100 -> #REF! | AQ19: =#REF!/Summary!I19*100 -> #REF!
A21: TREND CYCLE ESTIMATES
A22: GDP at market prices | B22: =#REF!/Summary!#REF!*100 -> #REF! | C22: =#REF!/Summary!#REF!*100 -> #REF! | D22: =#REF!/Summary!#REF!*100 -> #REF! | E22: =#REF!/Summary!#REF!*100 -> #REF! | F22: =#REF!/Summary!#REF!*100 -> #REF! | G22: =#REF!/Summary!#REF!*100 -> #REF! | H22: =#REF!/Summary!#REF!*100 -> #REF! | I22: =#REF!/Summary!#REF!*100 -> #REF! | ... AI22: =#REF!/Summary!#REF!*100 -> #REF! | AJ22: =#REF!/Summary!B22*100 -> #REF! | AK22: =#REF!/Summary!C22*100 -> #REF! | AL22: =#REF!/Summary!D22*100 -> #REF! | AM22: =#REF!/Summary!E22*100 -> #REF! | AN22: =#REF!/Summary!F22*100 -> #REF! | AO22: =#REF!/Summary!G22*100 -> #REF! | AP22: =#REF!/Summary!H22*100 -> #REF! | AQ22: =#REF!/Summary!I22*100 -> #REF!
A23: Agriculture, Forestry & Fishing | B23: =#REF!/Summary!#REF!*100 -> #REF! | C23: =#REF!/Summary!#REF!*100 -> #REF! | D23: =#REF!/Summary!#REF!*100 -> #REF! | E23: =#REF!/Summary!#REF!*100 -> #REF! | F23: =#REF!/Summary!#REF!*100 -> #REF! | G23: =#REF!/Summary!#REF!*100 -> #REF! | H23: =#REF!/Summary!#REF!*100 -> #REF! | I23: =#REF!/Summary!#REF!*100 -> #REF! | ... AI23: =#REF!/Summary!#REF!*100 -> #REF! | AJ23: =#REF!/Summary!B23*100 -> #REF! | AK23: =#REF!/Summary!C23*100 -> #REF! | AL23: =#REF!/Summary!D23*100 -> #REF! | AM23: =#REF!/Summary!E23*100 -> #REF! | AN23: =#REF!/Summary!F23*100 -> #REF! | AO23: =#REF!/Summary!G23*100 -> #REF! | AP23: =#REF!/Summary!H23*100 -> #REF! | AQ23: =#REF!/Summary!I23*100 -> #REF!
A24: Industry | B24: =#REF!/Summary!#REF!*100 -> #REF! | C24: =#REF!/Summary!#REF!*100 -> #REF! | D24: =#REF!/Summary!#REF!*100 -> #REF! | E24: =#REF!/Summary!#REF!*100 -> #REF! | F24: =#REF!/Summary!#REF!*100 -> #REF! | G24: =#REF!/Summary!#REF!*100 -> #REF! | H24: =#REF!/Summary!#REF!*100 -> #REF! | I24: =#REF!/Summary!#REF!*100 -> #REF! | ... AI24: =#REF!/Summary!#REF!*100 -> #REF! | AJ24: =#REF!/Summary!B24*100 -> #REF! | AK24: =#REF!/Summary!C24*100 -> #REF! | AL24: =#REF!/Summary!D24*100 -> #REF! | AM24: =#REF!/Summary!E24*100 -> #REF! | AN24: =#REF!/Summary!F24*100 -> #REF! | AO24: =#REF!/Summary!G24*100 -> #REF! | AP24: =#REF!/Summary!H24*100 -> #REF! | AQ24: =#REF!/Summary!I24*100 -> #REF!
A25: Services | B25: =#REF!/Summary!#REF!*100 -> #REF! | C25: =#REF!/Summary!#REF!*100 -> #REF! | D25: =#REF!/Summary!#REF!*100 -> #REF! | E25: =#REF!/Summary!#REF!*100 -> #REF! | F25: =#REF!/Summary!#REF!*100 -> #REF! | G25: =#REF!/Summary!#REF!*100 -> #REF! | H25: =#REF!/Summary!#REF!*100 -> #REF! | I25: =#REF!/Summary!#REF!*100 -> #REF! | ... AI25: =#REF!/Summary!#REF!*100 -> #REF! | AJ25: =#REF!/Summary!B25*100 -> #REF! | AK25: =#REF!/Summary!C25*100 -> #REF! | AL25: =#REF!/Summary!D25*100 -> #REF! | AM25: =#REF!/Summary!E25*100 -> #REF! | AN25: =#REF!/Summary!F25*100 -> #REF! | AO25: =#REF!/Summary!G25*100 -> #REF! | AP25: =#REF!/Summary!H25*100 -> #REF! | AQ25: =#REF!/Summary!I25*100 -> #REF!
A26: Adjustments
A27: Taxes on products | B27: =#REF!/Summary!#REF!*100 -> #REF! | C27: =#REF!/Summary!#REF!*100 -> #REF! | D27: =#REF!/Summary!#REF!*100 -> #REF! | E27: =#REF!/Summary!#REF!*100 -> #REF! | F27: =#REF!/Summary!#REF!*100 -> #REF! | G27: =#REF!/Summary!#REF!*100 -> #REF! | H27: =#REF!/Summary!#REF!*100 -> #REF! | I27: =#REF!/Summary!#REF!*100 -> #REF! | ... AI27: =#REF!/Summary!#REF!*100 -> #REF! | AJ27: =#REF!/Summary!B27*100 -> #REF! | AK27: =#REF!/Summary!C27*100 -> #REF! | AL27: =#REF!/Summary!D27*100 -> #REF! | AM27: =#REF!/Summary!E27*100 -> #REF! | AN27: =#REF!/Summary!F27*100 -> #REF! | AO27: =#REF!/Summary!G27*100 -> #REF! | AP27: =#REF!/Summary!H27*100 -> #REF! | AQ27: =#REF!/Summary!I27*100 -> #REF!
A28: Uganda Bureau of Statistics
X30: Table 4: Summary of QGDP at constant prices, PERCENTAGE SHARE, 2013/14-2017/18
B31: 2007/08 | D31: 2008/09 | H31: 2009/10 | L31: 2010/11 | P31: 2011/12 | U31: 2012/13 | X31: 2013/14 | AB31: 2014/15 | AF31: 2015/16 | AJ31: 2016/17 | AN31: 2017/18
A32: ACTIVITY | B32: Q3 | C32: Q4 | D32: Q1 | E32: Q2 | F32: Q3 | G32: Q4 | H32: Q1 | I32: Q2 | J32: Q3 | K32: Q4 | L32: Q1 | M32: Q2 | N32: Q3 | O32: Q4 | P32: Q1 | Q32: Q2 | R32: Q3 | S32: Q4 | T32: Q1 | U32: Q2 | V32: Q3 | W32: Q4 | X32: Q1 | Y32: Q2 | Z32: Q3 | AA32: Q4 | AB32: Q1 | AC32: Q2 | AD32: Q3 | AE32: Q4 | AF32: Q1 | AG32: Q2 | AH32: Q3 | AI32: Q4 | AJ32: Q1 | AK32: Q2 | AL32: Q3 | AM32: Q4 | AN32: Q1 | AO32: Q2 | AP32: Q3 | AQ32: Q4
A33: ORIGINAL ESTIMATES
A34: GDP at market prices | B34: =Summary!#REF!/Summary!#REF!*100 -> #REF! | C34: =Summary!#REF!/Summary!#REF!*100 -> #REF! | D34: =Summary!#REF!/Summary!#REF!*100 -> #REF! | E34: =Summary!#REF!/Summary!#REF!*100 -> #REF! | F34: =Summary!#REF!/Summary!#REF!*100 -> #REF! | G34: =Summary!#REF!/Summary!#REF!*100 -> #REF! | H34: =Summary!#REF!/Summary!#REF!*100 -> #REF! | I34: =Summary!#REF!/Summary!#REF!*100 -> #REF! | J34: =Summary!#REF!/Summary!#REF!*100 -> #REF! | K34: =SUM(K35:K39) -> #REF! | L34: =SUM(L35:L39) -> #REF! | M34: =SUM(M35:M39) -> #REF! | N34: =SUM(N35:N39) -> #REF! | O34: =SUM(O35:O39) -> #REF! | P34: =SUM(P35:P39) -> #REF! | Q34: =SUM(Q35:Q39) -> #REF! | R34: =SUM(R35:R39) -> #REF! | ... AQ34: =SUM(AQ35:AQ39) -> 100
A35: Agriculture, Forestry & Fishing | B35: =Summary!#REF!/Summary!#REF!*100 -> #REF! | C35: =Summary!#REF!/Summary!#REF!*100 -> #REF! | D35: =Summary!#REF!/Summary!#REF!*100 -> #REF! | E35: =Summary!#REF!/Summary!#REF!*100 -> #REF! | F35: =Summary!#REF!/Summary!#REF!*100 -> #REF! | G35: =Summary!#REF!/Summary!#REF!*100 -> #REF! | H35: =Summary!#REF!/Summary!#REF!*100 -> #REF! | I35: =Summary!#REF!/Summary!#REF!*100 -> #REF! | ... AI35: =Summary!#REF!/Summary!#REF!*100 -> #REF! | AJ35: =Summary!B7/Summary!B$6*100 -> 28.037654 | AK35: =Summary!C7/Summary!C$6*100 -> 22.963232 | AL35: =Summary!D7/Summary!D$6*100 -> 20.424136 | AM35: =Summary!E7/Summary!E$6*100 -> 22.054985 | AN35: =Summary!F7/Summary!F$6*100 -> 28.54441 | AO35: =Summary!G7/Summary!G$6*100 -> 21.87934 | AP35: =Summary!H7/Summary!H$6*100 -> 19.871348 | AQ35: =Summary!I7/Summary!I$6*100 -> 21.316147
A36: Industry | B36: =Summary!#REF!/Summary!#REF!*100 -> #REF! | C36: =Summary!#REF!/Summary!#REF!*100 -> #REF! | D36: =Summary!#REF!/Summary!#REF!*100 -> #REF! | E36: =Summary!#REF!/Summary!#REF!*100 -> #REF! | F36: =Summary!#REF!/Summary!#REF!*100 -> #REF! | G36: =Summary!#REF!/Summary!#REF!*100 -> #REF! | H36: =Summary!#REF!/Summary!#REF!*100 -> #REF! | I36: =Summary!#REF!/Summary!#REF!*100 -> #REF! | ... AI36: =Summary!#REF!/Summary!#REF!*100 -> #REF! | AJ36: =Summary!B8/Summary!B$6*100 -> 23.685672 | AK36: =Summary!C8/Summary!C$6*100 -> 26.707319 | AL36: =Summary!D8/Summary!D$6*100 -> 27.840592 | AM36: =Summary!E8/Summary!E$6*100 -> 26.087901 | AN36: =Summary!F8/Summary!F$6*100 -> 23.186179 | AO36: =Summary!G8/Summary!G$6*100 -> 25.807515 | AP36: =Summary!H8/Summary!H$6*100 -> 27.256037 | AQ36: =Summary!I8/Summary!I$6*100 -> 26.685471
A37: Services | B37: =Summary!#REF!/Summary!#REF!*100 -> #REF! | C37: =Summary!#REF!/Summary!#REF!*100 -> #REF! | D37: =Summary!#REF!/Summary!#REF!*100 -> #REF! | E37: =Summary!#REF!/Summary!#REF!*100 -> #REF! | F37: =Summary!#REF!/Summary!#REF!*100 -> #REF! | G37: =Summary!#REF!/Summary!#REF!*100 -> #REF! | H37: =Summary!#REF!/Summary!#REF!*100 -> #REF! | I37: =Summary!#REF!/Summary!#REF!*100 -> #REF! | ... AI37: =Summary!#REF!/Summary!#REF!*100 -> #REF! | AJ37: =Summary!B9/Summary!B$6*100 -> 41.773507 | AK37: =Summary!C9/Summary!C$6*100 -> 43.498031 | AL37: =Summary!D9/Summary!D$6*100 -> 44.309022 | AM37: =Summary!E9/Summary!E$6*100 -> 44.453427 | AN37: =Summary!F9/Summary!F$6*100 -> 41.798402 | AO37: =Summary!G9/Summary!G$6*100 -> 45.226965 | AP37: =Summary!H9/Summary!H$6*100 -> 45.87259 | AQ37: =Summary!I9/Summary!I$6*100 -> 44.888904
A38: Adjustments
A39: Taxes on products | B39: =Summary!#REF!/Summary!#REF!*100 -> #REF! | C39: =Summary!#REF!/Summary!#REF!*100 -> #REF! | D39: =Summary!#REF!/Summary!#REF!*100 -> #REF! | E39: =Summary!#REF!/Summary!#REF!*100 -> #REF! | F39: =Summary!#REF!/Summary!#REF!*100 -> #REF! | G39: =Summary!#REF!/Summary!#REF!*100 -> #REF! | H39: =Summary!#REF!/Summary!#REF!*100 -> #REF! | I39: =Summary!#REF!/Summary!#REF!*100 -> #REF! | ... AI39: =Summary!#REF!/Summary!#REF!*100 -> #REF! | AJ39: =Summary!B11/Summary!B$6*100 -> 6.5031669 | AK39: =Summary!C11/Summary!C$6*100 -> 6.8314186 | AL39: =Summary!D11/Summary!D$6*100 -> 7.4262494 | AM39: =Summary!E11/Summary!E$6*100 -> 7.4036868 | AN39: =Summary!F11/Summary!F$6*100 -> 6.4710095 | AO39: =Summary!G11/Summary!G$6*100 -> 7.0861789 | AP39: =Summary!H11/Summary!H$6*100 -> 7.0000257 | AQ39: =Summary!I11/Summary!I$6*100 -> 7.1094781
A41: SEASONALLY ADJUSTED ESTIMATES
A42: GDP at market prices | B42: =Summary!#REF!/Summary!#REF!*100 -> #REF! | C42: =Summary!#REF!/Summary!#REF!*100 -> #REF! | D42: =Summary!#REF!/Summary!#REF!*100 -> #REF! | E42: =Summary!#REF!/Summary!#REF!*100 -> #REF! | F42: =Summary!#REF!/Summary!#REF!*100 -> #REF! | G42: =Summary!#REF!/Summary!#REF!*100 -> #REF! | H42: =Summary!#REF!/Summary!#REF!*100 -> #REF! | I42: =Summary!#REF!/Summary!#REF!*100 -> #REF! | J42: =Summary!#REF!/Summary!#REF!*100 -> #REF! | K42: =SUM(K43:K47) -> #REF! | L42: =SUM(L43:L47) -> #REF! | M42: =SUM(M43:M47) -> #REF! | N42: =SUM(N43:N47) -> #REF! | O42: =SUM(O43:O47) -> #REF! | P42: =SUM(P43:P47) -> #REF! | Q42: =SUM(Q43:Q47) -> #REF! | R42: =SUM(R43:R47) -> #REF! | ... AQ42: =SUM(AQ43:AQ47) -> 100
A43: Agriculture, Forestry & Fishing | B43: =Summary!#REF!/Summary!#REF!*100 -> #REF! | C43: =Summary!#REF!/Summary!#REF!*100 -> #REF! | D43: =Summary!#REF!/Summary!#REF!*100 -> #REF! | E43: =Summary!#REF!/Summary!#REF!*100 -> #REF! | F43: =Summary!#REF!/Summary!#REF!*100 -> #REF! | G43: =Summary!#REF!/Summary!#REF!*100 -> #REF! | H43: =Summary!#REF!/Summary!#REF!*100 -> #REF! | I43: =Summary!#REF!/Summary!#REF!*100 -> #REF! | ... AI43: =Summary!#REF!/Summary!#REF!*100 -> #REF! | AJ43: =Summary!B15/Summary!B$14*100 -> 23.141435 | AK43: =Summary!C15/Summary!C$14*100 -> 23.733443 | AL43: =Summary!D15/Summary!D$14*100 -> 23.832955 | AM43: =Summary!E15/Summary!E$14*100 -> 23.47966 | AN43: =Summary!F15/Summary!F$14*100 -> 23.41497 | AO43: =Summary!G15/Summary!G$14*100 -> 22.874529 | AP43: =Summary!H15/Summary!H$14*100 -> 23.563422 | AQ43: =Summary!I15/Summary!I$14*100 -> 22.629999
A44: Industry | B44: =Summary!#REF!/Summary!#REF!*100 -> #REF! | C44: =Summary!#REF!/Summary!#REF!*100 -> #REF! | D44: =Summary!#REF!/Summary!#REF!*100 -> #REF! | E44: =Summary!#REF!/Summary!#REF!*100 -> #REF! | F44: =Summary!#REF!/Summary!#REF!*100 -> #REF! | G44: =Summary!#REF!/Summary!#REF!*100 -> #REF! | H44: =Summary!#REF!/Summary!#REF!*100 -> #REF! | I44: =Summary!#REF!/Summary!#REF!*100 -> #REF! | ... AI44: =Summary!#REF!/Summary!#REF!*100 -> #REF! | AJ44: =Summary!B16/Summary!B$14*100 -> 25.779841 | AK44: =Summary!C16/Summary!C$14*100 -> 26.337324 | AL44: =Summary!D16/Summary!D$14*100 -> 26.263783 | AM44: =Summary!E16/Summary!E$14*100 -> 25.615754 | AN44: =Summary!F16/Summary!F$14*100 -> 25.330982 | AO44: =Summary!G16/Summary!G$14*100 -> 25.297642 | AP44: =Summary!H16/Summary!H$14*100 -> 25.672472 | AQ44: =Summary!I16/Summary!I$14*100 -> 26.257305
A45: Services | B45: =Summary!#REF!/Summary!#REF!*100 -> #REF! | C45: =Summary!#REF!/Summary!#REF!*100 -> #REF! | D45: =Summary!#REF!/Summary!#REF!*100 -> #REF! | E45: =Summary!#REF!/Summary!#REF!*100 -> #REF! | F45: =Summary!#REF!/Summary!#REF!*100 -> #REF! | G45: =Summary!#REF!/Summary!#REF!*100 -> #REF! | H45: =Summary!#REF!/Summary!#REF!*100 -> #REF! | I45: =Summary!#REF!/Summary!#REF!*100 -> #REF! | ... AI45: =Summary!#REF!/Summary!#REF!*100 -> #REF! | AJ45: =Summary!B17/Summary!B$14*100 -> 43.950024 | AK45: =Summary!C17/Summary!C$14*100 -> 43.199067 | AL45: =Summary!D17/Summary!D$14*100 -> 42.77316 | AM45: =Summary!E17/Summary!E$14*100 -> 43.807962 | AN45: =Summary!F17/Summary!F$14*100 -> 44.144299 | AO45: =Summary!G17/Summary!G$14*100 -> 44.86476 | AP45: =Summary!H17/Summary!H$14*100 -> 44.055858 | AQ45: =Summary!I17/Summary!I$14*100 -> 44.273692
A46: Adjustments | Z46: 8.5
A47: Taxes on products | B47: =Summary!#REF!/Summary!#REF!*100 -> #REF! | C47: =Summary!#REF!/Summary!#REF!*100 -> #REF! | D47: =Summary!#REF!/Summary!#REF!*100 -> #REF! | E47: =Summary!#REF!/Summary!#REF!*100 -> #REF! | F47: =Summary!#REF!/Summary!#REF!*100 -> #REF! | G47: =Summary!#REF!/Summary!#REF!*100 -> #REF! | H47: =Summary!#REF!/Summary!#REF!*100 -> #REF! | I47: =Summary!#REF!/Summary!#REF!*100 -> #REF! | ... AI47: =Summary!#REF!/Summary!#REF!*100 -> #REF! | AJ47: =Summary!B19/Summary!B$14*100 -> 7.1286997 | AK47: =Summary!C19/Summary!C$14*100 -> 6.7301662 | AL47: =Summary!D19/Summary!D$14*100 -> 7.1301017 | AM47: =Summary!E19/Summary!E$14*100 -> 7.0966241 | AN47: =Summary!F19/Summary!F$14*100 -> 7.1097498 | AO47: =Summary!G19/Summary!G$14*100 -> 6.9630698 | AP47: =Summary!H19/Summary!H$14*100 -> 6.7082484 | AQ47: =Summary!I19/Summary!I$14*100 -> 6.8390047
A49: TREND CYCLE ESTIMATES
A50: GDP at market prices | B50: =Summary!#REF!/Summary!#REF!*100 -> #REF! | C50: =Summary!#REF!/Summary!#REF!*100 -> #REF! | D50: =Summary!#REF!/Summary!#REF!*100 -> #REF! | E50: =Summary!#REF!/Summary!#REF!*100 -> #REF! | F50: =Summary!#REF!/Summary!#REF!*100 -> #REF! | G50: =Summary!#REF!/Summary!#REF!*100 -> #REF! | H50: =Summary!#REF!/Summary!#REF!*100 -> #REF! | I50: =Summary!#REF!/Summary!#REF!*100 -> #REF! | J50: =Summary!#REF!/Summary!#REF!*100 -> #REF! | K50: =SUM(K51:K55) -> #REF! | L50: =SUM(L51:L55) -> #REF! | M50: =SUM(M51:M55) -> #REF! | N50: =SUM(N51:N55) -> #REF! | O50: =SUM(O51:O55) -> #REF! | P50: =SUM(P51:P55) -> #REF! | Q50: =SUM(Q51:Q55) -> #REF! | R50: =SUM(R51:R55) -> #REF! | ... AQ50: =SUM(AQ51:AQ55) -> 100
A51: Agriculture, Forestry & Fishing | B51: =Summary!#REF!/Summary!#REF!*100 -> #REF! | C51: =Summary!#REF!/Summary!#REF!*100 -> #REF! | D51: =Summary!#REF!/Summary!#REF!*100 -> #REF! | E51: =Summary!#REF!/Summary!#REF!*100 -> #REF! | F51: =Summary!#REF!/Summary!#REF!*100 -> #REF! | G51: =Summary!#REF!/Summary!#REF!*100 -> #REF! | H51: =Summary!#REF!/Summary!#REF!*100 -> #REF! | I51: =Summary!#REF!/Summary!#REF!*100 -> #REF! | ... AI51: =Summary!#REF!/Summary!#REF!*100 -> #REF! | AJ51: =Summary!B23/Summary!B$22*100 -> 23.502272 | AK51: =Summary!C23/Summary!C$22*100 -> 23.4045 | AL51: =Summary!D23/Summary!D$22*100 -> 23.39984 | AM51: =Summary!E23/Summary!E$22*100 -> 23.28027 | AN51: =Summary!F23/Summary!F$22*100 -> 23.053691 | AO51: =Summary!G23/Summary!G$22*100 -> 22.83319 | AP51: =Summary!H23/Summary!H$22*100 -> 22.766725 | AQ51: =Summary!I23/Summary!I$22*100 -> 22.673161
A52: Industry | B52: =Summary!#REF!/Summary!#REF!*100 -> #REF! | C52: =Summary!#REF!/Summary!#REF!*100 -> #REF! | D52: =Summary!#REF!/Summary!#REF!*100 -> #REF! | E52: =Summary!#REF!/Summary!#REF!*100 -> #REF! | F52: =Summary!#REF!/Summary!#REF!*100 -> #REF! | G52: =Summary!#REF!/Summary!#REF!*100 -> #REF! | H52: =Summary!#REF!/Summary!#REF!*100 -> #REF! | I52: =Summary!#REF!/Summary!#REF!*100 -> #REF! | ... AI52: =Summary!#REF!/Summary!#REF!*100 -> #REF! | AJ52: =Summary!B24/Summary!B$22*100 -> 25.662646 | AK52: =Summary!C24/Summary!C$22*100 -> 26.314794 | AL52: =Summary!D24/Summary!D$22*100 -> 26.294894 | AM52: =Summary!E24/Summary!E$22*100 -> 25.801678 | AN52: =Summary!F24/Summary!F$22*100 -> 25.373029 | AO52: =Summary!G24/Summary!G$22*100 -> 25.458684 | AP52: =Summary!H24/Summary!H$22*100 -> 25.865434 | AQ52: =Summary!I24/Summary!I$22*100 -> 26.142999
A53: Services | B53: =Summary!#REF!/Summary!#REF!*100 -> #REF! | C53: =Summary!#REF!/Summary!#REF!*100 -> #REF! | D53: =Summary!#REF!/Summary!#REF!*100 -> #REF! | E53: =Summary!#REF!/Summary!#REF!*100 -> #REF! | F53: =Summary!#REF!/Summary!#REF!*100 -> #REF! | G53: =Summary!#REF!/Summary!#REF!*100 -> #REF! | H53: =Summary!#REF!/Summary!#REF!*100 -> #REF! | I53: =Summary!#REF!/Summary!#REF!*100 -> #REF! | ... AI53: =Summary!#REF!/Summary!#REF!*100 -> #REF! | AJ53: =Summary!B25/Summary!B$22*100 -> 43.795718 | AK53: =Summary!C25/Summary!C$22*100 -> 43.174765 | AL53: =Summary!D25/Summary!D$22*100 -> 43.180224 | AM53: =Summary!E25/Summary!E$22*100 -> 43.760868 | AN53: =Summary!F25/Summary!F$22*100 -> 44.464658 | AO53: =Summary!G25/Summary!G$22*100 -> 44.742364 | AP53: =Summary!H25/Summary!H$22*100 -> 44.537722 | AQ53: =Summary!I25/Summary!I$22*100 -> 44.426198
A54: Adjustments
A55: Taxes on products | B55: =Summary!#REF!/Summary!#REF!*100 -> #REF! | C55: =Summary!#REF!/Summary!#REF!*100 -> #REF! | D55: =Summary!#REF!/Summary!#REF!*100 -> #REF! | E55: =Summary!#REF!/Summary!#REF!*100 -> #REF! | F55: =Summary!#REF!/Summary!#REF!*100 -> #REF! | G55: =Summary!#REF!/Summary!#REF!*100 -> #REF! | H55: =Summary!#REF!/Summary!#REF!*100 -> #REF! | I55: =Summary!#REF!/Summary!#REF!*100 -> #REF! | ... AI55: =Summary!#REF!/Summary!#REF!*100 -> #REF! | AJ55: =Summary!B27/Summary!B$22*100 -> 7.039364 | AK55: =Summary!C27/Summary!C$22*100 -> 7.1059405 | AL55: =Summary!D27/Summary!D$22*100 -> 7.1250412 | AM55: =Summary!E27/Summary!E$22*100 -> 7.1571833 | AN55: =Summary!F27/Summary!F$22*100 -> 7.1086221 | AO55: =Summary!G27/Summary!G$22*100 -> 6.965761 | AP55: =Summary!H27/Summary!H$22*100 -> 6.8301193 | AQ55: =Summary!I27/Summary!I$22*100 -> 6.7576422
A56: Uganda Bureau of Statistics

Sheet Original_VA
A1: Table 3: ORIGINAL UNADJUSTED Value Added by activity at constant 2016/17 prices, BILLION SHILLINGS, 2016/17-2025/26
A3: Year | B3: 2016/17 | F3: 2017/18 | J3: 2018/19 | N3: 2019/20 | R3: 2020/21 | V3: 2021/22 | Z3: 2022/23 | AD3: 2023/24 | AH3: 2024/25 | AL3: 2025/26
A4: Period | B4: Q1 | C4: Q2 | D4: Q3 | E4: Q4 | F4: Q1 | G4: Q2 | H4: Q3 | I4: Q4 | J4: Q1 | K4: Q2 | L4: Q3 | M4: Q4 | N4: Q1 | O4: Q2 | P4: Q3 | Q4: Q4 | R4: Q1 | S4: Q2 | T4: Q3 | U4: Q4 | V4: Q1 | W4: Q2 | X4: Q3 | Y4: Q4 | Z4: Q1 | AA4: Q2 | AB4: Q3 | AC4: Q4 | AD4: Q1 | AE4: Q2 | AF4: Q3 | AG4: Q4 | AH4: Q1 | AI4: Q2 | AJ4: Q3 | AK4: Q4 | AL4: Q1 | AM4: Q2
A5: GDP AT MARKET PRICES | B5: 28577.247 | C5: 26610.18 | D5: 26240.178 | E5: 27090.435 | F5: 30772.237 | G5: 28335.28 | H5: 27653.331 | I5: 28598.087 | J5: 32487.642 | K5: 29958.631 | L5: 29773.235 | M5: 30567.095 | N5: 34943.779 | O5: 32466.458 | P5: 30130.072 | Q5: 28870.102 | R5: 34802.923 | S5: 32477.008 | T5: 30975.024 | U5: 32626.063 | V5: 35622.436 | W5: 34024.49 | X5: 32716.662 | Y5: 34522.28 | Z5: 38746.737 | AA5: 35492.013 | AB5: 33446.228 | AC5: 36506.452 | AD5: 41068.072 | AE5: 37544.31 | AF5: 35728.791 | AG5: 38581.884 | AH5: 43605.836 | AI5: 39557.991 | AJ5: 38727.987 | AK5: 40714.044 | AL5: 45718.884 | AM5: 42903.876
A6: AGRICULTURE,FORESTRY&FISHING | B6: 8012.3898 | C6: 6110.5575 | D6: 5359.3298 | E6: 5974.7915 | F6: 8783.7536 | G6: 6199.5724 | H6: 5495.0897 | I6: 6096.0101 | J6: 8974.6097 | K6: 6448.4413 | L6: 5935.2774 | M6: 6628.7289 | N6: 9517.4185 | O6: 6941.2508 | P6: 5858.4835 | Q6: 7019.6669 | R6: 10178.838 | S6: 7480.0514 | T6: 5874.7257 | U6: 7070.5839 | V6: 10624.95 | W6: 7330.892 | X6: 6120.4467 | Y6: 7804.9868 | Z6: 11088.263 | AA6: 8197.4364 | AB6: 6452.1008 | AC6: 7589.8403 | AD6: 11715.27 | AE6: 8365.8311 | AF6: 6712.9791 | AG6: 8392.5624 | AH6: 12457.04 | AI6: 9018.0558 | AJ6: 7404.8569 | AK6: 8683.3829 | AL6: 12839.64 | AM6: 9809.0589
A7: Cash crops | B7: 503.80349 | C7: 751.47235 | D7: 756.6638 | E7: 540.01006 | F7: 711.49019 | G7: 721.04285 | H7: 772.20685 | I7: 498.20843 | J7: 708.23323 | K7: 768.35837 | L7: 790.47225 | M7: 563.82244 | N7: 726.02296 | O7: 837.1285 | P7: 928.12524 | Q7: 560.87771 | R7: 782.35957 | S7: 933.39018 | T7: 1033.3276 | U7: 683.9495 | V7: 965.22972 | W7: 980.0504 | X7: 993.72889 | Y7: 688.45779 | Z7: 969.15812 | AA7: 928.29383 | AB7: 1072.7337 | AC7: 681.86824 | AD7: 1030.9453 | AE7: 1070.8634 | AF7: 1245.7712 | AG7: 753.11773 | AH7: 1200.8309 | AI7: 1173.3745 | AJ7: 1357.3298 | AK7: 833.80664 | AL7: 1285.3573 | AM7: 1320.8624
A8: Food crops | B8: 5158.2444 | C8: 2956.6065 | D8: 2216.3688 | E8: 3063.7253 | F8: 5764.4524 | G8: 3189.0326 | H8: 2406.5075 | I8: 3180.2595 | J8: 5806.2349 | K8: 3120.4628 | L8: 2491.5732 | M8: 3355.7462 | N8: 6087.3682 | O8: 3386.3637 | P8: 2210.2087 | Q8: 3770.8716 | R8: 6729.3932 | S8: 3733.7504 | T8: 2032.2914 | U8: 3595.1715 | V8: 6847.8466 | W8: 3553.494 | X8: 2141.0816 | Y8: 4113.2181 | Z8: 7367.019 | AA8: 4243.1851 | AB8: 2047.1733 | AC8: 3777.0373 | AD8: 7740.0659 | AE8: 4232.3299 | AF8: 2190.283 | AG8: 4166.6736 | AH8: 8152.8624 | AI8: 4529.7878 | AJ8: 2262.5053 | AK8: 4257.0001 | AL8: 8108.2689 | AM8: 4878.8645
A9: Livestock | B9: 803.94776 | C9: 820.59322 | D9: 836.92932 | E9: 847.61996 | F9: 869.7722 | G9: 875.22137 | H9: 895.75739 | I9: 904.19998 | J9: 927.06886 | K9: 942.41424 | L9: 958.71971 | M9: 977.13017 | N9: 999.62611 | O9: 1016.5699 | P9: 1037.6779 | Q9: 1051.9475 | R9: 1075.0903 | S9: 1093.5814 | T9: 1117.645 | U9: 1139.3805 | V9: 1164.9148 | W9: 1183.7106 | X9: 1209.2184 | Y9: 1235.4276 | Z9: 1266.6927 | AA9: 1289.0045 | AB9: 1324.7443 | AC9: 1336.3725 | AD9: 1364.9638 | AE9: 1392.5445 | AF9: 1421.1592 | AG9: 1449.5255 | AH9: 1480.2991 | AI9: 1512.2661 | AJ9: 1550.6613 | AK9: 1577.5316 | AL9: 1617.3459 | AM9: 1651.731
A10: Agriculture Support Services | B10: 6.2837288 | C10: 3.325037 | D10: 2.0494802 | E10: 4.8141938 | F10: 6.2956095 | G10: 3.2755887 | H10: 2.0080248 | I10: 4.8329083 | J10: 6.6083068 | K10: 3.5884171 | L10: 2.1829168 | M10: 5.4791027 | N10: 7.7829336 | O10: 4.3860543 | P10: 2.1540787 | Q10: 4.6823231 | R10: 7.2284747 | S10: 3.9801091 | T10: 2.7383126 | U10: 5.4484674 | V10: 7.7592654 | W10: 4.0780685 | X10: 2.8418931 | Y10: 5.5823033 | Z10: 7.9640725 | AA10: 4.2517334 | AB10: 2.8588657 | AC10: 5.6398941 | AD10: 8.3887802 | AE10: 4.5610538 | AF10: 3.0962641 | AG10: 6.1329907 | AH10: 8.7481039 | AI10: 4.4104034 | AJ10: 3.0707098 | AK10: 7.1536239 | AL10: 7.7163285 | AM10: 4.4194806
A11: Forestry | B11: 977.93029 | C11: 992.65352 | D11: 1004.7215 | E11: 1027.2691 | F11: 1007.3811 | G11: 1003.7501 | H11: 1044.0648 | I11: 1082.2855 | J11: 1044.1093 | K11: 1056.6287 | L11: 1070.8268 | M11: 1114.9791 | N11: 1086.4176 | O11: 1108.061 | P11: 1120.3878 | Q11: 1111.3554 | R11: 1056.878 | S11: 1149.2585 | T11: 1181.6024 | U11: 1168.9939 | V11: 1107.6165 | W11: 1115.7609 | X11: 1243.7005 | Y11: 1233.5857 | Z11: 1152.8066 | AA11: 1158.8936 | AB11: 1275.3325 | AC11: 1260.9317 | AD11: 1214.7921 | AE11: 1190.4314 | AF11: 1200.1467 | AG11: 1391.5844 | AH11: 1260.4901 | AI11: 1251.7752 | AJ11: 1287.4128 | AK11: 1362.3897 | AL11: 1383.2163 | AM11: 1355.0945
A12: Fishing | B12: 562.18016 | C12: 585.90691 | D12: 542.59683 | E12: 491.35281 | F12: 424.36218 | G12: 407.24998 | H12: 374.54516 | I12: 426.22385 | J12: 482.35514 | K12: 556.98883 | L12: 621.50255 | M12: 611.57191 | N12: 610.20066 | O12: 588.74175 | P12: 559.92985 | Q12: 519.93242 | R12: 527.88856 | S12: 566.09095 | T12: 507.12106 | U12: 477.64002 | V12: 531.58287 | W12: 493.79799 | X12: 529.87529 | Y12: 528.71517 | Z12: 324.62227 | AA12: 573.80759 | AB12: 729.25809 | AC12: 527.99078 | AD12: 356.11407 | AE12: 475.10096 | AF12: 652.52279 | AG12: 625.52817 | AH12: 353.80898 | AI12: 546.44166 | AJ12: 943.87711 | AK12: 645.50127 | AL12: 437.73547 | AM12: 598.08703
A13: INDUSTRY | B13: 6768.7131 | C13: 7106.8656 | D13: 7305.421 | E13: 7067.3259 | F13: 7134.9059 | G13: 7312.6318 | H13: 7537.2021 | I13: 7631.5343 | J13: 7779.6918 | K13: 8068.1838 | L13: 8243.5123 | M13: 8201.8824 | N13: 8570.2406 | O13: 8886.3356 | P13: 8486.7958 | Q13: 7398.8511 | R13: 8381.1058 | S13: 8755.7883 | T13: 8669.0779 | U13: 8693.4802 | V13: 8370.9467 | W13: 9440.8925 | X13: 9148.3498 | Y13: 9308.0376 | Z13: 9399.6503 | AA13: 9216.6242 | AB13: 9213.4013 | AC13: 9899.9765 | AD13: 10329.779 | AE13: 9629.9206 | AF13: 9832.8272 | AG13: 10008.679 | AH13: 10858.986 | AI13: 10366.745 | AJ13: 10560.436 | AK13: 10766.195 | AL13: 11507.782 | AM13: 11637.499
A14: Mining & quarrying | B14: 282.95293 | C14: 276.59929 | D14: 375.75679 | E14: 401.80833 | F14: 319.7555 | G14: 224.76187 | H14: 339.81152 | I14: 399.51644 | J14: 397.45267 | K14: 270.96658 | L14: 456.76541 | M14: 382.76325 | N14: 454.84011 | O14: 474.18067 | P14: 511.09849 | Q14: 317.00352 | R14: 645.34983 | S14: 468.64606 | T14: 394.79031 | U14: 370.03532 | V14: 281.63209 | W14: 699.91945 | X14: 555.65764 | Y14: 685.74265 | Z14: 531.92636 | AA14: 337.30454 | AB14: 418.13259 | AC14: 1047.8039 | AD14: 1057.992 | AE14: 661.67504 | AF14: 435.10339 | AG14: 254.56755 | AH14: 967.23315 | AI14: 725.91079 | AJ14: 433.19398 | AK14: 365.58098 | AL14: 866.42074 | AM14: 924.2791
A15: Manufacturing | B15: 4040.705 | C15: 4238.5858 | D15: 4435.5484 | E15: 4130.4121 | F15: 4261.464 | G15: 4439.8418 | H15: 4503.4215 | I15: 4419.5601 | J15: 4561.6635 | K15: 4852.9223 | L15: 4835.1147 | M15: 4731.8722 | N15: 5096.6336 | O15: 5278.1396 | P15: 4784.5996 | Q15: 4060.5317 | R15: 4909.3533 | S15: 5000.3958 | T15: 4890.4733 | U15: 4843.5145 | V15: 4617.2239 | W15: 5323.9039 | X15: 5273.5154 | Y15: 5182.5961 | Z15: 5339.1513 | AA15: 5395.2734 | AB15: 5202.2022 | AC15: 5098.4633 | AD15: 5590.3484 | AE15: 5307.7672 | AF15: 5461.8901 | AG15: 5659.4204 | AH15: 5935.8741 | AI15: 5719.2052 | AJ15: 5747.7099 | AK15: 5854.8503 | AL15: 6218.0588 | AM15: 6229.6419
A16: Electricity | B16: 330.50837 | C16: 338.39281 | D16: 360.04769 | E16: 350.52748 | F16: 365.87468 | G16: 364.64894 | H16: 366.75833 | I16: 356.45256 | J16: 365.71697 | K16: 363.9283 | L16: 374.53323 | M16: 385.58107 | N16: 410.67753 | O16: 420.90578 | P16: 438.26559 | Q16: 382.38906 | R16: 446.83511 | S16: 458.60371 | T16: 470.86524 | U16: 468.11348 | V16: 469.51958 | W16: 473.62344 | X16: 480.90714 | Y16: 478.24728 | Z16: 498.13323 | AA16: 511.1819 | AB16: 524.08967 | AC16: 529.54458 | AD16: 557.4673 | AE16: 553.71387 | AF16: 569.86152 | AG16: 565.92799 | AH16: 593.4025 | AI16: 611.79592 | AJ16: 646.30896 | AK16: 661.7343 | AL16: 749.36438 | AM16: 677.86404
... A33: Activities of Households | B33: 220.43437 | C33: 222.05653 | D33: 223.6473 | E33: 225.21208 | F33: 226.75658 | G33: 228.3158 | H33: 229.88331 | I33: 231.46596 | J33: 233.07033 | K33: 234.68168 | L33: 236.29337 | M33: 237.91141 | N33: 239.54242 | O33: 241.1751 | P33: 242.80326 | Q33: 244.43246 | R33: 246.06921 | S33: 247.72055 | T33: 249.44396 | U33: 251.18214 | V33: 252.87801 | W33: 254.57335 | X33: 256.32765 | Y33: 258.08109 | Z33: 259.77441 | AA33: 261.48299 | AB33: 263.3354 | AC33: 265.20368 | AD33: 266.95973 | AE33: 268.7154 | AF33: 270.60323 | AG33: 272.49078 | AH33: 274.24576 | AI33: 276.01332 | AJ33: 278.0007 | AK33: 280.00154 | AL33: 281.80886 | AM33: 281.80886
A35: ADJUSTMENTS
A36: Taxes on products | B36: 1858.4261 | C36: 1817.8528 | D36: 1948.6611 | E36: 2005.691 | F36: 1991.2744 | G36: 2007.8887 | H36: 1935.7403 | I36: 2033.1747 | J36: 1979.1119 | K36: 2073.2514 | L36: 2129.377 | M36: 2135.7379 | N36: 2197.3365 | O36: 2270.9524 | P36: 2114.9878 | Q36: 1601.8521 | R36: 2123.5437 | S36: 2166.7043 | T36: 2039.8093 | U36: 2366.598 | V36: 2087.3237 | W36: 2349.8691 | X36: 2484.895 | Y36: 2428.7012 | Z36: 2459.0041 | AA36: 2470.6617 | AB36: 2587.0261 | AC36: 2698.9015 | AD36: 2801.1416 | AE36: 2642.3794 | AF36: 2764.0558 | AG36: 2801.4262 | AH36: 3096.8575 | AI36: 2889.5255 | AJ36: 2914.9594 | AK36: 3024.8849 | AL36: 3200.5564 | AM36: 3095.8858
A37: Source: Uganda Bureau of Statistics

Sheet Original_Growth
A1: Table 4: ORIGINAL UNADJUSTED Value Added at constant 2016/17 prices, PERCENTAGE CHANGE, 2016/17-2025/26
B3: 2016/17 | F3: 2017/18 | J3: 2018/19 | N3: 2019/20 | R3: 2020/21 | V3: 2021/22 | Z3: 2022/23 | AD3: 2023/24 | AH3: 2024/25 | AL3: 2025/26
B4: Q1 | C4: Q2 | D4: Q3 | E4: Q4 | F4: Q1 | G4: Q2 | H4: Q3 | I4: Q4 | J4: Q1 | K4: Q2 | L4: Q3 | M4: Q4 | N4: Q1 | O4: Q2 | P4: Q3 | Q4: Q4 | R4: Q1 | S4: Q2 | T4: Q3 | U4: Q4 | V4: Q1 | W4: Q2 | X4: Q3 | Y4: Q4 | Z4: Q1 | AA4: Q2 | AB4: Q3 | AC4: Q4 | AD4: Q1 | AE4: Q2 | AF4: Q3 | AG4: Q4 | AH4: Q1 | AI4: Q2 | AJ4: Q3 | AK4: Q4 | AL4: Q1 | AM4: Q2
A5: GDP AT MARKET PRICES | B5: -0.26122599 | C5: 0.50756396 | D5: 6.7464548 | E5: 6.1811727 | F5: 7.6808998 | G5: 6.4828574 | H5: 5.3854549 | I5: 5.5652552 | J5: 5.5745218 | K5: 5.7290794 | L5: 7.6659989 | M5: 6.8851035 | N5: 7.5602194 | O5: 8.3709675 | P5: 1.1985158 | Q5: -5.5516965 | R5: -0.40309239 | S5: 0.032495737 | T5: 2.804345 | U5: 13.009861 | V5: 2.354724 | W5: 4.7648514 | X5: 5.6227189 | Y5: 5.811971 | Z5: 8.7705981 | AA5: 4.3131379 | AB5: 2.2299523 | AC5: 5.7475112 | AD5: 5.9910476 | AE5: 5.7824205 | AF5: 6.8245768 | AG5: 5.6851104 | AH5: 6.1794064 | AI5: 5.3634777 | AJ5: 8.394339 | AK5: 5.5263248 | AL5: 4.8457919 | AM5: 8.4581777
A6: AGRICULTURE,FORESTRY&FISHING | B6: 1.1733408 | C6: 3.2296506 | D6: 1.0636812 | E6: 6.0861995 | F6: 9.6271373 | G6: 1.4567401 | H6: 2.5331515 | I6: 2.0288347 | J6: 2.172831 | K6: 4.0142917 | L6: 8.010565 | M6: 8.7388102 | N6: 6.0482714 | O6: 7.6423041 | P6: -1.2938559 | Q6: 5.8976315 | R6: 6.9495696 | S6: 7.7622984 | T6: 0.27724211 | U6: 0.72534795 | V6: 4.382736 | W6: -1.9940967 | X6: 4.1826802 | Y6: 10.386736 | Z6: 4.3606145 | AA6: 11.82045 | AB6: 5.4187897 | AC6: -2.7565253 | AD6: 5.654692 | AE6: 2.0542364 | AF6: 4.0433085 | AG6: 10.57627 | AH6: 6.331648 | AI6: 7.796292 | AJ6: 10.306569 | AK6: 3.4652179 | AL6: 3.0713611 | AM6: 8.7713266
A7: Cash crops | B7: -16.007927 | C7: 23.751211 | D7: 12.020404 | E7: 19.986916 | F7: 41.223752 | G7: -4.0493176 | H7: 2.0541554 | I7: -7.7408987 | J7: -0.45776578 | K7: 6.5620954 | L7: 2.36535 | M7: 13.169991 | N7: 2.5118453 | O7: 8.9502677 | P7: 17.41402 | Q7: -0.52227954 | R7: 7.7596194 | S7: 11.499033 | T7: 11.334927 | U7: 21.942714 | V7: 23.374182 | W7: 4.9990053 | X7: -3.8321506 | Y7: 0.65915566 | Z7: 0.4069914 | AA7: -5.2810114 | AB7: 7.9503397 | AC7: -0.95714691 | AD7: 6.3753418 | AE7: 15.358235 | AF7: 16.13052 | AG7: 10.449158 | AH7: 16.47863 | AI7: 9.5727556 | AJ7: 8.954976 | AK7: 10.713984 | AL7: 7.0389932 | AM7: 12.569547
A8: Food crops | B8: 1.7376881 | C8: -3.4995387 | D8: 6.1821644 | E8: 6.4109612 | F8: 11.752214 | G8: 7.8612466 | H8: 8.578837 | I8: 3.8036746 | J8: 0.72483173 | K8: -2.1501749 | L8: 3.5348213 | M8: 5.5179991 | N8: 4.8419209 | O8: 8.5211992 | P8: -11.292646 | Q8: 12.370584 | R8: 10.54684 | S8: 10.2584 | T8: -8.0497943 | U8: -4.6594018 | V8: 1.7602391 | W8: -4.8277555 | X8: 5.3530803 | Y8: 14.409511 | Z8: 7.5815419 | AA8: 19.408815 | AB8: -4.386021 | AC8: -8.1731832 | AD8: 5.0637427 | AE8: -0.25582669 | AF8: 6.9905976 | AG8: 10.315924 | AH8: 5.3332431 | AI8: 7.0282315 | AJ8: 3.2973958 | AK8: 2.167834 | AL8: -0.5469674 | AM8: 7.7062476
A9: Livestock | B9: 5.6220551 | C9: 7.3369226 | D9: 8.0046056 | E9: 7.0651484 | F9: 8.1876515 | G9: 6.6571546 | H9: 7.0290372 | I9: 6.6751637 | J9: 6.5875482 | K9: 7.677242 | L9: 7.0289477 | M9: 8.065715 | N9: 7.8265223 | O9: 7.8686926 | P9: 8.2357916 | Q9: 7.6568416 | R9: 7.5492368 | S9: 7.5756165 | T9: 7.7063501 | U9: 8.311535 | V9: 8.3550688 | W9: 8.2416626 | X9: 8.1934317 | Y9: 8.4297719 | Z9: 8.7369443 | AA9: 8.8952394 | AB9: 9.5537611 | AC9: 8.1708417 | AD9: 7.7580832 | AE9: 8.032551 | AF9: 7.2780032 | AG9: 8.46718 | AH9: 8.4496924 | AI9: 8.5973316 | AJ9: 9.1124298 | AK9: 8.8308919 | AL9: 9.2580536 | AM9: 9.2222406
A10: Agriculture Support Services | B10: 1.7603391 | C10: 5.0997732 | D10: 4.9594275 | E10: 5.1449869 | F10: 0.18907177 | G10: -1.4871507 | H10: -2.0227286 | I10: 0.38873457 | J10: 4.9669107 | K10: 9.5502966 | L10: 8.709657 | M10: 13.370715 | N10: 17.775003 | O10: 22.228107 | P10: -1.3210824 | Q10: -14.542154 | R10: -7.1240347 | S10: -9.255361 | T10: 27.122216 | U10: 16.362482 | V10: 7.3430525 | W10: 2.4612239 | X10: 3.7826391 | Y10: 2.4563964 | Z10: 2.6395159 | AA10: 4.2585086 | AB10: 0.59723142 | AC10: 1.0316667 | AD10: 5.3327958 | AE10: 7.2751607 | AF10: 8.3039338 | AG10: 8.7430127 | AH10: 4.2833839 | AI10: -3.3029737 | AJ10: -0.82532569 | AK10: 16.641687 | AL10: -11.794275 | AM10: 0.20581178
A11: Forestry | B11: 9.2270813 | C11: 12.389945 | D11: -13.360354 | E11: 10.596833 | F11: 3.0115427 | G11: 1.1178658 | H11: 3.9158384 | I11: 5.3555936 | J11: 3.645907 | K11: 5.2681081 | L11: 2.5632508 | M11: 3.0207938 | N11: 4.0520984 | O11: 4.8675828 | P11: 4.6282912 | Q11: -0.32500304 | R11: -2.7189866 | S11: 3.7179826 | T11: 5.4636969 | U11: 5.186329 | V11: 4.8007818 | W11: -2.9147167 | X11: 5.2554205 | Y11: 5.5254169 | Z11: 4.0799476 | AA11: 3.8657717 | AB11: 2.5433767 | AC11: 2.2167842 | AD11: 5.376921 | AE11: 2.7213663 | AF11: -5.8953936 | AG11: 10.3616 | AH11: 3.761795 | AI11: 5.153076 | AJ11: 7.271286 | AK11: -2.0979444 | AL11: 9.7363837 | AM11: 8.2538254
A12: Fishing | B12: -4.204575 | C12: -1.9275876 | D12: -10.109137 | E12: -14.947848 | F12: -24.514914 | G12: -30.492374 | H12: -30.971737 | I12: -13.25503 | J12: 13.665911 | K12: 36.768289 | L12: 65.935276 | M12: 43.486083 | N12: 26.504438 | O12: 5.7008185 | P12: -9.9070707 | Q12: -14.984255 | R12: -13.489349 | S12: -3.8473233 | T12: -9.4313234 | U12: -8.1342105 | V12: 0.69982751 | W12: -12.770556 | X12: 4.4869431 | Y12: 10.69323 | Z12: -38.932895 | AA12: 16.202901 | AB12: 37.628249 | AC12: -0.13700969 | AD12: 9.7010594 | AE12: -17.202043 | AF12: -10.522378 | AG12: 18.473315 | AH12: -0.64729068 | AI12: 15.015903 | AJ12: 44.650443 | AK12: 3.1929969 | AL12: 23.72085 | AM12: 9.4512128
A13: INDUSTRY | B13: -0.60233732 | C13: 4.5995317 | D13: 16.225662 | E13: 7.9277803 | F13: 5.4100804 | G13: 2.8953153 | H13: 3.1727275 | I13: 7.983336 | J13: 9.0370626 | K13: 10.33215 | L13: 9.3709856 | M13: 7.4735698 | N13: 10.161699 | O13: 10.14047 | P13: 2.9512124 | Q13: -9.7908167 | R13: -2.2068791 | S13: -1.4690787 | T13: 2.1478318 | U13: 17.497705 | V13: -0.121214 | W13: 7.8245859 | X13: 5.5285218 | Y13: 7.0691761 | Z13: 12.288976 | AA13: -2.3754988 | AB13: 0.71107424 | AC13: 6.3594382 | AD13: 9.8953589 | AE13: 4.4842493 | AF13: 6.7230965 | AG13: 1.0980079 | AH13: 5.1231152 | AI13: 7.6514026 | AJ13: 7.3997957 | AK13: 7.5685941 | AL13: 5.9747366 | AM13: 12.257991
A14: Mining & quarrying | B14: -1.0176412 | C14: 27.163369 | D14: 42.921379 | E14: 66.601672 | F14: 13.006608 | G14: -18.740982 | H14: -9.5661008 | I14: -0.57039491 | J14: 24.298931 | K14: 20.557187 | L14: 34.417285 | M14: -4.1933679 | N14: 14.438809 | O14: 74.995995 | P14: 11.895181 | Q14: -17.180262 | R14: 41.884989 | S14: -1.1671934 | T14: -22.75651 | U14: 16.729088 | V14: -56.35978 | W14: 49.349266 | X14: 40.747538 | Y14: 85.318163 | Z14: 88.87278 | AA14: -51.808093 | AB14: -24.749961 | AC14: 52.798407 | AD14: 98.898205 | AE14: 96.165475 | AF14: 4.0587122 | AG14: -75.704656 | AH14: -8.5784039 | AI14: 9.7080505 | AJ14: -0.43884077 | AK14: 43.608635 | AL14: -10.422763 | AM14: 27.326816
A15: Manufacturing | B15: -5.7702586 | C15: -0.1731616 | D15: 19.811423 | E15: 2.5311368 | F15: 5.4633796 | G15: 4.7481879 | H15: 1.5302076 | I15: 7.0004646 | J15: 7.0445137 | K15: 9.3039472 | L15: 7.3653602 | M15: 7.0665881 | N15: 11.727523 | O15: 8.7620878 | P15: -1.0447553 | Q15: -14.187631 | R15: -3.6745882 | S15: -5.2621545 | T15: 2.2128016 | U15: 19.282766 | V15: -5.9504663 | W15: 6.4696502 | X15: 7.8324133 | Y15: 7.0007348 | Z15: 15.63553 | AA15: 1.340548 | AB15: -1.3522881 | AC15: -1.6233706 | AD15: 4.7048134 | AE15: -1.6219041 | AF15: 4.9918833 | AG15: 11.002473 | AH15: 6.180753 | AI15: 7.7516204 | AJ15: 5.2329828 | AK15: 3.4531782 | AL15: 4.7538875 | AM15: 8.9249589
A16: Electricity | B16: 6.141503 | C16: 9.4323279 | D16: 14.545286 | E16: 9.0047431 | F16: 10.700578 | G16: 7.7590666 | H16: 1.8638188 | I16: 1.6903329 | J16: -0.043102909 | K16: -0.19762631 | L16: 2.1198978 | M16: 8.1717764 | N16: 12.293811 | O16: 15.65624 | P16: 17.016475 | Q16: -0.82784518 | R16: 8.8043734 | S16: 8.9563825 | T16: 7.4383342 | U16: 22.418117 | V16: 5.076699 | W16: 3.2750999 | X16: 2.1326469 | Y16: 2.1648167 | Z16: 6.0942389 | AA16: 7.9300241 | AB16: 8.9793904 | AC16: 10.726104 | AD16: 11.911286 | AE16: 8.3203213 | AF16: 8.7335926 | AG16: 6.8706984 | AH16: 6.4461531 | AI16: 10.489541 | AJ16: 13.415091 | AK16: 16.929063 | AL16: 26.282647 | AM16: 10.799047
... A33: Activities of Households | B33: 2.6609965 | C33: 2.8320844 | D33: 2.924144 | E33: 2.936326 | F33: 2.8680716 | G33: 2.818773 | H33: 2.7883234 | I33: 2.776886 | J33: 2.7843704 | K33: 2.7881906 | L33: 2.7883971 | M33: 2.7846182 | N33: 2.776885 | O33: 2.7669055 | P33: 2.7550021 | Q33: 2.7409598 | R33: 2.7246889 | S33: 2.7139813 | T33: 2.7350163 | U33: 2.7613682 | V33: 2.767027 | W33: 2.7663441 | X33: 2.7596131 | Y33: 2.7465927 | Z33: 2.7271632 | AA33: 2.7142034 | AB33: 2.7339014 | AC33: 2.7598254 | AD33: 2.7659861 | AE33: 2.7659177 | AF33: 2.759914 | AG33: 2.7477363 | AH33: 2.729262 | AI33: 2.7158552 | AJ33: 2.7336983 | AK33: 2.7563359 | AL33: 2.7577825 | AM33: 2.0997339
A35: ADJUSTMENTS
A36: Taxes on products | B36: 10.604422 | C36: 4.5985732 | D36: 17.953651 | E36: 10.804192 | F36: 7.14843 | G36: 10.453864 | H36: -0.66306097 | I36: 1.3702884 | J36: -0.61078727 | K36: 3.2552983 | L36: 10.00324 | M36: 5.0444829 | N36: 11.026391 | O36: 9.535794 | P36: -0.67574802 | Q36: -24.997721 | R36: -3.3582876 | S36: -4.5905031 | T36: -3.5545582 | U36: 47.741356 | V36: -1.7056382 | W36: 8.453615 | X36: 21.819967 | Y36: 2.6241571 | Z36: 17.806552 | AA36: 5.1403958 | AB36: 4.1100754 | AC36: 11.125298 | AD36: 13.913662 | AE36: 6.9502737 | AF36: 6.8429801 | AG36: 3.7987589 | AH36: 10.556979 | AI36: 9.3531628 | AJ36: 5.4594994 | AK36: 7.9766044 | AL36: 3.3485178 | AM36: 7.1416697
A37: Source: Uganda Bureau of Statistics

Sheet Original_IPD
A1: Table 5: ORIGINAL UNADJUSTED Value Added by activity at constant 2016/17 prices, IMPLICIT PRICE DEFLATORS, 2016/17-2025/26
B3: 2016/17 | F3: 2017/18 | J3: 2018/19 | N3: 2019/20 | R3: 2020/21 | V3: 2021/22 | Z3: 2022/23 | AD3: 2023/24 | AH3: 2024/25 | AL3: 2025/26
B4: Q1 | C4: Q2 | D4: Q3 | E4: Q4 | F4: Q1 | G4: Q2 | H4: Q3 | I4: Q4 | J4: Q1 | K4: Q2 | L4: Q3 | M4: Q4 | N4: Q1 | O4: Q2 | P4: Q3 | Q4: Q4 | R4: Q1 | S4: Q2 | T4: Q3 | U4: Q4 | V4: Q1 | W4: Q2 | X4: Q3 | Y4: Q4 | Z4: Q1 | AA4: Q2 | AB4: Q3 | AC4: Q4 | AD4: Q1 | AE4: Q2 | AF4: Q3 | AG4: Q4 | AH4: Q1 | AI4: Q2 | AJ4: Q3 | AK4: Q4 | AL4: Q1 | AM4: Q2
A5: GDP AT MARKET PRICES | B5: 97.215836 | C5: 99.79734 | D5: 101.85497 | E5: 101.33928 | F5: 102.26658 | G5: 100.32084 | H5: 106.43321 | I5: 108.94625 | J5: 105.17889 | K5: 107.41318 | L5: 108.25572 | M5: 109.62404 | N5: 108.59653 | O5: 112.11937 | P5: 111.87089 | Q5: 109.5713 | R5: 111.82212 | S5: 113.61348 | T5: 113.49602 | U5: 114.44594 | V5: 115.62812 | W5: 117.15356 | X5: 120.01326 | Y5: 122.92108 | Z5: 124.85851 | AA5: 124.95112 | AB5: 125.78236 | AC5: 132.0552 | AD5: 131.47936 | AE5: 132.18532 | AF5: 133.38064 | AG5: 135.88858 | AH5: 137.02383 | AI5: 139.24656 | AJ5: 141.32051 | AK5: 143.21957 | AL5: 138.14077 | AM5: 144.51254
A6: AGRICULTURE,FORESTRY&FISHING | B6: 99.737591 | C6: 100.23805 | D6: 101.19892 | E6: 99.033022 | F6: 102.1439 | G6: 94.090336 | H6: 110.99282 | I6: 116.61139 | J6: 100.941 | K6: 106.60955 | L6: 112.26615 | M6: 116.33675 | N6: 109.1623 | O6: 119.14168 | P6: 116.5524 | Q6: 113.09197 | R6: 111.07646 | S6: 116.78887 | T6: 113.6891 | U6: 122.17881 | V6: 116.82436 | W6: 125.01556 | X6: 124.38789 | Y6: 126.69701 | Z6: 126.59093 | AA6: 130.35159 | AB6: 131.35436 | AC6: 143.45017 | AD6: 131.11952 | AE6: 138.64971 | AF6: 149.15088 | AG6: 157.02048 | AH6: 144.17438 | AI6: 155.71279 | AJ6: 173.0638 | AK6: 169.65936 | AL6: 143.33398 | AM6: 162.06104
A7: Cash crops | B7: 99.772367 | C7: 99.947414 | D7: 99.685328 | E7: 100.72647 | F7: 105.81673 | G7: 98.947392 | H7: 96.083137 | I7: 99.648115 | J7: 99.414192 | K7: 92.19866 | L7: 90.703541 | M7: 85.109567 | N7: 87.523451 | O7: 91.094546 | P7: 95.195838 | Q7: 83.117464 | R7: 83.505256 | S7: 82.513327 | T7: 91.362995 | U7: 99.879566 | V7: 99.839085 | W7: 129.30555 | X7: 134.38605 | Y7: 130.05268 | Z7: 121.61468 | AA7: 125.57803 | AB7: 122.30878 | AC7: 145.72257 | AD7: 144.71131 | AE7: 161.23451 | AF7: 185.19541 | AG7: 226.18064 | AH7: 182.79688 | AI7: 228.95285 | AJ7: 251.13171 | AK7: 369.85491 | AL7: 208.02325 | AM7: 236.88199
A8: Food crops | B8: 102.75752 | C8: 100.34971 | D8: 98.214039 | E8: 96.31181 | F8: 104.09123 | G8: 95.676742 | H8: 104.08751 | I8: 107.29512 | J8: 98.31158 | K8: 101.05843 | L8: 103.59143 | M8: 111.69825 | N8: 103.71697 | O8: 105.27323 | P8: 105.65049 | Q8: 105.10924 | R8: 105.48664 | S8: 99.341063 | T8: 100.55751 | U8: 115.43198 | V8: 110.68597 | W8: 112.24303 | X8: 101.0998 | Y8: 116.94817 | Z8: 122.99657 | AA8: 122.02214 | AB8: 109.09079 | AC8: 137.56287 | AD8: 123.11563 | AE8: 123.66148 | AF8: 111.28913 | AG8: 139.30163 | AH8: 132.83579 | AI8: 133.07466 | AJ8: 121.68379 | AK8: 125.97285 | AL8: 123.03799 | AM8: 137.14503
A9: Livestock | B9: 98.505192 | C9: 98.757796 | D9: 100.92045 | E9: 101.71154 | F9: 107.75111 | G9: 108.3424 | H9: 110.46133 | I9: 110.66984 | J9: 114.35907 | K9: 116.52011 | L9: 120.52753 | M9: 120.41222 | N9: 123.28849 | O9: 126.6288 | P9: 130.8191 | Q9: 132.20314 | R9: 131.72258 | S9: 132.04385 | T9: 129.43381 | U9: 134.16454 | V9: 135.70079 | W9: 136.93406 | X9: 133.02029 | Y9: 133.21037 | Z9: 136.95174 | AA9: 139.33305 | AB9: 145.36231 | AC9: 147.65167 | AD9: 147.94711 | AE9: 149.34967 | AF9: 152.95487 | AG9: 155.18396 | AH9: 159.4172 | AI9: 161.84656 | AJ9: 166.66257 | AK9: 169.94579 | AL9: 170.1319 | AM9: 171.44877
A10: Agriculture Support Services | B10: 88.439807 | C10: 107.36705 | D10: 136.79856 | E10: 94.33498 | F10: 77.401398 | G10: 90.847301 | H10: 118.76132 | I10: 87.647031 | J10: 85.864393 | K10: 108.2144 | L10: 144.61752 | M10: 101.51429 | N10: 87.121766 | O10: 102.08232 | P10: 154.0771 | Q10: 104.68774 | R10: 85.635646 | S10: 108.84554 | T10: 144.37767 | U10: 103.79515 | V10: 89.094779 | W10: 115.16745 | X10: 141.56272 | Y10: 102.45637 | Z10: 88.338806 | AA10: 113.10301 | AB10: 153.24617 | AC10: 107.70576 | AD10: 88.644334 | AE10: 111.42295 | AF10: 151.44526 | AG10: 105.2623 | AH10: 90.506313 | AI10: 117.73876 | AJ10: 147.83692 | AK10: 95.903419 | AL10: 92.280156 | AM10: 121.6039
A11: Forestry | B11: 86.405516 | C11: 103.79918 | D11: 108.39324 | E11: 101.06138 | F11: 80.820459 | G11: 63.400907 | H11: 136.99288 | I11: 155.29977 | J11: 93.706838 | K11: 114.53052 | L11: 128.10361 | M11: 133.24456 | N11: 126.97269 | O11: 154.59371 | P11: 120.23834 | Q11: 118.04491 | R11: 118.82764 | S11: 168.29651 | T11: 122.08634 | U11: 125.67034 | V11: 131.22554 | W11: 135.19181 | X11: 134.93645 | Y11: 134.4754 | Z11: 136.47611 | AA11: 143.52795 | AB11: 137.40431 | AC11: 139.18001 | AD11: 145.52087 | AE11: 149.79949 | AF11: 155.3167 | AG11: 158.3514 | AH11: 158.95804 | AI11: 161.29439 | AJ11: 172.31061 | AK11: 163.61483 | AL11: 164.09121 | AM11: 164.17629
A12: Fishing | B12: 97.077496 | C12: 96.046702 | D12: 102.47552 | E12: 105.32413 | F12: 109.02746 | G12: 118.10552 | H12: 114.85298 | I12: 120.64649 | J12: 124.91048 | K12: 125.78344 | L12: 134.32268 | M12: 133.37373 | N12: 134.66077 | O12: 159.26676 | P12: 161.02638 | Q12: 154.14502 | R12: 165.97843 | S12: 154.40058 | T12: 157.37526 | U12: 167.96606 | V12: 155.77262 | W12: 156.93254 | X12: 155.18709 | Y12: 165.05811 | Z12: 148.42394 | AA12: 153.00882 | AB12: 171.04625 | AC12: 182.57639 | AD12: 153.10927 | AE12: 162.22542 | AF12: 187.788 | AG12: 193.58219 | AH12: 159.24947 | AI12: 156.65071 | AJ12: 195.58469 | AK12: 212.04481 | AL12: 165.62424 | AM12: 169.65202
A13: INDUSTRY | B13: 96.933266 | C13: 98.42523 | D13: 102.02209 | E13: 102.43052 | F13: 105.6728 | G13: 105.27361 | H13: 106.50997 | I13: 109.34371 | J13: 111.4677 | K13: 108.46498 | L13: 108.24198 | M13: 107.49894 | N13: 108.76951 | O13: 110.34755 | P13: 112.08224 | Q13: 113.05143 | R13: 115.37585 | S13: 115.57812 | T13: 118.03021 | U13: 117.83228 | V13: 119.16088 | W13: 113.40245 | X13: 123.02174 | Y13: 124.90641 | Z13: 125.63705 | AA13: 122.83105 | AB13: 123.6165 | AC13: 127.37306 | AD13: 128.91093 | AE13: 129.29454 | AF13: 125.21425 | AG13: 125.63411 | AH13: 127.18904 | AI13: 130.46511 | AJ13: 129.99549 | AK13: 132.3054 | AL13: 129.18592 | AM13: 130.95823
A14: Mining & quarrying | B14: 106.4737 | C14: 105.4776 | D14: 104.40306 | E14: 87.552939 | F14: 104.96698 | G14: 119.47703 | H14: 116.27097 | I14: 134.457 | J14: 160.28022 | K14: 161.90769 | L14: 142.78991 | M14: 140.90341 | N14: 124.32963 | O14: 127.32376 | P14: 122.89787 | Q14: 147.92699 | R14: 133.97547 | S14: 148.69934 | T14: 168.11232 | U14: 154.30862 | V14: 136.13166 | W14: 65.561307 | X14: 135.17824 | Y14: 106.99265 | Z14: 106.19465 | AA14: 95.016501 | AB14: 106.70185 | AC14: 129.24527 | AD14: 121.77041 | AE14: 94.269127 | AF14: 97.415384 | AG14: 103.83744 | AH14: 80.447827 | AI14: 127.0965 | AJ14: 121.72326 | AK14: 107.74948 | AL14: 89.35853 | AM14: 101.56045
A15: Manufacturing | B15: 95.562873 | C15: 98.243413 | D15: 102.10076 | E15: 103.88739 | F15: 107.72909 | G15: 106.10424 | H15: 107.58899 | I15: 110.07518 | J15: 109.69786 | K15: 106.73219 | L15: 106.95549 | M15: 107.23689 | N15: 110.58499 | O15: 113.17243 | P15: 117.42755 | Q15: 119.10495 | R15: 121.0688 | S15: 122.57135 | T15: 126.09668 | U15: 126.63247 | V15: 128.66391 | W15: 123.97294 | X15: 131.54376 | Y15: 138.2961 | Z15: 137.59516 | AA15: 133.69207 | AB15: 135.76712 | AC15: 137.6228 | AD15: 139.22407 | AE15: 141.2314 | AF15: 139.82766 | AG15: 138.91915 | AH15: 143.36815 | AI15: 136.02035 | AJ15: 142.78295 | AK15: 144.93102 | AL15: 143.72909 | AM15: 142.40218
A16: Electricity | B16: 94.097288 | C16: 94.195905 | D16: 106.22288 | E16: 104.77688 | F16: 104.30515 | G16: 103.92619 | H16: 108.92026 | I16: 108.37647 | J16: 117.52897 | K16: 116.87987 | L16: 117.06797 | M16: 116.43945 | N16: 116.69465 | O16: 116.89553 | P16: 117.14703 | Q16: 116.93719 | R16: 116.58566 | S16: 115.8339 | T16: 115.37569 | U16: 115.1067 | V16: 114.12435 | W16: 114.15975 | X16: 114.65458 | Y16: 115.49627 | Z16: 116.6274 | AA16: 104.34724 | AB16: 102.59173 | AC16: 101.18212 | AD16: 99.281847 | AE16: 98.003931 | AF16: 96.41854 | AG16: 98.464028 | AH16: 97.075129 | AI16: 96.721012 | AJ16: 94.577707 | AK16: 92.401641 | AL16: 92.180405 | AM16: 92.000705
... A33: Activities of Households | B33: 97.136675 | C33: 99.142049 | D33: 100.95861 | E33: 102.69657 | F33: 102.765 | G33: 103.72044 | H33: 104.06692 | I33: 105.14766 | J33: 105.88385 | K33: 106.27333 | L33: 106.38412 | M33: 107.28481 | N33: 107.60228 | O33: 108.32187 | P33: 108.89799 | Q33: 110.20219 | R33: 110.61554 | S33: 111.06746 | T33: 111.30051 | U33: 112.34583 | V33: 112.91445 | W33: 113.89133 | X33: 115.05044 | Y33: 119.24795 | Z33: 123.22687 | AA33: 126.03663 | AB33: 126.16875 | AC33: 126.9131 | AD33: 127.31756 | AE33: 129.16219 | AF33: 130.04935 | AG33: 131.34408 | AH33: 131.71412 | AI33: 133.0791 | AJ33: 134.64642 | AK33: 136.24796 | AL33: 136.76319 | AM33: 137.37987
A35: ADJUSTMENTS
A36: Taxes on products | B36: 95.161404 | C36: 100.67969 | D36: 102.7198 | E36: 101.22483 | F36: 98.860365 | G36: 106.25056 | H36: 116.03619 | I36: 112.94704 | J36: 118.81179 | K36: 122.87996 | L36: 116.97476 | M36: 113.88375 | N36: 113.05824 | O36: 117.37788 | P36: 123.89242 | Q36: 102.89785 | R36: 118.15688 | S36: 125.57577 | T36: 128.99381 | U36: 116.67932 | V36: 129.05725 | W36: 136.24321 | X36: 129.96752 | Y36: 131.56069 | Z36: 131.32229 | AA36: 129.29171 | AB36: 138.11395 | AC36: 147.96689 | AD36: 129.26802 | AE36: 138.78259 | AF36: 136.47988 | AG36: 141.37944 | AH36: 132.01223 | AI36: 143.53575 | AJ36: 141.95384 | AK36: 156.2819 | AL36: 131.19511 | AM36: 146.30101
A37: Source: Uganda Bureau of Statistics

Sheet Deseason_VA
A1: Table 6: SEASONALLY ADJUSTED Value Added at constant 2016/17 prices, BILLION SHILLINGS, 2016/17-2025/26
B3: 2016/17 | F3: 2017/18 | J3: 2018/19 | N3: 2019/20 | R3: 2020/21 | V3: 2021/22 | Z3: 2022/23 | AD3: 2023/24 | AH3: 2024/25 | AL3: 2025/26
B4: Q1 | C4: Q2 | D4: Q3 | E4: Q4 | F4: Q1 | G4: Q2 | H4: Q3 | I4: Q4 | J4: Q1 | K4: Q2 | L4: Q3 | M4: Q4 | N4: Q1 | O4: Q2 | P4: Q3 | Q4: Q4 | R4: Q1 | S4: Q2 | T4: Q3 | U4: Q4 | V4: Q1 | W4: Q2 | X4: Q3 | Y4: Q4 | Z4: Q1 | AA4: Q2 | AB4: Q3 | AC4: Q4 | AD4: Q1 | AE4: Q2 | AF4: Q3 | AG4: Q4 | AH4: Q1 | AI4: Q2 | AJ4: Q3 | AK4: Q4 | AL4: Q1 | AM4: Q2
A5: GDP AT MARKET PRICES | B5: 26418.33 | C5: 26820.341 | D5: 27619.794 | E5: 27877.519 | F5: 28291.339 | G5: 28562.977 | H5: 29225.636 | I5: 29425.25 | J5: 29958.925 | K5: 30153.094 | L5: 31561.031 | M5: 31371.83 | N5: 32311.887 | O5: 32681.047 | P5: 31941.991 | Q5: 29638.437 | R5: 31936.886 | S5: 32665.96 | T5: 32913.148 | U5: 33266.263 | V5: 32690.007 | W5: 34248.282 | X5: 35004.411 | Y5: 35114.23 | Z5: 35517.737 | AA5: 35836.545 | AB5: 35798.781 | AC5: 36969.932 | AD5: 37483.15 | AE5: 38034.023 | AF5: 38330.506 | AG5: 38995.258 | AH5: 39825.16 | AI5: 40146.528 | AJ5: 41458.228 | AK5: 41147.854 | AL5: 41936.505 | AM5: 43598.4
A6: AGRICULTURE,FORESTRY&FISHING | B6: 6113.5807 | C6: 6365.3902 | D6: 6582.613 | E6: 6545.5468 | F6: 6624.4085 | G6: 6533.6463 | H6: 6886.5598 | I6: 6658.9337 | J6: 6779.4574 | K6: 6777.7826 | L6: 7530.1008 | M6: 7187.1377 | N6: 7185.5965 | O6: 7287.0483 | P6: 7449.7978 | Q6: 7591.413 | R6: 7576.6284 | S6: 7813.6823 | T6: 7522.4789 | U6: 7637.3368 | V6: 7927.1369 | W6: 7630.167 | X6: 8035.5081 | Y6: 8447.1775 | Z6: 8159.0795 | AA6: 8513.0207 | AB6: 8383.2101 | AC6: 8246.0464 | AD6: 8605.2413 | AE6: 8671.4432 | AF6: 8843.9697 | AG6: 9113.9734 | AH6: 9189.0095 | AI6: 9308.9636 | AJ6: 9634.1005 | AK6: 9429.3307 | AL6: 9593.9998 | AM6: 10108.554
A7: Cash crops | B7: 503.29632 | C7: 710.83298 | D7: 654.68381 | E7: 689.97222 | F7: 709.65641 | G7: 670.79429 | H7: 664.81656 | I7: 663.4659 | J7: 709.16014 | K7: 706.23062 | L7: 675.59063 | M7: 745.91241 | N7: 727.03459 | O7: 768.45264 | P7: 801.87024 | Q7: 763.86523 | R7: 774.63835 | S7: 864.80681 | T7: 898.74536 | U7: 905.64558 | V7: 939.73283 | W7: 921.77075 | X7: 850.02556 | Y7: 925.76687 | Z7: 924.82376 | AA7: 885.18484 | AB7: 916.57424 | AC7: 931.72517 | AD7: 975.85508 | AE7: 1037.1508 | AF7: 1078.9022 | AG7: 1012.031 | AH7: 1141.169 | AI7: 1144.1992 | AJ7: 1183.1209 | AK7: 1098.1975 | AL7: 1224.9757 | AM7: 1290.8856
A8: Food crops | B8: 3247.5872 | C8: 3276.5302 | D8: 3540.1141 | E8: 3485.1205 | F8: 3588.4065 | G8: 3582.1453 | H8: 3913.4832 | I8: 3586.8716 | J8: 3585.2374 | K8: 3511.1463 | L8: 4220.9966 | M8: 3744.6507 | N8: 3721.8283 | O8: 3791.5554 | P8: 3961.9236 | Q8: 4159.1174 | R8: 4084.7044 | S8: 4119.4213 | T8: 3866.9148 | U8: 3972.0725 | V8: 4100.8812 | W8: 3883.8984 | X8: 4273.931 | Y8: 4566.6634 | Z8: 4381.479 | AA8: 4559.5451 | AB8: 4232.1355 | AC8: 4249.0299 | AD8: 4561.0119 | AE8: 4516.1356 | AF8: 4603.3385 | AG8: 4706.6803 | AH8: 4805.8781 | AI8: 4787.236 | AJ8: 4790.1824 | AK8: 4821.6983 | AL8: 4777.2363 | AM8: 5144.5355
A9: Livestock | B9: 802.21645 | C9: 821.04987 | D9: 836.02238 | E9: 849.95016 | F9: 867.88349 | G9: 875.60992 | H9: 894.96076 | I9: 906.56364 | J9: 925.00599 | K9: 942.90375 | L9: 958.0089 | M9: 979.44664 | N9: 997.41556 | O9: 1017.1628 | P9: 1037.161 | Q9: 1053.9591 | R9: 1072.9428 | S9: 1094.2655 | T9: 1117.2575 | U9: 1141.018 | V9: 1163.0541 | W9: 1184.3333 | X9: 1208.916 | Y9: 1236.7749 | Z9: 1265.1188 | AA9: 1289.5708 | AB9: 1324.4009 | AC9: 1337.6003 | AD9: 1363.6458 | AE9: 1392.9689 | AF9: 1420.8064 | AG9: 1450.6673 | AH9: 1479.2252 | AI9: 1512.5413 | AJ9: 1550.2705 | AK9: 1578.6672 | AL9: 1616.4082 | AM9: 1651.8822
A10: Agriculture Support Services | B10: 4.0799985 | C10: 4.1050673 | D10: 4.1434359 | E10: 4.178764 | F10: 4.0862557 | G10: 4.0174434 | H10: 4.0500986 | I10: 4.2471734 | J10: 4.2716475 | K10: 4.3753032 | L10: 4.3327387 | M10: 4.9040641 | N10: 5.0061099 | O10: 5.3388342 | P10: 4.1480272 | Q10: 4.2807176 | R10: 4.6282604 | S10: 4.8545926 | T10: 5.1152568 | U10: 5.0403182 | V10: 4.9733821 | W10: 4.9806352 | X10: 5.2000083 | Y10: 5.1848425 | Z10: 5.1189173 | AA10: 5.1979803 | AB10: 5.1817555 | AC10: 5.2290971 | AD10: 5.4102962 | AE10: 5.5776223 | AF10: 5.5930664 | AG10: 5.6771782 | AH10: 5.6485223 | AI10: 5.4027254 | AJ10: 5.5356849 | AK10: 6.6136967 | AL10: 4.9875103 | AM10: 5.4154926
A11: Forestry | B11: 984.7739 | C11: 981.27089 | D11: 1007.3471 | E11: 1019.5561 | F11: 1019.8897 | G11: 1005.9334 | H11: 1038.3109 | I11: 1066.2147 | J11: 1062.5455 | K11: 1066.9156 | L11: 1058.131 | M11: 1093.6539 | N11: 1108.9099 | O11: 1126.5173 | P11: 1099.9411 | Q11: 1085.9132 | R11: 1083.4074 | S11: 1175.1844 | T11: 1153.3392 | U11: 1141.3259 | V11: 1136.1756 | W11: 1147.7067 | X11: 1211.0768 | Y11: 1204.0299 | Z11: 1180.0475 | AA11: 1196.9188 | AB11: 1241.1562 | AC11: 1228.9552 | AD11: 1240.2378 | AE11: 1232.0035 | AF11: 1167.1098 | AG11: 1358.0152 | AH11: 1283.2852 | AI11: 1295.6842 | AJ11: 1255.2839 | AK11: 1328.3632 | AL11: 1404.7432 | AM11: 1399.5019
A12: Fishing | B12: 571.62688 | C12: 571.60122 | D12: 540.30214 | E12: 496.76894 | F12: 434.48616 | G12: 395.14589 | H12: 370.93825 | I12: 431.57077 | J12: 493.2367 | K12: 546.21105 | L12: 613.04091 | M12: 618.56988 | N12: 625.40201 | O12: 578.02138 | P12: 544.75389 | Q12: 524.2773 | R12: 556.30729 | S12: 555.14969 | T12: 481.10665 | U12: 472.23446 | V12: 582.31983 | W12: 487.47724 | X12: 486.35877 | Y12: 508.7576 | Z12: 402.49159 | AA12: 576.60321 | AB12: 663.76156 | AC12: 493.5068 | AD12: 459.08052 | AE12: 487.60682 | AF12: 568.21962 | AG12: 580.90232 | AH12: 473.80348 | AI12: 563.90025 | AJ12: 849.70702 | AK12: 595.79076 | AL12: 565.64886 | AM12: 616.33333
A13: INDUSTRY | B13: 6810.6034 | C13: 7063.7601 | D13: 7254.0027 | E13: 7141.0369 | F13: 7166.4739 | G13: 7225.7595 | H13: 7502.9433 | I13: 7726.2775 | J13: 7801.3782 | K13: 7960.7061 | L13: 8233.1105 | M13: 8293.8714 | N13: 8575.638 | O13: 8793.2643 | P13: 8516.0149 | Q13: 7475.9913 | R13: 8344.0458 | S13: 8664.3391 | T13: 8746.7761 | U13: 8744.402 | V13: 8320.4574 | W13: 9400.4202 | X13: 9287.252 | Y13: 9327.8918 | Z13: 9270.1095 | AA13: 9216.431 | AB13: 9362.2701 | AC13: 9903.2747 | AD13: 10051.235 | AE13: 9693.1081 | AF13: 10001.426 | AG13: 9991.0365 | AH13: 10553.501 | AI13: 10470.413 | AJ13: 10737.855 | AK13: 10743.283 | AL13: 11200.126 | AM13: 11777.905
A14: Mining & quarrying | B14: 279.59312 | C14: 345.39172 | D14: 338.30383 | E14: 382.32306 | F14: 309.05654 | G14: 272.06749 | H14: 310.89 | I14: 390.58963 | J14: 378.22495 | K14: 313.7687 | L14: 432.68767 | M14: 378.9447 | N14: 424.97731 | O14: 529.31732 | P14: 509.24228 | Q14: 312.14721 | R14: 594.24487 | S14: 501.17591 | T14: 422.12589 | U14: 364.28493 | V14: 249.28243 | W14: 728.53758 | X14: 641.83588 | Y14: 678.19367 | Z14: 451.98361 | AA14: 342.60879 | AB14: 518.87754 | AC14: 1052.8732 | AD14: 855.23706 | AE14: 671.13577 | AF14: 564.91015 | AG14: 260.58698 | AH14: 756.03455 | AI14: 735.19236 | AJ14: 576.91568 | AK14: 379.13373 | AL14: 663.20976 | AM14: 943.15898
A15: Manufacturing | B15: 4065.9476 | C15: 4167.4455 | D15: 4379.7397 | E15: 4248.1633 | F15: 4280.8726 | G15: 4339.8829 | H15: 4463.707 | I15: 4548.9121 | J15: 4580.3004 | K15: 4727.7723 | L15: 4819.249 | M15: 4855.8436 | N15: 5115.8421 | O15: 5140.2102 | P15: 4788.4091 | Q15: 4180.4203 | R15: 4913.8244 | S15: 4865.0387 | T15: 4918.2704 | U15: 4951.2894 | V15: 4594.0413 | W15: 5215.5774 | X15: 5312.0112 | Y15: 5282.1414 | Z15: 5280.8115 | AA15: 5323.8342 | AB15: 5246.577 | AC15: 5189.5747 | AD15: 5498.8241 | AE15: 5272.7982 | AF15: 5506.6988 | AG15: 5748.7105 | AH15: 5814.5781 | AI15: 5711.6919 | AJ15: 5794.7468 | AK15: 5941.3569 | AL15: 6080.6432 | AM15: 6241.9486
A16: Electricity | B16: 327.91569 | C16: 340.55795 | D16: 358.50664 | E16: 352.86582 | F16: 363.2532 | G16: 366.34659 | H16: 364.71318 | I16: 359.46388 | J16: 363.55749 | K16: 365.02414 | L16: 372.04481 | M16: 389.35001 | N16: 408.69815 | O16: 421.5859 | P16: 435.14903 | Q16: 386.45991 | R16: 444.86438 | S16: 459.04174 | T16: 467.36391 | U16: 473.32124 | V16: 467.55331 | W16: 473.94687 | X16: 477.3924 | Y16: 483.47467 | Z16: 495.92268 | AA16: 511.83145 | AB16: 520.14571 | AC16: 535.41815 | AD16: 554.56891 | AE16: 554.79153 | AF16: 565.74519 | AG16: 572.09128 | AH16: 589.69083 | AI16: 613.66967 | AJ16: 641.58664 | AK16: 668.97905 | AL16: 744.20131 | AM16: 680.4615
... A33: Activities of Households | B33: 220.43331 | C33: 222.06147 | D33: 223.6417 | E33: 225.21541 | F33: 226.75373 | G33: 228.31958 | H33: 229.88097 | I33: 231.46466 | J33: 233.06866 | K33: 234.68827 | L33: 236.29336 | M33: 237.90414 | N33: 239.54063 | O33: 241.18784 | P33: 242.80332 | Q33: 244.41613 | R33: 246.06797 | S33: 247.74398 | T33: 249.4434 | U33: 251.15455 | V33: 252.87642 | W33: 254.61022 | X33: 256.32659 | Y33: 258.03995 | Z33: 259.7722 | AA33: 261.5346 | AB33: 263.33352 | AC33: 265.15038 | AD33: 266.95643 | AE33: 268.77986 | AF33: 270.60052 | AG33: 272.42827 | AH33: 274.24133 | AI33: 276.08681 | AJ33: 277.99682 | AK33: 279.93447 | AL33: 281.80456 | AM33: 281.8867
A35: ADJUSTMENTS
A36: Taxes on products | B36: 1883.2834 | C36: 1805.0535 | D36: 1969.3194 | E36: 1978.3628 | F36: 2011.4434 | G36: 1988.86 | H36: 1960.5283 | I36: 2012.3942 | J36: 1994.9695 | K36: 2050.8934 | L36: 2154.0345 | M36: 2120.9253 | N36: 2208.6176 | O36: 2252.0829 | P36: 2134.1464 | Q36: 1594.4186 | R36: 2124.7071 | S36: 2157.3562 | T36: 2055.1209 | U36: 2365.9306 | V36: 2069.2315 | W36: 2358.027 | X36: 2497.7416 | Y36: 2434.6792 | Z36: 2415.2547 | AA36: 2500.4775 | AB36: 2598.2494 | AC36: 2709.924 | AD36: 2733.946 | AE36: 2690.3075 | AF36: 2776.001 | AG36: 2815.5688 | AH36: 3011.7728 | AI36: 2949.7457 | AJ36: 2928.624 | AK36: 3039.6326 | AL36: 3107.2263 | AM36: 3162.5776
A37: Source: Uganda Bureau of Statistics

Sheet Deseason_Growth
A1: Table 7: SEASONALLY ADJUSTED Value Added at constant 2016/17 prices,PERCENTAGE CHANGE, 2016/17-2025/26
B3: 2016/17 | F3: 2017/18 | J3: 2018/19 | N3: 2019/20 | R3: 2020/21 | V3: 2021/22 | Z3: 2022/23 | AD3: 2023/24 | AH3: 2024/25 | AL3: 2025/26
B4: Q1 | C4: Q2 | D4: Q3 | E4: Q4 | F4: Q1 | G4: Q2 | H4: Q3 | I4: Q4 | J4: Q1 | K4: Q2 | L4: Q3 | M4: Q4 | N4: Q1 | O4: Q2 | P4: Q3 | Q4: Q4 | R4: Q1 | S4: Q2 | T4: Q3 | U4: Q4 | V4: Q1 | W4: Q2 | X4: Q3 | Y4: Q4 | Z4: Q1 | AA4: Q2 | AB4: Q3 | AC4: Q4 | AD4: Q1 | AE4: Q2 | AF4: Q3 | AG4: Q4 | AH4: Q1 | AI4: Q2 | AJ4: Q3 | AK4: Q4 | AL4: Q1 | AM4: Q2
A5: GDP AT MARKET PRICES | B5: 0.86546068 | C5: 1.5217117 | D5: 2.9807704 | E5: 0.93312038 | F5: 1.4844207 | G5: 0.96014433 | H5: 2.3199933 | I5: 0.68300934 | J5: 1.8136644 | K5: 0.64811638 | L5: 4.6692978 | M5: -0.5994792 | N5: 2.996502 | O5: 1.1424887 | P5: -2.2614196 | Q5: -7.2116804 | R5: 7.7549618 | S5: 2.2828561 | T5: 0.75671459 | U5: 1.0728699 | V5: -1.7322538 | W5: 4.766823 | X5: 2.2077868 | Y5: 0.31372912 | Z5: 1.149128 | AA5: 0.89760246 | AB5: -0.10537823 | AC5: 3.2714827 | AD5: 1.3882041 | AE5: 1.4696532 | AF5: 0.77952016 | AG5: 1.7342644 | AH5: 2.1282137 | AI5: 0.80694549 | AJ5: 3.2672815 | AK5: -0.74864265 | AL5: 1.9166271 | AM5: 3.9628848
A6: AGRICULTURE,FORESTRY&FISHING | B6: -0.95264124 | C6: 4.1188552 | D6: 3.4125598 | E6: -0.56309295 | F6: 1.2048157 | G6: -1.3701187 | H6: 5.4014788 | I6: -3.3053667 | J6: 1.809954 | K6: -0.024703168 | L6: 11.099768 | M6: -4.554562 | N6: -0.02144354 | O6: 1.4118782 | P6: 2.2334067 | Q6: 1.9009271 | R6: -0.19475384 | S6: 3.1287517 | T6: -3.7268402 | U6: 1.5268624 | V6: 3.7945184 | W6: -3.7462449 | X6: 5.3123497 | Y6: 5.1231289 | Z6: -3.4105828 | AA6: 4.3380037 | AB6: -1.5248479 | AC6: -1.6361716 | AD6: 4.3559656 | AE6: 0.76931957 | AF6: 1.9895942 | AG6: 3.0529694 | AH6: 0.82330881 | AI6: 1.3054081 | AJ6: 3.492729 | AK6: -2.1254685 | AL6: 1.7463496 | AM6: 5.3632931
A7: Cash crops | B7: -14.185823 | C7: 41.235482 | D7: -7.8990666 | E7: 5.3901456 | F7: 2.8528957 | G7: -5.4761885 | H7: -0.89114126 | I7: -0.20316342 | J7: 6.8872025 | K7: -0.41309662 | L7: -4.3385248 | M7: 10.408934 | N7: -2.530836 | O7: 5.6968462 | P7: 4.3486876 | Q7: -4.7395463 | R7: 1.4103426 | S7: 11.640072 | T7: 3.9244079 | U7: 0.76776137 | V7: 3.763862 | W7: -1.9114032 | X7: -7.7834092 | Y7: 8.9104744 | Z7: -0.10187259 | AA7: -4.2861052 | AB7: 3.5460836 | AC7: 1.6529953 | AD7: 4.7363663 | AE7: 6.2812293 | AF7: 4.0255911 | AG7: -6.1980761 | AH7: 12.760276 | AI7: 0.2655331 | AJ7: 3.4016587 | AK7: -7.1779173 | AL7: 11.544208 | AM7: 5.3805076
A8: Food crops | B8: -0.5603528 | C8: 0.89121728 | D8: 8.0446054 | E8: -1.5534415 | F8: 2.9636262 | G8: -0.17448244 | H8: 9.2497048 | I8: -8.3458035 | J8: -0.045561749 | K8: -2.0665594 | L8: 20.217053 | M8: -11.285151 | N8: -0.60946783 | O8: 1.8734641 | P8: 4.4933586 | Q8: 4.9772247 | R8: -1.7891549 | S8: 0.84992526 | T8: -6.1296588 | U8: 2.7194209 | V8: 3.2428579 | W8: -5.2911268 | X8: 10.042297 | Y8: 6.8492558 | Z8: -4.055137 | AA8: 4.0640649 | AB8: -7.180753 | AC8: 0.39919366 | AD8: 7.3424284 | AE8: -0.9839111 | AF8: 1.9309202 | AG8: 2.2449307 | AH8: 2.1075967 | AI8: -0.38790253 | AJ8: 0.061547826 | AK8: 0.65792668 | AL8: -0.92212443 | AM8: 7.6885297
A9: Livestock | B9: 1.0613387 | C9: 2.3476732 | D9: 1.8235811 | E9: 1.6659583 | F9: 2.1099268 | G9: 0.89026145 | H9: 2.2099842 | I9: 1.2964677 | J9: 2.0343139 | K9: 1.9348798 | L9: 1.6019821 | M9: 2.2377397 | N9: 1.8345995 | O9: 1.9798366 | P9: 1.9660764 | Q9: 1.6196284 | R9: 1.8011741 | S9: 1.9873158 | T9: 2.101138 | U9: 2.1266802 | V9: 1.9312606 | W9: 1.8295976 | X9: 2.075659 | Y9: 2.3044513 | Z9: 2.2917626 | AA9: 1.9327795 | AB9: 2.7009082 | AC9: 0.99663189 | AD9: 1.9471817 | AE9: 2.1503439 | AF9: 1.9984304 | AG9: 2.1016875 | AH9: 1.9686057 | AI9: 2.2522626 | AJ9: 2.4944248 | AK9: 1.8317274 | AL9: 2.3906883 | AM9: 2.1946202
A10: Agriculture Support Services | B10: 2.8525106 | C10: 0.61443328 | D10: 0.93466239 | E10: 0.85262862 | F10: -2.2137703 | G10: -1.6839961 | H10: 0.81283644 | I10: 4.8659255 | J10: 0.57624593 | K10: 2.4265978 | L10: -0.97283705 | M10: 13.186242 | N10: 2.0808428 | O10: 6.6463629 | P10: -22.304625 | Q10: 3.1988789 | R10: 8.1187962 | S10: 4.890223 | T10: 5.3694357 | U10: -1.4650024 | V10: -1.3280125 | W10: 0.14583715 | X10: 4.4045211 | Y10: -0.29165056 | Z10: -1.2714987 | AA10: 1.5445263 | AB10: -0.31213568 | AC10: 0.91362128 | AD10: 3.4652082 | AE10: 3.0927336 | AF10: 0.27689393 | AG10: 1.5038593 | AH10: -0.50475684 | AI10: -4.3515248 | AJ10: 2.4609699 | AK10: 19.473866 | AL10: -24.588162 | AM10: 8.5810803
A11: Forestry | B11: 5.3147909 | C11: -0.35571699 | D11: 2.6573898 | E11: 1.212 | F11: 0.032720786 | G11: -1.3684174 | H11: 3.2186543 | I11: 2.6874176 | J11: -0.3441249 | K11: 0.41128346 | L11: -0.8233656 | M11: 3.3571393 | N11: 1.3949553 | O11: 1.5878127 | P11: -2.3591521 | Q11: -1.275328 | R11: -0.23075511 | S11: 8.4711436 | T11: -1.8588726 | U11: -1.0416172 | V11: -0.45124934 | W11: 1.0149017 | X11: 5.521454 | Y11: -0.58186949 | Z11: -1.9918472 | AA11: 1.4297144 | AB11: 3.6959412 | AC11: -0.98303782 | AD11: 0.91806689 | AE11: -0.66392875 | AF11: -5.2673265 | AG11: 16.357105 | AH11: -5.5028885 | AI11: 0.9661924 | AJ11: -3.1180633 | AK11: 5.8217348 | AL11: 5.7499335 | AM11: -0.37311342
A12: Fishing | B12: -2.6459897 | C12: -0.0044894642 | D12: -5.4756839 | E12: -8.0571952 | F12: -12.537575 | G12: -9.0544359 | H12: -6.1262549 | I12: 16.34572 | J12: 14.288716 | K12: 10.740148 | L12: 12.235171 | M12: 0.90189225 | N12: 1.1045045 | O12: -7.5760273 | P12: -5.7554087 | Q12: -3.7588694 | R12: 6.1093598 | S12: -0.20808575 | T12: -13.337492 | U12: -1.8441206 | V12: 23.31159 | W12: -16.287026 | X12: -0.22944132 | Y12: 4.6054135 | Z12: -20.887355 | AA12: 43.258449 | AB12: 15.115828 | AC12: -25.649988 | AD12: -6.9758487 | AE12: 6.2137916 | AF12: 16.532336 | AG12: 2.2320077 | AH12: -18.436636 | AI12: 19.015642 | AJ12: 50.683923 | AK12: -29.882801 | AL12: -5.0591413 | AM12: 8.9604123
A13: INDUSTRY | B13: 3.1670471 | C13: 3.717097 | D13: 2.6932197 | E13: -1.5572898 | F13: 0.35620939 | G13: 0.82726373 | H13: 3.8360498 | I13: 2.9766219 | J13: 0.97201608 | K13: 2.042305 | L13: 3.4218618 | M13: 0.73800683 | N13: 3.3972867 | O13: 2.5377276 | P13: -3.1529752 | Q13: -12.212562 | R13: 11.61123 | S13: 3.8385845 | T13: 0.95145188 | U13: -0.027142845 | V13: -4.8481825 | W13: 12.979608 | X13: -1.2038631 | Y13: 0.43758695 | Z13: -0.61945777 | AA13: -0.57904912 | AB13: 1.582382 | AC13: 5.778562 | AD13: 1.4940567 | AE13: -3.5630162 | AF13: 3.1808 | AG13: -0.10388497 | AH13: 5.6296866 | AI13: -0.78729527 | AJ13: 2.5542563 | AK13: 0.050557372 | AL13: 4.2523591 | AM13: 5.15868
A14: Mining & quarrying | B14: 25.417911 | C14: 23.533698 | D14: -2.0521314 | E14: 13.011745 | F14: -19.16351 | G14: -11.968378 | H14: 14.269441 | I14: 25.63596 | J14: -3.1656452 | K14: -17.041775 | L14: 37.900199 | M14: -12.420731 | N14: 12.14758 | O14: 24.5519 | P14: -3.7926273 | Q14: -38.703595 | R14: 90.373276 | S14: -15.661719 | T14: -15.772908 | U14: -13.702302 | V14: -31.569381 | W14: 192.25388 | X14: -11.900786 | Y14: 5.6646558 | Z14: -33.354787 | AA14: -24.198848 | AB14: 51.448987 | AC14: 102.91361 | AD14: -18.771121 | AE14: -21.526347 | AF14: -15.827738 | AG14: -53.871076 | AH14: 190.12753 | AI14: -2.7567772 | AJ14: -21.528607 | AK14: -34.282644 | AL14: 74.927658 | AM14: 42.211262
A15: Manufacturing | B15: -1.3921086 | C15: 2.4962924 | D15: 5.0941081 | E15: -3.0042057 | F15: 0.76996214 | G15: 1.3784662 | H15: 2.8531667 | I15: 1.9088417 | J15: 0.69001748 | K15: 3.2196988 | L15: 1.9348787 | M15: 0.75934367 | N15: 5.3543423 | O15: 0.47632587 | P15: -6.8441001 | Q15: -12.697093 | R15: 17.543788 | S15: -0.9928236 | T15: 1.0941662 | U15: 0.67135411 | V15: -7.2152534 | W15: 13.52918 | X15: 1.8489576 | Y15: -0.56230809 | Z15: -0.02517626 | AA15: 0.81469753 | AB15: -1.451157 | AC15: -1.0864655 | AD15: 5.9590514 | AE15: -4.1104409 | AF15: 4.4359853 | AG15: 4.3948609 | AH15: 1.1457807 | AI15: -1.7694528 | AJ15: 1.4541208 | AK15: 2.5300505 | AL15: 2.3443521 | AM15: 2.6527694
A16: Electricity | B16: 1.5657569 | C16: 3.8553358 | D16: 5.2703794 | E16: -1.573422 | F16: 2.94372 | G16: 0.85157853 | H16: -0.44586435 | I16: -1.4392962 | J16: 1.1388104 | K16: 0.40341749 | L16: 1.9233442 | M16: 4.6513735 | N16: 4.9693439 | O16: 3.1533662 | P16: 3.2171688 | Q16: -11.189068 | R16: 15.112687 | S16: 3.1868945 | T16: 1.8129442 | U16: 1.2746656 | V16: -1.2186086 | W16: 1.3674514 | X16: 0.72698718 | Y16: 1.2740603 | Z16: 2.5746978 | AA16: 3.2079139 | AB16: 1.624413 | AC16: 2.936185 | AD16: 3.5767854 | AE16: 0.04014256 | AF16: 1.9743745 | AG16: 1.121722 | AH16: 3.0763544 | AI16: 4.0663409 | AJ16: 4.5491844 | AK16: 4.2694799 | AL16: 11.244337 | AM16: -8.564861
... A33: Activities of Households | B33: 0.75038501 | C33: 0.73862216 | D33: 0.71161552 | E33: 0.70367416 | F33: 0.68304667 | G33: 0.69055088 | H33: 0.68385857 | I33: 0.68892014 | J33: 0.69297558 | K33: 0.69490646 | L33: 0.68392567 | M33: 0.68168851 | N33: 0.68787608 | O33: 0.68765305 | P33: 0.66980461 | Q33: 0.6642449 | R33: 0.67583 | S33: 0.68111548 | T33: 0.68595705 | U33: 0.68598895 | V33: 0.68558065 | W33: 0.68563247 | X33: 0.6741159 | Y33: 0.66842853 | Z33: 0.67131186 | AA33: 0.67843888 | AB33: 0.68783591 | AC33: 0.68994424 | AD33: 0.68114069 | AE33: 0.68304718 | AF33: 0.67737918 | AG33: 0.67544162 | AH33: 0.66551722 | AI33: 0.67294094 | AJ33: 0.69181505 | AK33: 0.69700212 | AL33: 0.66804633 | AM33: 0.029148651
A35: ADJUSTMENT
A36: Taxes on products | B36: 5.8309683 | C36: -4.1539103 | D36: 9.1003326 | E36: 0.45921373 | F36: 1.6721228 | G36: -1.1227465 | H36: -1.4245218 | I36: 2.6455086 | J36: -0.86586866 | K36: 2.8032472 | L36: 5.0290772 | M36: -1.5370745 | N36: 4.134624 | O36: 1.9679872 | P36: -5.2367755 | Q36: -25.290101 | R36: 33.259047 | S36: 1.5366438 | T36: -4.7389196 | U36: 15.123673 | V36: -12.540484 | W36: 13.956656 | X36: 5.9250661 | Y36: -2.5247783 | Z36: -0.79782628 | AA36: 3.5285237 | AB36: 3.9101277 | AC36: 4.2980714 | AD36: 0.88644397 | AE36: -1.5961719 | AF36: 3.1852689 | AG36: 1.4253527 | AH36: 6.9685372 | AI36: -2.0594866 | AJ36: -0.71605213 | AK36: 3.7904706 | AL36: 2.2237433 | AM36: 1.7813745
A37: Source: Uganda Bureau of Statistics

Sheet Deseason_Growth_Decomp
A1: Table 8: SEASONALLY ADJUSTED Value Added at constant 2016/17 prices, DECOMPOSITION OF GROWTH, 2016/17-2025/26
J2: 2018/19
B3: 2016/17 | F3: 2017/18 | J3: 2018/19 | N3: 2019/20 | R3: 2020/21 | V3: 2021/22 | Z3: 2022/23 | AD3: 2023/24 | AH3: 2024/25 | AL3: 2025/26
B4: Q1 | C4: Q2 | D4: Q3 | E4: Q4 | F4: Q1 | G4: Q2 | H4: Q3 | I4: Q4 | J4: Q1 | K4: Q2 | L4: Q3 | M4: Q4 | N4: Q1 | O4: Q2 | P4: Q3 | Q4: Q4 | R4: Q1 | S4: Q2 | T4: Q3 | U4: Q4 | V4: Q1 | W4: Q2 | X4: Q3 | Y4: Q4 | Z4: Q1 | AA4: Q2 | AB4: Q3 | AC4: Q4 | AD4: Q1 | AE4: Q2 | AF4: Q3 | AG4: Q4 | AH4: Q1 | AI4: Q2 | AJ4: Q3 | AK4: Q4 | AL4: Q1 | AM4: Q2
A5: GDP AT MARKET PRICES | B5: 0.86546068 | C5: 1.5217117 | D5: 2.9807704 | E5: 0.93312038 | F5: 1.4844207 | G5: 0.96014433 | H5: 2.3199933 | I5: 0.68300934 | J5: 1.8136644 | K5: 0.64811638 | L5: 4.6692978 | M5: -0.5994792 | N5: 2.996502 | O5: 1.1424887 | P5: -2.2614196 | Q5: -7.2116804 | R5: 7.7549618 | S5: 2.2828561 | T5: 0.75671459 | U5: 1.0728699 | V5: -1.7322538 | W5: 4.766823 | X5: 2.2077868 | Y5: 0.31372912 | Z5: 1.149128 | AA5: 0.89760246 | AB5: -0.10537823 | AC5: 3.2714827 | AD5: 1.3882041 | AE5: 1.4696532 | AF5: 0.77952016 | AG5: 1.7342644 | AH5: 2.1282137 | AI5: 0.80694549 | AJ5: 3.2672815 | AK5: -0.74864265 | AL5: 1.9166271 | AM5: 3.9628848
A6: AGRICULTURE,FORESTRY&FISHING | B6: -0.2245015 | C6: 0.95316221 | D6: 0.80991794 | E6: -0.13420169 | F6: 0.28288663 | G6: -0.32081289 | H6: 1.2355628 | I6: -0.77885748 | J6: 0.40959257 | K6: -0.0055901229 | L6: 2.4949948 | M6: -1.0866663 | N6: -0.0049126136 | O6: 0.31397692 | P6: 0.49799331 | Q6: 0.44335128 | R6: -0.049883091 | S6: 0.74225737 | T6: -0.89145845 | U6: 0.3489727 | V6: 0.87115331 | W6: -0.90844265 | X6: 1.1835372 | Y6: 1.1760502 | Z6: -0.82045936 | AA6: 0.9965195 | AB6: -0.36222972 | AC6: -0.38315189 | AD6: 0.9715867 | AE6: 0.17661751 | AF6: 0.45361106 | AG6: 0.70440942 | AH6: 0.19242377 | AI6: 0.30120174 | AJ6: 0.80987545 | AK6: -0.49391831 | AL6: 0.40018874 | AM6: 1.2269843
A7: Cash crops | B7: -0.31765548 | C7: 0.78557828 | D7: -0.20935294 | E7: 0.12776493 | F7: 0.070609539 | G7: -0.13736403 | H7: -0.020928227 | I7: -0.0046215045 | J7: 0.15528922 | K7: -0.0097784435 | L7: -0.10161475 | M7: 0.22281205 | N7: -0.06017443 | O7: 0.12818206 | P7: 0.10225378 | Q7: -0.11898135 | R7: 0.036348465 | S7: 0.2823333 | T7: 0.10389576 | U7: 0.020964934 | V7: 0.10246793 | W7: -0.054946709 | X7: -0.20948552 | Y7: 0.21637648 | Z7: -0.0026858134 | AA7: -0.11160317 | AB7: 0.08759046 | AC7: 0.042322473 | AD7: 0.11936705 | AE7: 0.16352867 | AF7: 0.10977395 | AG7: -0.17445943 | AH7: 0.33116322 | AI7: 0.0076087112 | AJ7: 0.096949234 | AK7: -0.20484099 | AL7: 0.30810405 | AM7: 0.15716596
A8: Food crops | B8: -0.069871473 | C8: 0.10955673 | D8: 0.98277621 | E8: -0.19910938 | F8: 0.37049905 | G8: -0.022130939 | H8: 1.1600257 | I8: -1.1175518 | J8: -0.0055538744 | K8: -0.24730881 | L8: 2.3541541 | M8: -1.5092848 | N8: -0.0727482 | O8: 0.21579401 | P8: 0.52130576 | Q8: 0.61734986 | R8: -0.25106943 | S8: 0.10870482 | T8: -0.77299572 | U8: 0.31950056 | V8: 0.3872051 | W8: -0.66375889 | X8: 1.1388385 | Y8: 0.83627308 | Z8: -0.52737725 | AA8: 0.50134429 | AB8: -0.91361953 | AC8: 0.047192714 | AD8: 0.84388031 | AE8: -0.11972393 | AF8: 0.22927623 | AG8: 0.26960709 | AH8: 0.25438436 | AI8: -0.046809912 | AJ8: 0.0073392143 | AK8: 0.076018416 | AL8: -0.10805438 | AM8: 0.87584607
A9: Livestock | B9: 0.032166043 | C9: 0.071289217 | D9: 0.055825205 | E9: 0.050426823 | F9: 0.064328988 | G9: 0.027310238 | H9: 0.067747985 | I9: 0.039701026 | J9: 0.062675255 | K9: 0.059740975 | L9: 0.050094858 | M9: 0.067924731 | N9: 0.057277256 | O9: 0.061114346 | P9: 0.061192034 | Q9: 0.052589561 | R9: 0.064050742 | S9: 0.06676531 | T9: 0.070385285 | U9: 0.0721915 | V9: 0.066241381 | W9: 0.065093927 | X9: 0.071777967 | Y9: 0.079586772 | Z9: 0.080719254 | AA9: 0.068844355 | AB9: 0.097191631 | AC9: 0.036871092 | AD9: 0.070450516 | AE9: 0.078230016 | AF9: 0.073191085 | AG9: 0.077903773 | AH9: 0.073234337 | AI9: 0.083655751 | AJ9: 0.093978748 | AK9: 0.068494796 | AL9: 0.091720489 | AM9: 0.084589839
A10: Agriculture Support Services | B10: 0.00043202561 | C10: 9.489195e-05 | D10: 0.00014305754 | E10: 0.0001279087 | F10: -0.00033183812 | G10: -0.00024322775 | H10: 0.00011432717 | I10: 0.00067432161 | J10: 8.3174022e-05 | K10: 0.00034599273 | L10: -0.00014116154 | M10: 0.0018102241 | N10: 0.00032527865 | O10: 0.001029727 | P10: -0.0036437233 | Q10: 0.00041541044 | R10: 0.0011726082 | S10: 0.00070868602 | T10: 0.00079796899 | U10: -0.00022768601 | V10: -0.00020121303 | W10: 2.2187328e-05 | X10: 0.00064053762 | Y10: -4.3325549e-05 | Z10: -0.00018774498 | AA10: 0.00022260152 | AB10: -4.5274317e-05 | AC10: 0.00013224367 | AD10: 0.00049012561 | AE10: 0.00044640338 | AF10: 4.0606006e-05 | AG10: 0.0002194384 | AH10: -7.3485719e-05 | AI10: -0.00061718985 | AJ10: 0.00033118543 | AK10: 0.0026002362 | AL10: -0.0039520566 | AM10: 0.0010205483
A11: Forestry | B11: 0.18974505 | C11: -0.013259763 | D11: 0.097225432 | E11: 0.044203974 | F11: 0.0011966875 | G11: -0.049330817 | H11: 0.11335484 | I11: 0.095476963 | J11: -0.012469257 | K11: 0.014586886 | L11: -0.029133382 | M11: 0.11255314 | N11: 0.048629561 | O11: 0.054492059 | P11: -0.08132009 | Q11: -0.043916662 | R11: -0.0084545627 | S11: 0.2873699 | T11: -0.06687445 | U11: -0.036500245 | V11: -0.015481827 | W11: 0.035273979 | X11: 0.18503146 | Y11: -0.020131424 | Z11: -0.068298341 | AA11: 0.04750108 | AB11: 0.12344218 | AC11: -0.034082263 | AD11: 0.030518396 | AE11: -0.021967991 | AF11: -0.17061999 | AG11: 0.49805078 | AH11: -0.19163885 | AI11: 0.031133594 | AJ11: -0.100632 | AK11: 0.17627213 | AL11: 0.1856233 | AM11: -0.012498146
A12: Fishing | B12: -0.059317666 | C12: -9.7140828e-05 | D12: -0.11669902 | E12: -0.15761594 | F12: -0.22341579 | G12: -0.13905411 | H12: -0.084751827 | I12: 0.2074635 | J12: 0.20956806 | K12: 0.17682328 | L12: 0.22163516 | M12: 0.017518339 | N12: 0.021777921 | O12: -0.14663528 | P12: -0.10179445 | Q12: -0.064105543 | R12: 0.10806908 | S12: -0.0036246369 | T12: -0.22666729 | U12: -0.026956361 | V12: 0.33092194 | W12: -0.29012715 | X12: -0.0032657821 | Y12: 0.0639886 | Z12: -0.30262947 | AA12: 0.49021034 | AB12: 0.24321081 | AC12: -0.47558815 | AD12: -0.093119695 | AE12: 0.076104346 | AF12: 0.21194918 | AG12: 0.03308776 | AH12: -0.27464582 | AI12: 0.22623079 | AJ12: 0.71190906 | AK12: -0.6124629 | AL12: -0.073252657 | AM12: 0.12086003
A13: INDUSTRY | B13: 0.79824503 | C13: 0.95826169 | D13: 0.70932202 | E13: -0.40900321 | F13: 0.091245723 | G13: 0.20955402 | H13: 0.97043013 | I13: 0.76417242 | J13: 0.25522522 | K13: 0.53182127 | L13: 0.90340436 | M13: 0.19251879 | N13: 0.89815159 | O13: 0.67351786 | P13: -0.84834935 | Q13: -3.255976 | R13: 2.9288135 | S13: 1.0028944 | T13: 0.25236368 | U13: -0.0072132994 | V13: -1.2743979 | W13: 3.3036481 | X13: -0.33043466 | Y13: 0.11609909 | Z13: -0.16455537 | AA13: -0.1511315 | AB13: 0.40695647 | AC13: 1.5112374 | AD13: 0.40021858 | AE13: -0.955435 | AF13: 0.81063838 | AG13: -0.027106292 | AH13: 1.4423909 | AI13: -0.20862995 | AJ13: 0.6661627 | AK13: 0.013094571 | AL13: 1.1102474 | AM13: 1.3777464
A14: Mining & quarrying | B14: 0.21634352 | C14: 0.2490642 | D14: -0.026427301 | E14: 0.15937567 | F14: -0.26281578 | G14: -0.13074338 | H14: 0.13591899 | I14: 0.27270454 | J14: -0.042020652 | K14: -0.21514873 | L14: 0.39438396 | M14: -0.17028268 | N14: 0.14673231 | O14: 0.32291523 | P14: -0.061427143 | Q14: -0.61704066 | R14: 0.95179668 | S14: -0.29141527 | T14: -0.24199508 | U14: -0.17573817 | V14: -0.34570309 | W14: 1.4660601 | X14: -0.25315635 | Y14: 0.10386632 | Z14: -0.64421193 | AA14: -0.30794425 | AB14: 0.4918687 | AC14: 1.4916587 | AD14: -0.53458603 | AE14: -0.49115748 | AF14: -0.27929103 | AG14: -0.79394512 | AH14: 1.2705329 | AI14: -0.052334223 | AJ14: -0.39424748 | AK14: -0.47706321 | AL14: 0.69037873 | AM14: 0.66755495
A15: Manufacturing | B15: -0.21915951 | C15: 0.38419514 | D15: 0.7915417 | E15: -0.4763844 | F15: 0.11733199 | G15: 0.20858108 | H15: 0.43351257 | I15: 0.29154234 | J15: 0.10667127 | K15: 0.49224689 | L15: 0.30337405 | M15: 0.11594888 | N15: 0.82876419 | O15: 0.075415217 | P15: -1.0764684 | Q15: -1.9034154 | R15: 2.4745032 | S15: -0.15275631 | T15: 0.16295744 | U15: 0.10032164 | V15: -1.073905 | W15: 1.9013031 | X15: 0.28157271 | Y15: -0.08533173 | Z15: -0.0037871987 | AA15: 0.12113002 | AB15: -0.21558215 | AC15: -0.15922958 | AD15: 0.83648902 | AE15: -0.60300672 | AF15: 0.61497716 | AG15: 0.63138159 | AH15: 0.16891186 | AI15: -0.25834476 | AJ15: 0.20687942 | AK15: 0.35363311 | AL15: 0.33850204 | AM15: 0.38464208
A16: Electricity | B16: 0.019300847 | C16: 0.047854089 | D16: 0.066921953 | E16: -0.020423115 | F16: 0.037260782 | G16: 0.01093404 | H16: -0.0057186226 | I16: -0.017961295 | J16: 0.013911902 | K16: 0.0048955511 | L16: 0.023283418 | M16: 0.054830888 | N16: 0.061673614 | O16: 0.039885473 | P16: 0.041501517 | Q16: -0.15242982 | R16: 0.19705653 | S16: 0.0443918 | T16: 0.025476584 | U16: 0.018100144 | V16: -0.017338688 | W16: 0.019558161 | X16: 0.010060455 | Y16: 0.017375716 | Z16: 0.035450049 | AA16: 0.044791064 | AB16: 0.023200497 | AC16: 0.0426619 | AD16: 0.051800902 | AE16: 0.00059391529 | AF16: 0.028799642 | AG16: 0.016556234 | AH16: 0.045132553 | AI16: 0.060210278 | AJ16: 0.069537682 | AK16: 0.066072319 | AL16: 0.18280968 | AM16: -0.15199123
... A33: Activities of Households | B33: 0.0062683288 | C33: 0.0061630287 | D33: 0.0058918861 | E33: 0.0056977575 | F33: 0.0055181607 | G33: 0.0055347323 | H33: 0.0054664577 | I33: 0.00541886 | J33: 0.0054510789 | K33: 0.005406099 | L33: 0.0053231463 | M33: 0.0051037137 | N33: 0.0052164178 | O33: 0.0050978404 | P33: 0.0049431931 | Q33: 0.0050491803 | R33: 0.0055732951 | S33: 0.0052478724 | T33: 0.0052024104 | U33: 0.0051989987 | V33: 0.0051760157 | W33: 0.0053037702 | X33: 0.0050115448 | Y33: 0.0048946976 | Z33: 0.0049331931 | AA33: 0.0049620155 | AB33: 0.0050198167 | AC33: 0.0050751853 | AD33: 0.0048851784 | AE33: 0.0048646881 | AF33: 0.0047869216 | AG33: 0.0047683915 | AH33: 0.0046494296 | AI33: 0.0046339605 | AJ33: 0.0047575973 | AK33: 0.0046737255 | AL33: 0.0045448103 | AM33: 0.00019587285
A35: ADJUSTMENTS
A36: Taxes on products | B36: 0.3961692 | C36: -0.29611979 | D36: 0.61246751 | E36: 0.032742406 | F36: 0.11866427 | G36: -0.079824467 | H36: -0.099190448 | I36: 0.17746729 | J36: -0.059216798 | K36: 0.18666867 | L36: 0.34205782 | M36: -0.10490504 | N36: 0.27952558 | O36: 0.13451803 | P36: -0.36087133 | Q36: -1.6897124 | R36: 1.7891917 | S36: 0.10223031 | T36: -0.31297222 | U36: 0.94433317 | V36: -0.89189207 | W36: 0.8834367 | X36: 0.40794647 | Y36: -0.1801557 | Z36: -0.05531806 | AA36: 0.23994444 | AB36: 0.27282726 | AC36: 0.31195088 | AD36: 0.064977014 | AE36: -0.11642158 | AF36: 0.22530756 | AG36: 0.10322798 | AH36: 0.50314826 | AI36: -0.15574841 | AJ36: -0.052611567 | AK36: 0.2677602 | AL36: 0.16427012 | AM36: 0.13198844
A37: Source: Uganda Bureau of Statistics

Sheet Deseason
X1: Table 11: SEASONALLY ADJUSTED Value Added at constant 2009/10 prices, IMPLICIT PRICE DEFLATORS, 2013/14-2017/18
B2: 2008Q1 | C2: 2008Q2 | D2: 2008Q3 | E2: 2008Q4 | F2: 2009Q1 | G2: 2009Q2 | H2: 2009Q3 | I2: 2009Q4 | J2: 2010Q1 | K2: 2010Q2 | L2: 2010Q3 | M2: 2010Q4 | N2: 2011Q1 | O2: 2011Q2 | P2: 2011Q3 | Q2: 2011Q4 | R2: 2012Q1 | S2: 2012Q2 | T2: 2012Q3 | U2: 2012Q4 | V2: 2013Q1 | W2: 2013Q2 | X2: 2013Q3 | Y2: 2013Q4 | Z2: 2014Q1 | AA2: 2014Q2 | AB2: 2014Q3 | AC2: 2014Q4 | AD2: 2015Q1 | AE2: 2015Q2 | AF2: 2015Q3
B3: 2007/08 | D3: 2008/09 | H3: 2009/10 | L3: 2010/11 | P3: 2011/12 | U3: 2012/13 | X3: 2013/14 | AB3: 2014/15 | AF3: 2015/16 | AJ3: 2016/17 | AN3: 2017/18
A4: ACTIVITY | B4: Q3 | C4: Q4 | D4: Q1 | E4: Q2 | F4: Q3 | G4: Q4 | H4: Q1 | I4: Q2 | J4: Q3 | K4: Q4 | L4: Q1 | M4: Q2 | N4: Q3 | O4: Q4 | P4: Q1 | Q4: Q2 | R4: Q3 | S4: Q4 | T4: Q1 | U4: Q2 | V4: Q3 | W4: Q4 | X4: Q1 | Y4: Q2 | Z4: Q3 | AA4: Q4 | AB4: Q1 | AC4: Q2 | AD4: Q3 | AE4: Q4 | AF4: Q1 | AG4: Q2 | AH4: Q3 | AI4: Q4 | AJ4: Q1 | AK4: Q2 | AL4: Q3 | AM4: Q4 | AN4: Q1 | AO4: Q2 | AP4: Q3 | AQ4: Q4
A5: GDP AT MARKET PRICES | B5: =#REF!/Deseason_VA!#REF!*100 -> #REF! | C5: =#REF!/Deseason_VA!#REF!*100 -> #REF! | D5: =#REF!/Deseason_VA!#REF!*100 -> #REF! | E5: =#REF!/Deseason_VA!#REF!*100 -> #REF! | F5: =#REF!/Deseason_VA!#REF!*100 -> #REF! | G5: =#REF!/Deseason_VA!#REF!*100 -> #REF! | H5: =#REF!/Deseason_VA!#REF!*100 -> #REF! | I5: =#REF!/Deseason_VA!#REF!*100 -> #REF! | ... AI5: =#REF!/Deseason_VA!#REF!*100 -> #REF! | AJ5: =#REF!/Deseason_VA!B5*100 -> #REF! | AK5: =#REF!/Deseason_VA!C5*100 -> #REF! | AL5: =#REF!/Deseason_VA!D5*100 -> #REF! | AM5: =#REF!/Deseason_VA!E5*100 -> #REF! | AN5: =#REF!/Deseason_VA!F5*100 -> #REF! | AO5: =#REF!/Deseason_VA!G5*100 -> #REF! | AP5: =#REF!/Deseason_VA!H5*100 -> #REF! | AQ5: =#REF!/Deseason_VA!I5*100 -> #REF!
A6: AGRICULTURE,FORESTRY&FISHING | B6: =#REF!/Deseason_VA!#REF!*100 -> #REF! | C6: =#REF!/Deseason_VA!#REF!*100 -> #REF! | D6: =#REF!/Deseason_VA!#REF!*100 -> #REF! | E6: =#REF!/Deseason_VA!#REF!*100 -> #REF! | F6: =#REF!/Deseason_VA!#REF!*100 -> #REF! | G6: =#REF!/Deseason_VA!#REF!*100 -> #REF! | H6: =#REF!/Deseason_VA!#REF!*100 -> #REF! | I6: =#REF!/Deseason_VA!#REF!*100 -> #REF! | ... AI6: =#REF!/Deseason_VA!#REF!*100 -> #REF! | AJ6: =#REF!/Deseason_VA!B6*100 -> #REF! | AK6: =#REF!/Deseason_VA!C6*100 -> #REF! | AL6: =#REF!/Deseason_VA!D6*100 -> #REF! | AM6: =#REF!/Deseason_VA!E6*100 -> #REF! | AN6: =#REF!/Deseason_VA!F6*100 -> #REF! | AO6: =#REF!/Deseason_VA!G6*100 -> #REF! | AP6: =#REF!/Deseason_VA!H6*100 -> #REF! | AQ6: =#REF!/Deseason_VA!I6*100 -> #REF!
A7: Cash crops | B7: =#REF!/Deseason_VA!#REF!*100 -> #REF! | C7: =#REF!/Deseason_VA!#REF!*100 -> #REF! | D7: =#REF!/Deseason_VA!#REF!*100 -> #REF! | E7: =#REF!/Deseason_VA!#REF!*100 -> #REF! | F7: =#REF!/Deseason_VA!#REF!*100 -> #REF! | G7: =#REF!/Deseason_VA!#REF!*100 -> #REF! | H7: =#REF!/Deseason_VA!#REF!*100 -> #REF! | I7: =#REF!/Deseason_VA!#REF!*100 -> #REF! | ... AI7: =#REF!/Deseason_VA!#REF!*100 -> #REF! | AJ7: =#REF!/Deseason_VA!B7*100 -> #REF! | AK7: =#REF!/Deseason_VA!C7*100 -> #REF! | AL7: =#REF!/Deseason_VA!D7*100 -> #REF! | AM7: =#REF!/Deseason_VA!E7*100 -> #REF! | AN7: =#REF!/Deseason_VA!F7*100 -> #REF! | AO7: =#REF!/Deseason_VA!G7*100 -> #REF! | AP7: =#REF!/Deseason_VA!H7*100 -> #REF! | AQ7: =#REF!/Deseason_VA!I7*100 -> #REF!
A8: Food crops | B8: =#REF!/Deseason_VA!#REF!*100 -> #REF! | C8: =#REF!/Deseason_VA!#REF!*100 -> #REF! | D8: =#REF!/Deseason_VA!#REF!*100 -> #REF! | E8: =#REF!/Deseason_VA!#REF!*100 -> #REF! | F8: =#REF!/Deseason_VA!#REF!*100 -> #REF! | G8: =#REF!/Deseason_VA!#REF!*100 -> #REF! | H8: =#REF!/Deseason_VA!#REF!*100 -> #REF! | I8: =#REF!/Deseason_VA!#REF!*100 -> #REF! | ... AI8: =#REF!/Deseason_VA!#REF!*100 -> #REF! | AJ8: =#REF!/Deseason_VA!B8*100 -> #REF! | AK8: =#REF!/Deseason_VA!C8*100 -> #REF! | AL8: =#REF!/Deseason_VA!D8*100 -> #REF! | AM8: =#REF!/Deseason_VA!E8*100 -> #REF! | AN8: =#REF!/Deseason_VA!F8*100 -> #REF! | AO8: =#REF!/Deseason_VA!G8*100 -> #REF! | AP8: =#REF!/Deseason_VA!H8*100 -> #REF! | AQ8: =#REF!/Deseason_VA!I8*100 -> #REF!
A9: Livestock | B9: =#REF!/Deseason_VA!#REF!*100 -> #REF! | C9: =#REF!/Deseason_VA!#REF!*100 -> #REF! | D9: =#REF!/Deseason_VA!#REF!*100 -> #REF! | E9: =#REF!/Deseason_VA!#REF!*100 -> #REF! | F9: =#REF!/Deseason_VA!#REF!*100 -> #REF! | G9: =#REF!/Deseason_VA!#REF!*100 -> #REF! | H9: =#REF!/Deseason_VA!#REF!*100 -> #REF! | I9: =#REF!/Deseason_VA!#REF!*100 -> #REF! | ... AI9: =#REF!/Deseason_VA!#REF!*100 -> #REF! | AJ9: =#REF!/Deseason_VA!B9*100 -> #REF! | AK9: =#REF!/Deseason_VA!C9*100 -> #REF! | AL9: =#REF!/Deseason_VA!D9*100 -> #REF! | AM9: =#REF!/Deseason_VA!E9*100 -> #REF! | AN9: =#REF!/Deseason_VA!F9*100 -> #REF! | AO9: =#REF!/Deseason_VA!G9*100 -> #REF! | AP9: =#REF!/Deseason_VA!H9*100 -> #REF! | AQ9: =#REF!/Deseason_VA!I9*100 -> #REF!
A10: Agriculture Support Services | B10: =#REF!/Deseason_VA!#REF!*100 -> #REF! | C10: =#REF!/Deseason_VA!#REF!*100 -> #REF! | D10: =#REF!/Deseason_VA!#REF!*100 -> #REF! | E10: =#REF!/Deseason_VA!#REF!*100 -> #REF! | F10: =#REF!/Deseason_VA!#REF!*100 -> #REF! | G10: =#REF!/Deseason_VA!#REF!*100 -> #REF! | H10: =#REF!/Deseason_VA!#REF!*100 -> #REF! | I10: =#REF!/Deseason_VA!#REF!*100 -> #REF! | ... AI10: =#REF!/Deseason_VA!#REF!*100 -> #REF! | AJ10: =#REF!/Deseason_VA!B10*100 -> #REF! | AK10: =#REF!/Deseason_VA!C10*100 -> #REF! | AL10: =#REF!/Deseason_VA!D10*100 -> #REF! | AM10: =#REF!/Deseason_VA!E10*100 -> #REF! | AN10: =#REF!/Deseason_VA!F10*100 -> #REF! | AO10: =#REF!/Deseason_VA!G10*100 -> #REF! | AP10: =#REF!/Deseason_VA!H10*100 -> #REF! | AQ10: =#REF!/Deseason_VA!I10*100 -> #REF!
A11: Forestry | B11: =#REF!/Deseason_VA!#REF!*100 -> #REF! | C11: =#REF!/Deseason_VA!#REF!*100 -> #REF! | D11: =#REF!/Deseason_VA!#REF!*100 -> #REF! | E11: =#REF!/Deseason_VA!#REF!*100 -> #REF! | F11: =#REF!/Deseason_VA!#REF!*100 -> #REF! | G11: =#REF!/Deseason_VA!#REF!*100 -> #REF! | H11: =#REF!/Deseason_VA!#REF!*100 -> #REF! | I11: =#REF!/Deseason_VA!#REF!*100 -> #REF! | ... AI11: =#REF!/Deseason_VA!#REF!*100 -> #REF! | AJ11: =#REF!/Deseason_VA!B11*100 -> #REF! | AK11: =#REF!/Deseason_VA!C11*100 -> #REF! | AL11: =#REF!/Deseason_VA!D11*100 -> #REF! | AM11: =#REF!/Deseason_VA!E11*100 -> #REF! | AN11: =#REF!/Deseason_VA!F11*100 -> #REF! | AO11: =#REF!/Deseason_VA!G11*100 -> #REF! | AP11: =#REF!/Deseason_VA!H11*100 -> #REF! | AQ11: =#REF!/Deseason_VA!I11*100 -> #REF!
A12: Fishing | B12: =#REF!/Deseason_VA!#REF!*100 -> #REF! | C12: =#REF!/Deseason_VA!#REF!*100 -> #REF! | D12: =#REF!/Deseason_VA!#REF!*100 -> #REF! | E12: =#REF!/Deseason_VA!#REF!*100 -> #REF! | F12: =#REF!/Deseason_VA!#REF!*100 -> #REF! | G12: =#REF!/Deseason_VA!#REF!*100 -> #REF! | H12: =#REF!/Deseason_VA!#REF!*100 -> #REF! | I12: =#REF!/Deseason_VA!#REF!*100 -> #REF! | ... AI12: =#REF!/Deseason_VA!#REF!*100 -> #REF! | AJ12: =#REF!/Deseason_VA!B12*100 -> #REF! | AK12: =#REF!/Deseason_VA!C12*100 -> #REF! | AL12: =#REF!/Deseason_VA!D12*100 -> #REF! | AM12: =#REF!/Deseason_VA!E12*100 -> #REF! | AN12: =#REF!/Deseason_VA!F12*100 -> #REF! | AO12: =#REF!/Deseason_VA!G12*100 -> #REF! | AP12: =#REF!/Deseason_VA!H12*100 -> #REF! | AQ12: =#REF!/Deseason_VA!I12*100 -> #REF!
A13: INDUSTRY | B13: =#REF!/Deseason_VA!#REF!*100 -> #REF! | C13: =#REF!/Deseason_VA!#REF!*100 -> #REF! | D13: =#REF!/Deseason_VA!#REF!*100 -> #REF! | E13: =#REF!/Deseason_VA!#REF!*100 -> #REF! | F13: =#REF!/Deseason_VA!#REF!*100 -> #REF! | G13: =#REF!/Deseason_VA!#REF!*100 -> #REF! | H13: =#REF!/Deseason_VA!#REF!*100 -> #REF! | I13: =#REF!/Deseason_VA!#REF!*100 -> #REF! | ... AI13: =#REF!/Deseason_VA!#REF!*100 -> #REF! | AJ13: =#REF!/Deseason_VA!B13*100 -> #REF! | AK13: =#REF!/Deseason_VA!C13*100 -> #REF! | AL13: =#REF!/Deseason_VA!D13*100 -> #REF! | AM13: =#REF!/Deseason_VA!E13*100 -> #REF! | AN13: =#REF!/Deseason_VA!F13*100 -> #REF! | AO13: =#REF!/Deseason_VA!G13*100 -> #REF! | AP13: =#REF!/Deseason_VA!H13*100 -> #REF! | AQ13: =#REF!/Deseason_VA!I13*100 -> #REF!
A14: Mining & quarrying | B14: =#REF!/Deseason_VA!#REF!*100 -> #REF! | C14: =#REF!/Deseason_VA!#REF!*100 -> #REF! | D14: =#REF!/Deseason_VA!#REF!*100 -> #REF! | E14: =#REF!/Deseason_VA!#REF!*100 -> #REF! | F14: =#REF!/Deseason_VA!#REF!*100 -> #REF! | G14: =#REF!/Deseason_VA!#REF!*100 -> #REF! | H14: =#REF!/Deseason_VA!#REF!*100 -> #REF! | I14: =#REF!/Deseason_VA!#REF!*100 -> #REF! | ... AI14: =#REF!/Deseason_VA!#REF!*100 -> #REF! | AJ14: =#REF!/Deseason_VA!B14*100 -> #REF! | AK14: =#REF!/Deseason_VA!C14*100 -> #REF! | AL14: =#REF!/Deseason_VA!D14*100 -> #REF! | AM14: =#REF!/Deseason_VA!E14*100 -> #REF! | AN14: =#REF!/Deseason_VA!F14*100 -> #REF! | AO14: =#REF!/Deseason_VA!G14*100 -> #REF! | AP14: =#REF!/Deseason_VA!H14*100 -> #REF! | AQ14: =#REF!/Deseason_VA!I14*100 -> #REF!
A15: Manufacturing | B15: =#REF!/Deseason_VA!#REF!*100 -> #REF! | C15: =#REF!/Deseason_VA!#REF!*100 -> #REF! | D15: =#REF!/Deseason_VA!#REF!*100 -> #REF! | E15: =#REF!/Deseason_VA!#REF!*100 -> #REF! | F15: =#REF!/Deseason_VA!#REF!*100 -> #REF! | G15: =#REF!/Deseason_VA!#REF!*100 -> #REF! | H15: =#REF!/Deseason_VA!#REF!*100 -> #REF! | I15: =#REF!/Deseason_VA!#REF!*100 -> #REF! | ... AI15: =#REF!/Deseason_VA!#REF!*100 -> #REF! | AJ15: =#REF!/Deseason_VA!B15*100 -> #REF! | AK15: =#REF!/Deseason_VA!C15*100 -> #REF! | AL15: =#REF!/Deseason_VA!D15*100 -> #REF! | AM15: =#REF!/Deseason_VA!E15*100 -> #REF! | AN15: =#REF!/Deseason_VA!F15*100 -> #REF! | AO15: =#REF!/Deseason_VA!G15*100 -> #REF! | AP15: =#REF!/Deseason_VA!H15*100 -> #REF! | AQ15: =#REF!/Deseason_VA!I15*100 -> #REF!
A16: Electricity | B16: =#REF!/Deseason_VA!#REF!*100 -> #REF! | C16: =#REF!/Deseason_VA!#REF!*100 -> #REF! | D16: =#REF!/Deseason_VA!#REF!*100 -> #REF! | E16: =#REF!/Deseason_VA!#REF!*100 -> #REF! | F16: =#REF!/Deseason_VA!#REF!*100 -> #REF! | G16: =#REF!/Deseason_VA!#REF!*100 -> #REF! | H16: =#REF!/Deseason_VA!#REF!*100 -> #REF! | I16: =#REF!/Deseason_VA!#REF!*100 -> #REF! | ... AI16: =#REF!/Deseason_VA!#REF!*100 -> #REF! | AJ16: =#REF!/Deseason_VA!B16*100 -> #REF! | AK16: =#REF!/Deseason_VA!C16*100 -> #REF! | AL16: =#REF!/Deseason_VA!D16*100 -> #REF! | AM16: =#REF!/Deseason_VA!E16*100 -> #REF! | AN16: =#REF!/Deseason_VA!F16*100 -> #REF! | AO16: =#REF!/Deseason_VA!G16*100 -> #REF! | AP16: =#REF!/Deseason_VA!H16*100 -> #REF! | AQ16: =#REF!/Deseason_VA!I16*100 -> #REF!
... A30: Human Health & Social Work | B30: =#REF!/Deseason_VA!#REF!*100 -> #REF! | C30: =#REF!/Deseason_VA!#REF!*100 -> #REF! | D30: =#REF!/Deseason_VA!#REF!*100 -> #REF! | E30: =#REF!/Deseason_VA!#REF!*100 -> #REF! | F30: =#REF!/Deseason_VA!#REF!*100 -> #REF! | G30: =#REF!/Deseason_VA!#REF!*100 -> #REF! | H30: =#REF!/Deseason_VA!#REF!*100 -> #REF! | I30: =#REF!/Deseason_VA!#REF!*100 -> #REF! | ... AI30: =#REF!/Deseason_VA!#REF!*100 -> #REF! | AJ30: =#REF!/Deseason_VA!B30*100 -> #REF! | AK30: =#REF!/Deseason_VA!C30*100 -> #REF! | AL30: =#REF!/Deseason_VA!D30*100 -> #REF! | AM30: =#REF!/Deseason_VA!E30*100 -> #REF! | AN30: =#REF!/Deseason_VA!F30*100 -> #REF! | AO30: =#REF!/Deseason_VA!G30*100 -> #REF! | AP30: =#REF!/Deseason_VA!H30*100 -> #REF! | AQ30: =#REF!/Deseason_VA!I30*100 -> #REF!
A31: Arts, Entertainment & Recreation | B31: =#REF!/Deseason_VA!#REF!*100 -> #REF! | C31: =#REF!/Deseason_VA!#REF!*100 -> #REF! | D31: =#REF!/Deseason_VA!#REF!*100 -> #REF! | E31: =#REF!/Deseason_VA!#REF!*100 -> #REF! | F31: =#REF!/Deseason_VA!#REF!*100 -> #REF! | G31: =#REF!/Deseason_VA!#REF!*100 -> #REF! | H31: =#REF!/Deseason_VA!#REF!*100 -> #REF! | I31: =#REF!/Deseason_VA!#REF!*100 -> #REF! | ... P31: =#REF!/Deseason_VA!#REF!*100 -> #REF! | Q31: Table 10: Summary of QGDP at constant 2009/10 prices, percentage change, 2010/11-2015/16 | R31: =#REF!/Deseason_VA!#REF!*100 -> #REF! | S31: =#REF!/Deseason_VA!#REF!*100 -> #REF! | T31: =#REF!/Deseason_VA!#REF!*100 -> #REF! | U31: =#REF!/Deseason_VA!#REF!*100 -> #REF! | V31: =#REF!/Deseason_VA!#REF!*100 -> #REF! | W31: =#REF!/Deseason_VA!#REF!*100 -> #REF! | X31: =#REF!/Deseason_VA!#REF!*100 -> #REF! | Y31: =#REF!/Deseason_VA!#REF!*100 -> #REF! | ... AI31: =#REF!/Deseason_VA!#REF!*100 -> #REF! | AJ31: =#REF!/Deseason_VA!B31*100 -> #REF! | AK31: =#REF!/Deseason_VA!C31*100 -> #REF! | AL31: =#REF!/Deseason_VA!D31*100 -> #REF! | AM31: =#REF!/Deseason_VA!E31*100 -> #REF! | AN31: =#REF!/Deseason_VA!F31*100 -> #REF! | AO31: =#REF!/Deseason_VA!G31*100 -> #REF! | AP31: =#REF!/Deseason_VA!H31*100 -> #REF! | AQ31: =#REF!/Deseason_VA!I31*100 -> #REF!
A32: Other Service Activities | B32: =#REF!/Deseason_VA!#REF!*100 -> #REF! | C32: =#REF!/Deseason_VA!#REF!*100 -> #REF! | D32: =#REF!/Deseason_VA!#REF!*100 -> #REF! | E32: =#REF!/Deseason_VA!#REF!*100 -> #REF! | F32: =#REF!/Deseason_VA!#REF!*100 -> #REF! | G32: =#REF!/Deseason_VA!#REF!*100 -> #REF! | H32: =#REF!/Deseason_VA!#REF!*100 -> #REF! | I32: =#REF!/Deseason_VA!#REF!*100 -> #REF! | ... AI32: =#REF!/Deseason_VA!#REF!*100 -> #REF! | AJ32: =#REF!/Deseason_VA!B32*100 -> #REF! | AK32: =#REF!/Deseason_VA!C32*100 -> #REF! | AL32: =#REF!/Deseason_VA!D32*100 -> #REF! | AM32: =#REF!/Deseason_VA!E32*100 -> #REF! | AN32: =#REF!/Deseason_VA!F32*100 -> #REF! | AO32: =#REF!/Deseason_VA!G32*100 -> #REF! | AP32: =#REF!/Deseason_VA!H32*100 -> #REF! | AQ32: =#REF!/Deseason_VA!I32*100 -> #REF!
A33: Activities of Households | B33: =#REF!/Deseason_VA!#REF!*100 -> #REF! | C33: =#REF!/Deseason_VA!#REF!*100 -> #REF! | D33: =#REF!/Deseason_VA!#REF!*100 -> #REF! | E33: =#REF!/Deseason_VA!#REF!*100 -> #REF! | F33: =#REF!/Deseason_VA!#REF!*100 -> #REF! | G33: =#REF!/Deseason_VA!#REF!*100 -> #REF! | H33: =#REF!/Deseason_VA!#REF!*100 -> #REF! | I33: =#REF!/Deseason_VA!#REF!*100 -> #REF! | ... AI33: =#REF!/Deseason_VA!#REF!*100 -> #REF! | AJ33: =#REF!/Deseason_VA!B33*100 -> #REF! | AK33: =#REF!/Deseason_VA!C33*100 -> #REF! | AL33: =#REF!/Deseason_VA!D33*100 -> #REF! | AM33: =#REF!/Deseason_VA!E33*100 -> #REF! | AN33: =#REF!/Deseason_VA!F33*100 -> #REF! | AO33: =#REF!/Deseason_VA!G33*100 -> #REF! | AP33: =#REF!/Deseason_VA!H33*100 -> #REF! | AQ33: =#REF!/Deseason_VA!I33*100 -> #REF!
A35: ADJUSTMENTS
A36: Taxes on Products | B36: =#REF!/Deseason_VA!#REF!*100 -> #REF! | C36: =#REF!/Deseason_VA!#REF!*100 -> #REF! | D36: =#REF!/Deseason_VA!#REF!*100 -> #REF! | E36: =#REF!/Deseason_VA!#REF!*100 -> #REF! | F36: =#REF!/Deseason_VA!#REF!*100 -> #REF! | G36: =#REF!/Deseason_VA!#REF!*100 -> #REF! | H36: =#REF!/Deseason_VA!#REF!*100 -> #REF! | I36: =#REF!/Deseason_VA!#REF!*100 -> #REF! | ... AI36: =#REF!/Deseason_VA!#REF!*100 -> #REF! | AJ36: =#REF!/Deseason_VA!B36*100 -> #REF! | AK36: =#REF!/Deseason_VA!C36*100 -> #REF! | AL36: =#REF!/Deseason_VA!D36*100 -> #REF! | AM36: =#REF!/Deseason_VA!E36*100 -> #REF! | AN36: =#REF!/Deseason_VA!F36*100 -> #REF! | AO36: =#REF!/Deseason_VA!G36*100 -> #REF! | AP36: =#REF!/Deseason_VA!H36*100 -> #REF! | AQ36: =#REF!/Deseason_VA!I36*100 -> #REF!
A37: Source: Uganda Bureau of Statistics
Z38: 8.5

Sheet Trend_VA
A1: Table 9: TREND-CYCLE Value Added at constant 2016/17 prices, BILLION SHILLINGS, 2016/17-2025/26
B3: 2016/17 | F3: 2017/18 | J3: 2018/19 | N3: 2019/20 | R3: 2020/21 | V3: 2021/22 | Z3: 2022/23 | AD3: 2023/24 | AH3: 2024/25 | AL3: 2025/26
B4: Q1 | C4: Q2 | D4: Q3 | E4: Q4 | F4: Q1 | G4: Q2 | H4: Q3 | I4: Q4 | J4: Q1 | K4: Q2 | L4: Q3 | M4: Q4 | N4: Q1 | O4: Q2 | P4: Q3 | Q4: Q4 | R4: Q1 | S4: Q2 | T4: Q3 | U4: Q4 | V4: Q1 | W4: Q2 | X4: Q3 | Y4: Q4 | Z4: Q1 | AA4: Q2 | AB4: Q3 | AC4: Q4 | AD4: Q1 | AE4: Q2 | AF4: Q3 | AG4: Q4 | AH4: Q1 | AI4: Q2 | AJ4: Q3 | AK4: Q4 | AL4: Q1 | AM4: Q2
A5: GDP AT MARKET PRICES | B5: 26462.729 | C5: 26896.395 | D5: 27382.403 | E5: 27823.292 | F5: 28161.943 | G5: 28513.962 | H5: 28957.26 | I5: 29462.114 | J5: 29881.613 | K5: 30348.906 | L5: 30850.88 | M5: 31471.349 | N5: 32206.382 | O5: 32534.765 | P5: 32175.212 | Q5: 32026.06 | R5: 32219.26 | S5: 32509.801 | T5: 32839.663 | U5: 32898.971 | V5: 33160.329 | W5: 34069.828 | X5: 34839.343 | Y5: 35033.552 | Z5: 35348.49 | AA5: 35585.28 | AB5: 36078.587 | AC5: 36779.913 | AD5: 37191.742 | AE5: 37418.391 | AF5: 38268.834 | AG5: 39291.159 | AH5: 39872.71 | AI5: 40241.212 | AJ5: 40656.363 | AK5: 41347.988 | AL5: 42239.942 | AM5: 43273.383
A6: AGRICULTURE,FORESTRY&FISHING | B6: 6219.3427 | C6: 6294.9669 | D6: 6407.4385 | E6: 6477.3375 | F6: 6492.3673 | G6: 6510.6472 | H6: 6592.6195 | I6: 6679.9926 | J6: 6762.4404 | K6: 6851.8703 | L6: 6974.0034 | M6: 7093.5297 | N6: 7177.9759 | O6: 7247.1952 | P6: 7351.7641 | Q6: 7498.5506 | R6: 7601.7848 | S6: 7595.9446 | T6: 7545.8478 | U6: 7498.9166 | V6: 7553.2979 | W6: 7784.6192 | X6: 8052.5733 | Y6: 8303.0837 | Z6: 8440.4735 | AA6: 8395.4301 | AB6: 8324.0587 | AC6: 8334.4393 | AD6: 8415.4908 | AE6: 8575.3602 | AF6: 8756.8475 | AG6: 8934.4361 | AH6: 9086.7845 | AI6: 9205.3115 | AJ6: 9283.9208 | AK6: 9390.2858 | AL6: 9596.0021 | AM6: 9897.4766
A7: Cash crops | B7: 593.8839 | C7: 581.5683 | D7: 575.38572 | E7: 579.05577 | F7: 594.02893 | G7: 625.02609 | H7: 660.49115 | I7: 690.8385 | J7: 699.78988 | K7: 679.58257 | L7: 659.62713 | M7: 673.60512 | N7: 700.29756 | O7: 699.93064 | P7: 699.66811 | Q7: 719.21383 | R7: 741.30593 | S7: 768.59936 | T7: 788.36202 | U7: 770.44304 | V7: 786.84496 | W7: 852.70488 | X7: 896.90722 | Y7: 915.44522 | Z7: 931.67221 | AA7: 916.34439 | AB7: 899.32037 | AC7: 915.99688 | AD7: 917.1866 | AE7: 899.64921 | AF7: 906.84638 | AG7: 935.91273 | AH7: 977.68317 | AI7: 1034.5749 | AJ7: 1075.6778 | AK7: 1106.9736 | AL7: 1131.3063 | AM7: 1154.3996
A8: Food crops | B8: 3262.4339 | C8: 3335.2603 | D8: 3445.8387 | E8: 3529.946 | F8: 3574.7998 | G8: 3597.6619 | H8: 3615.8432 | I8: 3589.5615 | J8: 3575.8472 | K8: 3611.3525 | L8: 3679.781 | M8: 3724.7958 | N8: 3749.3135 | O8: 3825.5891 | P8: 3966.4225 | Q8: 4097.1781 | R8: 4121.6822 | S8: 4044.5544 | T8: 3984.7991 | U8: 3966.853 | V8: 3984.5389 | W8: 4100.832 | X8: 4258.6117 | Y8: 4435.7343 | Z8: 4507.1351 | AA8: 4411.3474 | AB8: 4326.9767 | AC8: 4342.4308 | AD8: 4431.1763 | AE8: 4549.8146 | AF8: 4627.4999 | AG8: 4702.654 | AH8: 4774.5389 | AI8: 4802.2589 | AJ8: 4782.8249 | AK8: 4778.2088 | AL8: 4870.7283 | AM8: 5068.9499
A9: Livestock | B9: 803.553 | C9: 820.12361 | D9: 835.87344 | E9: 851.0684 | F9: 866.06488 | G9: 880.37119 | H9: 893.42534 | I9: 907.94118 | J9: 924.62887 | K9: 942.06865 | L9: 959.39861 | M9: 978.34168 | N9: 997.91298 | O9: 1017.304 | P9: 1036.5121 | Q9: 1054.3433 | R9: 1073.0032 | S9: 1094.2825 | T9: 1117.3744 | U9: 1140.7639 | V9: 1162.827 | W9: 1184.6334 | X9: 1209.1322 | Y9: 1236.8382 | Z9: 1264.4031 | AA9: 1289.8974 | AB9: 1313.783 | AC9: 1337.8199 | AD9: 1364.032 | AE9: 1392.3319 | AF9: 1421.2593 | AG9: 1450.1158 | AH9: 1480.198 | AI9: 1512.4747 | AJ9: 1546.75 | AK9: 1581.3848 | AL9: 1616.4683 | AM9: 1651.8116
A10: Agriculture Support Services | B10: 4.0612309 | C10: 4.1137115 | D10: 4.1513994 | E10: 4.1584742 | F10: 4.0916717 | G10: 4.0185315 | H10: 4.0794672 | I10: 4.2039396 | J10: 4.297091 | K10: 4.3413185 | L10: 4.5411854 | M10: 4.8447886 | N10: 5.0170854 | O10: 4.8535724 | P10: 4.5075072 | Q10: 4.3633832 | R10: 4.5656339 | S10: 4.8931766 | T10: 5.062864 | U10: 5.0606881 | V10: 4.9681142 | W10: 5.0235596 | X10: 5.1537174 | Y10: 5.1839637 | Z10: 5.150933 | AA10: 5.1686735 | AB10: 5.1882584 | AC10: 5.2451057 | AD10: 5.4095824 | AE10: 5.5512946 | AF10: 5.6225828 | AG10: 5.6686383 | AH10: 5.6086299 | AI10: 5.5166149 | AJ10: 5.4772843 | AK10: 5.3912296 | AL10: 5.3255614 | AM10: 5.3648882
A11: Forestry | B11: 978.97089 | C11: 987.13302 | D11: 1004.0107 | E11: 1019.8797 | F11: 1015.261 | G11: 1014.1154 | H11: 1036.5701 | I11: 1061.3163 | J11: 1067.0103 | K11: 1061.1402 | L11: 1067.0917 | M11: 1087.2517 | N11: 1113.9876 | O11: 1118.9348 | P11: 1102.2752 | Q11: 1089.6564 | R11: 1110.2068 | S11: 1141.2018 | T11: 1151.6434 | U11: 1142.6549 | V11: 1134.9625 | W11: 1156.6753 | X11: 1193.2401 | Y11: 1201.1238 | Z11: 1185.9285 | AA11: 1202.0819 | AB11: 1229.1343 | AC11: 1237.9809 | AD11: 1234.2254 | AE11: 1234.7073 | AF11: 1246.6906 | AG11: 1270.0972 | AH11: 1288.8524 | AI11: 1282.6345 | AJ11: 1283.3617 | AK11: 1324.6049 | AL11: 1376.799 | AM11: 1407.8689
A12: Fishing | B12: 576.43978 | C12: 566.76804 | D12: 542.17854 | E12: 493.22923 | F12: 438.12092 | G12: 389.45405 | H12: 382.21028 | I12: 426.1312 | J12: 490.86707 | K12: 553.38508 | L12: 603.56371 | M12: 624.6907 | N12: 611.44715 | O12: 580.58308 | P12: 542.3787 | Q12: 533.79563 | R12: 551.02112 | S12: 542.41338 | T12: 498.60607 | U12: 473.14101 | V12: 479.15641 | W12: 484.74999 | X12: 489.52843 | Y12: 508.75811 | Z12: 546.18361 | AA12: 570.59035 | AB12: 549.65598 | AC12: 494.9656 | AD12: 463.46085 | AE12: 493.30596 | AF12: 548.92875 | AG12: 569.98772 | AH12: 559.9034 | AI12: 567.85192 | AJ12: 589.82921 | AK12: 593.72242 | AL12: 595.37456 | AM12: 609.08165
A13: INDUSTRY | B13: 6791.0364 | C13: 7077.731 | D13: 7200.174 | E13: 7178.8762 | F13: 7145.538 | G13: 7259.2795 | H13: 7489.921 | I13: 7702.2802 | J13: 7816.3296 | K13: 7986.6672 | L13: 8177.1601 | M13: 8347.9343 | N13: 8583.36 | O13: 8719.0967 | P13: 8659.4439 | Q13: 8631.8724 | R13: 8675.9397 | S13: 8693.6963 | T13: 8724.2683 | U13: 8713.2737 | V13: 8889.5175 | W13: 9198.4026 | X13: 9353.5156 | Y13: 9306.4883 | Z13: 9263.289 | AA13: 9216.4138 | AB13: 9447.5444 | AC13: 9800.8344 | AD13: 9860.4728 | AE13: 9788.7521 | AF13: 9945.4833 | AG13: 10259.871 | AH13: 10474.648 | AI13: 10592.303 | AJ13: 10632.774 | AK13: 10784.478 | AL13: 11190.244 | AM13: 11740.477
A14: Mining & quarrying | B14: 281.36408 | C14: 330.76919 | D14: 357.75506 | E14: 354.83967 | F14: 315.4116 | G14: 278.03989 | H14: 318.08632 | I14: 377.89314 | J14: 363.8705 | K14: 357.20081 | L14: 386.54093 | M14: 401.99372 | N14: 435.34913 | O14: 509.25741 | P14: 499.21953 | Q14: 503.10774 | R14: 544.95893 | S14: 518.7187 | T14: 418.8228 | U14: 353.68606 | V14: 436.75701 | W14: 595.70647 | X14: 692.57774 | Y14: 626.66512 | Z14: 467.44686 | AA14: 349.71098 | AB14: 604.15823 | AC14: 918.17026 | AD14: 905.22775 | AE14: 679.55804 | AF14: 538.76095 | AG14: 552.22134 | AH14: 689.30256 | AI14: 734.76867 | AJ14: 546.9457 | AK14: 453.09985 | AL14: 644.61012 | AM14: 943.91648
A15: Manufacturing | B15: 4044.8539 | C15: 4210.8977 | D15: 4309.0429 | E15: 4295.6072 | F15: 4267.913 | G15: 4350.3055 | H15: 4457.2282 | I15: 4535.321 | J15: 4605.4108 | K15: 4715.0554 | L15: 4798.8971 | M15: 4909.9825 | N15: 5081.2139 | O15: 5101.7609 | P15: 5022.7249 | Q15: 4988.4422 | R15: 4938.8864 | S15: 4874.649 | T15: 4913.6287 | U15: 4914.9471 | V15: 4978.9996 | W15: 5167.2241 | X15: 5307.0854 | Y15: 5292.35 | Z15: 5294.061 | AA15: 5301.4268 | AB15: 5244.2992 | AC15: 5229.2382 | AD15: 5264.7774 | AE15: 5333.1716 | AF15: 5502.6746 | AG15: 5733.9353 | AH15: 5789.0768 | AI15: 5746.7223 | AJ15: 5790.9648 | AK15: 5933.9979 | AL15: 6085.7624 | AM15: 6237.9066
A16: Electricity | B16: 329.43074 | C16: 340.19575 | D16: 351.74221 | E16: 359.08073 | F16: 363.63249 | G16: 365.99965 | H16: 363.84416 | I16: 361.29608 | J16: 362.07881 | K16: 365.27727 | L16: 372.99731 | M16: 389.36923 | N16: 407.54982 | O16: 422.75634 | P16: 433.85251 | Q16: 440.8351 | R16: 447.88188 | S16: 458.17999 | T16: 468.01599 | U16: 471.49498 | V16: 471.58804 | W16: 473.04233 | X16: 477.37492 | Y16: 483.96178 | Z16: 496.52113 | AA16: 509.95115 | AB16: 521.66479 | AC16: 535.93933 | AD16: 549.12608 | AE16: 557.42488 | AF16: 563.79777 | AG16: 573.58402 | AH16: 589.51218 | AI16: 613.87557 | AJ16: 642.51888 | AK16: 665.64601 | AL16: 675.72283 | AM16: 680.91248
... A33: Activities of Households | B33: 220.42507 | C33: 222.05591 | D33: 223.64686 | E33: 225.20867 | F33: 226.7607 | G33: 228.31527 | H33: 229.88308 | I33: 231.46486 | J33: 233.07053 | K33: 234.68457 | L33: 236.29337 | M33: 237.90692 | N33: 239.54183 | O33: 241.18096 | P33: 242.8019 | Q33: 244.42109 | R33: 246.06725 | S33: 247.7447 | T33: 249.44261 | U33: 251.15438 | V33: 252.87866 | W33: 254.607 | X33: 256.32604 | Y33: 258.04073 | Z33: 259.77256 | AA33: 261.53643 | AB33: 263.33427 | AC33: 265.1462 | AD33: 266.95998 | AE33: 268.77822 | AF33: 270.60062 | AG33: 272.41806 | AH33: 274.24381 | AI33: 276.10091 | AJ33: 278.00335 | AK33: 279.90262 | AL33: 281.72406 | AM33: 283.50323
A35: ADJUSTMENTS
A36: Taxes on products | B36: 1862.8078 | C36: 1911.2419 | D36: 1951.0075 | E36: 1991.364 | F36: 2001.9261 | G36: 1986.2144 | H36: 1977.8154 | I36: 1990.9443 | J36: 2007.3618 | K36: 2062.4461 | L36: 2121.6887 | M36: 2151.9172 | N36: 2205.1039 | O36: 2219.1416 | P36: 2179.3171 | Q36: 2150.1665 | R36: 2151.1983 | S36: 2136.3114 | T36: 2145.5 | U36: 2173.405 | V36: 2248.7455 | W36: 2373.1712 | X36: 2462.8291 | Y36: 2448.2929 | Z36: 2426.4969 | AA36: 2493.6157 | AB36: 2605.8057 | AC36: 2700.9992 | AD36: 2720.9495 | AE36: 2717.6552 | AF36: 2750.6356 | AG36: 2851.2955 | AH36: 2941.015 | AI36: 2955.3882 | AJ36: 2950.618 | AK36: 3024.4541 | AL36: 3106.1235 | AM36: 3164.8249
A37: Source: Uganda Bureau of Statistics

Sheet Trend_Growth
A1: Table 10: TREND-CYCLE Value Added at constant 2016/17 prices, PERCENTAGE CHANGE, 2016/17-2025/26
B3: 2016/17 | F3: 2017/18 | J3: 2018/19 | N3: 2019/20 | R3: 2020/21 | V3: 2021/22 | Z3: 2022/23 | AD3: 2023/24 | AH3: 2024/25 | AL3: 2025/26
B4: Q1 | C4: Q2 | D4: Q3 | E4: Q4 | F4: Q1 | G4: Q2 | H4: Q3 | I4: Q4 | J4: Q1 | K4: Q2 | L4: Q3 | M4: Q4 | N4: Q1 | O4: Q2 | P4: Q3 | Q4: Q4 | R4: Q1 | S4: Q2 | T4: Q3 | U4: Q4 | V4: Q1 | W4: Q2 | X4: Q3 | Y4: Q4 | Z4: Q1 | AA4: Q2 | AB4: Q3 | AC4: Q4 | AD4: Q1 | AE4: Q2 | AF4: Q3 | AG4: Q4 | AH4: Q1 | AI4: Q2 | AJ4: Q3 | AK4: Q4 | AL4: Q1 | AM4: Q2
A5: GDP AT MARKET PRICES | B5: 1.1600043 | C5: 1.6387808 | D5: 1.8069627 | E5: 1.6101159 | F5: 1.2171498 | G5: 1.249981 | H5: 1.5546698 | I5: 1.743448 | J5: 1.4238561 | K5: 1.5638156 | L5: 1.6540111 | M5: 2.0111873 | N5: 2.3355632 | O5: 1.0196182 | P5: -1.1051348 | Q5: -0.46355991 | R5: 0.60325829 | S5: 0.90176095 | T5: 1.0146551 | U5: 0.18059848 | V5: 0.79442676 | W5: 2.742732 | X5: 2.2586389 | Y5: 0.55744241 | Z5: 0.89896211 | AA5: 0.66987123 | AB5: 1.386268 | AC5: 1.9438837 | AD5: 1.1197133 | AE5: 0.6094055 | AF5: 2.2727936 | AG5: 2.6714297 | AH5: 1.4801069 | AI5: 0.9241967 | AJ5: 1.031655 | AK5: 1.7011504 | AL5: 2.1571877 | AM5: 2.4465953
A6: AGRICULTURE,FORESTRY&FISHING | B6: -0.32447705 | C6: 1.2159518 | D6: 1.7866906 | E6: 1.0909037 | F6: 0.23203631 | G6: 0.28155949 | H6: 1.2590512 | I6: 1.3253156 | J6: 1.2342505 | K6: 1.3224506 | L6: 1.7824778 | M6: 1.713884 | N6: 1.1904674 | O6: 0.96432903 | P6: 1.4428886 | Q6: 1.9966159 | R6: 1.3767221 | S6: -0.07682714 | T6: -0.65951993 | U6: -0.62194756 | V6: 0.72518788 | W6: 3.0625205 | X6: 3.4420974 | Y6: 3.1109351 | Z6: 1.6546843 | AA6: -0.53365901 | AB6: -0.85012281 | AC6: 0.12470577 | AD6: 0.97248991 | AE6: 1.8997033 | AF6: 2.116381 | AG6: 2.0279976 | AH6: 1.7051817 | AI6: 1.3043889 | AJ6: 0.85395584 | AK6: 1.1456899 | AL6: 2.1907354 | AM6: 3.1416674
A7: Cash crops | B7: 0.59312482 | C7: -2.073738 | D7: -1.063088 | E7: 0.63784096 | F7: 2.5857892 | G7: 5.2181238 | H7: 5.6741727 | I7: 4.594664 | J7: 1.2957259 | K7: -2.8876248 | L7: -2.9364267 | M7: 2.1190746 | N7: 3.9626248 | O7: -0.052395646 | P7: -0.037507447 | Q7: 2.7935705 | R7: 3.0717013 | S7: 3.6818037 | T7: 2.571256 | U7: -2.2729375 | V7: 2.1288947 | W7: 8.3701255 | X7: 5.1837794 | Y7: 2.0668805 | Z7: 1.7725791 | AA7: -1.6451935 | AB7: -1.8578194 | AC7: 1.8543462 | AD7: 0.12988165 | AE7: -1.9120847 | AF7: 0.79999672 | AG7: 3.2052131 | AH7: 4.4630698 | AI7: 5.8190378 | AJ7: 3.9729215 | AK7: 2.9094047 | AL7: 2.1981321 | AM7: 2.0412896
A8: Food crops | B8: -0.41191842 | C8: 2.2322699 | D8: 3.3154365 | E8: 2.4408363 | F8: 1.2706668 | G8: 0.6395335 | H8: 0.5053662 | I8: -0.72685089 | J8: -0.38205982 | K8: 0.9929217 | L8: 1.8948157 | M8: 1.2233001 | N8: 0.65822933 | O8: 2.0343892 | P8: 3.6813518 | Q8: 3.296562 | R8: 0.59807186 | S8: -1.8712684 | T8: -1.4774275 | U8: -0.45036191 | V8: 0.44584147 | W8: 2.9186094 | X8: 3.8475029 | Y8: 4.159164 | Z8: 1.6096725 | AA8: -2.1252456 | AB8: -1.9125829 | AC8: 0.35715656 | AD8: 2.0436828 | AE8: 2.6773528 | AF8: 1.7074388 | AG8: 1.6240769 | AH8: 1.5286026 | AI8: 0.58057889 | AJ8: -0.40468509 | AK8: -0.096514158 | AL8: 1.9362817 | AM8: 4.0696499
A9: Livestock | B9: 1.9677258 | C9: 2.0621673 | D9: 1.9204222 | E9: 1.8178536 | F9: 1.7620777 | G9: 1.651875 | H9: 1.4827999 | I9: 1.6247405 | J9: 1.8379704 | K9: 1.8861385 | L9: 1.8395647 | M9: 1.9744731 | N9: 2.0004569 | O9: 1.9431589 | P9: 1.8881379 | Q9: 1.7203033 | R9: 1.7698169 | S9: 1.983149 | T9: 2.110239 | U9: 2.0932547 | V9: 1.9340587 | W9: 1.8752953 | X9: 2.0680475 | Y9: 2.2913978 | Z9: 2.2286548 | AA9: 2.0163114 | AB9: 1.8517463 | AC9: 1.8295922 | AD9: 1.9593165 | AE9: 2.0747207 | AF9: 2.0776228 | AG9: 2.030348 | AH9: 2.0744719 | AI9: 2.1805662 | AJ9: 2.2661715 | AK9: 2.2392018 | AL9: 2.2185253 | AM9: 2.1864556
A10: Agriculture Support Services | B10: 2.042257 | C10: 1.2922336 | D10: 0.9161529 | E10: 0.17041831 | F10: -1.6064169 | G10: -1.7875381 | H10: 1.5163661 | I10: 3.0511942 | J10: 2.2158115 | K10: 1.029242 | L10: 4.6038292 | M10: 6.6855492 | N10: 3.5563329 | O10: -3.259122 | P10: -7.1301133 | Q10: -3.1974211 | R10: 4.6351798 | S10: 7.1740905 | T10: 3.4678375 | U10: -0.042977562 | V10: -1.8292755 | W10: 1.1160258 | X10: 2.5909462 | Y10: 0.58688386 | Z10: -0.63717113 | AA10: 0.34441425 | AB10: 0.37891517 | AC10: 1.0956918 | AD10: 3.1358128 | AE10: 2.6196504 | AF10: 1.284173 | AG10: 0.81911644 | AH10: -1.058603 | AI10: -1.6405965 | AJ10: -0.71294947 | AK10: -1.5711185 | AL10: -1.2180561 | AM10: 0.73845323
A11: Forestry | B11: -1.4665134 | C11: 0.83374597 | D11: 1.70977 | E11: 1.5805549 | F11: -0.45285893 | G11: -0.11284089 | H11: 2.2142106 | I11: 2.3873173 | J11: 0.53650644 | K11: -0.55014884 | L11: 0.56086575 | M11: 1.8892395 | N11: 2.4590406 | O11: 0.44409429 | P11: -1.4888778 | Q11: -1.1447924 | R11: 1.8859473 | S11: 2.791824 | T11: 0.9149633 | U11: -0.78049172 | V11: -0.67320685 | W11: 1.9130851 | X11: 3.1611996 | Y11: 0.66069955 | Z11: -1.2650888 | AA11: 1.3620866 | AB11: 2.2504619 | AC11: 0.71974611 | AD11: -0.30335694 | AE11: 0.039040728 | AF11: 0.97054167 | AG11: 1.8774989 | AH11: 1.4766684 | AI11: -0.48243822 | AJ11: 0.0566993 | AK11: 3.2136861 | AL11: 3.9403517 | AM11: 2.2566743
A12: Fishing | B12: -1.9177872 | C12: -1.6778409 | D12: -4.338547 | E12: -9.0282643 | F12: -11.17296 | G12: -11.108091 | H12: -1.8599819 | I12: 11.491298 | J12: 15.191535 | K12: 12.73624 | L12: 9.0675794 | M12: 3.5003731 | N12: -2.1200159 | O12: -5.0477093 | P12: -6.5803465 | Q12: -1.5824875 | R12: 3.2269827 | S12: -1.5621436 | T12: -8.0763689 | U12: -5.1072502 | V12: 1.2713754 | W12: 1.1673799 | X12: 0.9857548 | Y12: 3.9282053 | Z12: 7.3562462 | AA12: 4.4685952 | AB12: -3.6688969 | AC12: -9.9499286 | AD12: -6.3650372 | AE12: 6.4396163 | AF12: 11.275516 | AG12: 3.8363764 | AH12: -1.7692169 | AI12: 1.4196235 | AJ12: 3.8702495 | AK12: 0.66005696 | AL12: 0.278269 | AM12: 2.302263
A13: INDUSTRY | B13: 3.8740071 | C13: 4.2216624 | D13: 1.7299746 | E13: -0.29579554 | F13: -0.46439365 | G13: 1.5917849 | H13: 3.177195 | I13: 2.8352659 | J13: 1.480723 | K13: 2.1792533 | L13: 2.3851353 | M13: 2.0884291 | N13: 2.8201673 | O13: 1.5813933 | P13: -0.68416167 | Q13: -0.31839831 | R13: 0.5105181 | S13: 0.20466531 | T13: 0.35165734 | U13: -0.12602364 | V13: 2.022705 | W13: 3.4747112 | X13: 1.6863042 | Y13: -0.50277734 | Z13: -0.46418428 | AA13: -0.5060324 | AB13: 2.5078151 | AC13: 3.7394904 | AD13: 0.60850301 | AE13: -0.72735566 | AF13: 1.6011356 | AG13: 3.1611068 | AH13: 2.0933719 | AI13: 1.1232365 | AJ13: 0.38207511 | AK13: 1.4267595 | AL13: 3.762507 | AM13: 4.9170773
A14: Mining & quarrying | B14: 22.707927 | C14: 17.559138 | D14: 8.1585189 | E14: -0.81491129 | F14: -11.111517 | G14: -11.848554 | H14: 14.403125 | I14: 18.802073 | J14: -3.7107425 | K14: -1.8329829 | L14: 8.2139 | M14: 3.9977114 | N14: 8.2974945 | O14: 16.976785 | P14: -1.9710826 | Q14: 0.7788575 | R14: 8.3185355 | S14: -4.8150847 | T14: -19.258203 | U14: -15.552338 | V14: 23.487199 | W14: 36.393109 | X14: 16.261578 | Y14: -9.5170001 | Z14: -25.407231 | AA14: -25.18701 | AB14: 72.7593 | AC14: 51.975131 | AD14: -1.4095979 | AE14: -24.929606 | AF14: -20.718921 | AG14: 2.4983971 | AH14: 24.823601 | AI14: 6.5959598 | AJ14: -25.562192 | AK14: -17.158165 | AL14: 42.266682 | AM14: 46.432153
A15: Manufacturing | B15: 2.7190006 | C15: 4.1050621 | D15: 2.330743 | E15: -0.3118023 | F15: -0.64471039 | G15: 1.9305106 | H15: 2.4578217 | I15: 1.7520476 | J15: 1.5454205 | K15: 2.3807783 | L15: 1.7781705 | M15: 2.3148107 | N15: 3.487413 | O15: 0.40437242 | P15: -1.5491906 | Q15: -0.68255096 | R15: -0.99341237 | S15: -1.3006472 | T15: 0.79964182 | U15: 0.026832644 | V15: 1.3032168 | W15: 3.7803691 | X15: 2.7067008 | Y15: -0.27765649 | Z15: 0.03232985 | AA15: 0.13913373 | AB15: -1.077588 | AC15: -0.28718828 | AD15: 0.67962338 | AE15: 1.2990911 | AF15: 3.1782775 | AG15: 4.2026971 | AH15: 0.96166776 | AI15: -0.73162627 | AJ15: 0.7698734 | AK15: 2.4699353 | AL15: 2.5575422 | AM15: 2.5000024
A16: Electricity | B16: 2.6027061 | C16: 3.2677621 | D16: 3.3940637 | E16: 2.0863338 | F16: 1.2676132 | G16: 0.65097686 | H16: -0.58893243 | I16: -0.70032222 | J16: 0.21664625 | K16: 0.88335856 | L16: 2.1134748 | M16: 4.389286 | N16: 4.6692427 | O16: 3.7312045 | P16: 2.6247195 | Q16: 1.6094391 | R16: 1.5985083 | S16: 2.29929 | T16: 2.1467541 | U16: 0.74335036 | V16: 0.019736948 | W16: 0.30838083 | X16: 0.91589947 | Y16: 1.3798085 | Z16: 2.5951116 | AA16: 2.7048231 | AB16: 2.2970118 | AC16: 2.7363438 | AD16: 2.4604943 | AE16: 1.511274 | AF16: 1.1432722 | AG16: 1.735774 | AH16: 2.7769535 | AI16: 4.1328052 | AJ16: 4.6659791 | AK16: 3.5994473 | AL16: 1.5138408 | AM16: 0.76801396
... A33: Activities of Households | B33: 0.74306536 | C33: 0.73986149 | D33: 0.7164632 | E33: 0.69833688 | F33: 0.68915326 | G33: 0.68555382 | H33: 0.68668765 | I33: 0.68807918 | J33: 0.69369776 | K33: 0.69251325 | L33: 0.68551759 | M33: 0.68285568 | N33: 0.68720821 | O33: 0.68427597 | P33: 0.67208379 | Q33: 0.66687938 | R33: 0.67349307 | S33: 0.68170325 | T33: 0.68534786 | U33: 0.68623843 | V33: 0.68654121 | W33: 0.68346634 | X33: 0.67517197 | Y33: 0.66894915 | Z33: 0.67114504 | AA33: 0.67900717 | AB33: 0.68741353 | AC33: 0.68807252 | AD33: 0.68406751 | AE33: 0.68109042 | AF33: 0.67803095 | AG33: 0.67163372 | AH33: 0.67020032 | AI33: 0.67717272 | AJ33: 0.68903857 | AK33: 0.68318188 | AL33: 0.65073868 | AM33: 0.63153093
A35: ADJUSTMENTS
A36: Taxes on products | B36: 4.9532628 | C36: 2.6000544 | D36: 2.0806191 | E36: 2.0684931 | F36: 0.53039555 | G36: -0.78482691 | H36: -0.42286606 | I36: 0.66380713 | J36: 0.82460852 | K36: 2.7441136 | L36: 2.8724442 | M36: 1.4247401 | N36: 2.4715954 | O36: 0.63659811 | P36: -1.7945864 | Q36: -1.3376045 | R36: 0.047985802 | S36: -0.69202804 | T36: 0.43011652 | U36: 1.3006287 | V36: 3.4664753 | W36: 5.5331139 | X36: 3.7779798 | Y36: -0.59022444 | Z36: -0.89025433 | AA36: 2.766078 | AB36: 4.4990892 | AC36: 3.6531322 | AD36: 0.73862534 | AE36: -0.12106867 | AF36: 1.2135592 | AG36: 3.6595137 | AH36: 3.1466241 | AI36: 0.48871519 | AJ36: -0.16140776 | AK36: 2.5023932 | AL36: 2.7003025 | AM36: 1.8898611
A37: Source: Uganda Bureau of Statistics

Sheet TS IPD
X1: Table 15: TREND-CYCLE Value Added at constant 2009/10 prices, IMPLICIT PRICE DEFLATORS, 2013/14-2017/18
B2: 2008Q1 | C2: 2008Q2 | D2: 2008Q3 | E2: 2008Q4 | F2: 2009Q1 | G2: 2009Q2 | H2: 2009Q3 | I2: 2009Q4 | J2: 2010Q1 | K2: 2010Q2 | L2: 2010Q3 | M2: 2010Q4 | N2: 2011Q1 | O2: 2011Q2 | P2: 2011Q3 | Q2: 2011Q4 | R2: 2012Q1 | S2: 2012Q2 | T2: 2012Q3 | U2: 2012Q4 | V2: 2013Q1 | W2: 2013Q2 | X2: 2013Q3 | Y2: 2013Q4 | Z2: 2014Q1 | AA2: 2014Q2 | AB2: 2014Q3 | AC2: 2014Q4 | AD2: 2015Q1 | AE2: 2015Q2 | AF2: 2015Q3
B3: 2007/08 | D3: 2008/09 | H3: 2009/10 | L3: 2010/11 | P3: 2011/12 | T3: 2012/13 | X3: 2013/14 | AB3: 2014/15 | AF3: 2015/16 | AJ3: 2016/17 | AN3: 2017/18
A4: Activity | B4: Q3 | C4: Q4 | D4: Q1 | E4: Q2 | F4: Q3 | G4: Q4 | H4: Q1 | I4: Q2 | J4: Q3 | K4: Q4 | L4: Q1 | M4: Q2 | N4: Q3 | O4: Q4 | P4: Q1 | Q4: Q2 | R4: Q3 | S4: Q4 | T4: Q1 | U4: Q2 | V4: Q3 | W4: Q4 | X4: Q1 | Y4: Q2 | Z4: Q3 | AA4: Q4 | AB4: Q1 | AC4: Q2 | AD4: Q3 | AE4: Q4 | AF4: Q1 | AG4: Q2 | AH4: Q3 | AI4: Q4 | AJ4: Q1 | AK4: Q2 | AL4: Q3 | AM4: Q4 | AN4: Q1 | AO4: Q2 | AP4: Q3 | AQ4: Q4
A5: GDP AT MARKET PRICES | B5: =#REF!/Trend_VA!#REF!*100 -> #REF! | C5: =#REF!/Trend_VA!#REF!*100 -> #REF! | D5: =#REF!/Trend_VA!#REF!*100 -> #REF! | E5: =#REF!/Trend_VA!#REF!*100 -> #REF! | F5: =#REF!/Trend_VA!#REF!*100 -> #REF! | G5: =#REF!/Trend_VA!#REF!*100 -> #REF! | H5: =#REF!/Trend_VA!#REF!*100 -> #REF! | I5: =#REF!/Trend_VA!#REF!*100 -> #REF! | ... AI5: =#REF!/Trend_VA!#REF!*100 -> #REF! | AJ5: =#REF!/Trend_VA!B5*100 -> #REF! | AK5: =#REF!/Trend_VA!C5*100 -> #REF! | AL5: =#REF!/Trend_VA!D5*100 -> #REF! | AM5: =#REF!/Trend_VA!E5*100 -> #REF! | AN5: =#REF!/Trend_VA!F5*100 -> #REF! | AO5: =#REF!/Trend_VA!G5*100 -> #REF! | AP5: =#REF!/Trend_VA!H5*100 -> #REF! | AQ5: =#REF!/Trend_VA!I5*100 -> #REF!
A6: AGRICULTURE,FORESTRY&FISHING | B6: =#REF!/Trend_VA!#REF!*100 -> #REF! | C6: =#REF!/Trend_VA!#REF!*100 -> #REF! | D6: =#REF!/Trend_VA!#REF!*100 -> #REF! | E6: =#REF!/Trend_VA!#REF!*100 -> #REF! | F6: =#REF!/Trend_VA!#REF!*100 -> #REF! | G6: =#REF!/Trend_VA!#REF!*100 -> #REF! | H6: =#REF!/Trend_VA!#REF!*100 -> #REF! | I6: =#REF!/Trend_VA!#REF!*100 -> #REF! | ... AI6: =#REF!/Trend_VA!#REF!*100 -> #REF! | AJ6: =#REF!/Trend_VA!B6*100 -> #REF! | AK6: =#REF!/Trend_VA!C6*100 -> #REF! | AL6: =#REF!/Trend_VA!D6*100 -> #REF! | AM6: =#REF!/Trend_VA!E6*100 -> #REF! | AN6: =#REF!/Trend_VA!F6*100 -> #REF! | AO6: =#REF!/Trend_VA!G6*100 -> #REF! | AP6: =#REF!/Trend_VA!H6*100 -> #REF! | AQ6: =#REF!/Trend_VA!I6*100 -> #REF!
A7: Cash crops | B7: =#REF!/Trend_VA!#REF!*100 -> #REF! | C7: =#REF!/Trend_VA!#REF!*100 -> #REF! | D7: =#REF!/Trend_VA!#REF!*100 -> #REF! | E7: =#REF!/Trend_VA!#REF!*100 -> #REF! | F7: =#REF!/Trend_VA!#REF!*100 -> #REF! | G7: =#REF!/Trend_VA!#REF!*100 -> #REF! | H7: =#REF!/Trend_VA!#REF!*100 -> #REF! | I7: =#REF!/Trend_VA!#REF!*100 -> #REF! | ... AI7: =#REF!/Trend_VA!#REF!*100 -> #REF! | AJ7: =#REF!/Trend_VA!B7*100 -> #REF! | AK7: =#REF!/Trend_VA!C7*100 -> #REF! | AL7: =#REF!/Trend_VA!D7*100 -> #REF! | AM7: =#REF!/Trend_VA!E7*100 -> #REF! | AN7: =#REF!/Trend_VA!F7*100 -> #REF! | AO7: =#REF!/Trend_VA!G7*100 -> #REF! | AP7: =#REF!/Trend_VA!H7*100 -> #REF! | AQ7: =#REF!/Trend_VA!I7*100 -> #REF!
A8: Food crops | B8: =#REF!/Trend_VA!#REF!*100 -> #REF! | C8: =#REF!/Trend_VA!#REF!*100 -> #REF! | D8: =#REF!/Trend_VA!#REF!*100 -> #REF! | E8: =#REF!/Trend_VA!#REF!*100 -> #REF! | F8: =#REF!/Trend_VA!#REF!*100 -> #REF! | G8: =#REF!/Trend_VA!#REF!*100 -> #REF! | H8: =#REF!/Trend_VA!#REF!*100 -> #REF! | I8: =#REF!/Trend_VA!#REF!*100 -> #REF! | ... AI8: =#REF!/Trend_VA!#REF!*100 -> #REF! | AJ8: =#REF!/Trend_VA!B8*100 -> #REF! | AK8: =#REF!/Trend_VA!C8*100 -> #REF! | AL8: =#REF!/Trend_VA!D8*100 -> #REF! | AM8: =#REF!/Trend_VA!E8*100 -> #REF! | AN8: =#REF!/Trend_VA!F8*100 -> #REF! | AO8: =#REF!/Trend_VA!G8*100 -> #REF! | AP8: =#REF!/Trend_VA!H8*100 -> #REF! | AQ8: =#REF!/Trend_VA!I8*100 -> #REF!
A9: Livestock | B9: =#REF!/Trend_VA!#REF!*100 -> #REF! | C9: =#REF!/Trend_VA!#REF!*100 -> #REF! | D9: =#REF!/Trend_VA!#REF!*100 -> #REF! | E9: =#REF!/Trend_VA!#REF!*100 -> #REF! | F9: =#REF!/Trend_VA!#REF!*100 -> #REF! | G9: =#REF!/Trend_VA!#REF!*100 -> #REF! | H9: =#REF!/Trend_VA!#REF!*100 -> #REF! | I9: =#REF!/Trend_VA!#REF!*100 -> #REF! | ... AI9: =#REF!/Trend_VA!#REF!*100 -> #REF! | AJ9: =#REF!/Trend_VA!B9*100 -> #REF! | AK9: =#REF!/Trend_VA!C9*100 -> #REF! | AL9: =#REF!/Trend_VA!D9*100 -> #REF! | AM9: =#REF!/Trend_VA!E9*100 -> #REF! | AN9: =#REF!/Trend_VA!F9*100 -> #REF! | AO9: =#REF!/Trend_VA!G9*100 -> #REF! | AP9: =#REF!/Trend_VA!H9*100 -> #REF! | AQ9: =#REF!/Trend_VA!I9*100 -> #REF!
A10: Agriculture Support Services | B10: =#REF!/Trend_VA!#REF!*100 -> #REF! | C10: =#REF!/Trend_VA!#REF!*100 -> #REF! | D10: =#REF!/Trend_VA!#REF!*100 -> #REF! | E10: =#REF!/Trend_VA!#REF!*100 -> #REF! | F10: =#REF!/Trend_VA!#REF!*100 -> #REF! | G10: =#REF!/Trend_VA!#REF!*100 -> #REF! | H10: =#REF!/Trend_VA!#REF!*100 -> #REF! | I10: =#REF!/Trend_VA!#REF!*100 -> #REF! | ... AI10: =#REF!/Trend_VA!#REF!*100 -> #REF! | AJ10: =#REF!/Trend_VA!B10*100 -> #REF! | AK10: =#REF!/Trend_VA!C10*100 -> #REF! | AL10: =#REF!/Trend_VA!D10*100 -> #REF! | AM10: =#REF!/Trend_VA!E10*100 -> #REF! | AN10: =#REF!/Trend_VA!F10*100 -> #REF! | AO10: =#REF!/Trend_VA!G10*100 -> #REF! | AP10: =#REF!/Trend_VA!H10*100 -> #REF! | AQ10: =#REF!/Trend_VA!I10*100 -> #REF!
A11: Forestry | B11: =#REF!/Trend_VA!#REF!*100 -> #REF! | C11: =#REF!/Trend_VA!#REF!*100 -> #REF! | D11: =#REF!/Trend_VA!#REF!*100 -> #REF! | E11: =#REF!/Trend_VA!#REF!*100 -> #REF! | F11: =#REF!/Trend_VA!#REF!*100 -> #REF! | G11: =#REF!/Trend_VA!#REF!*100 -> #REF! | H11: =#REF!/Trend_VA!#REF!*100 -> #REF! | I11: =#REF!/Trend_VA!#REF!*100 -> #REF! | ... AI11: =#REF!/Trend_VA!#REF!*100 -> #REF! | AJ11: =#REF!/Trend_VA!B11*100 -> #REF! | AK11: =#REF!/Trend_VA!C11*100 -> #REF! | AL11: =#REF!/Trend_VA!D11*100 -> #REF! | AM11: =#REF!/Trend_VA!E11*100 -> #REF! | AN11: =#REF!/Trend_VA!F11*100 -> #REF! | AO11: =#REF!/Trend_VA!G11*100 -> #REF! | AP11: =#REF!/Trend_VA!H11*100 -> #REF! | AQ11: =#REF!/Trend_VA!I11*100 -> #REF!
A12: Fishing | B12: =#REF!/Trend_VA!#REF!*100 -> #REF! | C12: =#REF!/Trend_VA!#REF!*100 -> #REF! | D12: =#REF!/Trend_VA!#REF!*100 -> #REF! | E12: =#REF!/Trend_VA!#REF!*100 -> #REF! | F12: =#REF!/Trend_VA!#REF!*100 -> #REF! | G12: =#REF!/Trend_VA!#REF!*100 -> #REF! | H12: =#REF!/Trend_VA!#REF!*100 -> #REF! | I12: =#REF!/Trend_VA!#REF!*100 -> #REF! | ... AI12: =#REF!/Trend_VA!#REF!*100 -> #REF! | AJ12: =#REF!/Trend_VA!B12*100 -> #REF! | AK12: =#REF!/Trend_VA!C12*100 -> #REF! | AL12: =#REF!/Trend_VA!D12*100 -> #REF! | AM12: =#REF!/Trend_VA!E12*100 -> #REF! | AN12: =#REF!/Trend_VA!F12*100 -> #REF! | AO12: =#REF!/Trend_VA!G12*100 -> #REF! | AP12: =#REF!/Trend_VA!H12*100 -> #REF! | AQ12: =#REF!/Trend_VA!I12*100 -> #REF!
A13: INDUSTRY | B13: =#REF!/Trend_VA!#REF!*100 -> #REF! | C13: =#REF!/Trend_VA!#REF!*100 -> #REF! | D13: =#REF!/Trend_VA!#REF!*100 -> #REF! | E13: =#REF!/Trend_VA!#REF!*100 -> #REF! | F13: =#REF!/Trend_VA!#REF!*100 -> #REF! | G13: =#REF!/Trend_VA!#REF!*100 -> #REF! | H13: =#REF!/Trend_VA!#REF!*100 -> #REF! | I13: =#REF!/Trend_VA!#REF!*100 -> #REF! | ... AI13: =#REF!/Trend_VA!#REF!*100 -> #REF! | AJ13: =#REF!/Trend_VA!B13*100 -> #REF! | AK13: =#REF!/Trend_VA!C13*100 -> #REF! | AL13: =#REF!/Trend_VA!D13*100 -> #REF! | AM13: =#REF!/Trend_VA!E13*100 -> #REF! | AN13: =#REF!/Trend_VA!F13*100 -> #REF! | AO13: =#REF!/Trend_VA!G13*100 -> #REF! | AP13: =#REF!/Trend_VA!H13*100 -> #REF! | AQ13: =#REF!/Trend_VA!I13*100 -> #REF!
A14: Mining & quarrying | B14: =#REF!/Trend_VA!#REF!*100 -> #REF! | C14: =#REF!/Trend_VA!#REF!*100 -> #REF! | D14: =#REF!/Trend_VA!#REF!*100 -> #REF! | E14: =#REF!/Trend_VA!#REF!*100 -> #REF! | F14: =#REF!/Trend_VA!#REF!*100 -> #REF! | G14: =#REF!/Trend_VA!#REF!*100 -> #REF! | H14: =#REF!/Trend_VA!#REF!*100 -> #REF! | I14: =#REF!/Trend_VA!#REF!*100 -> #REF! | ... AI14: =#REF!/Trend_VA!#REF!*100 -> #REF! | AJ14: =#REF!/Trend_VA!B14*100 -> #REF! | AK14: =#REF!/Trend_VA!C14*100 -> #REF! | AL14: =#REF!/Trend_VA!D14*100 -> #REF! | AM14: =#REF!/Trend_VA!E14*100 -> #REF! | AN14: =#REF!/Trend_VA!F14*100 -> #REF! | AO14: =#REF!/Trend_VA!G14*100 -> #REF! | AP14: =#REF!/Trend_VA!H14*100 -> #REF! | AQ14: =#REF!/Trend_VA!I14*100 -> #REF!
A15: Manufacturing | B15: =#REF!/Trend_VA!#REF!*100 -> #REF! | C15: =#REF!/Trend_VA!#REF!*100 -> #REF! | D15: =#REF!/Trend_VA!#REF!*100 -> #REF! | E15: =#REF!/Trend_VA!#REF!*100 -> #REF! | F15: =#REF!/Trend_VA!#REF!*100 -> #REF! | G15: =#REF!/Trend_VA!#REF!*100 -> #REF! | H15: =#REF!/Trend_VA!#REF!*100 -> #REF! | I15: =#REF!/Trend_VA!#REF!*100 -> #REF! | ... AI15: =#REF!/Trend_VA!#REF!*100 -> #REF! | AJ15: =#REF!/Trend_VA!B15*100 -> #REF! | AK15: =#REF!/Trend_VA!C15*100 -> #REF! | AL15: =#REF!/Trend_VA!D15*100 -> #REF! | AM15: =#REF!/Trend_VA!E15*100 -> #REF! | AN15: =#REF!/Trend_VA!F15*100 -> #REF! | AO15: =#REF!/Trend_VA!G15*100 -> #REF! | AP15: =#REF!/Trend_VA!H15*100 -> #REF! | AQ15: =#REF!/Trend_VA!I15*100 -> #REF!
A16: Electricity | B16: =#REF!/Trend_VA!#REF!*100 -> #REF! | C16: =#REF!/Trend_VA!#REF!*100 -> #REF! | D16: =#REF!/Trend_VA!#REF!*100 -> #REF! | E16: =#REF!/Trend_VA!#REF!*100 -> #REF! | F16: =#REF!/Trend_VA!#REF!*100 -> #REF! | G16: =#REF!/Trend_VA!#REF!*100 -> #REF! | H16: =#REF!/Trend_VA!#REF!*100 -> #REF! | I16: =#REF!/Trend_VA!#REF!*100 -> #REF! | ... AI16: =#REF!/Trend_VA!#REF!*100 -> #REF! | AJ16: =#REF!/Trend_VA!B16*100 -> #REF! | AK16: =#REF!/Trend_VA!C16*100 -> #REF! | AL16: =#REF!/Trend_VA!D16*100 -> #REF! | AM16: =#REF!/Trend_VA!E16*100 -> #REF! | AN16: =#REF!/Trend_VA!F16*100 -> #REF! | AO16: =#REF!/Trend_VA!G16*100 -> #REF! | AP16: =#REF!/Trend_VA!H16*100 -> #REF! | AQ16: =#REF!/Trend_VA!I16*100 -> #REF!
... A30: Human Health & Social Work | B30: =#REF!/Trend_VA!#REF!*100 -> #REF! | C30: =#REF!/Trend_VA!#REF!*100 -> #REF! | D30: =#REF!/Trend_VA!#REF!*100 -> #REF! | E30: =#REF!/Trend_VA!#REF!*100 -> #REF! | F30: =#REF!/Trend_VA!#REF!*100 -> #REF! | G30: =#REF!/Trend_VA!#REF!*100 -> #REF! | H30: =#REF!/Trend_VA!#REF!*100 -> #REF! | I30: =#REF!/Trend_VA!#REF!*100 -> #REF! | ... AI30: =#REF!/Trend_VA!#REF!*100 -> #REF! | AJ30: =#REF!/Trend_VA!B30*100 -> #REF! | AK30: =#REF!/Trend_VA!C30*100 -> #REF! | AL30: =#REF!/Trend_VA!D30*100 -> #REF! | AM30: =#REF!/Trend_VA!E30*100 -> #REF! | AN30: =#REF!/Trend_VA!F30*100 -> #REF! | AO30: =#REF!/Trend_VA!G30*100 -> #REF! | AP30: =#REF!/Trend_VA!H30*100 -> #REF! | AQ30: =#REF!/Trend_VA!I30*100 -> #REF!
A31: Arts, Entertainment & Recreation | B31: =#REF!/Trend_VA!#REF!*100 -> #REF! | C31: =#REF!/Trend_VA!#REF!*100 -> #REF! | D31: =#REF!/Trend_VA!#REF!*100 -> #REF! | E31: =#REF!/Trend_VA!#REF!*100 -> #REF! | F31: =#REF!/Trend_VA!#REF!*100 -> #REF! | G31: =#REF!/Trend_VA!#REF!*100 -> #REF! | H31: =#REF!/Trend_VA!#REF!*100 -> #REF! | I31: =#REF!/Trend_VA!#REF!*100 -> #REF! | ... P31: =#REF!/Trend_VA!#REF!*100 -> #REF! | Q31: Table 10: Summary of QGDP at constant 2009/10 prices, percentage change, 2010/11-2015/16 | R31: =#REF!/Trend_VA!#REF!*100 -> #REF! | S31: =#REF!/Trend_VA!#REF!*100 -> #REF! | T31: =#REF!/Trend_VA!#REF!*100 -> #REF! | U31: =#REF!/Trend_VA!#REF!*100 -> #REF! | V31: =#REF!/Trend_VA!#REF!*100 -> #REF! | W31: =#REF!/Trend_VA!#REF!*100 -> #REF! | X31: =#REF!/Trend_VA!#REF!*100 -> #REF! | Y31: =#REF!/Trend_VA!#REF!*100 -> #REF! | ... AI31: =#REF!/Trend_VA!#REF!*100 -> #REF! | AJ31: =#REF!/Trend_VA!B31*100 -> #REF! | AK31: =#REF!/Trend_VA!C31*100 -> #REF! | AL31: =#REF!/Trend_VA!D31*100 -> #REF! | AM31: =#REF!/Trend_VA!E31*100 -> #REF! | AN31: =#REF!/Trend_VA!F31*100 -> #REF! | AO31: =#REF!/Trend_VA!G31*100 -> #REF! | AP31: =#REF!/Trend_VA!H31*100 -> #REF! | AQ31: =#REF!/Trend_VA!I31*100 -> #REF!
A32: Other Service Activities | B32: =#REF!/Trend_VA!#REF!*100 -> #REF! | C32: =#REF!/Trend_VA!#REF!*100 -> #REF! | D32: =#REF!/Trend_VA!#REF!*100 -> #REF! | E32: =#REF!/Trend_VA!#REF!*100 -> #REF! | F32: =#REF!/Trend_VA!#REF!*100 -> #REF! | G32: =#REF!/Trend_VA!#REF!*100 -> #REF! | H32: =#REF!/Trend_VA!#REF!*100 -> #REF! | I32: =#REF!/Trend_VA!#REF!*100 -> #REF! | ... AI32: =#REF!/Trend_VA!#REF!*100 -> #REF! | AJ32: =#REF!/Trend_VA!B32*100 -> #REF! | AK32: =#REF!/Trend_VA!C32*100 -> #REF! | AL32: =#REF!/Trend_VA!D32*100 -> #REF! | AM32: =#REF!/Trend_VA!E32*100 -> #REF! | AN32: =#REF!/Trend_VA!F32*100 -> #REF! | AO32: =#REF!/Trend_VA!G32*100 -> #REF! | AP32: =#REF!/Trend_VA!H32*100 -> #REF! | AQ32: =#REF!/Trend_VA!I32*100 -> #REF!
A33: Activities of Households | B33: =#REF!/Trend_VA!#REF!*100 -> #REF! | C33: =#REF!/Trend_VA!#REF!*100 -> #REF! | D33: =#REF!/Trend_VA!#REF!*100 -> #REF! | E33: =#REF!/Trend_VA!#REF!*100 -> #REF! | F33: =#REF!/Trend_VA!#REF!*100 -> #REF! | G33: =#REF!/Trend_VA!#REF!*100 -> #REF! | H33: =#REF!/Trend_VA!#REF!*100 -> #REF! | I33: =#REF!/Trend_VA!#REF!*100 -> #REF! | ... AI33: =#REF!/Trend_VA!#REF!*100 -> #REF! | AJ33: =#REF!/Trend_VA!B33*100 -> #REF! | AK33: =#REF!/Trend_VA!C33*100 -> #REF! | AL33: =#REF!/Trend_VA!D33*100 -> #REF! | AM33: =#REF!/Trend_VA!E33*100 -> #REF! | AN33: =#REF!/Trend_VA!F33*100 -> #REF! | AO33: =#REF!/Trend_VA!G33*100 -> #REF! | AP33: =#REF!/Trend_VA!H33*100 -> #REF! | AQ33: =#REF!/Trend_VA!I33*100 -> #REF!
A35: ADJUSTMENTS
A36: Taxes on Products | B36: =#REF!/Trend_VA!#REF!*100 -> #REF! | C36: =#REF!/Trend_VA!#REF!*100 -> #REF! | D36: =#REF!/Trend_VA!#REF!*100 -> #REF! | E36: =#REF!/Trend_VA!#REF!*100 -> #REF! | F36: =#REF!/Trend_VA!#REF!*100 -> #REF! | G36: =#REF!/Trend_VA!#REF!*100 -> #REF! | H36: =#REF!/Trend_VA!#REF!*100 -> #REF! | I36: =#REF!/Trend_VA!#REF!*100 -> #REF! | ... AI36: =#REF!/Trend_VA!#REF!*100 -> #REF! | AJ36: =#REF!/Trend_VA!B36*100 -> #REF! | AK36: =#REF!/Trend_VA!C36*100 -> #REF! | AL36: =#REF!/Trend_VA!D36*100 -> #REF! | AM36: =#REF!/Trend_VA!E36*100 -> #REF! | AN36: =#REF!/Trend_VA!F36*100 -> #REF! | AO36: =#REF!/Trend_VA!G36*100 -> #REF! | AP36: =#REF!/Trend_VA!H36*100 -> #REF! | AQ36: =#REF!/Trend_VA!I36*100 -> #REF!
A37: Source: Uganda Bureau of Statistics
Z38: 8.5

Sheet Graphs 

Sheet Original_Expenditure
A1: Updated: | C1: 2016 | D1: 2016 | E1: 2017 | F1: 2017 | G1: 2017 | H1: 2017 | I1: 2018 | J1: 2018 | K1: 2018 | L1: 2018 | M1: 2019 | N1: 2019 | O1: 2019 | P1: 2019 | Q1: 2020 | R1: 2020 | S1: 2020 | T1: 2020 | U1: 2021 | V1: 2021 | W1: 2021 | X1: 2021 | Y1: 2022 | Z1: 2022 | AA1: 2022 | AB1: 2022 | AC1: 2023 | AD1: 2023 | AE1: 2023 | AF1: 2023 | AG1: 2024 | AH1: 2024 | AI1: 2024 | AJ1: 2024 | AK1: 2025 | AL1: 2025 | AM1: 2025 | AN1: 2025
B2: Accounts for | C2: 2016/17 | G2: 2017/18 | K2: 2018/19 | O2: 2019/20 | S2: 2020/21 | W2: 2021/22 | AA2: 2022/23 | AE2: 2023/24 | AI2: 2024/25 | AM2: 2025/26
B3: EXPENDITURE Constant prices | G3: Q1 | H3: Q2 | I3: Q3 | J3: Q4 | K3: Q1 | L3: Q2 | M3: Q3 | N3: Q4 | O3: Q1 | P3: Q2 | Q3: Q3 | R3: Q4 | S3: Q1 | T3: Q2 | U3: Q3 | V3: Q4 | W3: Q1 | X3: Q2 | Y3: Q3 | Z3: Q4 | AA3: Q1 | AB3: Q2 | AC3: Q3 | AD3: Q4 | AE3: Q1 | AF3: Q2 | AG3: Q3 | AH3: Q4 | AI3: Q1 | AJ3: Q2 | AK3: Q3 | AL3: Q4 | AM3: Q1 | AN3: Q2
B4: Final Consumption Expenditure | C4: 21056.108 | D4: 21809.964 | E4: 20873.407 | F4: 21882.071 | G4: 23635.343 | H4: 22889.457 | I4: 23080.407 | J4: 24400.686 | K4: 24578.433 | L4: 25052.237 | M4: 24429.744 | N4: 26518.577 | O4: 27496.761 | P4: 27762.147 | Q4: 24507.264 | R4: 24079.789 | S4: 27567.685 | T4: 28215.331 | U4: 26474.967 | V4: 27848.232 | W4: 27972.652 | X4: 28348.573 | Y4: 28267.668 | Z4: 30291.768 | AA4: 31361.55 | AB4: 30181.181 | AC4: 27673.232 | AD4: 29957.688 | AE4: 32920.649 | AF4: 31184.09 | AG4: 27447.646 | AH4: 30593.885 | AI4: 35471.975 | AJ4: 32619.179 | AK4: 33546.458 | AL4: 33303.938 | AM4: 40054.618 | AN4: 38294.026
B5: General Government FCE | C5: 1993.8506 | D5: 2102.9782 | E5: 2058.9446 | F5: 2535.9086 | G5: 2354.6136 | H5: 2575.5965 | I5: 2456.0321 | J5: 2687.4359 | K5: 2424.4707 | L5: 2664.4656 | M5: 2471.3663 | N5: 3312.0474 | O5: 2637.0772 | P5: 3251.1259 | Q5: 3009.6177 | R5: 3359.6022 | S5: 2846.0464 | T5: 3376.3583 | U5: 3362.9828 | V5: 3472.7615 | W5: 3032.8623 | X5: 3015.6576 | Y5: 3658.1947 | Z5: 4024.1061 | AA5: 3634.3062 | AB5: 3550.8516 | AC5: 3429.2703 | AD5: 3641.0718 | AE5: 3683.2098 | AF5: 3467.0343 | AG5: 4088.2917 | AH5: 5147.0988 | AI5: 4964.2111 | AJ5: 4789.4265 | AK5: 5523.6046 | AL5: 5842.8153 | AM5: 5942.9168 | AN5: 5193.7444
B6: NPISH FCE | C6: 1028.3715 | D6: 1050.8996 | E6: 1079.8473 | F6: 1103.0017 | G6: 1143.1427 | H6: 1190.9272 | I6: 1244.3071 | J6: 1298.9417 | K6: 1377.0939 | L6: 1406.5254 | M6: 1388.0897 | N6: 1337.5424 | O6: 1258.8632 | P6: 1195.4984 | Q6: 1138.9556 | R6: 1109.131 | S6: 1105.8405 | T6: 1116.5329 | U6: 1151.8145 | V6: 1193.2397 | W6: 1238.0769 | X6: 1276.9131 | Y6: 1301.2069 | Z6: 1332.261 | AA6: 1372.9372 | AB6: 1362.645 | AC6: 1376.6523 | AD6: 1383.4521 | AE6: 1419.8263 | AF6: 1450.6647 | AG6: 1325.2086 | AH6: 1347.1035 | AI6: 1340.0776 | AJ6: 1345.2022 | AK6: 1179.8711 | AL6: 1283.1168 | AM6: 1363.595 | AN6: 1298.6396
B7: Household FCE | C7: 18033.886 | D7: 18656.086 | E7: 17734.615 | F7: 18243.161 | G7: 20137.586 | H7: 19122.934 | I7: 19380.068 | J7: 20414.308 | K7: 20776.869 | L7: 20981.246 | M7: 20570.288 | N7: 21868.987 | O7: 23600.821 | P7: 23315.523 | Q7: 20358.69 | R7: 19611.056 | S7: 23615.798 | T7: 23722.439 | U7: 21960.17 | V7: 23182.231 | W7: 23701.713 | X7: 24056.002 | Y7: 23308.267 | Z7: 24935.401 | AA7: 26354.307 | AB7: 25267.685 | AC7: 22867.309 | AD7: 24933.164 | AE7: 27817.613 | AF7: 26266.391 | AG7: 22034.146 | AH7: 24099.682 | AI7: 29167.687 | AJ7: 26484.55 | AK7: 26842.982 | AL7: 26178.006 | AM7: 32748.106 | AN7: 31801.642
B8: Gross Fixed Capital Formation | C8: 6395.6537 | D8: 6857.9603 | E8: 6318.6139 | F8: 6528.9902 | G8: 7184.0049 | H8: 7297.7366 | I8: 7060.1156 | J8: 7108.5563 | K8: 7675.5755 | L8: 7828.7503 | M8: 7691.5252 | N8: 8232.0251 | O8: 7984.0966 | P8: 8101.5448 | Q8: 8238.9369 | R8: 7080.2528 | S8: 7125.6248 | T8: 8633.175 | U8: 8524.5459 | V8: 8565.9508 | W8: 8756.0932 | X8: 9192.4806 | Y8: 8534.4336 | Z8: 8763.0548 | AA8: 9047.7164 | AB8: 9154.8138 | AC8: 8919.6258 | AD8: 9429.5564 | AE8: 9575.9233 | AF8: 9262.3743 | AG8: 9968.3771 | AH8: 10179.465 | AI8: 9888.709 | AJ8: 9942.4045 | AK8: 10839.635 | AL8: 11106.42 | AM8: 11190.179 | AN8: 11496.008
B9: Dwellings | C9: 82.406705 | D9: 82.390972 | E9: 82.525201 | F9: 82.811741 | G9: 83.25297 | H9: 83.659714 | I9: 84.031412 | J9: 84.367496 | K9: 84.667391 | L9: 84.977296 | M9: 85.297353 | N9: 85.627707 | O9: 85.968504 | P9: 86.308472 | Q9: 86.64758 | R9: 86.985801 | S9: 87.323103 | T9: 87.662248 | U9: 88.003248 | V9: 88.346116 | W9: 88.690867 | X9: 89.036832 | Y9: 89.384016 | Z9: 89.732421 | AA9: 90.082051 | AB9: 90.433074 | AC9: 90.785498 | AD9: 91.139328 | AE9: 91.494569 | AF9: 91.851187 | AG9: 92.209187 | AH9: 92.568575 | AI9: 92.929355 | AJ9: 93.291543 | AK9: 93.655145 | AL9: 94.020165 | AM9: 94.386609 | AN9: 94.754481
B10: Other Buildings | C10: 1421.5075 | D10: 1560.3049 | E10: 1455.7505 | F10: 1542.0243 | G10: 1514.0816 | H10: 1547.0148 | I10: 1638.2659 | J10: 1757.562 | K10: 1735.3264 | L10: 1776.0615 | M10: 1787.2149 | N10: 1930.7897 | O10: 1859.4191 | P10: 1956.231 | Q10: 1940.3932 | R10: 1821.8274 | S10: 1558.7432 | T10: 1942.0978 | U10: 2020.6703 | V10: 2177.5291 | W10: 2305.3667 | X10: 2189.282 | Y10: 2041.6952 | Z10: 2154.6246 | AA10: 2225.3554 | AB10: 2093.8053 | AC10: 2165.8792 | AD10: 2194.0547 | AE10: 2312.7802 | AF10: 2065.9426 | AG10: 2297.647 | AH10: 2474.026 | AI10: 2405.5274 | AJ10: 2475.7329 | AK10: 2838.778 | AL10: 2904.1867 | AM10: 2836.7169 | AN10: 2893.7273
B11: Other Structures | C11: 2300.0523 | D11: 2500.2614 | E11: 2276.4166 | F11: 2300.5622 | G11: 2320.5892 | H11: 2525.1316 | I11: 2527.9708 | J11: 2723.5185 | K11: 2711.6484 | L11: 2982.8216 | M11: 2942.8028 | N11: 3100.1009 | O11: 2905.5806 | P11: 3071.0241 | Q11: 3166.287 | R11: 2972.8705 | S11: 2527.8992 | T11: 3295.3763 | U11: 3413.5643 | V11: 3478.8037 | W11: 3273.0874 | X11: 3213.7684 | Y11: 3063.248 | Z11: 3251.4972 | AA11: 3344.7909 | AB11: 3317.8393 | AC11: 3450.7843 | AD11: 3781.0932 | AE11: 3551.4131 | AF11: 3503.4834 | AG11: 3909.6946 | AH11: 4132.7349 | AI11: 3794.6654 | AJ11: 3605.0321 | AK11: 4338.6867 | AL11: 4648.9834 | AM11: 4144.947 | AN11: 4409.9236
B12: Transport Equipment | C12: 467.46982 | D12: 541.96879 | E12: 439.51209 | F12: 431.44024 | G12: 648.72579 | H12: 660.22085 | I12: 587.38285 | J12: 613.15448 | K12: 590.12291 | L12: 563.68262 | M12: 502.07668 | N12: 554.7833 | O12: 541.36254 | P12: 469.22391 | Q12: 452.37275 | R12: 207.18267 | S12: 483.74848 | T12: 451.29433 | U12: 561.96974 | V12: 523.42195 | W12: 525.51274 | X12: 570.25763 | Y12: 500.79524 | Z12: 567.34225 | AA12: 550.24269 | AB12: 476.3246 | AC12: 557.30615 | AD12: 575.37771 | AE12: 508.5104 | AF12: 457.7731 | AG12: 505.29788 | AH12: 485.3277 | AI12: 502.32596 | AJ12: 705.50321 | AK12: 540.33548 | AL12: 644.91682 | AM12: 775.59679 | AN12: 715.29758
B13: ICT Equipment | C13: 47.130738 | D13: 178.07993 | E13: 352.88163 | F13: 167.93997 | G13: 160.2673 | H13: 180.91728 | I13: 135.48406 | J13: 101.2749 | K13: 129.491 | L13: 141.42411 | M13: 175.99962 | N13: 150.72942 | O13: 128.10082 | P13: 120.94143 | Q13: 121.74162 | R13: 124.56159 | S13: 102.51937 | T13: 130.43032 | U13: 106.50985 | V13: 122.84204 | W13: 88.108905 | X13: 132.29198 | Y13: 115.54869 | Z13: 165.02796 | AA13: 127.47252 | AB13: 127.89371 | AC13: 150.12625 | AD13: 116.71406 | AE13: 101.05715 | AF13: 80.534697 | AG13: 146.26476 | AH13: 126.111 | AI13: 79.209061 | AJ13: 153.16075 | AK13: 128.83212 | AL13: 98.460206 | AM13: 131.93873 | AN13: 310.50757
B14: Other Machinery and Equipment | C14: 1485.3314 | D14: 1460.2273 | E14: 1195.6421 | F14: 1559.7693 | G14: 1890.6726 | H14: 1724.4582 | I14: 1521.8294 | J14: 1262.2021 | K14: 1854.3913 | L14: 1765.0243 | M14: 1601.1083 | N14: 1835.5279 | O14: 1857.3206 | P14: 1767.4203 | Q14: 1875.9887 | R14: 1346.2051 | S14: 1740.0588 | T14: 2064.5847 | U14: 1714.2292 | V14: 1603.8935 | W14: 1796.7973 | X14: 2208.0139 | Y14: 2034.4344 | Z14: 1823.324 | AA14: 1920.0489 | AB14: 2219.8794 | AC14: 1590.0003 | AD14: 1683.7703 | AE14: 2018.8744 | AF14: 1999.3184 | AG14: 2047.661 | AH14: 1944.1629 | AI14: 1965.0744 | AJ14: 1850.6783 | AK14: 1826.6895 | AL14: 1790.5718 | AM14: 2233.8391 | AN14: 1982.2456
B15: Other Asset Types | C15: 591.75519 | D15: 534.72692 | E15: 515.88585 | F15: 444.44248 | G15: 566.41542 | H15: 576.33423 | I15: 565.15115 | J15: 566.47683 | K15: 569.92817 | L15: 514.75881 | M15: 597.02545 | N15: 574.46619 | O15: 606.34441 | P15: 630.39558 | Q15: 595.50609 | R15: 520.61983 | S15: 625.33258 | T15: 661.72935 | U15: 619.59925 | V15: 571.11439 | W15: 678.5293 | X15: 789.82982 | Y15: 689.32794 | Z15: 711.50633 | AA15: 789.72396 | AB15: 828.63849 | AC15: 914.74405 | AD15: 987.40709 | AE15: 991.79356 | AF15: 1063.4708 | AG15: 969.60262 | AH15: 924.53386 | AI15: 1048.9775 | AJ15: 1059.0056 | AK15: 1072.6579 | AL15: 925.28056 | AM15: 972.75339 | AN15: 1089.5522
... B25: GDP at Market Prices | C25: 28577.247 | D25: 26610.18 | E25: 26240.178 | F25: 27090.435 | G25: 30772.237 | H25: 28335.28 | I25: 27653.331 | J25: 28598.087 | K25: 32487.642 | L25: 29958.631 | M25: 29773.235 | N25: 30567.095 | O25: 34943.779 | P25: 32466.458 | Q25: 30130.072 | R25: 28870.102 | S25: 34802.923 | T25: 32477.008 | U25: 30975.024 | V25: 32626.063 | W25: 35622.436 | X25: 34024.49 | Y25: 32716.662 | Z25: 34522.28 | AA25: 38746.737 | AB25: 35492.013 | AC25: 33446.228 | AD25: 36506.452 | AE25: 41068.072 | AF25: 37544.31 | AG25: 35728.791 | AH25: 38581.884 | AI25: 43605.836 | AJ25: 39557.991 | AK25: 38727.987 | AL25: 40714.044 | AM25: 45718.884 | AN25: 42903.876
G26: 2017/18 | K26: 2018/19 | O26: 2019/20 | S26: 2020/21 | W26: 2021/22 | AA26: 2022/23 | AE26: 2023/24 | AI26: 2024/25 | AM26: 2025/26 | AN26: 2025/27
B27: QUARTERLY CHANGES Constant prices | G27: Q1 | H27: Q2 | I27: Q3 | J27: Q4 | K27: Q1 | L27: Q2 | M27: Q3 | N27: Q4 | O27: Q1 | P27: Q2 | Q27: Q3 | R27: Q4 | S27: Q1 | T27: Q2 | U27: Q3 | V27: Q4 | W27: Q1 | X27: Q2 | Y27: Q3 | Z27: Q4 | AA27: Q1 | AB27: Q2 | AC27: Q3 | AD27: Q4 | AE27: Q1 | AF27: Q2 | AG27: Q3 | AH27: Q4 | AI27: Q1 | AJ27: Q2 | AK27: Q3 | AL27: Q4 | AM27: Q1 | AN27: Q2
B28: Final Consumption Expenditure | C28: 0.9348094 | D28: 10.85888 | E28: -16.797519 | F28: 14.935017 | G28: 12.249344 | H28: 4.9495406 | I28: 10.573264 | J28: 11.509947 | K28: 3.9901712 | L28: 9.448802 | M28: 5.8462433 | N28: 8.6796387 | O28: 11.87353 | P28: 10.817039 | Q28: 0.31731668 | R28: -9.1965268 | S28: 0.25793547 | T28: 1.6323797 | U28: 8.0290634 | V28: 15.649817 | W28: 1.468993 | X28: 0.47223334 | Y28: 6.7713055 | Z28: 8.7744757 | AA28: 12.11504 | AB28: 6.4645531 | AC28: -2.1028846 | AD28: -1.102876 | AE28: 4.9713687 | AF28: 3.3229617 | AG28: -0.81517639 | AH28: 2.1236514 | AI28: 7.7499279 | AJ28: 4.6019901 | AK28: 22.2198 | AL28: 8.8581538 | AM28: 12.919051 | AN28: 17.39727
B29: General Government FCE | C29: 6.5162488 | D29: -0.050776206 | E29: 17.23704 | F29: 28.841789 | G29: 18.093785 | H29: 22.473761 | I29: 19.285971 | J29: 5.9752645 | K29: 2.9668197 | L29: 3.4504285 | M29: 0.62434938 | N29: 23.241915 | O29: 8.7691912 | P29: 22.017936 | Q29: 21.779508 | R29: 1.4358129 | S29: 7.9242733 | T29: 3.8519702 | U29: 11.741197 | V29: 3.3682338 | W29: 6.5640472 | X29: -10.68313 | Y29: 8.7782742 | Z29: 15.876258 | AA29: 19.830903 | AB29: 17.747173 | AC29: -6.2578515 | AD29: -9.518492 | AE29: 1.3456104 | AF29: -2.3604833 | AG29: 19.217541 | AH29: 41.362187 | AI29: 34.77948 | AJ29: 38.141885 | AK29: 35.107888 | AL29: 13.516674 | AM29: 19.715233 | AN29: 8.4418842
B30: NPISH FCE | C30: 5.8183991 | D30: 5.8445629 | E30: 8.6812151 | F30: 10.202213 | G30: 11.16048 | H30: 13.324545 | I30: 15.229913 | J30: 17.764245 | K30: 20.465624 | L30: 18.103399 | M30: 11.555232 | N30: 2.9717063 | O30: -8.5855267 | P30: -15.003432 | Q30: -17.947986 | R30: -17.076944 | S30: -12.155625 | T30: -6.605235 | U30: 1.1290148 | V30: 7.5832885 | W30: 11.958003 | X30: 14.364127 | Y30: 12.970178 | Z30: 11.65075 | AA30: 10.892725 | AB30: 6.7139968 | AC30: 5.7981081 | AD30: 3.8424214 | AE30: 3.4152391 | AF30: 6.4594763 | AG30: -3.7368706 | AH30: -2.627384 | AI30: -5.6167959 | AJ30: -7.2699458 | AK30: -10.967144 | AL30: -4.7499509 | AM30: 1.7549306 | AN30: -3.4613848
B31: Household FCE | C31: 0.091526703 | D31: 12.543954 | E31: -20.606679 | F31: 13.526464 | G31: 11.665266 | H31: 2.5023853 | I31: 9.2782003 | J31: 11.901159 | K31: 3.1745722 | L31: 9.7177145 | M31: 6.1414643 | N31: 7.1257818 | O31: 13.591808 | P31: 11.12554 | Q31: -1.0286566 | R31: -10.324811 | S31: 0.063461257 | T31: 1.7452611 | U31: 7.8663194 | V31: 18.21001 | W31: 0.36380343 | X31: 1.4061064 | Y31: 6.1388262 | Z31: 7.5625613 | AA31: 11.19157 | AB31: 5.0369245 | AC31: -1.89185 | AD31: -0.0089732255 | AE31: 5.5524344 | AF31: 3.9525055 | AG31: -3.6434692 | AH31: -3.342863 | AI31: 4.8533067 | AJ31: 0.83056357 | AK31: 21.824475 | AL31: 8.6238629 | AM31: 12.275294 | AN31: 20.076201
B32: Gross Fixed Capital Formation | C32: -1.7073961 | D32: 2.133728 | E32: 0.6016882 | F32: 7.1509196 | G32: 12.326358 | H32: 6.4126403 | I32: 11.735196 | J32: 8.8768103 | K32: 6.8425716 | L32: 7.2764155 | M32: 8.9433317 | N32: 15.804458 | O32: 4.0195165 | P32: 3.4845223 | Q32: 7.1170771 | R32: -13.99136 | S32: -10.752272 | T32: 6.5620839 | U32: 3.4665749 | V32: 20.983685 | W32: 22.88176 | X32: 6.4785617 | Y32: 0.11599133 | Z32: 2.3010175 | AA32: 3.3305177 | AB32: -0.40975605 | AC32: 4.5133893 | AD32: 7.6058135 | AE32: 5.8380135 | AF32: 1.1749059 | AG32: 11.757795 | AH32: 7.9527445 | AI32: 3.2663764 | AJ32: 7.341857 | AK32: 8.7402169 | AL32: 9.1061252 | AM32: 13.161167 | AN32: 15.626036
B33: Dwellings | C33: 3.8703884 | D33: 1.6857289 | E33: 0.51018813 | F33: 0.29268347 | G33: 1.0269369 | H33: 1.5399037 | I33: 1.8251533 | J33: 1.8786647 | K33: 1.6989445 | L33: 1.57493 | M33: 1.5065088 | N33: 1.493716 | O33: 1.5367344 | P33: 1.5665077 | Q33: 1.5829654 | R33: 1.5860449 | S33: 1.5756923 | T33: 1.5685324 | U33: 1.5645764 | V33: 1.5638363 | W33: 1.5663245 | X33: 1.5680456 | Y33: 1.5689967 | Z33: 1.5691746 | AA33: 1.5685765 | AB33: 1.5681627 | AC33: 1.567934 | AD33: 1.5678911 | AE33: 1.5680348 | AF33: 1.5681343 | AG33: 1.5681895 | AH33: 1.5682001 | AI33: 1.568166 | AJ33: 1.568142 | AK33: 1.568128 | AL33: 1.5681241 | AM33: 1.5681305 | AN33: 1.5681352
B34: Other Buildings | C34: 7.9732637 | D34: 12.736558 | E34: 7.6479014 | F34: 20.014063 | G34: 6.5123908 | H34: -0.8517645 | I34: 12.537549 | J34: 13.977576 | K34: 14.612474 | L34: 14.80572 | M34: 9.0918731 | N34: 9.8561374 | O34: 7.1509741 | P34: 10.14433 | Q34: 8.5707774 | R34: -5.6434075 | S34: -16.170421 | T34: -0.72247434 | U34: 4.1371568 | V34: 19.524447 | W34: 47.899065 | X34: 12.72769 | Y34: 1.0404954 | Z34: -1.0518546 | AA34: -3.4706507 | AB34: -4.3610973 | AC34: 6.0823943 | AD34: 1.8300212 | AE34: 3.9285733 | AF34: -1.330718 | AG34: 6.083804 | AH34: 12.760451 | AI34: 4.0102039 | AJ34: 19.835513 | AK34: 23.551529 | AL34: 17.387074 | AM34: 17.92495 | AN34: 16.883663
B35: Other Structures | C35: 14.995735 | D35: 15.106636 | E35: 6.6894839 | F35: 11.711146 | G35: 0.8928849 | H35: 0.99470081 | I35: 11.050447 | J35: 18.384913 | K35: 16.85172 | L35: 18.125395 | M35: 16.409682 | N35: 13.827053 | O35: 7.15182 | P35: 2.9570131 | Q35: 7.5942644 | R35: -4.1040741 | S35: -12.998482 | T35: 7.3054525 | U35: 7.8096915 | V35: 17.018341 | W35: 29.478557 | X35: -2.4764361 | Y35: -10.262477 | Z35: -6.5340418 | AA35: 2.1906983 | AB35: 3.2382828 | AC35: 12.651157 | AD35: 16.287757 | AE35: 6.1774325 | AF35: 5.5953333 | AG35: 13.298724 | AH35: 9.3000019 | AI35: 6.849451 | AJ35: 2.8985062 | AK35: 10.972522 | AL35: 12.491692 | AM35: 9.2308948 | AN35: 22.326886
B36: Transport Equipment | C36: -19.229177 | D36: 2.5459388 | E36: -9.2477908 | F36: -7.7458166 | G36: 38.773835 | H36: 21.818981 | I36: 33.6443 | J36: 42.118055 | K36: -9.0335363 | L36: -14.622111 | M36: -14.523095 | N36: -9.5198159 | O36: -8.262748 | P36: -16.757429 | Q36: -9.8996687 | R36: -62.655208 | S36: -10.642418 | T36: -3.8211138 | U36: 24.227142 | V36: 152.6379 | W36: 8.6334671 | X36: 26.360471 | Y36: -10.885729 | Z36: 8.3909919 | AA36: 4.7058691 | AB36: -16.472035 | AC36: 11.284235 | AD36: 1.4163354 | AE36: -7.5843426 | AF36: -3.894717 | AG36: -9.3320835 | AH36: -15.650591 | AI36: -1.2161876 | AJ36: 54.116354 | AK36: 6.9340488 | AL36: 32.882755 | AM36: 54.401099 | AN36: 1.3882808
B37: ICT Equipment | C37: -74.517676 | D37: 51.826403 | E37: 73.939727 | F37: -3.4003552 | G37: 240.04836 | H37: 1.5933032 | I37: -61.606372 | J37: -39.695774 | K37: -19.203108 | L37: -21.829409 | M37: 29.904298 | N37: 48.831959 | O37: -1.0735753 | P37: -14.48316 | Q37: -30.828473 | R37: -17.360796 | S37: -19.969776 | T37: 7.8458587 | U37: -12.511555 | V37: -1.3804842 | W37: -14.056333 | X37: 1.4273197 | Y37: 8.48639 | Z37: 34.341603 | AA37: 44.676091 | AB37: -3.3246695 | AC37: 29.924665 | AD37: -29.276191 | AE37: -20.722403 | AF37: -37.029977 | AG37: -2.5721613 | AH37: 8.0512487 | AI37: -21.619537 | AJ37: 90.179832 | AK37: -11.918551 | AL37: -21.92576 | AM37: 66.570244 | AN37: 102.73312
B38: Other Machinery and Equipment | C38: -12.428698 | D38: -14.682622 | E38: -14.324043 | F38: 5.9506128 | G38: 27.289615 | H38: 18.095187 | I38: 27.281354 | J38: -19.07764 | K38: -1.9189614 | L38: 2.3523992 | M38: 5.2094477 | N38: 45.422662 | O38: 0.15796374 | P38: 0.13575061 | Q38: 17.168132 | R38: -26.658422 | S38: -6.3134901 | T38: 16.813452 | U38: -8.6226259 | V38: 19.141837 | W38: 3.26072 | X38: 6.9471231 | Y38: 18.679252 | Z38: 13.681113 | AA38: 6.8595155 | AB38: 0.53738183 | AC38: -21.845586 | AD38: -7.6538054 | AE38: 5.1470317 | AF38: -9.93572 | AG38: 28.783687 | AH38: 15.46485 | AI38: -2.6648502 | AJ38: -7.4345371 | AK38: -10.79141 | AL38: -7.9001124 | AM38: 13.677076 | AN38: 7.1091359
B39: Other Asset Types | C39: -9.0869717 | D39: -25.750878 | E39: -18.112308 | F39: -19.595569 | G39: -4.2821385 | H39: 7.7810379 | I39: 9.5496512 | J39: 27.45785 | K39: 0.62017187 | L39: -10.683977 | M39: 5.6399602 | N39: 1.4103602 | O39: 6.3896203 | P39: 22.464262 | Q39: -0.25448814 | R39: -9.3732873 | S39: 3.1315817 | T39: 4.9704939 | U39: 4.0458295 | V39: 9.6989328 | W39: 8.5069477 | X39: 19.358439 | Y39: 11.253837 | Z39: 24.582105 | AA39: 16.387599 | AB39: 4.9135476 | AC39: 32.700852 | AD39: 38.776993 | AE39: 25.587371 | AF39: 28.339538 | AG39: 5.9971494 | AH39: -6.3675081 | AI39: 5.7657074 | AJ39: -0.41986802 | AK39: 10.628607 | AL39: 0.080764805 | AM39: -7.266513 | AN39: 2.8844531
... B49: GDP at Market Prices | C49: -0.26122599 | D49: 0.50756396 | E49: 6.7464548 | F49: 6.1811727 | G49: 7.6808998 | H49: 6.4828574 | I49: 5.3854549 | J49: 5.5652552 | K49: 5.5745218 | L49: 5.7290794 | M49: 7.6659989 | N49: 6.8851035 | O49: 7.5602194 | P49: 8.3709675 | Q49: 1.1985158 | R49: -5.5516965 | S49: -0.40309239 | T49: 0.032495737 | U49: 2.804345 | V49: 13.009861 | W49: 2.354724 | X49: 4.7648514 | Y49: 5.6227189 | Z49: 5.811971 | AA49: 8.7705981 | AB49: 4.3131379 | AC49: 2.2299523 | AD49: 5.7475112 | AE49: 5.9910476 | AF49: 5.7824205 | AG49: 6.8245768 | AH49: 5.6851104 | AI49: 6.1794064 | AJ49: 5.3634777 | AK49: 8.394339 | AL49: 5.5263248 | AM49: 4.8457919 | AN49: 8.4581777

Sheet Deseason_Exp
A1: Updated: | D1: 2016 | E1: 2016 | F1: 2017 | G1: 2017 | H1: 2017 | I1: 2017 | J1: 2018 | K1: 2018 | L1: 2018 | M1: 2018 | N1: 2019 | O1: 2019 | P1: 2019 | Q1: 2019 | R1: 2020 | S1: 2020 | T1: 2020 | U1: 2020 | V1: 2021 | W1: 2021 | X1: 2021 | Y1: 2021 | Z1: 2022 | AA1: 2022 | AB1: 2022 | AC1: 2022 | AD1: 2023 | AE1: 2023 | AF1: 2023 | AG1: 2023 | AH1: 2024 | AI1: 2024 | AJ1: 2024 | AK1: 2024 | AL1: 2025 | AM1: 2025 | AN1: 2025 | AO1: 2025
B2: Accounts for | D2: 2016/17 | H2: 2017/18 | L2: 2018/19 | P2: 2019/20 | T2: 2020/21 | X2: 2021/22 | AB2: 2022/23 | AF2: 2023/24 | AJ2: 2024/25 | AN2: 2025/26
B3: EXPENDITURE Constant prices | D3: Q1 | E3: Q2 | F3: Q3 | G3: Q4 | H3: Q1 | I3: Q2 | J3: Q3 | K3: Q4 | L3: Q1 | M3: Q2 | N3: Q3 | O3: Q4 | P3: Q1 | Q3: Q2 | R3: Q3 | S3: Q4 | T3: Q1 | U3: Q2 | V3: Q3 | W3: Q4 | X3: Q1 | Y3: Q2 | Z3: Q3 | AA3: Q4 | AB3: Q1 | AC3: Q2 | AD3: Q3 | AE3: Q4 | AF3: Q1 | AG3: Q2 | AH3: Q3 | AI3: Q4 | AJ3: Q1 | AK3: Q2 | AL3: Q3 | AM3: Q4 | AN3: Q1 | AO3: Q2
B4: Final Consumption Expenditure | D4: 20866.504 | E4: 21624.38 | F4: 21469.23 | G4: 21848.36 | H4: 23234.403 | I4: 22531.397 | J4: 23929.196 | K4: 24465.424 | L4: 24014.065 | M4: 24570.028 | N4: 25450.291 | O4: 26615.656 | P4: 26810.446 | Q4: 27158.448 | R4: 25764.174 | S4: 24206.287 | T4: 26703.547 | U4: 27548.116 | V4: 27979.496 | W4: 28057.963 | X4: 26781.943 | Y4: 27666.106 | Z4: 30031.896 | AA4: 30618.682 | AB4: 29736.483 | AC4: 29549.965 | AD4: 29681.132 | AE4: 30502.592 | AF4: 30846.838 | AG4: 30560.551 | AH4: 29675.691 | AI4: 31243.748 | AJ4: 33017.467 | AK4: 32059.568 | AL4: 35973.091 | AM4: 34071.256 | AN4: 37320.65 | AO4: 37744.522
B5: General Government FCE | D5: 2125.8237 | E5: 2056.8746 | F5: 2160.4492 | G5: 2341.5332 | H5: 2503.0233 | I5: 2510.6965 | J5: 2582.7472 | K5: 2484.851 | L5: 2569.9553 | M5: 2612.3413 | N5: 2582.1499 | O5: 3063.6103 | P5: 2791.2014 | Q5: 3218.1751 | R5: 3117.5104 | S5: 3110.5181 | T5: 2989.7174 | U5: 3398.5016 | V5: 3449.4979 | W5: 3218.8402 | X5: 3150.4522 | Y5: 3092.6304 | Z5: 3720.2051 | AA5: 3747.1478 | AB5: 3701.2213 | AC5: 3728.5539 | AD5: 3461.7289 | AE5: 3402.8238 | AF5: 3687.2783 | AG5: 3703.5602 | AH5: 4117.4003 | AI5: 4827.7031 | AJ5: 4891.0868 | AK5: 5186.0222 | AL5: 5565.7578 | AM5: 5475.8988 | AN5: 5817.0224 | AO5: 5656.5525
B6: NPISH FCE | D6: 1028.1709 | E6: 1046.908 | F6: 1079.5993 | G6: 1108.5004 | H6: 1141.3166 | I6: 1187.3329 | J6: 1244.2667 | K6: 1305.0389 | L6: 1374.1373 | M6: 1403.1679 | N6: 1388.7567 | O6: 1342.8005 | P6: 1255.5678 | Q6: 1193.7552 | R6: 1139.7441 | S6: 1112.4482 | T6: 1103.0035 | U6: 1115.5496 | V6: 1153.0132 | W6: 1195.4938 | X6: 1235.1994 | Y6: 1276.763 | Z6: 1302.3729 | AA6: 1333.4214 | AB6: 1370.627 | AC6: 1363.0432 | AD6: 1377.7646 | AE6: 1383.4154 | AF6: 1418.3292 | AG6: 1451.7125 | AH6: 1325.69 | AI6: 1346.4191 | AJ6: 1339.4248 | AK6: 1346.4406 | AL6: 1180.0538 | AM6: 1281.8079 | AN6: 1363.6085 | AO6: 1300.077
B7: Household FCE | D7: 17712.51 | E7: 18520.597 | F7: 18229.182 | G7: 18398.326 | H7: 19590.063 | I7: 18833.367 | J7: 20102.182 | K7: 20675.534 | L7: 20069.972 | M7: 20554.518 | N7: 21479.385 | O7: 22209.245 | P7: 22763.677 | Q7: 22746.518 | R7: 21506.919 | S7: 19983.321 | T7: 22610.826 | U7: 23034.064 | V7: 23376.985 | W7: 23643.629 | X7: 22396.292 | Y7: 23296.713 | Z7: 25009.318 | AA7: 25538.112 | AB7: 24664.635 | AC7: 24458.367 | AD7: 24841.639 | AE7: 25716.353 | AF7: 25741.231 | AG7: 25405.279 | AH7: 24232.601 | AI7: 25069.626 | AJ7: 26786.955 | AK7: 25527.105 | AL7: 29227.28 | AM7: 27313.549 | AN7: 30140.019 | AO7: 30787.892
B8: Gross Fixed Capital Formation | D8: 6331.582 | E8: 6657.792 | F8: 6574.8993 | G8: 6518.2942 | H8: 7102.1694 | I8: 7096.7585 | J8: 7180.1607 | K8: 7231.8436 | L8: 7627.4407 | M8: 7649.0534 | N8: 7862.8114 | O8: 8303.9669 | P8: 7965.4905 | Q8: 7943.8797 | R8: 8373.69 | S8: 7103.4344 | T8: 7132.359 | U8: 8484.2727 | V8: 8608.2865 | W8: 8585.5453 | X8: 8773.2233 | Y8: 9096.5654 | Z8: 8617.6563 | AA8: 8752.2459 | AB8: 9064.4918 | AC8: 9118.5402 | AD8: 8948.6135 | AE8: 9366.1383 | AF8: 9553.0903 | AG8: 9321.1729 | AH8: 9878.0544 | AI8: 10198.728 | AJ8: 9875.2868 | AK8: 10065.852 | AL8: 10816.033 | AM8: 10942.775 | AN8: 11202.686 | AO8: 11616.648
B9: Dwellings | D9: 82.406738 | E9: 82.390891 | F9: 82.525208 | G9: 82.811757 | H9: 83.253029 | I9: 83.659635 | J9: 84.031417 | K9: 84.367522 | L9: 84.66744 | M9: 84.977221 | N9: 85.297352 | O9: 85.627715 | P9: 85.968572 | Q9: 86.308393 | R9: 86.647586 | S9: 86.985826 | T9: 87.323148 | U9: 87.662171 | V9: 88.003251 | W9: 88.346132 | X9: 88.69092 | Y9: 89.036752 | Z9: 89.384025 | AA9: 89.732472 | AB9: 90.08206 | AC9: 90.433005 | AD9: 90.785506 | AE9: 91.139372 | AF9: 91.494577 | AG9: 91.851132 | AH9: 92.209191 | AI9: 92.568621 | AJ9: 92.929351 | AK9: 93.291507 | AL9: 93.655141 | AM9: 94.020194 | AN9: 94.386615 | AO9: 94.754455
B10: Other Buildings | D10: 1437.6835 | E10: 1535.1142 | F10: 1501.302 | G10: 1500.9963 | H10: 1534.7932 | I10: 1531.7973 | J10: 1669.8788 | K10: 1718.4013 | L10: 1756.4823 | M10: 1770.8883 | N10: 1806.4931 | O10: 1895.2918 | P10: 1873.4408 | Q10: 1963.9972 | R10: 1954.3022 | S10: 1791.3547 | T10: 1560.433 | U10: 1964.8589 | V10: 2031.2725 | W10: 2140.898 | X10: 2295.7157 | Y10: 2232.7017 | Z10: 2046.8356 | AA10: 2116.2827 | AB10: 2210.6567 | AC10: 2147.1143 | AD10: 2167.7068 | AE10: 2147.7231 | AF10: 2302.404 | AG10: 2125.8922 | AH10: 2292.2411 | AI10: 2413.6639 | AJ10: 2408.5951 | AK10: 2546.4623 | AL10: 2825.8756 | AM10: 2824.0459 | AN10: 2859.4483 | AO10: 2973.1505
B11: Other Structures | D11: 2350.457 | E11: 2407.9762 | F11: 2357.1112 | G11: 2246.0643 | H11: 2388.506 | I11: 2451.8012 | J11: 2455.8655 | K11: 2785.9881 | L11: 2794.1143 | M11: 2932.1883 | N11: 2968.4155 | O11: 3028.8766 | P11: 2993.4799 | Q11: 3051.6959 | R11: 3172.3322 | S11: 2885.0241 | T11: 2611.5818 | U11: 3315.6874 | V11: 3410.8892 | W11: 3361.7335 | X11: 3348.0139 | Y11: 3284.6673 | Z11: 3052.8634 | AA11: 3094.336 | AB11: 3419.6253 | AC11: 3435.0162 | AD11: 3434.7785 | AE11: 3579.6049 | AF11: 3635.0592 | AG11: 3663.0858 | AH11: 3756.852 | AI11: 4016.1363 | AJ11: 3897.1052 | AK11: 3794.0863 | AL11: 4292.5588 | AM11: 4383.5929 | AN11: 4264.7728 | AO11: 4617.9412
B12: Transport Equipment | D12: 459.97922 | E12: 539.13671 | F12: 468.38041 | G12: 418.82011 | H12: 635.60754 | I12: 654.91835 | J12: 617.21814 | K12: 603.74002 | L12: 574.64004 | M12: 558.74687 | N12: 533.29329 | O12: 541.41779 | P12: 526.79638 | Q12: 470.77866 | R12: 479.01389 | S12: 189.67845 | T12: 471.13056 | U12: 461.26588 | V12: 580.51156 | W12: 504.34108 | X12: 515.79042 | Y12: 585.28116 | Z12: 510.78455 | AA12: 552.82328 | AB12: 541.14644 | AC12: 489.04665 | AD12: 565.12209 | AE12: 567.92321 | AF12: 496.92369 | AG12: 465.98935 | AH12: 513.10275 | AI12: 486.26255 | AJ12: 486.72857 | AK12: 708.15442 | AL12: 550.1706 | AM12: 652.6428 | AN12: 757.15835 | AO12: 713.35135
B13: ICT Equipment | D13: 45.302428 | E13: 188.78476 | F13: 330.31724 | G13: 173.48822 | H13: 160.15746 | I13: 187.67296 | J13: 126.75296 | K13: 103.08463 | L13: 133.7252 | M13: 144.9608 | N13: 162.98674 | O13: 151.31957 | P13: 139.17144 | Q13: 119.9994 | R13: 111.7782 | S13: 126.00335 | T13: 115.85655 | U13: 123.59082 | V13: 98.515783 | W13: 125.04989 | X13: 103.41444 | Y13: 119.74652 | Z13: 108.10981 | AA13: 169.59191 | AB13: 152.95817 | AC13: 112.195 | AD13: 141.81397 | AE13: 120.3024 | AF13: 124.04663 | AG13: 69.139214 | AH13: 138.22749 | AI13: 130.94278 | AJ13: 99.412675 | AK13: 128.6098 | AL13: 121.19628 | AM13: 104.26841 | AN13: 167.61727 | AO13: 256.4845
B14: Other Machinery and Equipment | D14: 1384.0696 | E14: 1379.9165 | F14: 1324.4027 | G14: 1633.368 | H14: 1750.4398 | I14: 1627.1161 | J14: 1660.0496 | K14: 1340.1789 | L14: 1729.9093 | M14: 1660.405 | N14: 1700.9184 | O14: 1988.4495 | P14: 1758.7582 | Q14: 1637.7157 | R14: 1968.9797 | S14: 1468.7271 | T14: 1676.9209 | U14: 1895.7728 | V14: 1774.9129 | W14: 1758.7617 | X14: 1752.6861 | Y14: 2015.2719 | Z14: 2104.8581 | AA14: 1989.8709 | AB14: 1870.1033 | AC14: 2048.608 | AD14: 1638.5322 | AE14: 1830.9034 | AF14: 1943.5271 | AG14: 1875.3634 | AH14: 2117.1742 | AI14: 2095.3043 | AJ14: 1861.1261 | AK14: 1778.3422 | AL14: 1883.3181 | AM14: 1918.0854 | AN14: 2093.196 | AO14: 1935.6751
B15: Other Asset Types | D15: 571.68343 | E15: 524.4727 | F15: 510.86055 | G15: 462.7455 | H15: 549.41225 | I15: 559.79286 | J15: 566.36422 | K15: 596.08319 | L15: 553.90218 | M15: 496.88697 | N15: 605.40702 | O15: 612.98401 | P15: 587.87519 | Q15: 613.38457 | R15: 600.63617 | S15: 555.66087 | T15: 609.11308 | U15: 635.43474 | V15: 624.18134 | W15: 606.41496 | X15: 668.91184 | Y15: 769.86006 | Z15: 704.82082 | AA15: 739.60855 | AB15: 779.91989 | AC15: 796.12705 | AD15: 909.87447 | AE15: 1028.5419 | AF15: 959.63503 | AG15: 1029.8518 | AH15: 968.24765 | AI15: 963.85003 | AJ15: 1029.39 | AK15: 1016.9055 | AL15: 1049.2586 | AM15: 966.11955 | AN15: 966.10686 | AO15: 1025.291
... B25: GDP at Market Prices | D25: 26418.33 | E25: 26820.341 | F25: 27619.794 | G25: 27877.519 | H25: 28291.339 | I25: 28562.977 | J25: 29225.636 | K25: 29425.25 | L25: 29958.925 | M25: 30153.094 | N25: 31561.031 | O25: 31371.83 | P25: 32311.887 | Q25: 32681.047 | R25: 31941.991 | S25: 29638.437 | T25: 31936.886 | U25: 32665.96 | V25: 32913.148 | W25: 33266.263 | X25: 32690.007 | Y25: 34248.282 | Z25: 35004.411 | AA25: 35114.23 | AB25: 35517.737 | AC25: 35836.545 | AD25: 35798.781 | AE25: 36969.932 | AF25: 37483.15 | AG25: 38034.023 | AH25: 38330.506 | AI25: 38995.258 | AJ25: 39825.16 | AK25: 40146.528 | AL25: 41458.228 | AM25: 41147.854 | AN25: 41936.505 | AO25: 43598.4
H26: 2017/18 | L26: 2018/19 | P26: 2019/20 | T26: 2020/21 | X26: 2021/22 | AB26: 2022/23 | AF26: 2023/24 | AJ26: 2024/25 | AN26: 2025/26 | AO26: 2025/27
B27: QUARTERLY CHANGES Constant prices | H27: Q1 | I27: Q2 | J27: Q3 | K27: Q4 | L27: Q1 | M27: Q2 | N27: Q3 | O27: Q4 | P27: Q1 | Q27: Q2 | R27: Q3 | S27: Q4 | T27: Q1 | U27: Q2 | V27: Q3 | W27: Q4 | X27: Q1 | Y27: Q2 | Z27: Q3 | AA27: Q4 | AB27: Q1 | AC27: Q2 | AD27: Q3 | AE27: Q4 | AF27: Q1 | AG27: Q2 | AH27: Q3 | AI27: Q4 | AJ27: Q1 | AK27: Q2 | AL27: Q3 | AM27: Q4 | AN27: Q1 | AO27: Q2
B28: Final Consumption Expenditure | D28: 0.105831 | E28: 0.036320191 | F28: -0.0071747352 | G28: 0.017659197 | H28: 0.063439225 | I28: -0.030257119 | J28: 0.06203783 | K28: 0.022408959 | L28: -0.018448871 | M28: 0.023151557 | N28: 0.035826733 | O28: 0.045789831 | P28: 0.0073186294 | Q28: 0.012980103 | R28: -0.051338522 | S28: -0.06046718 | T28: 0.10316578 | U28: 0.03162757 | V28: 0.015659179 | W28: 0.0028044199 | X28: -0.045477978 | Y28: 0.033013392 | Z28: 0.085512197 | AA28: 0.019538761 | AB28: -0.02881243 | AC28: -0.0062723781 | AD28: 0.0044388508 | AE28: 0.027676142 | AF28: 0.01128582 | AG28: -0.0092809264 | AH28: -0.028954321 | AI28: 0.052839779 | AJ28: 0.056770344 | AK28: -0.029011881 | AL28: 0.12207038 | AM28: -0.052868272 | AN28: 0.095370522 | AO28: 0.01135758
B29: General Government FCE | D29: 0.17326258 | E29: -0.03243409 | F29: 0.050355342 | G29: 0.083817777 | H29: 0.068967645 | I29: 0.0030655914 | J29: 0.028697481 | K29: -0.037903917 | L29: 0.034249271 | M29: 0.016492886 | N29: -0.011557204 | O29: 0.1864572 | P29: -0.088917631 | Q29: 0.15297129 | R29: -0.031280048 | S29: -0.0022429171 | T29: -0.038836182 | U29: 0.13673004 | V29: 0.015005539 | W29: -0.06686705 | X29: -0.02124616 | Y29: -0.018353494 | Z29: 0.20292587 | AA29: 0.0072422587 | AB29: -0.012256386 | AC29: 0.0073847634 | AD29: -0.071562593 | AE29: -0.017016115 | AF29: 0.083593659 | AG29: 0.0044156929 | AH29: 0.11174117 | AI29: 0.17251245 | AJ29: 0.013129171 | AK29: 0.06030058 | AL29: 0.073222904 | AM29: -0.016144974 | AN29: 0.06229545 | AO29: -0.027586261
B30: NPISH FCE | D30: 0.023029756 | E30: 0.018223746 | F30: 0.031226539 | G30: 0.026770196 | H30: 0.029604163 | I30: 0.040318536 | J30: 0.047951013 | K30: 0.048841802 | L30: 0.052947355 | M30: 0.021126458 | N30: -0.010270475 | O30: -0.033091602 | P30: -0.064963291 | Q30: -0.04923081 | R30: -0.045244671 | S30: -0.023949162 | T30: -0.0084899728 | U30: 0.011374426 | V30: 0.033583114 | W30: 0.036843083 | X30: 0.033212721 | Y30: 0.033649329 | Z30: 0.020058467 | AA30: 0.023839959 | AB30: 0.027902342 | AC30: -0.0055330979 | AD30: 0.01080038 | AE30: 0.0041014525 | AF30: 0.025237412 | AG30: 0.023537013 | AH30: -0.08680949 | AI30: 0.01563645 | AJ30: -0.005194792 | AK30: 0.0052379309 | AL30: -0.12357529 | AM30: 0.086228337 | AN30: 0.063816597 | AO30: -0.046590686
B31: Household FCE | D31: 0.1034039 | E31: 0.045622415 | F31: -0.015734651 | G31: 0.0092787622 | H31: 0.064774194 | I31: -0.0386265 | J31: 0.067370559 | K31: 0.028521898 | L31: -0.029288827 | M31: 0.024142851 | N31: 0.04499577 | O31: 0.033979572 | P31: 0.024964011 | Q31: -0.00075377563 | R31: -0.054496203 | S31: -0.070842257 | T31: 0.13148494 | U31: 0.018718383 | V31: 0.014887555 | W31: 0.011406237 | X31: -0.052755735 | Y31: 0.040204021 | Z31: 0.073512727 | AA31: 0.021143912 | AB31: -0.034202909 | AC31: -0.0083628765 | AD31: 0.015670363 | AE31: 0.035211588 | AF31: 0.00096741778 | AG31: -0.013051138 | AH31: -0.046158823 | AI31: 0.034541281 | AJ31: 0.068502377 | AK31: -0.047032222 | AL31: 0.14495082 | AM31: -0.065477536 | AN31: 0.10348231 | AO31: 0.021495462
B32: Gross Fixed Capital Formation | D32: 0.023135011 | E32: 0.051521098 | F32: -0.012450477 | G32: -0.0086092753 | H32: 0.089574834 | I32: -0.00076186248 | J32: 0.011752152 | K32: 0.0071980264 | L32: 0.054702109 | M32: 0.0028335364 | N32: 0.027945681 | O32: 0.056106593 | P32: -0.040760812 | Q32: -0.0027130506 | R32: 0.054105834 | S32: -0.15169603 | T32: 0.0040719183 | U32: 0.18954649 | V32: 0.014616909 | W32: -0.0026417862 | X32: 0.02185977 | Y32: 0.036855565 | Z32: -0.052647243 | AA32: 0.015617882 | AB32: 0.035676096 | AC32: 0.0059626491 | AD32: -0.018635297 | AE32: 0.046658042 | AF32: 0.01996041 | AG32: -0.024276681 | AH32: 0.059743715 | AI32: 0.032463279 | AJ32: -0.031713919 | AK32: 0.019297181 | AL32: 0.074527322 | AM32: 0.011717984 | AN32: 0.023751848 | AO32: 0.036952021
B33: Dwellings | D33: -0.0019786864 | E33: -0.00019229326 | F33: 0.0016302369 | G33: 0.0034722583 | H33: 0.0053286228 | I33: 0.004883968 | J33: 0.0044439847 | K33: 0.0039997555 | L33: 0.0035548982 | M33: 0.0036588047 | N33: 0.0037672517 | O33: 0.0038730701 | P33: 0.0039806916 | Q33: 0.0039528476 | R33: 0.0039300113 | S33: 0.0039036346 | T33: 0.0038778965 | U33: 0.0038823948 | V33: 0.0038908451 | W33: 0.003896232 | X33: 0.0039026955 | Y33: 0.0038992933 | Z33: 0.0039003259 | AA33: 0.0038983187 | AB33: 0.0038958956 | AC33: 0.0038958312 | AD33: 0.0038979278 | AE33: 0.0038978278 | AF33: 0.0038973833 | AG33: 0.0038970032 | AH33: 0.0038982533 | AI33: 0.0038979853 | AJ33: 0.003896889 | AK33: 0.0038971169 | AL33: 0.0038978219 | AM33: 0.003897843 | AN33: 0.0038972591 | AO33: 0.0038971594
B34: Other Buildings | D34: 0.15274235 | E34: 0.067769204 | F34: -0.022025835 | G34: -0.00020362536 | H34: 0.022516315 | I34: -0.0019520154 | J34: 0.090143478 | K34: 0.029057478 | L34: 0.022160691 | M34: 0.0082016135 | N34: 0.020105611 | O34: 0.049155306 | P34: -0.011529077 | Q34: 0.048336913 | R34: -0.0049363466 | S34: -0.083378842 | T34: -0.12890899 | U34: 0.25917543 | V34: 0.033800685 | W34: 0.053968888 | X34: 0.072314399 | Y34: -0.027448533 | Z34: -0.083247161 | AA34: 0.033929012 | AB34: 0.044594203 | AC34: -0.02874365 | AD34: 0.0095907827 | AE34: -0.0092188422 | AF34: 0.072020874 | AG34: -0.076664112 | AH34: 0.078248969 | AI34: 0.052971207 | AJ34: -0.0021000558 | AK34: 0.057239696 | AL34: 0.10972606 | AM34: -0.00064746193 | AN34: 0.012536055 | AO34: 0.039763697
B35: Other Structures | D35: 0.096228293 | E35: 0.02447151 | F35: -0.021123559 | G35: -0.047111445 | H35: 0.063418367 | I35: 0.026499923 | J35: 0.0016576859 | K35: 0.13442208 | L35: 0.0029168131 | M35: 0.04941601 | N35: 0.012355013 | O35: 0.020368147 | P35: -0.011686402 | Q35: 0.019447574 | R35: 0.039530934 | S35: -0.090566842 | T35: -0.094779898 | U35: 0.26960884 | V35: 0.028712546 | W35: -0.014411396 | X35: -0.0040811215 | Y35: -0.018920642 | Z35: -0.070571491 | AA35: 0.013584815 | AB35: 0.10512409 | AC35: 0.0045007528 | AD35: -6.9205479e-05 | AE35: 0.04216471 | AF35: 0.015491745 | AG35: 0.0077100698 | AH35: 0.025597605 | AI35: 0.069016375 | AJ35: -0.029638224 | AK35: -0.026434702 | AL35: 0.13138141 | AM35: 0.02120743 | AN35: -0.027105632 | AO35: 0.082810594
B36: Transport Equipment | D36: 0.033214666 | E36: 0.17208927 | F36: -0.13124 | G36: -0.10581207 | H36: 0.51761464 | I36: 0.030381672 | J36: -0.05756475 | K36: -0.021836886 | L36: -0.048199529 | M36: -0.027657603 | N36: -0.045554765 | O36: 0.015234586 | P36: -0.027005774 | Q36: -0.10633657 | R36: 0.017492779 | S36: -0.60402307 | T36: 1.4838381 | U36: -0.020938325 | V36: 0.25851832 | W36: -0.13121267 | X36: 0.022701584 | Y36: 0.13472669 | Z36: -0.12728345 | AA36: 0.082302261 | AB36: -0.021122189 | AC36: -0.096276692 | AD36: 0.15555865 | AE36: 0.0049566684 | AF36: -0.12501606 | AG36: -0.062251681 | AH36: 0.10110402 | AI36: -0.052309607 | AJ36: 0.00095838101 | AK36: 0.45492675 | AL36: -0.22309233 | AM36: 0.18625532 | AN36: 0.16014204 | AO36: -0.05785712
B37: ICT Equipment | D37: -0.75470457 | E37: 3.1672107 | F37: 0.74970284 | G37: -0.47478301 | H37: -0.076839607 | I37: 0.17180285 | J37: -0.32460725 | K37: -0.186728 | L37: 0.29723698 | M37: 0.084020084 | N37: 0.12435048 | O37: -0.071583594 | P37: -0.080281302 | Q37: -0.13775843 | R37: -0.068510328 | S37: 0.12726231 | T37: -0.080528036 | U37: 0.066757286 | V37: -0.20288752 | W37: 0.2693386 | X37: -0.17301452 | Y37: 0.15792841 | Z37: -0.097177819 | AA37: 0.56870048 | AB37: -0.098080992 | AC37: -0.26649879 | AD37: 0.26399545 | AE37: -0.1516887 | AF37: 0.031123517 | AG37: -0.44263529 | AH37: 0.99926333 | AI37: -0.052700875 | AJ37: -0.24079303 | AK37: 0.29369623 | AL37: -0.05764352 | AM37: -0.13967321 | AN37: 0.60755572 | AO37: 0.53017941
B38: Other Machinery and Equipment | D38: -0.077020309 | E38: -0.0030006358 | F38: -0.040229842 | G38: 0.23328653 | H38: 0.071675092 | I38: -0.070452981 | J38: 0.020240357 | K38: -0.19268742 | L38: 0.29080479 | M38: -0.040178026 | N38: 0.02439974 | O38: 0.16904458 | P38: -0.11551277 | Q38: -0.0688227 | R38: 0.20227198 | S38: -0.25406692 | T38: 0.14175118 | U38: 0.13050822 | V38: -0.063752305 | W38: -0.0090997262 | X38: -0.0034544885 | Y38: 0.14981909 | Z38: 0.044453622 | AA38: -0.054629411 | AB38: -0.060188622 | AC38: 0.095451778 | AD38: -0.20017291 | AE38: 0.1174046 | AF38: 0.061512657 | AG38: -0.03507218 | AH38: 0.12894079 | AI38: -0.010329781 | AJ38: -0.11176335 | AK38: -0.044480541 | AL38: 0.059030199 | AM38: 0.018460657 | AN38: 0.091294499 | AO38: -0.075253793
B39: Other Asset Types | D39: -0.022900709 | E39: -0.08258195 | F39: -0.025953973 | G39: -0.094184324 | H39: 0.18728817 | I39: 0.018894033 | J39: 0.011738898 | K39: 0.052473259 | L39: -0.070763625 | M39: -0.10293372 | N39: 0.21839988 | O39: 0.012515521 | P39: -0.040961624 | Q39: 0.043392507 | R39: -0.020783686 | S39: -0.074879446 | T39: 0.096195745 | U39: 0.043213085 | V39: -0.017709764 | W39: -0.028463493 | X39: 0.1030596 | Y39: 0.1509141 | Z39: -0.084481904 | AA39: 0.049356837 | AB39: 0.054503621 | AC39: 0.020780549 | AD39: 0.14287596 | AE39: 0.13042181 | AF39: -0.066994747 | AG39: 0.073170316 | AH39: -0.059818486 | AI39: -0.0045418328 | AJ39: 0.067998044 | AK39: -0.012128035 | AL39: 0.031815281 | AM39: -0.079236007 | AN39: -1.3129736e-05 | AO39: 0.061260473
... B49: GDP at Market Prices | D49: 0.0086546068 | E49: 0.015217117 | F49: 0.029807704 | G49: 0.0093312038 | H49: 0.014844207 | I49: 0.0096014433 | J49: 0.023199933 | K49: 0.0068300934 | L49: 0.018136644 | M49: 0.0064811638 | N49: 0.046692978 | O49: -0.005994792 | P49: 0.02996502 | Q49: 0.011424887 | R49: -0.022614196 | S49: -0.072116804 | T49: 0.077549618 | U49: 0.022828561 | V49: 0.0075671459 | W49: 0.010728699 | X49: -0.017322538 | Y49: 0.04766823 | Z49: 0.022077868 | AA49: 0.0031372912 | AB49: 0.01149128 | AC49: 0.0089760246 | AD49: -0.0010537823 | AE49: 0.032714827 | AF49: 0.013882041 | AG49: 0.014696532 | AH49: 0.0077952016 | AI49: 0.017342644 | AJ49: 0.021282137 | AK49: 0.0080694549 | AL49: 0.032672815 | AM49: -0.0074864265 | AN49: 0.019166271 | AO49: 0.039628848

Sheet Graphs Original
