Workbook

Sheet USE OF DATA
C1: WHAT DO USERS WANT?
C2: MAIN USE OF DATA | D2: WHAT DATA SHOULD I USE? | E2: WORKSHEET
B3: 1 | C3: Policy Formulations | D3: The original unadjusted series and all components | E3: Original_VA
B4: 2 | C4: Macro-economic model building | D4: Could be Unadjusted, adjusted, trend-cycle or all components depending on the main purpose of the model | E4: Original_VA, Deseason_VA, Trend_VA
B5: 3 | C5: To determine what actually happened | D5: The original unadjusted series | E5: Original_VA
B6: 4 | C6: Analysis of the effect of particular events such as a strike | D6: The irregular component | E6: Deseason_VA and Trend_VA
B7: 5 | C7: Business Cycle analysis & detection of turning points | D7: Trend-cycle and irregular component | E7: Trend_VA
B8: 6 | C8: Short-term and medium term forecasting | D8: Original unadjusted series and all its components | E8: Original_VA
B9: 7 | C9: Long-term forecasting | D9: The trend cycle component | E9: Trend_VA
C12: Notes:
B13: a | C13: Original (Unadjusted) estimates have been benchmarked to the 2024/25 Annual GDP estimates (October release 2025) due to quarterly differences in source data for selected economic activities. The Denton benchmarking method revises quarterly estimates whenever new annual benchmarks are produced.
B14: b | C14: Therefore, there were no revisions in series because the benchmarks and input data have not been revised over the period. Quarterly input data includes Government Finance statistics (GFS), Customs data, Sales data, Electricity, water and Central bank data among others.
B15: c | C15: Seasonally adjusted data are subject to revisions as future data become available, even when the original data are not revised.
B16: d | C16: Seasonally adjusted and Trend-cycle estimates represent an analytical elaboration of the data designed to show the underlying movements that may be hidden by the seasonal variations.
B17: e | C17: Seasonally adjusted data is the sum of the Trend-cycle component and the Irregular component. When the Irregular component is strong, the Seasonally adjusted series may not present a smooth pattern.
B18: f | C18: Original (Unadjusted) data are useful in their own right. They show the actual economic events that have occurred and therefore Seasonally adjusted data should not replace the unadjusted data.
B19: h | C19: In terms of interpretation, original series consider year on year similar quarter changes due to seasonal effects while adjusted series consider quarter to quarter changes.

Sheet Summary
A2: TABLE 1: SUMMARY OF QGDP AT CONSTANT 2016/17 PRICES, BILLION SHILLINGS, 2016/17-2025/26
A3: Year | B3: 2007/08 | D3: 2008/09 | H3: 2009/10 | L3: 2010/11 | P3: 2011/12 | T3: 2012/13 | X3: 2013/14 | AB3: 2014/15 | AF3: 2015/16 | AJ3: 2016/17 | AN3: 2017/18 | AO3: 2017/18 | AR3: 2018/19 | AV3: 2019/20 | AZ3: 2020/21 | BD3: 2021/22 | BH3: 2022/23 | BL3: 2023/24 | BP3: 2024/25 | BT3: 2025/26
A4: Period | B4: Q3 | C4: Q4 | D4: Q1 | E4: Q2 | F4: Q3 | G4: Q4 | H4: Q1 | I4: Q2 | J4: Q3 | K4: Q4 | L4: Q1 | M4: Q2 | N4: Q3 | O4: Q4 | P4: Q1 | Q4: Q2 | R4: Q3 | S4: Q4 | T4: Q1 | U4: Q2 | V4: Q3 | W4: Q4 | X4: Q1 | Y4: Q2 | Z4: Q3 | AA4: Q4 | AB4: Q1 | AC4: Q2 | AD4: Q3 | AE4: Q4 | AF4: Q1 | AG4: Q2 | AH4: Q3 | AI4: Q4 | AJ4: Q1 | AK4: Q2 | AL4: Q3 | AM4: Q4 | AN4: Q1 | AO4: Q2 | AP4: Q3 | AQ4: Q4 | AR4: Q1 | AS4: Q2 | AT4: Q3 | AU4: Q4 | AV4: Q1 | AW4: Q2 | AX4: Q3 | AY4: Q4 | AZ4: Q1 | BA4: Q2 | BB4: Q3 | BC4: Q4 | BD4: Q1 | BE4: Q2 | BF4: Q3 | BG4: Q4 | BH4: Q1 | BI4: Q2 | BJ4: Q3 | BK4: Q4 | BL4: Q1 | BM4: Q2 | BN4: Q3 | BO4: Q4 | BP4: Q1 | BQ4: Q2 | BR4: Q3 | BS4: Q4 | BT4: Q1 | BU4: Q2 | BV4: Q3
A5: ORIGINAL ESTIMATES
A6: GDP at market prices | B6: 0 | C6: 0 | D6: 15766.403 | E6: 13927.632 | F6: 14022.629 | G6: 15998.234 | H6: 21078.882 | I6: 19122.748 | J6: 19608.559 | K6: 20695.656 | L6: 23193.526 | M6: 21456.643 | N6: 21240.165 | O6: 21202.324 | P6: 24535.906 | Q6: 21481.557 | R6: 21447.288 | S6: 22266.799 | T6: 26058 | U6: 22244.279 | V6: 21603.992 | W6: 21779.636 | X6: 25541.078 | Y6: 22459.838 | Z6: 23000.644 | AA6: 24675.991 | AB6: 26399.959 | AC6: 24996.444 | AD6: 24359.381 | AE6: 25617.315 | AF6: 28652.094 | AG6: 26475.799 | AH6: 24581.78 | AI6: 25513.407 | AJ6: 28577.247 | AK6: 26610.18 | AL6: 26240.178 | AM6: 27090.435 | AN6: 30772.237 | AO6: 28335.28 | AP6: 27653.331 | AQ6: 28598.087 | AR6: 32487.642 | AS6: 29958.631 | AT6: 29773.235 | AU6: 30567.095 | AV6: 34943.779 | AW6: 32466.458 | AX6: 30130.072 | AY6: 28870.102 | AZ6: 34802.923 | BA6: 32477.008 | BB6: 30975.024 | BC6: 32626.063 | BD6: 35622.436 | BE6: 34024.49 | BF6: 32716.662 | BG6: 34522.28 | BH6: 38746.737 | BI6: 35492.013 | BJ6: 33446.228 | BK6: 36506.452 | BL6: 41068.072 | BM6: 37544.31 | BN6: 35728.791 | BO6: 38581.884 | BP6: 43605.836 | BQ6: 39557.991 | BR6: 38727.987 | BS6: 40714.044 | BT6: 45718.884 | BU6: 42903.876 | BV6: 40970.227
A7: Agriculture, Forestry & Fishing | B7: 0 | C7: 0 | D7: 6507.5645 | E7: 4895.3189 | F7: 4423.9452 | G7: 5495.5749 | H7: 6875.3793 | I7: 5088.8484 | J7: 4451.0205 | K7: 5461.4456 | L7: 7007.5574 | M7: 5267.2451 | N7: 4769.982 | O7: 5440.697 | P7: 7871.5671 | Q7: 5290.0544 | R7: 4412.0205 | S7: 5051.4272 | T7: 8273.6224 | U7: 5294.8849 | V7: 4601.826 | W7: 4760.2442 | X7: 8300.5433 | Y7: 5337.7241 | Z7: 4567.2362 | AA7: 5324.0947 | AB7: 7787.9339 | AC7: 5886.4232 | AD7: 4831.2409 | AE7: 5566.2174 | AF7: 7919.4675 | AG7: 5919.3821 | AH7: 5302.9236 | AI7: 5632.0158 | AJ7: 8012.3898 | AK7: 6110.5575 | AL7: 5359.3298 | AM7: 5974.7915 | AN7: 8783.7536 | AO7: 6199.5724 | AP7: 5495.0897 | AQ7: 6096.0101 | AR7: 8974.6097 | AS7: 6448.4413 | AT7: 5935.2774 | AU7: 6628.7289 | AV7: 9517.4185 | AW7: 6941.2508 | AX7: 5858.4835 | AY7: 7019.6669 | AZ7: 10178.838 | BA7: 7480.0514 | BB7: 5874.7257 | BC7: 7070.5839 | BD7: 10624.95 | BE7: 7330.892 | BF7: 6120.4467 | BG7: 7804.9868 | BH7: 11088.263 | BI7: 8197.4364 | BJ7: 6452.1008 | BK7: 7589.8403 | BL7: 11715.27 | BM7: 8365.8311 | BN7: 6712.9791 | BO7: 8392.5624 | BP7: 12457.04 | BQ7: 9018.0558 | BR7: 7404.8569 | BS7: 8683.3829 | BT7: 12839.64 | BU7: 9809.0589 | BV7: 7563.1391
A8: Industry | B8: 0 | C8: 0 | D8: 1445.2869 | E8: 1434.6394 | F8: 1255.2376 | G8: 1878.6357 | H8: 4840.8447 | I8: 4784.2345 | J8: 5112.8414 | K8: 5061.3107 | L8: 5237.2134 | M8: 5571.0615 | N8: 5434.2561 | O8: 5453.5924 | P8: 5456.3648 | Q8: 5410.6693 | R8: 5788.7735 | S8: 5725.958 | T8: 5694.9937 | U8: 5636.6937 | V8: 5763.6888 | W8: 5400.4985 | X8: 5623.6031 | Y8: 5636.0437 | Z8: 6053.0605 | AA8: 6236.8023 | AB8: 6147.232 | AC8: 6295.2097 | AD8: 6521.915 | AE8: 6701.4139 | AF8: 6809.7306 | AG8: 6794.357 | AH8: 6285.5491 | AI8: 6548.1991 | AJ8: 6768.7131 | AK8: 7106.8656 | AL8: 7305.421 | AM8: 7067.3259 | AN8: 7134.9059 | AO8: 7312.6318 | AP8: 7537.2021 | AQ8: 7631.5343 | AR8: 7779.6918 | AS8: 8068.1838 | AT8: 8243.5123 | AU8: 8201.8824 | AV8: 8570.2406 | AW8: 8886.3356 | AX8: 8486.7958 | AY8: 7398.8511 | AZ8: 8381.1058 | BA8: 8755.7883 | BB8: 8669.0779 | BC8: 8693.4802 | BD8: 8370.9467 | BE8: 9440.8925 | BF8: 9148.3498 | BG8: 9308.0376 | BH8: 9399.6503 | BI8: 9216.6242 | BJ8: 9213.4013 | BK8: 9899.9765 | BL8: 10329.779 | BM8: 9629.9206 | BN8: 9832.8272 | BO8: 10008.679 | BP8: 10858.986 | BQ8: 10366.745 | BR8: 10560.436 | BS8: 10766.195 | BT8: 11507.782 | BU8: 11637.499 | BV8: 11186.239
A9: Services | B9: 0 | C9: 0 | D9: 6828.2243 | E9: 6685.4472 | F9: 7098.1846 | G9: 7433.0483 | H9: 8219.4414 | I9: 8170.5373 | J9: 8965.4911 | K9: 9084.0681 | L9: 9794.4675 | M9: 9376.4753 | N9: 9741.7914 | O9: 9084.9902 | P9: 9902.8734 | Q9: 9375.168 | R9: 9745.1126 | S9: 10034.585 | T9: 10681.667 | U9: 9953.8775 | V9: 9790.642 | W9: 10129.007 | X9: 10158.684 | Y9: 10046.633 | Z9: 10744.274 | AA9: 11519.17 | AB9: 10904.078 | AC9: 11159.16 | AD9: 11295.277 | AE9: 11541.693 | AF9: 12242.65 | AG9: 12024.127 | AH9: 11341.25 | AI9: 11523.07 | AJ9: 11937.718 | AK9: 11574.904 | AL9: 11626.766 | AM9: 12042.627 | AN9: 12862.303 | AO9: 12815.187 | AP9: 12685.299 | AQ9: 12837.368 | AR9: 13754.229 | AS9: 13368.754 | AT9: 13465.069 | AU9: 13600.746 | AV9: 14658.784 | AW9: 14367.919 | AX9: 13669.805 | AY9: 12849.732 | AZ9: 14119.436 | BA9: 14074.464 | BB9: 14391.411 | BC9: 14495.401 | BD9: 14539.216 | BE9: 14902.836 | BF9: 14962.971 | BG9: 14980.554 | BH9: 15799.82 | BI9: 15607.29 | BJ9: 15193.7 | BK9: 16317.733 | BL9: 16221.882 | BM9: 16906.179 | BN9: 16418.929 | BO9: 17379.216 | BP9: 17192.953 | BQ9: 17283.665 | BR9: 17847.735 | BS9: 18239.581 | BT9: 18170.905 | BU9: 18361.432 | BV9: 18894.608
A10: Adjustments
A11: Taxes on products | B11: 0 | C11: 0 | D11: 985.32762 | E11: 912.22689 | F11: 1245.2621 | G11: 1190.9755 | H11: 1143.2165 | I11: 1079.128 | J11: 1079.2056 | K11: 1088.832 | L11: 1154.2874 | M11: 1241.861 | N11: 1294.1352 | O11: 1223.0444 | P11: 1305.1011 | Q11: 1405.6656 | R11: 1501.3813 | S11: 1454.8283 | T11: 1407.7164 | U11: 1358.8227 | V11: 1447.8355 | W11: 1489.8856 | X11: 1458.2475 | Y11: 1439.4375 | Z11: 1636.0732 | AA11: 1595.9236 | AB11: 1560.7144 | AC11: 1655.6515 | AD11: 1710.9486 | AE11: 1807.9904 | AF11: 1680.2457 | AG11: 1737.9327 | AH11: 1652.0566 | AI11: 1810.1219 | AJ11: 1858.4261 | AK11: 1817.8528 | AL11: 1948.6611 | AM11: 2005.691 | AN11: 1991.2744 | AO11: 2007.8887 | AP11: 1935.7403 | AQ11: 2033.1747 | AR11: 1979.1119 | AS11: 2073.2514 | AT11: 2129.377 | AU11: 2135.7379 | AV11: 2197.3365 | AW11: 2270.9524 | AX11: 2114.9878 | AY11: 1601.8521 | AZ11: 2123.5437 | BA11: 2166.7043 | BB11: 2039.8093 | BC11: 2366.598 | BD11: 2087.3237 | BE11: 2349.8691 | BF11: 2484.895 | BG11: 2428.7012 | BH11: 2459.0041 | BI11: 2470.6617 | BJ11: 2587.0261 | BK11: 2698.9015 | BL11: 2801.1416 | BM11: 2642.3794 | BN11: 2764.0558 | BO11: 2801.4262 | BP11: 3096.8575 | BQ11: 2889.5255 | BR11: 2914.9594 | BS11: 3024.8849 | BT11: 3200.5564 | BU11: 3095.8858 | BV11: 3326.2404
A13: SEASONALLY ADJUSTED ESTIMATES
A14: GDP at market prices | B14: 0 | C14: 0 | D14: 0 | E14: 0 | F14: 0 | G14: 0 | H14: 19281.409 | I14: 19536.769 | J14: 20670.65 | K14: 21088.659 | L14: 21342.53 | M14: 21896.853 | N14: 22390.232 | O14: 21682.915 | P14: 22486.721 | Q14: 21911.014 | R14: 22517.31 | S14: 22741.164 | T14: 23670.651 | U14: 22632.373 | V14: 22653.884 | W14: 22266.491 | X14: 23206.646 | Y14: 22781.855 | Z14: 24142.298 | AA14: 25208.001 | AB14: 24323.405 | AC14: 25323.803 | AD14: 25570.867 | AE14: 26198.304 | AF14: 26581.324 | AG14: 26727.381 | AH14: 25866.214 | AI14: 26198.378 | AJ14: 26416.451 | AK14: 26812.127 | AL14: 27622.085 | AM14: 27889.914 | AN14: 28283.055 | AO14: 28554.154 | AP14: 29229.258 | AQ14: 29445.35 | AR14: 29941.017 | AS14: 30143.981 | AT14: 31566.283 | AU14: 31403.382 | AV14: 32277.506 | AW14: 32675.789 | AX14: 31950.55 | AY14: 29675.735 | AZ14: 31890.177 | BA14: 32666.766 | BB14: 32921.015 | BC14: 33306.169 | BD14: 32640.319 | BE14: 34251.442 | BF14: 35011.57 | BG14: 35145.427 | BH14: 35487.513 | BI14: 35824.548 | BJ14: 35816.891 | BK14: 36991.392 | BL14: 37471.979 | BM14: 37983.243 | BN14: 38376.532 | BO14: 39004.919 | BP14: 39841.908 | BQ14: 40048.472 | BR14: 41537.216 | BS14: 41152.31 | BT14: 41956.657 | BU14: 43451.338 | BV14: 43978.861
A15: Agriculture, Forestry & Fishing | B15: 0 | C15: 0 | D15: 0 | E15: 0 | F15: 0 | G15: 0 | H15: 5418.8793 | I15: 5379.0102 | J15: 5427.2084 | K15: 5738.8634 | L15: 5490.5743 | M15: 5532.3699 | N15: 5851.2593 | O15: 5835.9554 | P15: 6128.9977 | Q15: 5564.0629 | R15: 5419.9699 | S15: 5502.7141 | T15: 6154.724 | U15: 5509.1535 | V15: 5589.387 | W15: 5236.6888 | X15: 6195.7516 | Y15: 5535.5894 | Z15: 5643.2176 | AA15: 5850.6262 | AB15: 5919.8009 | AC15: 6130.1701 | AD15: 5947.1034 | AE15: 6098.914 | AF15: 6058.9851 | AG15: 6151.8418 | AH15: 6459.6385 | AI15: 6172.2801 | AJ15: 6113.4118 | AK15: 6365.2952 | AL15: 6582.8786 | AM15: 6545.6275 | AN15: 6624.1464 | AO15: 6533.1995 | AP15: 6887.5132 | AQ15: 6659.0806 | AR15: 6777.8345 | AS15: 6778.2824 | AT15: 7531.2265 | AU15: 7188.48 | AV15: 7180.5444 | AW15: 7289.088 | AX15: 7451.5711 | AY15: 7595.3947 | AZ15: 7565.5859 | BA15: 7818.2609 | BB15: 7524.9016 | BC15: 7643.6427 | BD15: 7912.3918 | BE15: 7634.5177 | BF15: 8038.7603 | BG15: 8456.0785 | BH15: 8143.4333 | BI15: 8514.0709 | BJ15: 8384.5547 | BK15: 8258.2818 | BL15: 8594.2364 | BM15: 8663.2015 | BN15: 8847.9762 | BO15: 9132.1583 | BP15: 9180.715 | BQ15: 9290.6771 | BR15: 9645.6266 | BS15: 9451.6369 | BT15: 9588.3204 | BU15: 10082.951 | BV15: 9947.8206
A16: Industry | B16: 0 | C16: 0 | D16: 0 | E16: 0 | F16: 0 | G16: 0 | H16: 4827.2019 | I16: 4837.9511 | J16: 5045.4056 | K16: 5080.7289 | L16: 5229.2668 | M16: 5654.5394 | N16: 5352.2274 | O16: 5467.2134 | P16: 5473.1409 | Q16: 5450.86 | R16: 5705.4645 | S16: 5710.1066 | T16: 5726.984 | U16: 5683.649 | V16: 5688.4441 | W16: 5393.8722 | X16: 5672.9448 | Y16: 5639.6677 | Z16: 5982.8773 | AA16: 6234.6007 | AB16: 6197.9643 | AC16: 6294.5185 | AD16: 6463.6108 | AE16: 6717.3836 | AF16: 6859.1499 | AG16: 6774.5135 | AH16: 6234.723 | AI16: 6603.0191 | AJ16: 6810.0732 | AK16: 7061.3088 | AL16: 7254.6058 | AM16: 7145.5964 | AN16: 7163.8099 | AO16: 7221.6637 | AP16: 7504.2004 | AQ16: 7734.8304 | AR16: 7795.0484 | AS16: 7955.7257 | AT16: 8235.0954 | AU16: 8306.1266 | AV16: 8565.2873 | AW16: 8788.3075 | AX16: 8519.1181 | AY16: 7489.7614 | AZ16: 8331.28 | BA16: 8659.1468 | BB16: 8751.579 | BC16: 8758.2813 | BD16: 8306.2219 | BE16: 9394.8316 | BF16: 9294.8048 | BG16: 9341.6653 | BH16: 9255.5267 | BI16: 9203.2318 | BJ16: 9383.2862 | BK16: 9914.2813 | BL16: 10037.899 | BM16: 9663.0934 | BN16: 10040.641 | BO16: 10001.922 | BP16: 10540.582 | BQ16: 10422.667 | BR16: 10795.036 | BS16: 10752.744 | BT16: 11182.707 | BU16: 11713.264 | BV16: 11447.732
A17: Services | B17: 0 | C17: 0 | D17: 0 | E17: 0 | F17: 0 | G17: 0 | H17: 7877.7986 | I17: 8234.0425 | J17: 9154.5646 | K17: 9167.8919 | L17: 9452.0913 | M17: 9458.9791 | N17: 9928.7761 | O17: 9149.6942 | P17: 9559.688 | Q17: 9479.3433 | R17: 9924.5286 | S17: 10075.781 | T17: 10355.4 | U17: 10071.589 | V17: 9954.1623 | W17: 10159.312 | X17: 9850.8713 | Y17: 10159.794 | Z17: 10894.89 | AA17: 11550.655 | AB17: 10614.952 | AC17: 11241.189 | AD17: 11449.704 | AE17: 11604.975 | AF17: 11954.947 | AG17: 12066.117 | AH17: 11510.078 | AI17: 11643.518 | AJ17: 11609.621 | AK17: 11580.561 | AL17: 11815.395 | AM17: 12220.121 | AN17: 12483.634 | AO17: 12810.474 | AP17: 12877.388 | AQ17: 13038.562 | AR17: 13373.209 | AS17: 13359.072 | AT17: 13646.548 | AU17: 13787.096 | AV17: 14323.205 | AW17: 14346.255 | AX17: 13846.436 | AY17: 12995.29 | AZ17: 13868.845 | BA17: 14031.988 | BB17: 14589.986 | BC17: 14537.278 | BD17: 14353.276 | BE17: 14863.887 | BF17: 15180.112 | BG17: 14912.123 | BH17: 15676.093 | BI17: 15605.013 | BJ17: 15449.46 | BK17: 16108.649 | BL17: 16111.275 | BM17: 16963.042 | BN17: 16708.756 | BO17: 17056.081 | BP17: 17116.937 | BQ17: 17379.74 | BR17: 18163.327 | BS17: 17910.008 | BT17: 18088.758 | BU17: 18487.026 | BV17: 19235.41
A18: Adjustments
A19: Taxes on products | B19: 0 | C19: 0 | D19: 0 | E19: 0 | F19: 0 | G19: 0 | H19: 1157.5288 | I19: 1085.765 | J19: 1043.4713 | K19: 1101.1745 | L19: 1170.5976 | M19: 1250.9646 | N19: 1257.9697 | O19: 1230.0517 | P19: 1324.8941 | Q19: 1416.7483 | R19: 1467.3473 | S19: 1452.5626 | T19: 1433.5429 | U19: 1367.9814 | V19: 1421.8904 | W19: 1476.618 | X19: 1487.0784 | Y19: 1446.8034 | Z19: 1621.3135 | AA19: 1572.1188 | AB19: 1590.6884 | AC19: 1657.9254 | AD19: 1710.4486 | AE19: 1777.0318 | AF19: 1708.2415 | AG19: 1734.9093 | AH19: 1661.7743 | AI19: 1779.5609 | AJ19: 1883.3454 | AK19: 1804.9623 | AL19: 1969.2047 | AM19: 1978.5694 | AN19: 2011.4652 | AO19: 1988.817 | AP19: 1960.1566 | AQ19: 2012.8766 | AR19: 1994.9247 | AS19: 2050.9008 | AT19: 2153.4128 | AU19: 2121.679 | AV19: 2208.4692 | AW19: 2252.1386 | AX19: 2133.4244 | AY19: 1595.2892 | AZ19: 2124.4659 | BA19: 2157.3696 | BB19: 2054.5485 | BC19: 2366.9671 | BD19: 2068.4292 | BE19: 2358.206 | BF19: 2497.8923 | BG19: 2435.561 | BH19: 2412.4606 | BI19: 2502.2327 | BJ19: 2599.5892 | BK19: 2710.1798 | BL19: 2728.5676 | BM19: 2693.9058 | BN19: 2779.159 | BO19: 2814.7584 | BP19: 3003.6741 | BQ19: 2955.3878 | BR19: 2933.2265 | BS19: 3037.9213 | BT19: 3096.8718 | BU19: 3168.0954 | BV19: 3347.8984
A21: TREND CYCLE ESTIMATES
A22: GDP at market prices | B22: 0 | C22: 0 | D22: 0 | E22: 0 | F22: 0 | G22: 0 | H22: 19321.521 | I22: 19646.987 | J22: 20838.39 | K22: 21122.126 | L22: 21418.024 | M22: 21679.12 | N22: 21679.066 | O22: 21729.735 | P22: 21900.113 | Q22: 22149.612 | R22: 22485.956 | S22: 22826.894 | T22: 22949.804 | U22: 22773.998 | V22: 22547.539 | W22: 22437.041 | X22: 22500.573 | Y22: 23012.92 | Z22: 23903.171 | AA22: 24489.84 | AB22: 24776.316 | AC22: 25114.087 | AD22: 25621.4 | AE22: 26114.928 | AF22: 26538.291 | AG22: 26545.612 | AH22: 26228.292 | AI22: 26164.867 | AJ22: 26459.003 | AK22: 26890.982 | AL22: 27386.001 | AM22: 27829.696 | AN22: 28157.98 | AO22: 28505.646 | AP22: 28964.892 | AQ22: 29471.224 | AR22: 29869.312 | AS22: 30328.589 | AT22: 30858.149 | AU22: 31484.421 | AV22: 32198.083 | AW22: 32489.962 | AX22: 32127.768 | AY22: 31925.614 | AZ22: 32151.054 | BA22: 32497.726 | BB22: 32852.132 | BC22: 32937.678 | BD22: 33205.301 | BE22: 34095.25 | BF22: 34842.847 | BG22: 35120.266 | BH22: 35413.009 | BI22: 35619.048 | BJ22: 36075.372 | BK22: 36783.201 | BL22: 37156.07 | BM22: 37436.947 | BN22: 38261.276 | BO22: 39229.273 | BP22: 39773.917 | BQ22: 40187.245 | BR22: 40669.909 | BS22: 41354.613 | BT22: 42247.595 | BU22: 43299.342 | BV22: 43749.461
A23: Agriculture, Forestry & Fishing | B23: 0 | C23: 0 | D23: 0 | E23: 0 | F23: 0 | G23: 0 | H23: 5456.4528 | I23: 5501.0784 | J23: 5622.9922 | K23: 5658.0279 | L23: 5604.7817 | M23: 5627.1605 | N23: 5712.0893 | O23: 5775.8788 | P23: 5770.1845 | Q23: 5670.4114 | R23: 5564.7467 | S23: 5524.5602 | T23: 5571.2425 | U23: 5579.444 | V23: 5522.0826 | W23: 5439.0315 | X23: 5493.6998 | Y23: 5593.7692 | Z23: 5679.3151 | AA23: 5849.0996 | AB23: 6013.0738 | AC23: 6026.2304 | AD23: 5992.5443 | AE23: 5989.9006 | AF23: 6028.0331 | AG23: 6154.1121 | AH23: 6248.4004 | AI23: 6239.5057 | AJ23: 6219.0738 | AK23: 6294.9721 | AL23: 6407.6262 | AM23: 6477.4047 | AN23: 6491.9933 | AO23: 6510.6556 | AP23: 6593.2904 | AQ23: 6679.911 | AR23: 6761.551 | AS23: 6852.1134 | AT23: 6975.3692 | AU23: 7095.5819 | AV23: 7180.5526 | AW23: 7249.5003 | AX23: 7355.6491 | AY23: 7495.235 | AZ23: 7590.5941 | BA23: 7587.172 | BB23: 7546.1287 | BC23: 7507.5132 | BD23: 7567.238 | BE23: 7797.3911 | BF23: 8061.116 | BG23: 8321.1141 | BH23: 8461.1524 | BI23: 8405.3815 | BJ23: 8326.4781 | BK23: 8334.9072 | BL23: 8409.8467 | BM23: 8569.3643 | BN23: 8758.1032 | BO23: 8937.1503 | BP23: 9086.2922 | BQ23: 9214.9188 | BR23: 9307.5554 | BS23: 9438.1408 | BT23: 9615.1067 | BU23: 9828.6601 | BV23: 9969.3845
A24: Industry | B24: 0 | C24: 0 | D24: 0 | E24: 0 | F24: 0 | G24: 0 | H24: 4762.3993 | I24: 4887.7176 | J24: 4991.0453 | K24: 5106.8593 | L24: 5235.9301 | M24: 5426.4245 | N24: 5512.3883 | O24: 5492.2461 | P24: 5449.0901 | Q24: 5507.1917 | R24: 5660.1333 | S24: 5728.8986 | T24: 5721.939 | U24: 5682.2286 | V24: 5604.6388 | W24: 5559.1196 | X24: 5569.6321 | Y24: 5692.5131 | Z24: 5967.2325 | AA24: 6174.2872 | AB24: 6236.1076 | AC24: 6289.1734 | AD24: 6478.9444 | AE24: 6711.3413 | AF24: 6848.7887 | AG24: 6738.781 | AH24: 6531.7343 | AI24: 6537.7427 | AJ24: 6789.8416 | AK24: 7076.0826 | AL24: 7201.3268 | AM24: 7181.2306 | AN24: 7144.0098 | AO24: 7255.6218 | AP24: 7492.5928 | AQ24: 7706.2398 | AR24: 7813.5987 | AS24: 7981.0773 | AT24: 8181.554 | AU24: 8353.3749 | AV24: 8582.9899 | AW24: 8706.9276 | AX24: 8615.8886 | AY24: 8575.2458 | AZ24: 8647.4598 | BA24: 8692.9233 | BB24: 8728.6795 | BC24: 8730.4523 | BD24: 8904.2465 | BE24: 9201.8962 | BF24: 9359.0755 | BG24: 9313.5986 | BH24: 9253.2018 | BI24: 9209.0996 | BJ24: 9459.294 | BK24: 9815.7914 | BL24: 9862.9134 | BM24: 9801.1103 | BN24: 9971.7823 | BO24: 10274.475 | BP24: 10441.688 | BQ24: 10556.827 | BR24: 10626.762 | BS24: 10832.183 | BT24: 11262.806 | BU24: 11552.607 | BV24: 11582.38
A25: Services | B25: 0 | C25: 0 | D25: 0 | E25: 0 | F25: 0 | G25: 0 | H25: 7943.1183 | I25: 8173.788 | J25: 9169.2212 | K25: 9262.4896 | L25: 9400.5815 | M25: 9383.5834 | N25: 9205.3745 | O25: 9210.7467 | P25: 9362.3681 | Q25: 9556.299 | R25: 9799.9901 | S25: 10113.276 | T25: 10238.375 | U25: 10123.442 | V25: 10004.329 | W25: 9970.7011 | X25: 9945.641 | Y25: 10193.99 | Z25: 10682.665 | AA25: 10885.594 | AB25: 10931.077 | AC25: 11147.524 | AD25: 11426.378 | AE25: 11664.576 | AF25: 11922.963 | AG25: 11949.407 | AH25: 11742.205 | AI25: 11612.695 | AJ25: 11587.203 | AK25: 11608.683 | AL25: 11826.031 | AM25: 12179.61 | AN25: 12519.955 | AO25: 12753.332 | AP25: 12901.271 | AQ25: 13093.978 | AR25: 13286.608 | AS25: 13433.235 | AT25: 13579.647 | AU25: 13883.356 | AV25: 14229.183 | AW25: 14314.426 | AX25: 13978.26 | AY25: 13707.136 | AZ25: 13763.144 | BA25: 14080.103 | BB25: 14429.394 | BC25: 14524.74 | BD25: 14485.152 | BE25: 14722.855 | BF25: 14959.208 | BG25: 15037.685 | BH25: 15273.056 | BI25: 15510.48 | BJ25: 15681.854 | BK25: 15932.939 | BL25: 16164.568 | BM25: 16347.416 | BN25: 16777.867 | BO25: 17166.186 | BP25: 17303.368 | BQ25: 17455.048 | BR25: 17780.576 | BS25: 18063.302 | BT25: 18275.622 | BU25: 18726.512 | BV25: 18869.73
A26: Adjustments
A27: Taxes on products | B27: 0 | C27: 0 | D27: 0 | E27: 0 | F27: 0 | G27: 0 | H27: 1159.5508 | I27: 1084.4034 | J27: 1055.1317 | K27: 1094.7496 | L27: 1176.7309 | M27: 1241.9519 | N27: 1249.2139 | O27: 1250.8631 | P27: 1318.4706 | Q27: 1415.7102 | R27: 1461.0856 | S27: 1460.159 | T27: 1418.2467 | U27: 1388.8833 | V27: 1416.4887 | W27: 1468.1885 | X27: 1491.6005 | Y27: 1532.6478 | Z27: 1573.9587 | AA27: 1580.8591 | AB27: 1596.0574 | AC27: 1651.1588 | AD27: 1723.5337 | AE27: 1749.1102 | AF27: 1738.5062 | AG27: 1703.3119 | AH27: 1705.9526 | AI27: 1774.9239 | AJ27: 1862.8842 | AK27: 1911.2443 | AL27: 1951.0168 | AM27: 1991.4507 | AN27: 2002.022 | AO27: 1986.037 | AP27: 1977.7382 | AQ27: 1991.0944 | AR27: 2007.5535 | AS27: 2062.1637 | AT27: 2121.5786 | AU27: 2152.1081 | AV27: 2205.3572 | AW27: 2219.1086 | AX27: 2177.9705 | AY27: 2147.9973 | AZ27: 2149.8566 | BA27: 2137.527 | BB27: 2147.9298 | BC27: 2174.9724 | BD27: 2248.6645 | BE27: 2373.1084 | BF27: 2463.4478 | BG27: 2447.8678 | BH27: 2425.5988 | BI27: 2494.0869 | BJ27: 2607.7459 | BK27: 2699.5631 | BL27: 2718.7423 | BM27: 2719.0569 | BN27: 2753.5235 | BO27: 2851.4611 | BP27: 2942.569 | BQ27: 2960.4515 | BR27: 2955.0151 | BS27: 3020.9878 | BT27: 3094.0604 | BU27: 3191.5626 | BV27: 3327.9668
A29: Source: Uganda Bureau of Statistics
A31: TABLE 2: SUMMARY OF QGDP AT CONSTANT 2016/17 PRICES, PERCENTAGE CHANGE, 2016/17-2025/26
A32: Year | B32: 2007/08 | D32: 2008/09 | H32: 2009/10 | L32: 2010/11 | P32: 2011/12 | T32: 2012/13 | X32: 2013/14 | AB32: 2014/15 | AF32: 2015/16 | AJ32: 2016/17 | AN32: 2017/18 | AO32: 2017/18 | AR32: 2018/19 | AV32: 2019/20 | AZ32: 2020/21 | BD32: 2021/22 | BH32: 2022/23 | BL32: 2023/24 | BP32: 2024/25 | BT32: 2025/26
A33: Period | B33: Q3 | C33: Q4 | D33: Q1 | E33: Q2 | F33: Q3 | G33: Q4 | H33: Q1 | I33: Q2 | J33: Q3 | K33: Q4 | L33: Q1 | M33: Q2 | N33: Q3 | O33: Q4 | P33: Q1 | Q33: Q2 | R33: Q3 | S33: Q4 | T33: Q1 | U33: Q2 | V33: Q3 | W33: Q4 | X33: Q1 | Y33: Q2 | Z33: Q3 | AA33: Q4 | AB33: Q1 | AC33: Q2 | AD33: Q3 | AE33: Q4 | AF33: Q1 | AG33: Q2 | AH33: Q3 | AI33: Q4 | AJ33: Q1 | AK33: Q2 | AL33: Q3 | AM33: Q4 | AN33: Q1 | AO33: Q2 | AP33: Q3 | AQ33: Q4 | AR33: Q1 | AS33: Q2 | AT33: Q3 | AU33: Q4 | AV33: Q1 | AW33: Q2 | AX33: Q3 | AY33: Q4 | AZ33: Q1 | BA33: Q2 | BB33: Q3 | BC33: Q4 | BD33: Q1 | BE33: Q2 | BF33: Q3 | BG33: Q4 | BH33: Q1 | BI33: Q2 | BJ33: Q3 | BK33: Q4 | BL33: Q1 | BM33: Q2 | BN33: Q3 | BO33: Q4 | BP33: Q1 | BQ33: Q2 | BR33: Q3 | BS33: Q4 | BT33: Q1 | BU33: Q2 | BV33: Q3
A34: ORIGINAL ESTIMATES
A35: GDP at market prices | C35: #DIV/0! | D35: #DIV/0! | E35: #VALUE! | F35: #DIV/0! | G35: #DIV/0! | H35: 33.69493 | I35: 37.300782 | J35: 39.835105 | K35: 29.362128 | L35: 10.032049 | M35: 12.204808 | N35: 8.3208874 | O35: 2.4481829 | P35: 5.7877391 | Q35: 0.11611492 | R35: 0.97514865 | S35: 5.0205571 | T35: 6.2035339 | U35: 3.5505873 | V35: 0.73064936 | W35: -2.187846 | X35: -1.9837358 | Y35: 0.96905631 | Z35: 6.4647828 | AA35: 13.298457 | AB35: 3.3627427 | AC35: 11.293963 | AD35: 5.90739 | AE35: 3.8147373 | AF35: 8.5308298 | AG35: 5.9182597 | AH35: 0.9129889 | AI35: -0.4056158 | AJ35: -0.26122599 | AK35: 0.50756396 | AL35: 6.7464548 | AM35: 6.1811727 | AN35: 7.6808998 | AO35: 6.4828574 | AP35: 5.3854549 | AQ35: 5.5652552 | AR35: 5.5745218 | AS35: 5.7290794 | AT35: 7.6659989 | AU35: 6.8851035 | AV35: 7.5602194 | AW35: 8.3709675 | AX35: 1.1985158 | AY35: -5.5516965 | AZ35: -0.40309239 | BA35: 0.032495737 | BB35: 2.804345 | BC35: 13.009861 | BD35: 2.354724 | BE35: 4.7648514 | BF35: 5.6227189 | BG35: 5.811971 | BH35: 8.7705981 | BI35: 4.3131379 | BJ35: 2.2299523 | BK35: 5.7475112 | BL35: 5.9910476 | BM35: 5.7824205 | BN35: 6.8245768 | BO35: 5.6851104 | BP35: 6.1794064 | BQ35: 5.3634777 | BR35: 8.394339 | BS35: 5.5263248 | BT35: 4.8457919 | BU35: 8.4581777 | BV35: 5.7897133
A36: Agriculture, Forestry & Fishing | C36: #DIV/0! | D36: #DIV/0! | E36: #VALUE! | F36: #DIV/0! | G36: #DIV/0! | H36: 5.6521111 | I36: 3.9533585 | J36: 0.61201628 | K36: -0.62103308 | L36: 1.9224835 | M36: 3.5056409 | N36: 7.1660324 | O36: -0.37990966 | P36: 12.329685 | Q36: 0.43304017 | R36: -7.504462 | S36: -7.1547783 | T36: 5.1076898 | U36: 0.091311944 | V36: 4.3020088 | W36: -5.7643713 | X36: 0.32538328 | Y36: 0.80906881 | Z36: -0.75165447 | AA36: 11.844991 | AB36: -6.1756126 | AC36: 10.279645 | AD36: 5.7804041 | AE36: 4.5476782 | AF36: 1.6889404 | AG36: 0.55991384 | AH36: 9.7631777 | AI36: 1.1821019 | AJ36: 1.1733408 | AK36: 3.2296506 | AL36: 1.0636812 | AM36: 6.0861995 | AN36: 9.6271373 | AO36: 1.4567401 | AP36: 2.5331515 | AQ36: 2.0288347 | AR36: 2.172831 | AS36: 4.0142917 | AT36: 8.010565 | AU36: 8.7388102 | AV36: 6.0482714 | AW36: 7.6423041 | AX36: -1.2938559 | AY36: 5.8976315 | AZ36: 6.9495696 | BA36: 7.7622984 | BB36: 0.27724211 | BC36: 0.72534795 | BD36: 4.382736 | BE36: -1.9940967 | BF36: 4.1826802 | BG36: 10.386736 | BH36: 4.3606145 | BI36: 11.82045 | BJ36: 5.4187897 | BK36: -2.7565253 | BL36: 5.654692 | BM36: 2.0542364 | BN36: 4.0433085 | BO36: 10.57627 | BP36: 6.331648 | BQ36: 7.796292 | BR36: 10.306569 | BS36: 3.4652179 | BT36: 3.0713611 | BU36: 8.7713266 | BV36: 2.1375446
A37: Industry | C37: #DIV/0! | D37: #DIV/0! | E37: #VALUE! | F37: #DIV/0! | G37: #DIV/0! | H37: 234.94004 | I37: 233.47993 | J37: 307.32062 | K37: 169.41417 | L37: 8.1880075 | M37: 16.446248 | N37: 6.28642 | O37: 7.7505946 | P37: 4.1845042 | Q37: -2.8790253 | R37: 6.5237527 | S37: 4.9942423 | T37: 4.3734039 | U37: 4.1773834 | V37: -0.43333384 | W37: -5.6839318 | X37: -1.2535665 | Y37: -0.011531378 | Z37: 5.0205984 | AA37: 15.485678 | AB37: 9.3112698 | AC37: 11.695546 | AD37: 7.7457436 | AE37: 7.4495173 | AF37: 10.777186 | AG37: 7.929001 | AH37: -3.6241797 | AI37: -2.2863059 | AJ37: -0.60233732 | AK37: 4.5995317 | AL37: 16.225662 | AM37: 7.9277803 | AN37: 5.4100804 | AO37: 2.8953153 | AP37: 3.1727275 | AQ37: 7.983336 | AR37: 9.0370626 | AS37: 10.33215 | AT37: 9.3709856 | AU37: 7.4735698 | AV37: 10.161699 | AW37: 10.14047 | AX37: 2.9512124 | AY37: -9.7908167 | AZ37: -2.2068791 | BA37: -1.4690787 | BB37: 2.1478318 | BC37: 17.497705 | BD37: -0.121214 | BE37: 7.8245859 | BF37: 5.5285218 | BG37: 7.0691761 | BH37: 12.288976 | BI37: -2.3754988 | BJ37: 0.71107424 | BK37: 6.3594382 | BL37: 9.8953589 | BM37: 4.4842493 | BN37: 6.7230965 | BO37: 1.0980079 | BP37: 5.1231152 | BQ37: 7.6514026 | BR37: 7.3997957 | BS37: 7.5685941 | BT37: 5.9747366 | BU37: 12.257991 | BV37: 5.9259193
A38: Services | C38: #DIV/0! | D38: #DIV/0! | E38: #VALUE! | F38: #DIV/0! | G38: #DIV/0! | H38: 20.374508 | I38: 22.213773 | J38: 26.306818 | K38: 22.211881 | L38: 19.162203 | M38: 14.759592 | N38: 8.6587584 | O38: 0.010149722 | P38: 1.1068078 | Q38: -0.01394228 | R38: 0.034092216 | S38: 10.452351 | T38: 7.8643215 | U38: 6.1727909 | V38: 0.46720325 | W38: 0.94096569 | X38: -4.8960841 | Y38: 0.93185245 | Z38: 9.7402359 | AA38: 13.724574 | AB38: 7.3375093 | AC38: 11.073626 | AD38: 5.1283416 | AE38: 0.19552666 | AF38: 12.275885 | AG38: 7.7511857 | AH38: 0.40701708 | AI38: -0.16135333 | AJ38: -2.4907341 | AK38: -3.736009 | AL38: 2.5175007 | AM38: 4.5088343 | AN38: 7.7450719 | AO38: 10.715277 | AP38: 9.1042744 | AQ38: 6.5993997 | AR38: 6.9344151 | AS38: 4.3196164 | AT38: 6.1470326 | AU38: 5.9465301 | AV38: 6.576558 | AW38: 7.4738828 | AX38: 1.5205013 | AY38: -5.5218535 | AZ38: -3.6793477 | BA38: -2.042432 | BB38: 5.2788271 | BC38: 12.807022 | BD38: 2.9730667 | BE38: 5.8856353 | BF38: 3.9715352 | BG38: 3.3469497 | BH38: 8.6703688 | BI38: 4.7269825 | BJ38: 1.5420013 | BK38: 8.9260995 | BL38: 2.6713069 | BM38: 8.3223194 | BN38: 8.0640636 | BO38: 6.505087 | BP38: 5.9861799 | BQ38: 2.2328288 | BR38: 8.7021833 | BS38: 4.9505378 | BT38: 5.6881024 | BU38: 6.2357551 | BV38: 5.8655812
A39: Adjustments
A40: Taxes on products | C40: #DIV/0! | D40: #DIV/0! | E40: #VALUE! | F40: #DIV/0! | G40: #DIV/0! | H40: 16.024002 | I40: 18.296005 | J40: -13.335066 | K40: -8.5764566 | L40: 0.96839961 | M40: 15.080046 | N40: 19.91554 | O40: 12.326273 | P40: 13.06552 | Q40: 13.190256 | R40: 16.01425 | S40: 18.951389 | T40: 7.8626362 | U40: -3.3324373 | V40: -3.5664363 | W40: 2.4097213 | X40: 3.5895789 | Y40: 5.9326991 | Z40: 13.001319 | AA40: 7.1171898 | AB40: 7.0267161 | AC40: 15.020728 | AD40: 4.576532 | AE40: 13.288031 | AF40: 7.6587553 | AG40: 4.9697145 | AH40: -3.4420658 | AI40: 0.11789288 | AJ40: 10.604422 | AK40: 4.5985732 | AL40: 17.953651 | AM40: 10.804192 | AN40: 7.14843 | AO40: 10.453864 | AP40: -0.66306097 | AQ40: 1.3702884 | AR40: -0.61078727 | AS40: 3.2552983 | AT40: 10.00324 | AU40: 5.0444829 | AV40: 11.026391 | AW40: 9.535794 | AX40: -0.67574802 | AY40: -24.997721 | AZ40: -3.3582876 | BA40: -4.5905031 | BB40: -3.5545582 | BC40: 47.741356 | BD40: -1.7056382 | BE40: 8.453615 | BF40: 21.819967 | BG40: 2.6241571 | BH40: 17.806552 | BI40: 5.1403958 | BJ40: 4.1100754 | BK40: 11.125298 | BL40: 13.913662 | BM40: 6.9502737 | BN40: 6.8429801 | BO40: 3.7987589 | BP40: 10.556979 | BQ40: 9.3531628 | BR40: 5.4594994 | BS40: 7.9766044 | BT40: 3.3485178 | BU40: 7.1416697 | BV40: 14.109321
A42: SEASONALLY ADJUSTED ESTIMATES
A43: GDP at market prices | C43: #DIV/0! | D43: #DIV/0! | E43: #DIV/0! | F43: #DIV/0! | G43: #DIV/0! | H43: #DIV/0! | I43: 1.3243858 | J43: 5.8038312 | K43: 2.0222336 | L43: 1.2038283 | M43: 2.5972695 | N43: 2.2531977 | O43: -3.1590458 | P43: 3.7070942 | Q43: -2.5602057 | R43: 2.7670824 | S43: 0.99414176 | T43: 4.087245 | U43: -4.3863552 | V43: 0.095047173 | W43: -1.7100512 | X43: 4.2222874 | Y43: -1.8304732 | Z43: 5.9716097 | AA43: 4.4142547 | AB43: -3.5091846 | AC43: 4.1129018 | AD43: 0.97561912 | AE43: 2.4537186 | AF43: 1.4620019 | AG43: 0.5494736 | AH43: -3.2220419 | AI43: 1.2841621 | AJ43: 0.83239308 | AK43: 1.4978379 | AL43: 3.0208624 | AM43: 0.96962078 | AN43: 1.4096175 | AO43: 0.95852186 | AP43: 2.3642921 | AQ43: 0.73929905 | AR43: 1.6833459 | AS43: 0.67788171 | AT43: 4.7183604 | AU43: -0.51606042 | AV43: 2.7835341 | AW43: 1.233933 | AX43: -2.2194993 | AY43: -7.1197978 | AZ43: 7.4621281 | BA43: 2.4351986 | BB43: 0.77831284 | BC43: 1.1699338 | BD43: -1.9991802 | BE43: 4.9359917 | BF43: 2.2192565 | BG43: 0.3823237 | BH43: 0.97334385 | BI43: 0.94972824 | BJ43: -0.021375292 | BK43: 3.2791842 | BL43: 1.2991837 | BM43: 1.3643908 | BN43: 1.0354276 | BO43: 1.6374267 | BP43: 2.1458546 | BQ43: 0.51845912 | BR43: 3.7173548 | BS43: -0.92665304 | BT43: 1.954561 | BU43: 3.5624392 | BV43: 1.2140564
A44: Agriculture, Forestry & Fishing | C44: #DIV/0! | D44: #DIV/0! | E44: #DIV/0! | F44: #DIV/0! | G44: #DIV/0! | H44: #DIV/0! | I44: -0.73574461 | J44: 0.89604237 | K44: 5.7424551 | L44: -4.326451 | M44: 0.76122511 | N44: 5.764064 | O44: -0.26154903 | P44: 5.0213261 | Q44: -9.2174101 | R44: -2.5897083 | S44: 1.5266548 | T44: 11.848879 | U44: -10.489025 | V44: 1.4563684 | W44: -6.3101413 | X44: 18.314298 | Y44: -10.655078 | Z44: 1.9442937 | AA44: 3.6753608 | AB44: 1.1823483 | AC44: 3.553653 | AD44: -2.9863239 | AE44: 2.5526819 | AF44: -0.65468886 | AG44: 1.5325457 | AH44: 5.0033258 | AI44: -4.4485212 | AJ44: -0.95375315 | AK44: 4.1201765 | AL44: 3.4182772 | AM44: -0.56587876 | AN44: 1.1995622 | AO44: -1.3729598 | AP44: 5.4232797 | AQ44: -3.3166197 | AR44: 1.7833388 | AS44: 0.0066075237 | AT44: 11.108185 | AU44: -4.5510055 | AV44: -0.11039391 | AW44: 1.5116347 | AX44: 2.229128 | AY44: 1.9301113 | AZ44: -0.39245801 | BA44: 3.3397942 | BB44: -3.7522327 | BC44: 1.5779749 | BD44: 3.5159819 | BE44: -3.5118845 | BF44: 5.2949332 | BG44: 5.1913246 | BH44: -3.6972832 | BI44: 4.5513684 | BJ44: -1.5212018 | BK44: -1.5060182 | BL44: 4.0680935 | BM44: 0.80245658 | BN44: 2.1328688 | BO44: 3.2118319 | BP44: 0.53171097 | BQ44: 1.1977514 | BR44: 3.8204911 | BS44: -2.0111679 | BT44: 1.4461358 | BU44: 5.158682 | BV44: -1.3401906
A45: Industry | C45: #DIV/0! | D45: #DIV/0! | E45: #DIV/0! | F45: #DIV/0! | G45: #DIV/0! | H45: #DIV/0! | I45: 0.22267979 | J45: 4.2880642 | K45: 0.70010748 | L45: 2.9235553 | M45: 8.1325471 | N45: -5.3463594 | O45: 2.1483782 | P45: 0.10841875 | Q45: -0.40709601 | R45: 4.6709058 | S45: 0.081361935 | T45: 0.2955701 | U45: -0.75668137 | V45: 0.084367622 | W45: -5.1784273 | X45: 5.1738829 | Y45: -0.58659302 | Z45: 6.0856356 | AA45: 4.2073961 | AB45: -0.58762935 | AC45: 1.5578362 | AD45: 2.686343 | AE45: 3.9261773 | AF45: 2.1104392 | AG45: -1.2339204 | AH45: -7.9679594 | AI45: 5.907176 | AJ45: 3.1357491 | AK45: 3.6891767 | AL45: 2.7374102 | AM45: -1.5026234 | AN45: 0.25489153 | AO45: 0.80758429 | AP45: 3.9123497 | AQ45: 3.0733444 | AR45: 0.77853025 | AS45: 2.0612748 | AT45: 3.5115546 | AU45: 0.86254315 | AV45: 3.1201146 | AW45: 2.6037675 | AX45: -3.0630401 | AY45: -12.082902 | AZ45: 11.235586 | BA45: 3.9353722 | BB45: 1.0674508 | BC45: 0.076583894 | BD45: -5.1615079 | BE45: 13.105955 | BF45: -1.0647003 | BG45: 0.50415779 | BH45: -0.92209023 | BI45: -0.56501245 | BJ45: 1.9564256 | BK45: 5.6589466 | BL45: 1.2468676 | BM45: -3.7339074 | BN45: 3.9071072 | BO45: -0.38562384 | BP45: 5.3855654 | BQ45: -1.118672 | BR45: 3.5726787 | BS45: -0.39176552 | BT45: 3.9986269 | BU45: 4.7444492 | BV45: -2.266936
A46: Services | C46: #DIV/0! | D46: #DIV/0! | E46: #DIV/0! | F46: #DIV/0! | G46: #DIV/0! | H46: #DIV/0! | I46: 4.522126 | J46: 11.179468 | K46: 0.14558072 | L46: 3.0999426 | M46: 0.072870878 | N46: 4.9666771 | O46: -7.8467062 | P46: 4.4809559 | Q46: -0.84045252 | R46: 4.6963727 | S46: 1.5240258 | T46: 2.7751642 | U46: -2.7407123 | V46: -1.165917 | W46: 2.060943 | X46: -3.0360385 | Y46: 3.1359953 | Z46: 8.5 | AA46: 6.0190173 | AB46: -8.1008687 | AC46: 5.8995797 | AD46: 1.8549196 | AE46: 1.3561089 | AF46: 3.0157122 | AG46: 0.92990201 | AH46: -4.608265 | AI46: 1.1593299 | AJ46: -0.29112186 | AK46: -0.25031112 | AL46: 2.0278347 | AM46: 3.4254062 | AN46: 2.1563854 | AO46: 2.6181518 | AP46: 0.52233515 | AQ46: 1.2516072 | AR46: 2.5665951 | AS46: -0.1057089 | AT46: 2.1519144 | AU46: 1.0299163 | AV46: 3.8884808 | AW46: 0.16092571 | AX46: -3.4839647 | AY46: -6.1470419 | AZ46: 6.7220879 | BA46: 1.1763311 | BB46: 3.9766139 | BC46: -0.36126091 | BD46: -1.2657258 | BE46: 3.5574523 | BF46: 2.1274735 | BG46: -1.7654006 | BH46: 5.1231474 | BI46: -0.45342903 | BJ46: -0.99680952 | BK46: 4.266744 | BL46: 0.016300497 | BM46: 5.286775 | BN46: -1.4990608 | BO46: 2.0787011 | BP46: 0.35680224 | BQ46: 1.5353372 | BR46: 4.5086241 | BS46: -1.3946764 | BT46: 0.99804961 | BU46: 2.2017437 | BV46: 4.0481563
A47: Adjustments
A48: Taxes on products | C48: #DIV/0! | D48: #DIV/0! | E48: #DIV/0! | F48: #DIV/0! | G48: #DIV/0! | H48: #DIV/0! | I48: -6.1997455 | J48: -3.8952903 | K48: 5.5299347 | L48: 6.3044543 | M48: 6.8654665 | N48: 0.55997529 | O48: -2.2192894 | P48: 7.7104461 | Q48: 6.9329412 | R48: 3.5714877 | S48: -1.0075799 | T48: -1.3093856 | U48: -4.5733933 | V48: 3.9407753 | W48: 3.8489285 | X48: 0.70840624 | Y48: -2.7083339 | Z48: 12.061769 | AA48: -3.0342507 | AB48: 1.181188 | AC48: 4.2269072 | AD48: 3.1680092 | AE48: 3.8927333 | AF48: -3.8710803 | AG48: 1.5611256 | AH48: -4.215494 | AI48: 7.0880063 | AJ48: 5.8320295 | AK48: -4.1619124 | AL48: 9.0994934 | AM48: 0.47555779 | AN48: 1.6626055 | AO48: -1.1259529 | AP48: -1.4410789 | AQ48: 2.6895816 | AR48: -0.89185605 | AS48: 2.8059271 | AT48: 4.9983918 | AU48: -1.4736532 | AV48: 4.0906394 | AW48: 1.9773566 | AX48: -5.2711742 | AY48: -25.224013 | AZ48: 33.171212 | BA48: 1.5488 | BB48: -4.7660425 | BC48: 15.206194 | BD48: -12.612679 | BE48: 14.009514 | BF48: 5.9234131 | BG48: -2.4953557 | BH48: -0.94846425 | BI48: 3.7211847 | BJ48: 3.8907839 | BK48: 4.2541587 | BL48: 0.67847061 | BM48: -1.2703291 | BN48: 3.1646677 | BO48: 1.2809435 | BP48: 6.7116112 | BQ48: -1.6075747 | BR48: -0.74985945 | BS48: 3.5692686 | BT48: 1.9404911 | BU48: 2.2998533 | BV48: 5.6754291
A50: TREND CYCLE ESTIMATES
A51: GDP at market prices | C51: #DIV/0! | D51: #DIV/0! | E51: #DIV/0! | F51: #DIV/0! | G51: #DIV/0! | H51: #DIV/0! | I51: 1.6844748 | J51: 6.0640499 | K51: 1.3616018 | L51: 1.4008903 | M51: 1.2190481 | N51: -0.00025007256 | O51: 0.2337217 | P51: 0.78408094 | Q51: 1.1392584 | R51: 1.5185069 | S51: 1.5162276 | T51: 0.53844331 | U51: -0.76604592 | V51: -0.99437262 | W51: -0.49006953 | X51: 0.28315963 | Y51: 2.2770394 | Z51: 3.8684832 | AA51: 2.4543562 | AB51: 1.1697748 | AC51: 1.36328 | AD51: 2.020036 | AE51: 1.9262314 | AF51: 1.6211533 | AG51: 0.027587412 | AH51: -1.1953773 | AI51: -0.24181672 | AJ51: 1.1241618 | AK51: 1.632637 | AL51: 1.8408356 | AM51: 1.6201534 | AN51: 1.179618 | AO51: 1.2346961 | AP51: 1.6110718 | AQ51: 1.748086 | AR51: 1.3507682 | AS51: 1.5376241 | AT51: 1.746073 | AU51: 2.0295204 | AV51: 2.2667146 | AW51: 0.9065115 | AX51: -1.114788 | AY51: -0.62921843 | AZ51: 0.70614142 | BA51: 1.0782583 | BB51: 1.0905574 | BC51: 0.26039664 | BD51: 0.81251268 | BE51: 2.6801433 | BF51: 2.1926708 | BG51: 0.79620017 | BH51: 0.83354557 | BI51: 0.58181811 | BJ51: 1.2811217 | BK51: 1.9620837 | BL51: 1.013695 | BM51: 0.75593885 | BN51: 2.2019125 | BO51: 2.5299646 | BP51: 1.3883609 | BQ51: 1.0391938 | BR51: 1.2010379 | BS51: 1.683564 | BT51: 2.1593287 | BU51: 2.4894841 | BV51: 1.0395514
A52: Agriculture, Forestry & Fishing | C52: #DIV/0! | D52: #DIV/0! | E52: #DIV/0! | F52: #DIV/0! | G52: #DIV/0! | H52: #DIV/0! | I52: 0.81785062 | J52: 2.2161802 | K52: 0.62307922 | L52: -0.94107447 | M52: 0.39928055 | N52: 1.5092659 | O52: 1.1167452 | P52: -0.098587316 | Q52: -1.729114 | R52: -1.8634406 | S52: -0.72216098 | T52: 0.84499587 | U52: 0.14721031 | V52: -1.0280836 | W52: -1.5039824 | X52: 1.0051118 | Y52: 1.8215304 | Z52: 1.5293064 | AA52: 2.9895243 | AB52: 2.8034086 | AC52: 0.21880115 | AD52: -0.55899133 | AE52: -0.044116347 | AF52: 0.63661171 | AG52: 2.091545 | AH52: 1.5321186 | AI52: -0.14235127 | AJ52: -0.32745986 | AK52: 1.220411 | AL52: 1.7895884 | AM52: 1.0889919 | AN52: 0.2252237 | AO52: 0.28746615 | AP52: 1.2692229 | AQ52: 1.3137687 | AR52: 1.2221723 | AS52: 1.3393735 | AT52: 1.7987992 | AU52: 1.7233887 | AV52: 1.1975154 | AW52: 0.96020036 | AX52: 1.4642229 | AY52: 1.8976689 | AZ52: 1.2722631 | BA52: -0.045082648 | BB52: -0.54095663 | BC52: -0.51172572 | BD52: 0.79553337 | BE52: 3.0414404 | BF52: 3.3822201 | BG52: 3.2253371 | BH52: 1.6829261 | BI52: -0.6591403 | BJ52: -0.93872453 | BK52: 0.10123289 | BL52: 0.89910315 | BM52: 1.8967957 | BN52: 2.2024842 | BO52: 2.04436 | BP52: 1.6687862 | BQ52: 1.4156109 | BR52: 1.005289 | BS52: 1.4030046 | BT52: 1.8750084 | BU52: 2.2210195 | BV52: 1.4317759
A53: Industry | C53: #DIV/0! | D53: #DIV/0! | E53: #DIV/0! | F53: #DIV/0! | G53: #DIV/0! | H53: #DIV/0! | I53: 2.6314095 | J53: 2.1140292 | K53: 2.3204341 | L53: 2.5274016 | M53: 3.6382151 | N53: 1.5841707 | O53: -0.36539942 | P53: -0.7857613 | Q53: 1.0662619 | R53: 2.7771241 | S53: 1.2149065 | T53: -0.12148173 | U53: -0.69400377 | V53: -1.3654803 | W53: -0.81217018 | X53: 0.18910246 | Y53: 2.206268 | Z53: 4.825978 | AA53: 3.4698605 | AB53: 1.0012571 | AC53: 0.85094376 | AD53: 3.0174239 | AE53: 3.5869559 | AF53: 2.0479872 | AG53: -1.6062364 | AH53: -3.0724653 | AI53: 0.091987505 | AJ53: 3.8560543 | AK53: 4.2157252 | AL53: 1.7699651 | AM53: -0.27906273 | AN53: -0.51830632 | AO53: 1.5623151 | AP53: 3.2660337 | AQ53: 2.8514423 | AR53: 1.393143 | AS53: 2.1434236 | AT53: 2.5119004 | AU53: 2.1001015 | AV53: 2.7487697 | AW53: 1.4439912 | AX53: -1.0455924 | AY53: -0.47171864 | AZ53: 0.84212099 | BA53: 0.52574394 | BB53: 0.41132591 | BC53: 0.020309673 | BD53: 1.9906662 | BE53: 3.3427848 | BF53: 1.7081177 | BG53: -0.48591221 | BH53: -0.64847966 | BI53: -0.47661529 | BJ53: 2.716817 | BK53: 3.7687532 | BL53: 0.48006255 | BM53: -0.62662086 | BN53: 1.7413534 | BO53: 3.0354953 | BP53: 1.6274545 | BQ53: 1.1026891 | BR53: 0.66246649 | BS53: 1.9330448 | BT53: 3.975408 | BU53: 2.5730844 | BV53: 0.2577115
A54: Services | C54: #DIV/0! | D54: #DIV/0! | E54: #DIV/0! | F54: #DIV/0! | G54: #DIV/0! | H54: #DIV/0! | I54: 2.9040192 | J54: 12.178359 | K54: 1.0171896 | L54: 1.4908728 | M54: -0.18082005 | N54: -1.8991565 | O54: 0.05835965 | P54: 1.6461362 | Q54: 2.0713868 | R54: 2.5500573 | S54: 3.1967997 | T54: 1.2369817 | U54: -1.1225764 | V54: -1.1766029 | W54: -0.33613494 | X54: -0.25133808 | Y54: 2.4970656 | Z54: 4.7937538 | AA54: 1.8996138 | AB54: 0.41782792 | AC54: 1.9801046 | AD54: 2.5014856 | AE54: 2.0846308 | AF54: 2.2151442 | AG54: 0.2217927 | AH54: -1.733998 | AI54: -1.1029397 | AJ54: -0.2195169 | AK54: 0.18537691 | AL54: 1.8722881 | AM54: 2.9898372 | AN54: 2.7943823 | AO54: 1.8640343 | AP54: 1.1600061 | AQ54: 1.4937093 | AR54: 1.4711338 | AS54: 1.1035667 | AT54: 1.0899228 | AU54: 2.2365038 | AV54: 2.4909472 | AW54: 0.59906913 | AX54: -2.3484417 | AY54: -1.9396099 | AZ54: 0.40860136 | BA54: 2.3029591 | BB54: 2.480739 | BC54: 0.66077623 | BD54: -0.27255716 | BE54: 1.6410108 | BF54: 1.6053482 | BG54: 0.52461007 | BH54: 1.5652078 | BI54: 1.5545299 | BJ54: 1.1048875 | BK54: 1.6011198 | BL54: 1.4537736 | BM54: 1.1311659 | BN54: 2.6331457 | BO54: 2.3144719 | BP54: 0.79913884 | BQ54: 0.87659032 | BR54: 1.8649534 | BS54: 1.5900818 | BT54: 1.1754223 | BU54: 2.4671663 | BV54: 0.76478726
A55: Adjustments
A56: Taxes on products | C56: #DIV/0! | D56: #DIV/0! | E56: #DIV/0! | F56: #DIV/0! | G56: #DIV/0! | H56: #DIV/0! | I56: -6.4807324 | J56: -2.6993351 | K56: 3.754784 | L56: 7.4885886 | M56: 5.5425539 | N56: 0.58473118 | O56: 0.13201979 | P56: 5.4048681 | Q56: 7.3751745 | R56: 3.2051402 | S56: -0.063424082 | T56: -2.8703881 | U56: -2.0704025 | V56: 1.9875951 | W56: 3.6498548 | X56: 1.5946204 | Y56: 2.7518968 | Z56: 2.6953915 | AA56: 0.43841337 | AB56: 0.96139379 | AC56: 3.4523414 | AD56: 4.3832833 | AE56: 1.4839566 | AF56: -0.60624953 | AG56: -2.0243998 | AH56: 0.15503229 | AI56: 4.0429808 | AJ56: 4.9557195 | AK56: 2.5959825 | AL56: 2.080974 | AM56: 2.0724493 | AN56: 0.53083666 | AO56: -0.79844297 | AP56: -0.4178564 | AQ56: 0.67532711 | AR56: 0.82663146 | AS56: 2.7202368 | AT56: 2.8811951 | AU56: 1.4389971 | AV56: 2.4742794 | AW56: 0.62354391 | AX56: -1.8538135 | AY56: -1.3762001 | AZ56: 0.086563959 | BA56: -0.57350927 | BB56: 0.48667534 | BC56: 1.2590056 | BD56: 3.388185 | BE56: 5.534126 | BF56: 3.8067953 | BG56: -0.63244602 | BH56: -0.90973097 | BI56: 2.8235548 | BJ56: 4.5571386 | BK56: 3.5209391 | BL56: 0.71045761 | BM56: 0.011569633 | BN56: 1.2675969 | BO56: 3.5568092 | BP56: 3.1951302 | BQ56: 0.60771805 | BR56: -0.18363619 | BS56: 2.2325693 | BT56: 2.4188298 | BU56: 3.1512721 | BV56: 4.2738986
A57: Source: Uganda Bureau of Statistics

Sheet Summary IPD
X2: Table 3: Summary of QGDP at constant 2009/10 prices, IMPLICIT PRICE DEFLATORS, 2013/14-2017/18
B3: 2007/08 | D3: 2008/09 | H3: 2009/10 | L3: 2010/11 | P3: 2011/12 | U3: 2012/13 | X3: 2013/14 | AB3: 2014/15 | AF3: 2015/16 | AJ3: 2016/17 | AN3: 2017/18
A4: ACTIVITY | B4: Q3 | C4: Q4 | D4: Q1 | E4: Q2 | F4: Q3 | G4: Q4 | H4: Q1 | I4: Q2 | J4: Q3 | K4: Q4 | L4: Q1 | M4: Q2 | N4: Q3 | O4: Q4 | P4: Q1 | Q4: Q2 | R4: Q3 | S4: Q4 | T4: Q1 | U4: Q2 | V4: Q3 | W4: Q4 | X4: Q1 | Y4: Q2 | Z4: Q3 | AA4: Q4 | AB4: Q1 | AC4: Q2 | AD4: Q3 | AE4: Q4 | AF4: Q1 | AG4: Q2 | AH4: Q3 | AI4: Q4 | AJ4: Q1 | AK4: Q2 | AL4: Q3 | AM4: Q4 | AN4: Q1 | AO4: Q2 | AP4: Q3 | AQ4: Q4
A5: ORIGINAL ESTIMATES
A6: GDP at market prices | B6: =#REF!/Summary!B6*100 -> #REF! | C6: =#REF!/Summary!C6*100 -> #REF! | D6: =#REF!/Summary!D6*100 -> #REF! | E6: =#REF!/Summary!E6*100 -> #REF! | F6: =#REF!/Summary!F6*100 -> #REF! | G6: =#REF!/Summary!G6*100 -> #REF! | H6: =#REF!/Summary!H6*100 -> #REF! | I6: =#REF!/Summary!I6*100 -> #REF! | ... AQ6: =#REF!/Summary!AQ6*100 -> #REF!
A7: Agriculture, Forestry & Fishing | B7: =#REF!/Summary!B7*100 -> #REF! | C7: =#REF!/Summary!C7*100 -> #REF! | D7: =#REF!/Summary!D7*100 -> #REF! | E7: =#REF!/Summary!E7*100 -> #REF! | F7: =#REF!/Summary!F7*100 -> #REF! | G7: =#REF!/Summary!G7*100 -> #REF! | H7: =#REF!/Summary!H7*100 -> #REF! | I7: =#REF!/Summary!I7*100 -> #REF! | ... AQ7: =#REF!/Summary!AQ7*100 -> #REF!
A8: Industry | B8: =#REF!/Summary!B8*100 -> #REF! | C8: =#REF!/Summary!C8*100 -> #REF! | D8: =#REF!/Summary!D8*100 -> #REF! | E8: =#REF!/Summary!E8*100 -> #REF! | F8: =#REF!/Summary!F8*100 -> #REF! | G8: =#REF!/Summary!G8*100 -> #REF! | H8: =#REF!/Summary!H8*100 -> #REF! | I8: =#REF!/Summary!I8*100 -> #REF! | ... AQ8: =#REF!/Summary!AQ8*100 -> #REF!
A9: Services | B9: =#REF!/Summary!B9*100 -> #REF! | C9: =#REF!/Summary!C9*100 -> #REF! | D9: =#REF!/Summary!D9*100 -> #REF! | E9: =#REF!/Summary!E9*100 -> #REF! | F9: =#REF!/Summary!F9*100 -> #REF! | G9: =#REF!/Summary!G9*100 -> #REF! | H9: =#REF!/Summary!H9*100 -> #REF! | I9: =#REF!/Summary!I9*100 -> #REF! | ... AQ9: =#REF!/Summary!AQ9*100 -> #REF!
A10: Adjustments
A11: Taxes on products | B11: =#REF!/Summary!B11*100 -> #REF! | C11: =#REF!/Summary!C11*100 -> #REF! | D11: =#REF!/Summary!D11*100 -> #REF! | E11: =#REF!/Summary!E11*100 -> #REF! | F11: =#REF!/Summary!F11*100 -> #REF! | G11: =#REF!/Summary!G11*100 -> #REF! | H11: =#REF!/Summary!H11*100 -> #REF! | I11: =#REF!/Summary!I11*100 -> #REF! | ... AQ11: =#REF!/Summary!AQ11*100 -> #REF!
A13: SEASONALLY ADJUSTED ESTIMATES
A14: GDP at market prices | B14: =#REF!/Summary!B14*100 -> #REF! | C14: =#REF!/Summary!C14*100 -> #REF! | D14: =#REF!/Summary!D14*100 -> #REF! | E14: =#REF!/Summary!E14*100 -> #REF! | F14: =#REF!/Summary!F14*100 -> #REF! | G14: =#REF!/Summary!G14*100 -> #REF! | H14: =#REF!/Summary!H14*100 -> #REF! | I14: =#REF!/Summary!I14*100 -> #REF! | ... AQ14: =#REF!/Summary!AQ14*100 -> #REF!
A15: Agriculture, Forestry & Fishing | B15: =#REF!/Summary!B15*100 -> #REF! | C15: =#REF!/Summary!C15*100 -> #REF! | D15: =#REF!/Summary!D15*100 -> #REF! | E15: =#REF!/Summary!E15*100 -> #REF! | F15: =#REF!/Summary!F15*100 -> #REF! | G15: =#REF!/Summary!G15*100 -> #REF! | H15: =#REF!/Summary!H15*100 -> #REF! | I15: =#REF!/Summary!I15*100 -> #REF! | ... AQ15: =#REF!/Summary!AQ15*100 -> #REF!
A16: Industry | B16: =#REF!/Summary!B16*100 -> #REF! | C16: =#REF!/Summary!C16*100 -> #REF! | D16: =#REF!/Summary!D16*100 -> #REF! | E16: =#REF!/Summary!E16*100 -> #REF! | F16: =#REF!/Summary!F16*100 -> #REF! | G16: =#REF!/Summary!G16*100 -> #REF! | H16: =#REF!/Summary!H16*100 -> #REF! | I16: =#REF!/Summary!I16*100 -> #REF! | ... AQ16: =#REF!/Summary!AQ16*100 -> #REF!
A17: Services | B17: =#REF!/Summary!B17*100 -> #REF! | C17: =#REF!/Summary!C17*100 -> #REF! | D17: =#REF!/Summary!D17*100 -> #REF! | E17: =#REF!/Summary!E17*100 -> #REF! | F17: =#REF!/Summary!F17*100 -> #REF! | G17: =#REF!/Summary!G17*100 -> #REF! | H17: =#REF!/Summary!H17*100 -> #REF! | I17: =#REF!/Summary!I17*100 -> #REF! | ... AQ17: =#REF!/Summary!AQ17*100 -> #REF!
A18: Adjustments
A19: Taxes on products | B19: =#REF!/Summary!B19*100 -> #REF! | C19: =#REF!/Summary!C19*100 -> #REF! | D19: =#REF!/Summary!D19*100 -> #REF! | E19: =#REF!/Summary!E19*100 -> #REF! | F19: =#REF!/Summary!F19*100 -> #REF! | G19: =#REF!/Summary!G19*100 -> #REF! | H19: =#REF!/Summary!H19*100 -> #REF! | I19: =#REF!/Summary!I19*100 -> #REF! | ... AQ19: =#REF!/Summary!AQ19*100 -> #REF!
A21: TREND CYCLE ESTIMATES
A22: GDP at market prices | B22: =#REF!/Summary!B22*100 -> #REF! | C22: =#REF!/Summary!C22*100 -> #REF! | D22: =#REF!/Summary!D22*100 -> #REF! | E22: =#REF!/Summary!E22*100 -> #REF! | F22: =#REF!/Summary!F22*100 -> #REF! | G22: =#REF!/Summary!G22*100 -> #REF! | H22: =#REF!/Summary!H22*100 -> #REF! | I22: =#REF!/Summary!I22*100 -> #REF! | ... AQ22: =#REF!/Summary!AQ22*100 -> #REF!
A23: Agriculture, Forestry & Fishing | B23: =#REF!/Summary!B23*100 -> #REF! | C23: =#REF!/Summary!C23*100 -> #REF! | D23: =#REF!/Summary!D23*100 -> #REF! | E23: =#REF!/Summary!E23*100 -> #REF! | F23: =#REF!/Summary!F23*100 -> #REF! | G23: =#REF!/Summary!G23*100 -> #REF! | H23: =#REF!/Summary!H23*100 -> #REF! | I23: =#REF!/Summary!I23*100 -> #REF! | ... AQ23: =#REF!/Summary!AQ23*100 -> #REF!
A24: Industry | B24: =#REF!/Summary!B24*100 -> #REF! | C24: =#REF!/Summary!C24*100 -> #REF! | D24: =#REF!/Summary!D24*100 -> #REF! | E24: =#REF!/Summary!E24*100 -> #REF! | F24: =#REF!/Summary!F24*100 -> #REF! | G24: =#REF!/Summary!G24*100 -> #REF! | H24: =#REF!/Summary!H24*100 -> #REF! | I24: =#REF!/Summary!I24*100 -> #REF! | ... AQ24: =#REF!/Summary!AQ24*100 -> #REF!
A25: Services | B25: =#REF!/Summary!B25*100 -> #REF! | C25: =#REF!/Summary!C25*100 -> #REF! | D25: =#REF!/Summary!D25*100 -> #REF! | E25: =#REF!/Summary!E25*100 -> #REF! | F25: =#REF!/Summary!F25*100 -> #REF! | G25: =#REF!/Summary!G25*100 -> #REF! | H25: =#REF!/Summary!H25*100 -> #REF! | I25: =#REF!/Summary!I25*100 -> #REF! | ... AQ25: =#REF!/Summary!AQ25*100 -> #REF!
A26: Adjustments
A27: Taxes on products | B27: =#REF!/Summary!B27*100 -> #REF! | C27: =#REF!/Summary!C27*100 -> #REF! | D27: =#REF!/Summary!D27*100 -> #REF! | E27: =#REF!/Summary!E27*100 -> #REF! | F27: =#REF!/Summary!F27*100 -> #REF! | G27: =#REF!/Summary!G27*100 -> #REF! | H27: =#REF!/Summary!H27*100 -> #REF! | I27: =#REF!/Summary!I27*100 -> #REF! | ... AQ27: =#REF!/Summary!AQ27*100 -> #REF!
A28: Uganda Bureau of Statistics
X30: Table 4: Summary of QGDP at constant prices, PERCENTAGE SHARE, 2013/14-2017/18
B31: 2007/08 | D31: 2008/09 | H31: 2009/10 | L31: 2010/11 | P31: 2011/12 | U31: 2012/13 | X31: 2013/14 | AB31: 2014/15 | AF31: 2015/16 | AJ31: 2016/17 | AN31: 2017/18
A32: ACTIVITY | B32: Q3 | C32: Q4 | D32: Q1 | E32: Q2 | F32: Q3 | G32: Q4 | H32: Q1 | I32: Q2 | J32: Q3 | K32: Q4 | L32: Q1 | M32: Q2 | N32: Q3 | O32: Q4 | P32: Q1 | Q32: Q2 | R32: Q3 | S32: Q4 | T32: Q1 | U32: Q2 | V32: Q3 | W32: Q4 | X32: Q1 | Y32: Q2 | Z32: Q3 | AA32: Q4 | AB32: Q1 | AC32: Q2 | AD32: Q3 | AE32: Q4 | AF32: Q1 | AG32: Q2 | AH32: Q3 | AI32: Q4 | AJ32: Q1 | AK32: Q2 | AL32: Q3 | AM32: Q4 | AN32: Q1 | AO32: Q2 | AP32: Q3 | AQ32: Q4
A33: ORIGINAL ESTIMATES
A34: GDP at market prices | B34: =Summary!B6/Summary!B$6*100 -> #DIV/0! | C34: =Summary!C6/Summary!C$6*100 -> #DIV/0! | D34: =Summary!D6/Summary!D$6*100 -> 100 | E34: =Summary!E6/Summary!E$6*100 -> 100 | F34: =Summary!F6/Summary!F$6*100 -> 100 | G34: =Summary!G6/Summary!G$6*100 -> 100 | H34: =Summary!H6/Summary!H$6*100 -> 100 | I34: =Summary!I6/Summary!I$6*100 -> 100 | J34: =Summary!J6/Summary!J$6*100 -> 100 | K34: =SUM(K35:K39) -> 100 | L34: =SUM(L35:L39) -> 100 | M34: =SUM(M35:M39) -> 100 | N34: =SUM(N35:N39) -> 100 | O34: =SUM(O35:O39) -> 100 | P34: =SUM(P35:P39) -> 100 | Q34: =SUM(Q35:Q39) -> 100 | R34: =SUM(R35:R39) -> 100 | ... AQ34: =SUM(AQ35:AQ39) -> 100
A35: Agriculture, Forestry & Fishing | B35: =Summary!B7/Summary!B$6*100 -> #DIV/0! | C35: =Summary!C7/Summary!C$6*100 -> #DIV/0! | D35: =Summary!D7/Summary!D$6*100 -> 41.274883 | E35: =Summary!E7/Summary!E$6*100 -> 35.148249 | F35: =Summary!F7/Summary!F$6*100 -> 31.548614 | G35: =Summary!G7/Summary!G$6*100 -> 34.351134 | H35: =Summary!H7/Summary!H$6*100 -> 32.617381 | I35: =Summary!I7/Summary!I$6*100 -> 26.611491 | ... AQ35: =Summary!AQ7/Summary!AQ$6*100 -> 21.316147
A36: Industry | B36: =Summary!B8/Summary!B$6*100 -> #DIV/0! | C36: =Summary!C8/Summary!C$6*100 -> #DIV/0! | D36: =Summary!D8/Summary!D$6*100 -> 9.1668778 | E36: =Summary!E8/Summary!E$6*100 -> 10.30067 | F36: =Summary!F8/Summary!F$6*100 -> 8.9515134 | G36: =Summary!G8/Summary!G$6*100 -> 11.742769 | H36: =Summary!H8/Summary!H$6*100 -> 22.965377 | I36: =Summary!I8/Summary!I$6*100 -> 25.018551 | ... AQ36: =Summary!AQ8/Summary!AQ$6*100 -> 26.685471
A37: Services | B37: =Summary!B9/Summary!B$6*100 -> #DIV/0! | C37: =Summary!C9/Summary!C$6*100 -> #DIV/0! | D37: =Summary!D9/Summary!D$6*100 -> 43.3087 | E37: =Summary!E9/Summary!E$6*100 -> 48.001319 | F37: =Summary!F9/Summary!F$6*100 -> 50.619498 | G37: =Summary!G9/Summary!G$6*100 -> 46.461679 | H37: =Summary!H9/Summary!H$6*100 -> 38.993726 | I37: =Summary!I9/Summary!I$6*100 -> 42.726795 | ... AQ37: =Summary!AQ9/Summary!AQ$6*100 -> 44.888904
A38: Adjustments
A39: Taxes on products | B39: =Summary!B11/Summary!B$6*100 -> #DIV/0! | C39: =Summary!C11/Summary!C$6*100 -> #DIV/0! | D39: =Summary!D11/Summary!D$6*100 -> 6.2495396 | E39: =Summary!E11/Summary!E$6*100 -> 6.5497628 | F39: =Summary!F11/Summary!F$6*100 -> 8.8803753 | G39: =Summary!G11/Summary!G$6*100 -> 7.4444184 | H39: =Summary!H11/Summary!H$6*100 -> 5.423516 | I39: =Summary!I11/Summary!I$6*100 -> 5.6431636 | ... AQ39: =Summary!AQ11/Summary!AQ$6*100 -> 7.1094781
A41: SEASONALLY ADJUSTED ESTIMATES
A42: GDP at market prices | B42: =Summary!B14/Summary!B$14*100 -> #DIV/0! | C42: =Summary!C14/Summary!C$14*100 -> #DIV/0! | D42: =Summary!D14/Summary!D$14*100 -> #DIV/0! | E42: =Summary!E14/Summary!E$14*100 -> #DIV/0! | F42: =Summary!F14/Summary!F$14*100 -> #DIV/0! | G42: =Summary!G14/Summary!G$14*100 -> #DIV/0! | H42: =Summary!H14/Summary!H$14*100 -> 100 | I42: =Summary!I14/Summary!I$14*100 -> 100 | J42: =Summary!J14/Summary!J$14*100 -> 100 | K42: =SUM(K43:K47) -> 100 | L42: =SUM(L43:L47) -> 100 | M42: =SUM(M43:M47) -> 100 | N42: =SUM(N43:N47) -> 100 | O42: =SUM(O43:O47) -> 100 | P42: =SUM(P43:P47) -> 100 | Q42: =SUM(Q43:Q47) -> 100 | R42: =SUM(R43:R47) -> 100 | ... AQ42: =SUM(AQ43:AQ47) -> 100
A43: Agriculture, Forestry & Fishing | B43: =Summary!B15/Summary!B$14*100 -> #DIV/0! | C43: =Summary!C15/Summary!C$14*100 -> #DIV/0! | D43: =Summary!D15/Summary!D$14*100 -> #DIV/0! | E43: =Summary!E15/Summary!E$14*100 -> #DIV/0! | F43: =Summary!F15/Summary!F$14*100 -> #DIV/0! | G43: =Summary!G15/Summary!G$14*100 -> #DIV/0! | H43: =Summary!H15/Summary!H$14*100 -> 28.104167 | I43: =Summary!I15/Summary!I$14*100 -> 27.532752 | ... AQ43: =Summary!AQ15/Summary!AQ$14*100 -> 22.61505
A44: Industry | B44: =Summary!B16/Summary!B$14*100 -> #DIV/0! | C44: =Summary!C16/Summary!C$14*100 -> #DIV/0! | D44: =Summary!D16/Summary!D$14*100 -> #DIV/0! | E44: =Summary!E16/Summary!E$14*100 -> #DIV/0! | F44: =Summary!F16/Summary!F$14*100 -> #DIV/0! | G44: =Summary!G16/Summary!G$14*100 -> #DIV/0! | H44: =Summary!H16/Summary!H$14*100 -> 25.035525 | I44: =Summary!I16/Summary!I$14*100 -> 24.763313 | ... AQ44: =Summary!AQ16/Summary!AQ$14*100 -> 26.268428
A45: Services | B45: =Summary!B17/Summary!B$14*100 -> #DIV/0! | C45: =Summary!C17/Summary!C$14*100 -> #DIV/0! | D45: =Summary!D17/Summary!D$14*100 -> #DIV/0! | E45: =Summary!E17/Summary!E$14*100 -> #DIV/0! | F45: =Summary!F17/Summary!F$14*100 -> #DIV/0! | G45: =Summary!G17/Summary!G$14*100 -> #DIV/0! | H45: =Summary!H17/Summary!H$14*100 -> 40.856966 | I45: =Summary!I17/Summary!I$14*100 -> 42.146389 | ... AQ45: =Summary!AQ17/Summary!AQ$14*100 -> 44.280548
A46: Adjustments | Z46: 8.5
A47: Taxes on products | B47: =Summary!B19/Summary!B$14*100 -> #DIV/0! | C47: =Summary!C19/Summary!C$14*100 -> #DIV/0! | D47: =Summary!D19/Summary!D$14*100 -> #DIV/0! | E47: =Summary!E19/Summary!E$14*100 -> #DIV/0! | F47: =Summary!F19/Summary!F$14*100 -> #DIV/0! | G47: =Summary!G19/Summary!G$14*100 -> #DIV/0! | H47: =Summary!H19/Summary!H$14*100 -> 6.0033415 | I47: =Summary!I19/Summary!I$14*100 -> 5.5575462 | ... AQ47: =Summary!AQ19/Summary!AQ$14*100 -> 6.8359746
A49: TREND CYCLE ESTIMATES
A50: GDP at market prices | B50: =Summary!B22/Summary!B$22*100 -> #DIV/0! | C50: =Summary!C22/Summary!C$22*100 -> #DIV/0! | D50: =Summary!D22/Summary!D$22*100 -> #DIV/0! | E50: =Summary!E22/Summary!E$22*100 -> #DIV/0! | F50: =Summary!F22/Summary!F$22*100 -> #DIV/0! | G50: =Summary!G22/Summary!G$22*100 -> #DIV/0! | H50: =Summary!H22/Summary!H$22*100 -> 100 | I50: =Summary!I22/Summary!I$22*100 -> 100 | J50: =Summary!J22/Summary!J$22*100 -> 100 | K50: =SUM(K51:K55) -> 100 | L50: =SUM(L51:L55) -> 100 | M50: =SUM(M51:M55) -> 100 | N50: =SUM(N51:N55) -> 100 | O50: =SUM(O51:O55) -> 100 | P50: =SUM(P51:P55) -> 100 | Q50: =SUM(Q51:Q55) -> 100 | R50: =SUM(R51:R55) -> 100 | ... AQ50: =SUM(AQ51:AQ55) -> 100
A51: Agriculture, Forestry & Fishing | B51: =Summary!B23/Summary!B$22*100 -> #DIV/0! | C51: =Summary!C23/Summary!C$22*100 -> #DIV/0! | D51: =Summary!D23/Summary!D$22*100 -> #DIV/0! | E51: =Summary!E23/Summary!E$22*100 -> #DIV/0! | F51: =Summary!F23/Summary!F$22*100 -> #DIV/0! | G51: =Summary!G23/Summary!G$22*100 -> #DIV/0! | H51: =Summary!H23/Summary!H$22*100 -> 28.240286 | I51: =Summary!I23/Summary!I$22*100 -> 27.999603 | ... AQ51: =Summary!AQ23/Summary!AQ$22*100 -> 22.665876
A52: Industry | B52: =Summary!B24/Summary!B$22*100 -> #DIV/0! | C52: =Summary!C24/Summary!C$22*100 -> #DIV/0! | D52: =Summary!D24/Summary!D$22*100 -> #DIV/0! | E52: =Summary!E24/Summary!E$22*100 -> #DIV/0! | F52: =Summary!F24/Summary!F$22*100 -> #DIV/0! | G52: =Summary!G24/Summary!G$22*100 -> #DIV/0! | H52: =Summary!H24/Summary!H$22*100 -> 24.648159 | I52: =Summary!I24/Summary!I$22*100 -> 24.877695 | ... AQ52: =Summary!AQ24/Summary!AQ$22*100 -> 26.148354
A53: Services | B53: =Summary!B25/Summary!B$22*100 -> #DIV/0! | C53: =Summary!C25/Summary!C$22*100 -> #DIV/0! | D53: =Summary!D25/Summary!D$22*100 -> #DIV/0! | E53: =Summary!E25/Summary!E$22*100 -> #DIV/0! | F53: =Summary!F25/Summary!F$22*100 -> #DIV/0! | G53: =Summary!G25/Summary!G$22*100 -> #DIV/0! | H53: =Summary!H25/Summary!H$22*100 -> 41.110212 | I53: =Summary!I25/Summary!I$22*100 -> 41.603264 | ... AQ53: =Summary!AQ25/Summary!AQ$22*100 -> 44.429707
A54: Adjustments
A55: Taxes on products | B55: =Summary!B27/Summary!B$22*100 -> #DIV/0! | C55: =Summary!C27/Summary!C$22*100 -> #DIV/0! | D55: =Summary!D27/Summary!D$22*100 -> #DIV/0! | E55: =Summary!E27/Summary!E$22*100 -> #DIV/0! | F55: =Summary!F27/Summary!F$22*100 -> #DIV/0! | G55: =Summary!G27/Summary!G$22*100 -> #DIV/0! | H55: =Summary!H27/Summary!H$22*100 -> 6.001343 | I55: =Summary!I27/Summary!I$22*100 -> 5.5194385 | ... AQ55: =Summary!AQ27/Summary!AQ$22*100 -> 6.756063
A56: Uganda Bureau of Statistics

Sheet Original_VA
A1: Table 3: ORIGINAL UNADJUSTED Value Added by activity at constant 2016/17 prices, BILLION SHILLINGS, 2016/17-2025/26
I2: 2008Q1 | J2: 2008Q2 | K2: 2008Q3 | L2: 2008Q4 | M2: 2009Q1 | N2: 2009Q2 | O2: 2009Q3 | P2: 2009Q4 | Q2: 2010Q1 | R2: 2010Q2 | S2: 2010Q3 | T2: 2010Q4 | U2: 2011Q1 | V2: 2011Q2 | W2: 2011Q3 | X2: 2011Q4 | Y2: 2012Q1 | Z2: 2012Q2 | AA2: 2012Q3 | AB2: 2012Q4 | AC2: 2013Q1 | AD2: 2013Q2 | AE2: 2013Q3 | AF2: 2013Q4 | AG2: 2014Q1 | AH2: 2014Q2 | AI2: 2014Q3 | AJ2: 2014Q4 | AK2: 2015Q1 | AL2: 2015Q2 | AM2: 2015Q3
A3: Year | I3: 2007/08 | K3: 2008/09 | O3: 2009/10 | S3: 2010/11 | W3: 2011/12 | AA3: 2012/13 | AC3: 2012/13 | AE3: 2013/14 | AF3: 2013/14 | AH3: 2013/14 | AI3: 2014/15 | AJ3: 2014/15 | AK3: 2014/15 | AM3: 2015/16 | AQ3: 2016/17 | AU3: 2017/18 | AY3: 2018/19 | BC3: 2019/20 | BG3: 2020/21 | BK3: 2021/22 | BO3: 2022/23 | BS3: 2023/24 | BW3: 2024/25 | CA3: 2025/26
A4: Period | B4: 2013/14 | C4: 2014/15 | D4: 2015/16 | E4: 2016/17 | F4: 2017/18 | I4: Q3 | J4: Q4 | K4: Q1 | L4: Q2 | M4: Q3 | N4: Q4 | O4: Q1 | P4: Q2 | Q4: Q3 | R4: Q4 | S4: Q1 | T4: Q2 | U4: Q3 | V4: Q4 | W4: Q1 | X4: Q2 | Y4: Q3 | Z4: Q4 | AA4: Q1 | AB4: Q2 | AC4: Q3 | AD4: Q4 | AE4: Q1 | AF4: Q2 | AG4: Q3 | AH4: Q4 | AI4: Q1 | AJ4: Q2 | AK4: Q3 | AL4: Q4 | AM4: Q1 | AN4: Q2 | AO4: Q3 | AP4: Q4 | AQ4: Q1 | AR4: Q2 | AS4: Q3 | AT4: Q4 | AU4: Q1 | AV4: Q2 | AW4: Q3 | AX4: Q4 | AY4: Q1 | AZ4: Q2 | BA4: Q3 | BB4: Q4 | BC4: Q1 | BD4: Q2 | BE4: Q3 | BF4: Q4 | BG4: Q1 | BH4: Q2 | BI4: Q3 | BJ4: Q4 | BK4: Q1 | BL4: Q2 | BM4: Q3 | BN4: Q4 | BO4: Q1 | BP4: Q2 | BQ4: Q3 | BR4: Q4 | BS4: Q1 | BT4: Q2 | BU4: Q3 | BV4: Q4 | BW4: Q1 | BX4: Q2 | BY4: Q3 | BZ4: Q4 | CA4: Q1 | CB4: Q2 | CC4: Q3
A5: GDP AT MARKET PRICES | B5: 95677.551 | C5: 101373.1 | D5: 105223.08 | E5: 108518.04 | F5: 115358.94 | H5: 0 | K5: 15766.403 | L5: 13927.632 | M5: 14022.629 | N5: 15998.234 | O5: 21078.882 | P5: 19122.748 | Q5: 19608.559 | R5: 20695.656 | S5: 23193.526 | T5: 21456.643 | U5: 21240.165 | V5: 21202.324 | W5: 24535.906 | X5: 21481.557 | Y5: 21447.288 | Z5: 22266.799 | AA5: 26058 | AB5: 22244.279 | AC5: 21603.992 | AD5: 21779.636 | AE5: 25541.078 | AF5: 22459.838 | AG5: 23000.644 | AH5: 24675.991 | AI5: 26399.959 | AJ5: 24996.444 | AK5: 24359.381 | AL5: 25617.315 | AM5: 28652.094 | AN5: 26475.799 | AO5: 24581.78 | AP5: 25513.407 | AQ5: 28577.247 | AR5: 26610.18 | AS5: 26240.178 | AT5: 27090.435 | AU5: 30772.237 | AV5: 28335.28 | AW5: 27653.331 | AX5: 28598.087 | AY5: 32487.642 | AZ5: 29958.631 | BA5: 29773.235 | BB5: 30567.095 | BC5: 34943.779 | BD5: 32466.458 | BE5: 30130.072 | BF5: 28870.102 | BG5: 34802.923 | BH5: 32477.008 | BI5: 30975.024 | BJ5: 32626.063 | BK5: 35622.436 | BL5: 34024.49 | BM5: 32716.662 | BN5: 34522.28 | BO5: 38746.737 | BP5: 35492.013 | BQ5: 33446.228 | BR5: 36506.452 | BS5: 41068.072 | BT5: 37544.31 | BU5: 35728.791 | BV5: 38581.884 | BW5: 43605.836 | BX5: 39557.991 | BY5: 38727.987 | BZ5: 40714.044 | CA5: 45718.884 | CB5: 42903.876 | CC5: 40970.227
A6: AGRICULTURE,FORESTRY&FISHING | B6: 23529.598 | C6: 24071.815 | D6: 24773.789 | E6: 25457.069 | F6: 26574.426 | K6: 6507.5645 | L6: 4895.3189 | M6: 4423.9452 | N6: 5495.5749 | O6: 6875.3793 | P6: 5088.8484 | Q6: 4451.0205 | R6: 5461.4456 | S6: 7007.5574 | T6: 5267.2451 | U6: 4769.982 | V6: 5440.697 | W6: 7871.5671 | X6: 5290.0544 | Y6: 4412.0205 | Z6: 5051.4272 | AA6: 8273.6224 | AB6: 5294.8849 | AC6: 4601.826 | AD6: 4760.2442 | AE6: 8300.5433 | AF6: 5337.7241 | AG6: 4567.2362 | AH6: 5324.0947 | AI6: 7787.9339 | AJ6: 5886.4232 | AK6: 4831.2409 | AL6: 5566.2174 | AM6: 7919.4675 | AN6: 5919.3821 | AO6: 5302.9236 | AP6: 5632.0158 | AQ6: 8012.3898 | AR6: 6110.5575 | AS6: 5359.3298 | AT6: 5974.7915 | AU6: 8783.7536 | AV6: 6199.5724 | AW6: 5495.0897 | AX6: 6096.0101 | AY6: 8974.6097 | AZ6: 6448.4413 | BA6: 5935.2774 | BB6: 6628.7289 | BC6: 9517.4185 | BD6: 6941.2508 | BE6: 5858.4835 | BF6: 7019.6669 | BG6: 10178.838 | BH6: 7480.0514 | BI6: 5874.7257 | BJ6: 7070.5839 | BK6: 10624.95 | BL6: 7330.892 | BM6: 6120.4467 | BN6: 7804.9868 | BO6: 11088.263 | BP6: 8197.4364 | BQ6: 6452.1008 | BR6: 7589.8403 | BS6: 11715.27 | BT6: 8365.8311 | BU6: 6712.9791 | BV6: 8392.5624 | BW6: 12457.04 | BX6: 9018.0558 | BY6: 7404.8569 | BZ6: 8683.3829 | CA6: 12839.64 | CB6: 9809.0589 | CC6: 7563.1391
A7: Cash crops | B7: 2077.9998 | C7: 2161.0304 | D7: 2332.5942 | E7: 2551.9497 | F7: 2702.9483 | K7: 399.61795 | L7: 634.82527 | M7: 662.45052 | N7: 513.9201 | O7: 405.66079 | P7: 538.9143 | Q7: 452.23425 | R7: 512.11823 | S7: 376.18328 | T7: 493.31842 | U7: 613.89027 | V7: 424.1042 | W7: 502.56926 | X7: 572.96078 | Y7: 573.37138 | Z7: 437.64169 | AA7: 455.48582 | AB7: 553.15128 | AC7: 634.25096 | AD7: 442.07724 | AE7: 509.03779 | AF7: 591.9906 | AG7: 581.34247 | AH7: 395.6289 | AI7: 502.58611 | AJ7: 538.13508 | AK7: 660.55567 | AL7: 459.75354 | AM7: 599.82266 | AN7: 607.24444 | AO7: 675.46962 | AP7: 450.05746 | AQ7: 503.80349 | AR7: 751.47235 | AS7: 756.6638 | AT7: 540.01006 | AU7: 711.49019 | AV7: 721.04285 | AW7: 772.20685 | AX7: 498.20843 | AY7: 708.23323 | AZ7: 768.35837 | BA7: 790.47225 | BB7: 563.82244 | BC7: 726.02296 | BD7: 837.1285 | BE7: 928.12524 | BF7: 560.87771 | BG7: 782.35957 | BH7: 933.39018 | BI7: 1033.3276 | BJ7: 683.9495 | BK7: 965.22972 | BL7: 980.0504 | BM7: 993.72889 | BN7: 688.45779 | BO7: 969.15812 | BP7: 928.29383 | BQ7: 1072.7337 | BR7: 681.86824 | BS7: 1030.9453 | BT7: 1070.8634 | BU7: 1245.7712 | BV7: 753.11773 | BW7: 1200.8309 | BX7: 1173.3745 | BY7: 1357.3298 | BZ7: 833.80664 | CA7: 1285.3573 | CB7: 1320.8624 | CC7: 1454.5946
A8: Food crops | B8: 12658.661 | C8: 12936.631 | D8: 13100.439 | E8: 13394.945 | F8: 14540.252 | K8: 4281.5106 | L8: 2451.0265 | M8: 2018.2066 | N8: 2897.7667 | O8: 4593.2382 | P8: 2657.0383 | Q8: 2072.3409 | R8: 2919.8031 | S8: 4627.9621 | T8: 2687.1305 | U8: 2145.4964 | V8: 3045.1339 | W8: 5002.0199 | X8: 2877.3534 | Y8: 1847.6599 | Z8: 2609.078 | AA8: 5742.9725 | AB8: 2416.9647 | AC8: 1728.4366 | AD8: 2411.7823 | AE8: 5602.7503 | AF8: 2407.5869 | AG8: 1852.7062 | AH8: 2795.6178 | AI8: 5040.2281 | AJ8: 3084.1246 | AK8: 1960.0486 | AL8: 2852.2293 | AM8: 5070.1412 | AN8: 3063.8262 | AO8: 2087.3268 | AP8: 2879.1445 | AQ8: 5158.2444 | AR8: 2956.6065 | AS8: 2216.3688 | AT8: 3063.7253 | AU8: 5764.4524 | AV8: 3189.0326 | AW8: 2406.5075 | AX8: 3180.2595 | AY8: 5806.2349 | AZ8: 3120.4628 | BA8: 2491.5732 | BB8: 3355.7462 | BC8: 6087.3682 | BD8: 3386.3637 | BE8: 2210.2087 | BF8: 3770.8716 | BG8: 6729.3932 | BH8: 3733.7504 | BI8: 2032.2914 | BJ8: 3595.1715 | BK8: 6847.8466 | BL8: 3553.494 | BM8: 2141.0816 | BN8: 4113.2181 | BO8: 7367.019 | BP8: 4243.1851 | BQ8: 2047.1733 | BR8: 3777.0373 | BS8: 7740.0659 | BT8: 4232.3299 | BU8: 2190.283 | BV8: 4166.6736 | BW8: 8152.8624 | BX8: 4529.7878 | BY8: 2262.5053 | BZ8: 4257.0001 | CA8: 8108.2689 | CB8: 4878.8645 | CC8: 2381.271
A9: Livestock | B9: 2922.9116 | C9: 3008.6418 | D9: 3092.2451 | E9: 3309.0902 | F9: 3544.9509 | K9: 645.89351 | L9: 642.39661 | M9: 648.87909 | N9: 652.65571 | O9: 651.96767 | P9: 659.3373 | Q9: 669.80162 | R9: 669.83864 | S9: 674.11805 | T9: 674.75889 | U9: 679.81969 | V9: 683.75147 | W9: 690.13315 | X9: 691.44572 | Y9: 696.56043 | Z9: 697.6197 | AA9: 694.1283 | AB9: 687.96788 | AC9: 732.72822 | AD9: 729.88094 | AE9: 730.74574 | AF9: 732.46069 | AG9: 729.28206 | AH9: 730.42308 | AI9: 744.36089 | AJ9: 748.7154 | AK9: 757.49263 | AL9: 758.07288 | AM9: 761.15519 | AN9: 764.50227 | AO9: 774.90151 | AP9: 791.68616 | AQ9: 803.94776 | AR9: 820.59322 | AS9: 836.92932 | AT9: 847.61996 | AU9: 869.7722 | AV9: 875.22137 | AW9: 895.75739 | AX9: 904.19998 | AY9: 927.06886 | AZ9: 942.41424 | BA9: 958.71971 | BB9: 977.13017 | BC9: 999.62611 | BD9: 1016.5699 | BE9: 1037.6779 | BF9: 1051.9475 | BG9: 1075.0903 | BH9: 1093.5814 | BI9: 1117.645 | BJ9: 1139.3805 | BK9: 1164.9148 | BL9: 1183.7106 | BM9: 1209.2184 | BN9: 1235.4276 | BO9: 1266.6927 | BP9: 1289.0045 | BQ9: 1324.7443 | BR9: 1336.3725 | BS9: 1364.9638 | BT9: 1392.5445 | BU9: 1421.1592 | BV9: 1449.5255 | BW9: 1480.2991 | BX9: 1512.2661 | BY9: 1550.6613 | BZ9: 1577.5316 | CA9: 1617.3459 | CB9: 1651.731 | CC9: 1652.4051
A10: Agriculture Support Services | B10: 14.143561 | C10: 16.636148 | D10: 15.869988 | E10: 16.47244 | F10: 16.412131 | K10: 5.2684781 | L10: 2.8887269 | M10: 1.7852487 | N10: 3.8214565 | O10: 5.2484117 | P10: 2.9083793 | Q10: 2.0130803 | R10: 4.3528051 | S10: 5.8403246 | T10: 3.0815591 | U10: 1.9768489 | V10: 4.08689 | W10: 5.029252 | X10: 2.5970925 | Y10: 1.6809127 | Z10: 3.7542687 | AA10: 5.2874578 | AB10: 2.8691069 | AC10: 1.8424318 | AD10: 4.0808902 | AE10: 5.2307922 | AF10: 2.7920344 | AG10: 1.8026609 | AH10: 4.3180733 | AI10: 6.2327006 | AJ10: 3.3809539 | AK10: 2.1372786 | AL10: 4.8852147 | AM10: 6.1750274 | AN10: 3.1636957 | AO10: 1.9526404 | AP10: 4.5786242 | AQ10: 6.2837288 | AR10: 3.325037 | AS10: 2.0494802 | AT10: 4.8141938 | AU10: 6.2956095 | AV10: 3.2755887 | AW10: 2.0080248 | AX10: 4.8329083 | AY10: 6.6083068 | AZ10: 3.5884171 | BA10: 2.1829168 | BB10: 5.4791027 | BC10: 7.7829336 | BD10: 4.3860543 | BE10: 2.1540787 | BF10: 4.6823231 | BG10: 7.2284747 | BH10: 3.9801091 | BI10: 2.7383126 | BJ10: 5.4484674 | BK10: 7.7592654 | BL10: 4.0780685 | BM10: 2.8418931 | BN10: 5.5823033 | BO10: 7.9640725 | BP10: 4.2517334 | BQ10: 2.8588657 | BR10: 5.6398941 | BS10: 8.3887802 | BT10: 4.5610538 | BU10: 3.0962641 | BV10: 6.1329907 | BW10: 8.7481039 | BX10: 4.4104034 | BY10: 3.0707098 | BZ10: 7.1536239 | CA10: 7.7163285 | CB10: 4.4194806 | CC10: 3.4144225
A11: Forestry | B11: 3631.3936 | C11: 3691.6987 | D11: 3867.0382 | E11: 4002.5745 | F11: 4137.4814 | K11: 631.38633 | L11: 576.26085 | M11: 580.94913 | N11: 878.106 | O11: 669.3003 | P11: 652.56728 | Q11: 696.29628 | R11: 795.52703 | S11: 787.43625 | T11: 831.64567 | U11: 762.18907 | V11: 732.9674 | W11: 1132.2042 | X11: 573.45764 | Y11: 700.34208 | Z11: 749.36263 | AA11: 803.07265 | AB11: 1025.0054 | AC11: 913.51194 | AD11: 766.19949 | AE11: 893.25768 | AF11: 1027.2584 | AG11: 837.4163 | AH11: 873.46123 | AI11: 948.52483 | AJ11: 918.5284 | AK11: 898.18312 | AL11: 926.46239 | AM11: 895.31852 | AN11: 883.22271 | AO11: 1159.6556 | AP11: 928.84137 | AQ11: 977.93029 | AR11: 992.65352 | AS11: 1004.7215 | AT11: 1027.2691 | AU11: 1007.3811 | AV11: 1003.7501 | AW11: 1044.0648 | AX11: 1082.2855 | AY11: 1044.1093 | AZ11: 1056.6287 | BA11: 1070.8268 | BB11: 1114.9791 | BC11: 1086.4176 | BD11: 1108.061 | BE11: 1120.3878 | BF11: 1111.3554 | BG11: 1056.878 | BH11: 1149.2585 | BI11: 1181.6024 | BJ11: 1168.9939 | BK11: 1107.6165 | BL11: 1115.7609 | BM11: 1243.7005 | BN11: 1233.5857 | BO11: 1152.8066 | BP11: 1158.8936 | BQ11: 1275.3325 | BR11: 1260.9317 | BS11: 1214.7921 | BT11: 1190.4314 | BU11: 1200.1467 | BV11: 1391.5844 | BW11: 1260.4901 | BX11: 1251.7752 | BY11: 1287.4128 | BZ11: 1362.3897 | CA11: 1383.2163 | CB11: 1355.0945 | CC11: 1225.0529
A12: Fishing | B12: 2224.4887 | C12: 2257.1777 | D12: 2365.6027 | E12: 2182.0367 | F12: 1632.3812 | K12: 543.8877 | L12: 587.92095 | M12: 511.67464 | N12: 549.30497 | O12: 549.96395 | P12: 578.0828 | Q12: 558.33437 | R12: 559.80578 | S12: 536.01737 | T12: 577.31004 | U12: 566.60978 | V12: 550.65321 | W12: 539.6114 | X12: 572.23982 | Y12: 592.40581 | Z12: 553.97091 | AA12: 572.67563 | AB12: 608.92647 | AC12: 591.05594 | AD12: 406.22338 | AE12: 559.52102 | AF12: 575.6355 | AG12: 564.68656 | AH12: 524.64564 | AI12: 546.0013 | AJ12: 593.53877 | AK12: 552.82358 | AL12: 564.81407 | AM12: 586.85491 | AN12: 597.42275 | AO12: 603.61733 | AP12: 577.70768 | AQ12: 562.18016 | AR12: 585.90691 | AS12: 542.59683 | AT12: 491.35281 | AU12: 424.36218 | AV12: 407.24998 | AW12: 374.54516 | AX12: 426.22385 | AY12: 482.35514 | AZ12: 556.98883 | BA12: 621.50255 | BB12: 611.57191 | BC12: 610.20066 | BD12: 588.74175 | BE12: 559.92985 | BF12: 519.93242 | BG12: 527.88856 | BH12: 566.09095 | BI12: 507.12106 | BJ12: 477.64002 | BK12: 531.58287 | BL12: 493.79799 | BM12: 529.87529 | BN12: 528.71517 | BO12: 324.62227 | BP12: 573.80759 | BQ12: 729.25809 | BR12: 527.99078 | BS12: 356.11407 | BT12: 475.10096 | BU12: 652.52279 | BV12: 625.52817 | BW12: 353.80898 | BX12: 546.44166 | BY12: 943.87711 | BZ12: 645.50127 | CA12: 437.73547 | CB12: 598.08703 | CC12: 846.40108
A13: INDUSTRY | B13: 23549.51 | C13: 25665.771 | D13: 26437.836 | E13: 28248.326 | F13: 29616.274 | K13: 1445.2869 | L13: 1434.6394 | M13: 1255.2376 | N13: 1878.6357 | O13: 4840.8447 | P13: 4784.2345 | Q13: 5112.8414 | R13: 5061.3107 | S13: 5237.2134 | T13: 5571.0615 | U13: 5434.2561 | V13: 5453.5924 | W13: 5456.3648 | X13: 5410.6693 | Y13: 5788.7735 | Z13: 5725.958 | AA13: 5694.9937 | AB13: 5636.6937 | AC13: 5763.6888 | AD13: 5400.4985 | AE13: 5623.6031 | AF13: 5636.0437 | AG13: 6053.0605 | AH13: 6236.8023 | AI13: 6147.232 | AJ13: 6295.2097 | AK13: 6521.915 | AL13: 6701.4139 | AM13: 6809.7306 | AN13: 6794.357 | AO13: 6285.5491 | AP13: 6548.1991 | AQ13: 6768.7131 | AR13: 7106.8656 | AS13: 7305.421 | AT13: 7067.3259 | AU13: 7134.9059 | AV13: 7312.6318 | AW13: 7537.2021 | AX13: 7631.5343 | AY13: 7779.6918 | AZ13: 8068.1838 | BA13: 8243.5123 | BB13: 8201.8824 | BC13: 8570.2406 | BD13: 8886.3356 | BE13: 8486.7958 | BF13: 7398.8511 | BG13: 8381.1058 | BH13: 8755.7883 | BI13: 8669.0779 | BJ13: 8693.4802 | BK13: 8370.9467 | BL13: 9440.8925 | BM13: 9148.3498 | BN13: 9308.0376 | BO13: 9399.6503 | BP13: 9216.6242 | BQ13: 9213.4013 | BR13: 9899.9765 | BS13: 10329.779 | BT13: 9629.9206 | BU13: 9832.8272 | BV13: 10008.679 | BW13: 10858.986 | BX13: 10366.745 | BY13: 10560.436 | BZ13: 10766.195 | CA13: 11507.782 | CB13: 11637.499 | CC13: 11186.239
A14: Mining & quarrying | B14: 759.05613 | C14: 896.13161 | D14: 1007.4675 | E14: 1337.1173 | F14: 1283.8453 | K14: 193.40922 | L14: 102.35464 | M14: 95.169266 | N14: 97.100521 | O14: 95.041573 | P14: 102.08737 | Q14: 155.11509 | R14: 176.08187 | S14: 206.44953 | T14: 156.79892 | U14: 192.49138 | V14: 127.41897 | W14: 95.621487 | X14: 65.537945 | Y14: 203.14779 | Z14: 280.92011 | AA14: 243.4757 | AB14: 112.38367 | AC14: 190.20348 | AD14: 172.34051 | AE14: 165.6714 | AF14: 85.864933 | AG14: 275.35266 | AH14: 232.16713 | AI14: 177.26173 | AJ14: 160.69236 | AK14: 281.06074 | AL14: 277.11678 | AM14: 285.86198 | AN14: 217.51491 | AO14: 262.91153 | AP14: 241.17905 | AQ14: 282.95293 | AR14: 276.59929 | AS14: 375.75679 | AT14: 401.80833 | AU14: 319.7555 | AV14: 224.76187 | AW14: 339.81152 | AX14: 399.51644 | AY14: 397.45267 | AZ14: 270.96658 | BA14: 456.76541 | BB14: 382.76325 | BC14: 454.84011 | BD14: 474.18067 | BE14: 511.09849 | BF14: 317.00352 | BG14: 645.34983 | BH14: 468.64606 | BI14: 394.79031 | BJ14: 370.03532 | BK14: 281.63209 | BL14: 699.91945 | BM14: 555.65764 | BN14: 685.74265 | BO14: 531.92636 | BP14: 337.30454 | BQ14: 418.13259 | BR14: 1047.8039 | BS14: 1057.992 | BT14: 661.67504 | BU14: 435.10339 | BV14: 254.56755 | BW14: 967.23315 | BX14: 725.91079 | BY14: 433.19398 | BZ14: 365.58098 | CA14: 866.42074 | CB14: 924.2791 | CC14: 490.62644
A15: Manufacturing | B15: 14483.497 | C15: 16168.423 | D15: 16264.635 | E15: 16845.251 | F15: 17624.287 | K15: 0 | L15: 0 | M15: 0 | N15: 0 | O15: 3125.5831 | P15: 3105.8274 | Q15: 3506.9505 | R15: 3393.291 | S15: 3460.5397 | T15: 3733.4911 | U15: 3455.0294 | V15: 3506.0596 | W15: 3585.5647 | X15: 3587.063 | Y15: 3810.7383 | Z15: 3553.7706 | AA15: 3512.1175 | AB15: 3509.0389 | AC15: 3619.075 | AD15: 3537.0062 | AE15: 3396.2649 | AF15: 3470.2636 | AG15: 3765.4051 | AH15: 3851.563 | AI15: 3875.8947 | AJ15: 3979.5545 | AK15: 4149.5068 | AL15: 4163.4668 | AM15: 4288.1419 | AN15: 4245.9381 | AO15: 3702.1081 | AP15: 4028.4466 | AQ15: 4040.705 | AR15: 4238.5858 | AS15: 4435.5484 | AT15: 4130.4121 | AU15: 4261.464 | AV15: 4439.8418 | AW15: 4503.4215 | AX15: 4419.5601 | AY15: 4561.6635 | AZ15: 4852.9223 | BA15: 4835.1147 | BB15: 4731.8722 | BC15: 5096.6336 | BD15: 5278.1396 | BE15: 4784.5996 | BF15: 4060.5317 | BG15: 4909.3533 | BH15: 5000.3958 | BI15: 4890.4733 | BJ15: 4843.5145 | BK15: 4617.2239 | BL15: 5323.9039 | BM15: 5273.5154 | BN15: 5182.5961 | BO15: 5339.1513 | BP15: 5395.2734 | BQ15: 5202.2022 | BR15: 5098.4633 | BS15: 5590.3484 | BT15: 5307.7672 | BU15: 5461.8901 | BV15: 5659.4204 | BW15: 5935.8741 | BX15: 5719.2052 | BY15: 5747.7099 | BZ15: 5854.8503 | CA15: 6218.0588 | CB15: 6229.6419 | CC15: 6023.0829
A16: Electricity | B16: 1143.3695 | C16: 1208.4053 | D16: 1256.509 | E16: 1379.4764 | F16: 1453.7345 | K16: 172.10637 | L16: 180.18251 | M16: 194.85158 | N16: 202.82569 | O16: 210.8761 | P16: 208.77959 | Q16: 218.74755 | R16: 228.07937 | S16: 233.25516 | T16: 235.7261 | U16: 240.92253 | V16: 241.06409 | W16: 236.54841 | X16: 228.78174 | Y16: 277.22973 | Z16: 278.37691 | AA16: 283.53182 | AB16: 284.19246 | AC16: 273.88168 | AD16: 280.82046 | AE16: 282.71111 | AF16: 280.38022 | AG16: 283.91372 | AH16: 296.3645 | AI16: 304.37354 | AJ16: 297.93757 | AK16: 303.93105 | AL16: 302.16316 | AM16: 311.38467 | AN16: 309.22564 | AO16: 314.32781 | AP16: 321.57085 | AQ16: 330.50837 | AR16: 338.39281 | AS16: 360.04769 | AT16: 350.52748 | AU16: 365.87468 | AV16: 364.64894 | AW16: 366.75833 | AX16: 356.45256 | AY16: 365.71697 | AZ16: 363.9283 | BA16: 374.53323 | BB16: 385.58107 | BC16: 410.67753 | BD16: 420.90578 | BE16: 438.26559 | BF16: 382.38906 | BG16: 446.83511 | BH16: 458.60371 | BI16: 470.86524 | BJ16: 468.11348 | BK16: 469.51958 | BL16: 473.62344 | BM16: 480.90714 | BN16: 478.24728 | BO16: 498.13323 | BP16: 511.1819 | BQ16: 524.08967 | BR16: 529.54458 | BS16: 557.4673 | BT16: 553.71387 | BU16: 569.86152 | BV16: 565.92799 | BW16: 593.4025 | BX16: 611.79592 | BY16: 646.30896 | BZ16: 661.7343 | CA16: 749.36438 | CB16: 677.86404 | CC16: 696.6052
A17: Water | B17: 2165.0561 | C17: 2297.1505 | D17: 2441.7072 | E17: 2577.9667 | F17: 2681.6101 | K17: 393.12478 | L17: 397.78811 | M17: 404.79354 | N17: 409.46995 | O17: 415.64402 | P17: 420.68376 | Q17: 428.06657 | R17: 436.68542 | S17: 440.78497 | T17: 446.64132 | U17: 454.23847 | V17: 463.26889 | W17: 469.47557 | X17: 474.0847 | Y17: 481.88564 | Z17: 490.22525 | AA17: 502.8843 | AB17: 502.62488 | AC17: 512.01348 | AD17: 518.46336 | AE17: 530.27577 | AF17: 536.1109 | AG17: 545.5687 | AH17: 553.10072 | AI17: 561.56595 | AJ17: 567.97938 | AK17: 580.23721 | AL17: 587.368 | AM17: 599.25416 | AN17: 604.59783 | AO17: 616.09813 | AP17: 621.75712 | AQ17: 633.10375 | AR17: 640.73533 | AS17: 648.32159 | AT17: 655.80608 | AU17: 661.9628 | AV17: 666.40452 | AW17: 673.05645 | AX17: 680.18634 | AY17: 691.54731 | AZ17: 698.09538 | BA17: 705.55612 | BB17: 713.26477 | BC17: 721.45542 | BD17: 725.38768 | BE17: 735.24121 | BF17: 741.47985 | BG17: 754.12433 | BH17: 760.22154 | BI17: 768.94239 | BJ17: 779.62606 | BK17: 798.69217 | BL17: 808.41428 | BM17: 819.5684 | BN17: 828.62438 | BO17: 836.37557 | BP17: 839.77321 | BQ17: 851.65137 | BR17: 863.70849 | BS17: 880.67205 | BT17: 884.92463 | BU17: 895.73851 | BV17: 910.04133 | BW17: 911.34445 | BX17: 912.32806 | BY17: 917.1223 | BZ17: 924.10698 | CA17: 937.01971 | CB17: 942.69242 | CC17: 955.96102
... A33: Activities of Households | B33: 815.59132 | C33: 838.56055 | D33: 866.74265 | E33: 891.35028 | F33: 916.42166 | K33: 176.8075 | L33: 178.5089 | M33: 180.32659 | N33: 182.26459 | O33: 184.36768 | P33: 186.25157 | Q33: 187.86556 | R33: 189.19983 | S33: 190.26808 | T33: 191.28094 | U33: 192.21201 | V33: 193.05882 | W33: 193.84542 | X33: 194.68476 | Y33: 195.55146 | Z33: 196.44706 | AA33: 197.39749 | AB33: 198.48217 | AC33: 199.68085 | AD33: 200.99795 | AE33: 202.46139 | AF33: 204.8907 | AG33: 208.29566 | AH33: 199.94357 | AI33: 204.7196 | AJ33: 208.61337 | AK33: 211.59238 | AL33: 213.6352 | AM33: 214.72066 | AN33: 215.9409 | AO33: 217.29333 | AP33: 218.78776 | AQ33: 220.43437 | AR33: 222.05653 | AS33: 223.6473 | AT33: 225.21208 | AU33: 226.75658 | AV33: 228.3158 | AW33: 229.88331 | AX33: 231.46596 | AY33: 233.07033 | AZ33: 234.68168 | BA33: 236.29337 | BB33: 237.91141 | BC33: 239.54242 | BD33: 241.1751 | BE33: 242.80326 | BF33: 244.43246 | BG33: 246.06921 | BH33: 247.72055 | BI33: 249.44396 | BJ33: 251.18214 | BK33: 252.87801 | BL33: 254.57335 | BM33: 256.32765 | BN33: 258.08109 | BO33: 259.77441 | BP33: 261.48299 | BQ33: 263.3354 | BR33: 265.20368 | BS33: 266.95973 | BT33: 268.7154 | BU33: 270.60323 | BV33: 272.49078 | BW33: 274.24576 | BX33: 276.01332 | BY33: 278.0007 | BZ33: 280.00154 | CA33: 281.80886 | CB33: 281.80886 | CC33: 285.6586
A35: ADJUSTMENTS
A36: Taxes on products | B36: 6129.6819 | C36: 6735.305 | D36: 6880.357 | E36: 7630.631 | F36: 7968.078 | K36: 985.32762 | L36: 912.22689 | M36: 1245.2621 | N36: 1190.9755 | O36: 1143.2165 | P36: 1079.128 | Q36: 1079.2056 | R36: 1088.832 | S36: 1154.2874 | T36: 1241.861 | U36: 1294.1352 | V36: 1223.0444 | W36: 1305.1011 | X36: 1405.6656 | Y36: 1501.3813 | Z36: 1454.8283 | AA36: 1407.7164 | AB36: 1358.8227 | AC36: 1447.8355 | AD36: 1489.8856 | AE36: 1458.2475 | AF36: 1439.4375 | AG36: 1636.0732 | AH36: 1595.9236 | AI36: 1560.7144 | AJ36: 1655.6515 | AK36: 1710.9486 | AL36: 1807.9904 | AM36: 1680.2457 | AN36: 1737.9327 | AO36: 1652.0566 | AP36: 1810.1219 | AQ36: 1858.4261 | AR36: 1817.8528 | AS36: 1948.6611 | AT36: 2005.691 | AU36: 1991.2744 | AV36: 2007.8887 | AW36: 1935.7403 | AX36: 2033.1747 | AY36: 1979.1119 | AZ36: 2073.2514 | BA36: 2129.377 | BB36: 2135.7379 | BC36: 2197.3365 | BD36: 2270.9524 | BE36: 2114.9878 | BF36: 1601.8521 | BG36: 2123.5437 | BH36: 2166.7043 | BI36: 2039.8093 | BJ36: 2366.598 | BK36: 2087.3237 | BL36: 2349.8691 | BM36: 2484.895 | BN36: 2428.7012 | BO36: 2459.0041 | BP36: 2470.6617 | BQ36: 2587.0261 | BR36: 2698.9015 | BS36: 2801.1416 | BT36: 2642.3794 | BU36: 2764.0558 | BV36: 2801.4262 | BW36: 3096.8575 | BX36: 2889.5255 | BY36: 2914.9594 | BZ36: 3024.8849 | CA36: 3200.5564 | CB36: 3095.8858 | CC36: 3326.2404
A37: Source: Uganda Bureau of Statistics

Sheet Original_Growth
A1: Table 4: ORIGINAL UNADJUSTED Value Added at constant 2016/17 prices, PERCENTAGE CHANGE, 2016/17-2025/26
H2: 2008Q1 | I2: 2008Q2 | J2: 2008Q3 | K2: 2008Q4 | L2: 2009Q1 | M2: 2009Q2 | N2: 2009Q3 | O2: 2009Q4 | P2: 2010Q1 | Q2: 2010Q2 | R2: 2010Q3 | S2: 2010Q4 | T2: 2011Q1 | U2: 2011Q2 | V2: 2011Q3 | W2: 2011Q4 | X2: 2012Q1 | Y2: 2012Q2 | Z2: 2012Q3 | AA2: 2012Q4 | AB2: 2013Q1 | AC2: 2013Q2 | AD2: 2013Q3 | AE2: 2013Q4 | AF2: 2014Q1 | AG2: 2014Q2 | AH2: 2014Q3 | AI2: 2014Q4 | AJ2: 2015Q1 | AK2: 2015Q2 | AL2: 2015Q3
H3: 2007/08 | J3: 2008/09 | N3: 2009/10 | R3: 2010/11 | V3: 2011/12 | Z3: 2012/13 | AB3: 2012/13 | AD3: 2013/14 | AE3: 2013/14 | AG3: 2013/14 | AH3: 2014/15 | AI3: 2014/15 | AL3: 2015/16 | AP3: 2016/17 | AT3: 2017/18 | AX3: 2018/19 | BB3: 2019/20 | BF3: 2020/21 | BJ3: 2021/22 | BN3: 2022/23 | BR3: 2023/24 | BV3: 2024/25 | BZ3: 2025/26
B4: 2014/15 | C4: 2015/16 | D4: 2016/17 | E4: 2017/18 | H4: Q3 | I4: Q4 | J4: Q1 | K4: Q2 | L4: Q3 | M4: Q4 | N4: Q1 | O4: Q2 | P4: Q3 | Q4: Q4 | R4: Q1 | S4: Q2 | T4: Q3 | U4: Q4 | V4: Q1 | W4: Q2 | X4: Q3 | Y4: Q4 | Z4: Q1 | AA4: Q2 | AB4: Q3 | AC4: Q4 | AD4: Q1 | AE4: Q2 | AF4: Q3 | AG4: Q4 | AH4: Q1 | AI4: Q2 | AJ4: Q3 | AK4: Q4 | AL4: Q1 | AM4: Q2 | AN4: Q3 | AO4: Q4 | AP4: Q1 | AQ4: Q2 | AR4: Q3 | AS4: Q4 | AT4: Q1 | AU4: Q2 | AV4: Q3 | AW4: Q4 | AX4: Q1 | AY4: Q2 | AZ4: Q3 | BA4: Q4 | BB4: Q1 | BC4: Q2 | BD4: Q3 | BE4: Q4 | BF4: Q1 | BG4: Q2 | BH4: Q3 | BI4: Q4 | BJ4: Q1 | BK4: Q2 | BL4: Q3 | BM4: Q4 | BN4: Q1 | BO4: Q2 | BP4: Q3 | BQ4: Q4 | BR4: Q1 | BS4: Q2 | BT4: Q3 | BU4: Q4 | BV4: Q1 | BW4: Q2 | BX4: Q3 | BY4: Q4 | BZ4: Q1 | CA4: Q2 | CB4: Q3
A5: GDP AT MARKET PRICES | B5: 5.9528577 | C5: 3.7978326 | D5: 3.1314055 | E5: 6.3039238 | L5: #DIV/0! | M5: #DIV/0! | N5: 33.69493 | O5: 37.300782 | P5: 39.835105 | Q5: 29.362128 | R5: 10.032049 | S5: 12.204808 | T5: 8.3208874 | U5: 2.4481829 | V5: 5.7877391 | W5: 0.11611492 | X5: 0.97514865 | Y5: 5.0205571 | Z5: 6.2035339 | AA5: 3.5505873 | AB5: 0.73064936 | AC5: -2.187846 | AD5: -1.9837358 | AE5: 0.96905631 | AF5: 6.4647828 | AG5: 13.298457 | AH5: 3.3627427 | AI5: 11.293963 | AJ5: 5.90739 | AK5: 3.8147373 | AL5: 8.5308298 | AM5: 5.9182597 | AN5: 0.9129889 | AO5: -0.4056158 | AP5: -0.26122599 | AQ5: 0.50756396 | AR5: 6.7464548 | AS5: 6.1811727 | AT5: 7.6808998 | AU5: 6.4828574 | AV5: 5.3854549 | AW5: 5.5652552 | AX5: 5.5745218 | AY5: 5.7290794 | AZ5: 7.6659989 | BA5: 6.8851035 | BB5: 7.5602194 | BC5: 8.3709675 | BD5: 1.1985158 | BE5: -5.5516965 | BF5: -0.40309239 | BG5: 0.032495737 | BH5: 2.804345 | BI5: 13.009861 | BJ5: 2.354724 | BK5: 4.7648514 | BL5: 5.6227189 | BM5: 5.811971 | BN5: 8.7705981 | BO5: 4.3131379 | BP5: 2.2299523 | BQ5: 5.7475112 | BR5: 5.9910476 | BS5: 5.7824205 | BT5: 6.8245768 | BU5: 5.6851104 | BV5: 6.1794064 | BW5: 5.3634777 | BX5: 8.394339 | BY5: 5.5263248 | BZ5: 4.8457919 | CA5: 8.4581777 | CB5: 5.7897133
A6: AGRICULTURE,FORESTRY&FISHING | B6: 2.3044044 | C6: 2.9161633 | D6: 2.7580748 | E6: 4.3891829 | L6: #DIV/0! | M6: #DIV/0! | N6: 5.6521111 | O6: 3.9533585 | P6: 0.61201628 | Q6: -0.62103308 | R6: 1.9224835 | S6: 3.5056409 | T6: 7.1660324 | U6: -0.37990966 | V6: 12.329685 | W6: 0.43304017 | X6: -7.504462 | Y6: -7.1547783 | Z6: 5.1076898 | AA6: 0.091311944 | AB6: 4.3020088 | AC6: -5.7643713 | AD6: 0.32538328 | AE6: 0.80906881 | AF6: -0.75165447 | AG6: 11.844991 | AH6: -6.1756126 | AI6: 10.279645 | AJ6: 5.7804041 | AK6: 4.5476782 | AL6: 1.6889404 | AM6: 0.55991384 | AN6: 9.7631777 | AO6: 1.1821019 | AP6: 1.1733408 | AQ6: 3.2296506 | AR6: 1.0636812 | AS6: 6.0861995 | AT6: 9.6271373 | AU6: 1.4567401 | AV6: 2.5331515 | AW6: 2.0288347 | AX6: 2.172831 | AY6: 4.0142917 | AZ6: 8.010565 | BA6: 8.7388102 | BB6: 6.0482714 | BC6: 7.6423041 | BD6: -1.2938559 | BE6: 5.8976315 | BF6: 6.9495696 | BG6: 7.7622984 | BH6: 0.27724211 | BI6: 0.72534795 | BJ6: 4.382736 | BK6: -1.9940967 | BL6: 4.1826802 | BM6: 10.386736 | BN6: 4.3606145 | BO6: 11.82045 | BP6: 5.4187897 | BQ6: -2.7565253 | BR6: 5.654692 | BS6: 2.0542364 | BT6: 4.0433085 | BU6: 10.57627 | BV6: 6.331648 | BW6: 7.796292 | BX6: 10.306569 | BY6: 3.4652179 | BZ6: 3.0713611 | CA6: 8.7713266 | CB6: 2.1375446
A7: Cash crops | B7: 3.9957006 | C7: 7.9389802 | D7: 9.4039298 | E7: 5.9169904 | L7: #DIV/0! | M7: #DIV/0! | N7: 1.5121553 | O7: -15.108247 | P7: -31.733129 | Q7: -0.3506114 | R7: -7.2665425 | S7: -8.460692 | T7: 35.746082 | U7: -17.186272 | V7: 33.596917 | W7: 16.144209 | X7: -6.6003472 | Y7: 3.1920201 | Z7: -9.3685464 | AA7: -3.4573917 | AB7: 10.617826 | AC7: 1.0135119 | AD7: 11.75711 | AE7: 7.0214637 | AF7: -8.3418856 | AG7: -10.506839 | AH7: -1.2674269 | AI7: -9.0973601 | AJ7: 13.62591 | AK7: 16.208281 | AL7: 19.347242 | AM7: 12.842381 | AN7: 2.2577883 | AO7: -2.1089741 | AP7: -16.007927 | AQ7: 23.751211 | AR7: 12.020404 | AS7: 19.986916 | AT7: 41.223752 | AU7: -4.0493176 | AV7: 2.0541554 | AW7: -7.7408987 | AX7: -0.45776578 | AY7: 6.5620954 | AZ7: 2.36535 | BA7: 13.169991 | BB7: 2.5118453 | BC7: 8.9502677 | BD7: 17.41402 | BE7: -0.52227954 | BF7: 7.7596194 | BG7: 11.499033 | BH7: 11.334927 | BI7: 21.942714 | BJ7: 23.374182 | BK7: 4.9990053 | BL7: -3.8321506 | BM7: 0.65915566 | BN7: 0.4069914 | BO7: -5.2810114 | BP7: 7.9503397 | BQ7: -0.95714691 | BR7: 6.3753418 | BS7: 15.358235 | BT7: 16.13052 | BU7: 10.449158 | BV7: 16.47863 | BW7: 9.5727556 | BX7: 8.954976 | BY7: 10.713984 | BZ7: 7.0389932 | CA7: 12.569547 | CB7: 7.1658965
A8: Food crops | B8: 2.1958836 | C8: 1.2662343 | D8: 2.2480641 | E8: 8.5502917 | L8: #DIV/0! | M8: #DIV/0! | N8: 7.2807859 | O8: 8.4051257 | P8: 2.6822972 | Q8: 0.76046168 | R8: 0.75597836 | S8: 1.1325476 | T8: 3.5300904 | U8: 4.2924389 | V8: 8.0825596 | W8: 7.0790314 | X8: -13.881936 | Y8: -14.319759 | Z8: 14.813068 | AA8: -16.000421 | AB8: -6.4526684 | AC8: -7.5618959 | AD8: -2.4416307 | AE8: -0.38799783 | AF8: 7.1897121 | AG8: 15.915017 | AH8: -10.040108 | AI8: 28.100238 | AJ8: 5.7938208 | AK8: 2.0250088 | AL8: 0.59348639 | AM8: -0.6581569 | AN8: 6.4936242 | AO8: 0.94365384 | AP8: 1.7376881 | AQ8: -3.4995387 | AR8: 6.1821644 | AS8: 6.4109612 | AT8: 11.752214 | AU8: 7.8612466 | AV8: 8.578837 | AW8: 3.8036746 | AX8: 0.72483173 | AY8: -2.1501749 | AZ8: 3.5348213 | BA8: 5.5179991 | BB8: 4.8419209 | BC8: 8.5211992 | BD8: -11.292646 | BE8: 12.370584 | BF8: 10.54684 | BG8: 10.2584 | BH8: -8.0497943 | BI8: -4.6594018 | BJ8: 1.7602391 | BK8: -4.8277555 | BL8: 5.3530803 | BM8: 14.409511 | BN8: 7.5815419 | BO8: 19.408815 | BP8: -4.386021 | BQ8: -8.1731832 | BR8: 5.0637427 | BS8: -0.25582669 | BT8: 6.9905976 | BU8: 10.315924 | BV8: 5.3332431 | BW8: 7.0282315 | BX8: 3.2973958 | BY8: 2.167834 | BZ8: -0.5469674 | CA8: 7.7062476 | CB8: 5.2493011
A9: Livestock | B9: 2.9330424 | C9: 2.7787733 | D9: 7.0125461 | E9: 7.1276597 | L9: #DIV/0! | M9: #DIV/0! | N9: 0.94042714 | O9: 2.6371076 | P9: 3.2244115 | Q9: 2.6327722 | R9: 3.397466 | S9: 2.3389539 | T9: 1.4956765 | U9: 2.0770411 | V9: 2.3757114 | W9: 2.4730064 | X9: 2.4625259 | Y9: 2.0282567 | Z9: 0.57889563 | AA9: -0.50298226 | AB9: 5.1923414 | AC9: 4.6244735 | AD9: 5.2753134 | AE9: 6.4672803 | AF9: -0.47031964 | AG9: 0.074276939 | AH9: 1.8631848 | AI9: 2.2191927 | AJ9: 3.8682667 | AK9: 3.7854505 | AL9: 2.2562049 | AM9: 2.1085281 | AN9: 2.2982238 | AO9: 4.4340431 | AP9: 5.6220551 | AQ9: 7.3369226 | AR9: 8.0046056 | AS9: 7.0651484 | AT9: 8.1876515 | AU9: 6.6571546 | AV9: 7.0290372 | AW9: 6.6751637 | AX9: 6.5875482 | AY9: 7.677242 | AZ9: 7.0289477 | BA9: 8.065715 | BB9: 7.8265223 | BC9: 7.8686926 | BD9: 8.2357916 | BE9: 7.6568416 | BF9: 7.5492368 | BG9: 7.5756165 | BH9: 7.7063501 | BI9: 8.311535 | BJ9: 8.3550688 | BK9: 8.2416626 | BL9: 8.1934317 | BM9: 8.4297719 | BN9: 8.7369443 | BO9: 8.8952394 | BP9: 9.5537611 | BQ9: 8.1708417 | BR9: 7.7580832 | BS9: 8.032551 | BT9: 7.2780032 | BU9: 8.46718 | BV9: 8.4496924 | BW9: 8.5973316 | BX9: 9.1124298 | BY9: 8.8308919 | BZ9: 9.2580536 | CA9: 9.2222406 | CB9: 6.5613119
A10: Agriculture Support Services | B10: 17.623476 | C10: -4.6053937 | D10: 3.7961726 | E10: -0.36611784 | L10: #DIV/0! | M10: #DIV/0! | N10: -0.38087512 | O10: 0.68031163 | P10: 12.761897 | Q10: 13.904349 | R10: 11.277943 | S10: 5.9545126 | T10: -1.7998003 | U10: -6.1090518 | V10: -13.887458 | W10: -15.721476 | X10: -14.970096 | Y10: -8.1387394 | Z10: 5.1340789 | AA10: 10.473802 | AB10: 9.6090127 | AC10: 8.7000035 | AD10: -1.0716972 | AE10: -2.6862889 | AF10: -2.1586101 | AG10: 5.8120434 | AH10: 19.154046 | AI10: 21.092848 | AJ10: 18.562431 | AK10: 13.134131 | AL10: -0.92533233 | AM10: -6.4259452 | AN10: -8.6389378 | AO10: -6.2758857 | AP10: 1.7603391 | AQ10: 5.0997732 | AR10: 4.9594275 | AS10: 5.1449869 | AT10: 0.18907177 | AU10: -1.4871507 | AV10: -2.0227286 | AW10: 0.38873457 | AX10: 4.9669107 | AY10: 9.5502966 | AZ10: 8.709657 | BA10: 13.370715 | BB10: 17.775003 | BC10: 22.228107 | BD10: -1.3210824 | BE10: -14.542154 | BF10: -7.1240347 | BG10: -9.255361 | BH10: 27.122216 | BI10: 16.362482 | BJ10: 7.3430525 | BK10: 2.4612239 | BL10: 3.7826391 | BM10: 2.4563964 | BN10: 2.6395159 | BO10: 4.2585086 | BP10: 0.59723142 | BQ10: 1.0316667 | BR10: 5.3327958 | BS10: 7.2751607 | BT10: 8.3039338 | BU10: 8.7430127 | BV10: 4.2833839 | BW10: -3.3029737 | BX10: -0.82532569 | BY10: 16.641687 | BZ10: -11.794275 | CA10: 0.20581178 | CB10: 11.193266
A11: Forestry | B11: 1.6606621 | C11: 4.7495611 | D11: 3.5049109 | E11: 3.3705046 | L11: #DIV/0! | M11: #DIV/0! | N11: 6.0048778 | O11: 13.241647 | P11: 19.854948 | Q11: -9.4042152 | R11: 17.650663 | S11: 27.442134 | T11: 9.4633267 | U11: -7.8639222 | V11: 43.783599 | W11: -31.045437 | X11: -8.1143891 | Y11: 2.2368292 | Z11: -29.06998 | AA11: 78.74126 | AB11: 30.437963 | AC11: 2.2468244 | AD11: 11.229996 | AE11: 0.21979855 | AF11: -8.3300105 | AG11: 13.999192 | AH11: 6.1871458 | AI11: -10.584481 | AJ11: 7.2564651 | AK11: 6.0679469 | AL11: -5.6093743 | AM11: -3.8437229 | AN11: 29.111269 | AO11: 0.25678097 | AP11: 9.2270813 | AQ11: 12.389945 | AR11: -13.360354 | AS11: 10.596833 | AT11: 3.0115427 | AU11: 1.1178658 | AV11: 3.9158384 | AW11: 5.3555936 | AX11: 3.645907 | AY11: 5.2681081 | AZ11: 2.5632508 | BA11: 3.0207938 | BB11: 4.0520984 | BC11: 4.8675828 | BD11: 4.6282912 | BE11: -0.32500304 | BF11: -2.7189866 | BG11: 3.7179826 | BH11: 5.4636969 | BI11: 5.186329 | BJ11: 4.8007818 | BK11: -2.9147167 | BL11: 5.2554205 | BM11: 5.5254169 | BN11: 4.0799476 | BO11: 3.8657717 | BP11: 2.5433767 | BQ11: 2.2167842 | BR11: 5.376921 | BS11: 2.7213663 | BT11: -5.8953936 | BU11: 10.3616 | BV11: 3.761795 | BW11: 5.153076 | BX11: 7.271286 | BY11: -2.0979444 | BZ11: 9.7363837 | CA11: 8.2538254 | CB11: -4.8438115
A12: Fishing | B12: 1.4695056 | C12: 4.8035635 | D12: -7.7597972 | E12: -25.190022 | L12: #DIV/0! | M12: #DIV/0! | N12: 1.1171875 | O12: -1.6733791 | P12: 9.119024 | Q12: 1.911654 | R12: -2.5359079 | S12: -0.13367641 | T12: 1.4821605 | U12: -1.6349547 | V12: 0.67050742 | W12: -0.87824913 | X12: 4.5526978 | Y12: 0.60250211 | Z12: 6.1274143 | AA12: 6.4110624 | AB12: -0.2278629 | AC12: -26.670629 | AD12: -2.2970431 | AE12: -5.4671575 | AF12: -4.4614015 | AG12: 29.152004 | AH12: -2.4163034 | AI12: 3.1101732 | AJ12: -2.1008085 | AK12: 7.656298 | AL12: 7.4823292 | AM12: 0.65437818 | AN12: 9.1880585 | AO12: 2.2828057 | AP12: -4.204575 | AQ12: -1.9275876 | AR12: -10.109137 | AS12: -14.947848 | AT12: -24.514914 | AU12: -30.492374 | AV12: -30.971737 | AW12: -13.25503 | AX12: 13.665911 | AY12: 36.768289 | AZ12: 65.935276 | BA12: 43.486083 | BB12: 26.504438 | BC12: 5.7008185 | BD12: -9.9070707 | BE12: -14.984255 | BF12: -13.489349 | BG12: -3.8473233 | BH12: -9.4313234 | BI12: -8.1342105 | BJ12: 0.69982751 | BK12: -12.770556 | BL12: 4.4869431 | BM12: 10.69323 | BN12: -38.932895 | BO12: 16.202901 | BP12: 37.628249 | BQ12: -0.13700969 | BR12: 9.7010594 | BS12: -17.202043 | BT12: -10.522378 | BU12: 18.473315 | BV12: -0.64729068 | BW12: 15.015903 | BX12: 44.650443 | BY12: 3.1929969 | BZ12: 23.72085 | CA12: 9.4512128 | CB12: -10.327195
A13: INDUSTRY | B13: 8.986434 | C13: 3.0081509 | D13: 6.8481014 | E13: 4.8425825 | L13: #DIV/0! | M13: #DIV/0! | N13: 234.94004 | O13: 233.47993 | P13: 307.32062 | Q13: 169.41417 | R13: 8.1880075 | S13: 16.446248 | T13: 6.28642 | U13: 7.7505946 | V13: 4.1845042 | W13: -2.8790253 | X13: 6.5237527 | Y13: 4.9942423 | Z13: 4.3734039 | AA13: 4.1773834 | AB13: -0.43333384 | AC13: -5.6839318 | AD13: -1.2535665 | AE13: -0.011531378 | AF13: 5.0205984 | AG13: 15.485678 | AH13: 9.3112698 | AI13: 11.695546 | AJ13: 7.7457436 | AK13: 7.4495173 | AL13: 10.777186 | AM13: 7.929001 | AN13: -3.6241797 | AO13: -2.2863059 | AP13: -0.60233732 | AQ13: 4.5995317 | AR13: 16.225662 | AS13: 7.9277803 | AT13: 5.4100804 | AU13: 2.8953153 | AV13: 3.1727275 | AW13: 7.983336 | AX13: 9.0370626 | AY13: 10.33215 | AZ13: 9.3709856 | BA13: 7.4735698 | BB13: 10.161699 | BC13: 10.14047 | BD13: 2.9512124 | BE13: -9.7908167 | BF13: -2.2068791 | BG13: -1.4690787 | BH13: 2.1478318 | BI13: 17.497705 | BJ13: -0.121214 | BK13: 7.8245859 | BL13: 5.5285218 | BM13: 7.0691761 | BN13: 12.288976 | BO13: -2.3754988 | BP13: 0.71107424 | BQ13: 6.3594382 | BR13: 9.8953589 | BS13: 4.4842493 | BT13: 6.7230965 | BU13: 1.0980079 | BV13: 5.1231152 | BW13: 7.6514026 | BX13: 7.3997957 | BY13: 7.5685941 | BZ13: 5.9747366 | CA13: 12.257991 | CB13: 5.9259193
A14: Mining & quarrying | B14: 18.058674 | C14: 12.424053 | D14: 32.720646 | E14: -3.9840941 | L14: #DIV/0! | M14: #DIV/0! | N14: -50.859855 | O14: -0.26111722 | P14: 62.98864 | Q14: 81.33978 | R14: 117.22024 | S14: 53.592865 | T14: 24.09584 | U14: -27.636519 | V14: -53.682875 | W14: -58.202553 | X14: 5.5360443 | Y14: 120.46961 | Z14: 154.62447 | AA14: 71.478778 | AB14: -6.3718661 | AC14: -38.651417 | AD14: -31.955673 | AE14: -23.596609 | AF14: 44.767416 | AG14: 34.714197 | AH14: 6.9959713 | AI14: 87.145498 | AJ14: 2.073005 | AK14: 19.360904 | AL14: 61.265479 | AM14: 35.361082 | AN14: -6.4573955 | AO14: -12.968443 | AP14: -1.0176412 | AQ14: 27.163369 | AR14: 42.921379 | AS14: 66.601672 | AT14: 13.006608 | AU14: -18.740982 | AV14: -9.5661008 | AW14: -0.57039491 | AX14: 24.298931 | AY14: 20.557187 | AZ14: 34.417285 | BA14: -4.1933679 | BB14: 14.438809 | BC14: 74.995995 | BD14: 11.895181 | BE14: -17.180262 | BF14: 41.884989 | BG14: -1.1671934 | BH14: -22.75651 | BI14: 16.729088 | BJ14: -56.35978 | BK14: 49.349266 | BL14: 40.747538 | BM14: 85.318163 | BN14: 88.87278 | BO14: -51.808093 | BP14: -24.749961 | BQ14: 52.798407 | BR14: 98.898205 | BS14: 96.165475 | BT14: 4.0587122 | BU14: -75.704656 | BV14: -8.5784039 | BW14: 9.7080505 | BX14: -0.43884077 | BY14: 43.608635 | BZ14: -10.422763 | CA14: 27.326816 | CB14: 13.257908
A15: Manufacturing | B15: 11.633422 | C15: 0.59506005 | D15: 3.5698101 | E15: 4.6246636 | L15: #DIV/0! | M15: #DIV/0! | N15: #DIV/0! | O15: #DIV/0! | P15: #DIV/0! | Q15: #DIV/0! | R15: 10.71661 | S15: 20.209227 | T15: -1.4805195 | U15: 3.3232824 | V15: 3.6128761 | W15: -3.9220163 | X15: 10.295395 | Y15: 1.3608132 | Z15: -2.0484117 | AA15: -2.1751518 | AB15: -5.0295597 | AC15: -0.47173467 | AD15: -3.2986564 | AE15: -1.1050127 | AF15: 4.0433016 | AG15: 8.8933069 | AH15: 14.122274 | AI15: 14.675857 | AJ15: 10.200809 | AK15: 8.0981097 | AL15: 10.636181 | AM15: 6.693805 | AN15: -10.781974 | AO15: -3.2429758 | AP15: -5.7702586 | AQ15: -0.1731616 | AR15: 19.811423 | AS15: 2.5311368 | AT15: 5.4633796 | AU15: 4.7481879 | AV15: 1.5302076 | AW15: 7.0004646 | AX15: 7.0445137 | AY15: 9.3039472 | AZ15: 7.3653602 | BA15: 7.0665881 | BB15: 11.727523 | BC15: 8.7620878 | BD15: -1.0447553 | BE15: -14.187631 | BF15: -3.6745882 | BG15: -5.2621545 | BH15: 2.2128016 | BI15: 19.282766 | BJ15: -5.9504663 | BK15: 6.4696502 | BL15: 7.8324133 | BM15: 7.0007348 | BN15: 15.63553 | BO15: 1.340548 | BP15: -1.3522881 | BQ15: -1.6233706 | BR15: 4.7048134 | BS15: -1.6219041 | BT15: 4.9918833 | BU15: 11.002473 | BV15: 6.180753 | BW15: 7.7516204 | BX15: 5.2329828 | BY15: 3.4531782 | BZ15: 4.7538875 | CA15: 8.9249589 | CB15: 4.7910044
A16: Electricity | B16: 5.6880806 | C16: 3.9807545 | D16: 9.786431 | E16: 5.3830679 | L16: #DIV/0! | M16: #DIV/0! | N16: 22.526607 | O16: 15.871173 | P16: 12.263682 | Q16: 12.450928 | R16: 10.612425 | S16: 12.906677 | T16: 10.137244 | U16: 5.6930714 | V16: 1.4118621 | W16: -2.9459426 | X16: 15.070072 | Y16: 15.478383 | Z16: 19.862072 | AA16: 24.219904 | AB16: -1.2076798 | AC16: 0.87778451 | AD16: -0.28945829 | AE16: -1.3414313 | AF16: 3.6629098 | AG16: 5.5352211 | AH16: 7.6623905 | AI16: 6.2619796 | AJ16: 7.0504995 | AK16: 1.9565988 | AL16: 2.3034612 | AM16: 3.7887364 | AN16: 3.4207632 | AO16: 6.4229179 | AP16: 6.141503 | AQ16: 9.4323279 | AR16: 14.545286 | AS16: 9.0047431 | AT16: 10.700578 | AU16: 7.7590666 | AV16: 1.8638188 | AW16: 1.6903329 | AX16: -0.043102909 | AY16: -0.19762631 | AZ16: 2.1198978 | BA16: 8.1717764 | BB16: 12.293811 | BC16: 15.65624 | BD16: 17.016475 | BE16: -0.82784518 | BF16: 8.8043734 | BG16: 8.9563825 | BH16: 7.4383342 | BI16: 22.418117 | BJ16: 5.076699 | BK16: 3.2750999 | BL16: 2.1326469 | BM16: 2.1648167 | BN16: 6.0942389 | BO16: 7.9300241 | BP16: 8.9793904 | BQ16: 10.726104 | BR16: 11.911286 | BS16: 8.3203213 | BT16: 8.7335926 | BU16: 6.8706984 | BV16: 6.4461531 | BW16: 10.489541 | BX16: 13.415091 | BY16: 16.929063 | BZ16: 26.282647 | CA16: 10.799047 | CB16: 7.7820731
A17: Water | B17: 6.1012027 | C17: 6.2928695 | D17: 5.5805016 | E17: 4.0203532 | L17: #DIV/0! | M17: #DIV/0! | N17: 5.7282691 | O17: 5.7557426 | P17: 5.7493582 | Q17: 6.6465101 | R17: 6.048673 | S17: 6.1703257 | T17: 6.1139791 | U17: 6.0875562 | V17: 6.5089776 | W17: 6.144388 | X17: 6.0864859 | Y17: 5.8187288 | Z17: 7.1161806 | AA17: 6.0200586 | AB17: 6.2520744 | AC17: 5.760233 | AD17: 5.4468733 | AE17: 6.6622288 | AF17: 6.5535809 | AG17: 6.6807725 | AH17: 5.9007383 | AI17: 5.9443831 | AJ17: 6.3545636 | AK17: 6.1954863 | AL17: 6.7112697 | AM17: 6.4471435 | AN17: 6.1803885 | AO17: 5.8547828 | AP17: 5.6486196 | AQ17: 5.9771139 | AR17: 5.2302482 | AS17: 5.4762481 | AT17: 4.5583456 | AU17: 4.0062086 | AV17: 3.8152152 | AW17: 3.717601 | AX17: 4.4692096 | AY17: 4.7554987 | AZ17: 4.8286695 | BA17: 4.8631427 | BB17: 4.324811 | BC17: 3.9095375 | BD17: 4.2073319 | BE17: 3.9557655 | BF17: 4.5281955 | BG17: 4.8021026 | BH17: 4.5836906 | BI17: 5.1446048 | BJ17: 5.9098788 | BK17: 6.3393024 | BL17: 6.5838491 | BM17: 6.2848493 | BN17: 4.7181389 | BO17: 3.8790669 | BP17: 3.9146173 | BQ17: 4.2340185 | BR17: 5.2962425 | BS17: 5.3766201 | BT17: 5.1766663 | BU17: 5.3644072 | BV17: 3.4828396 | BW17: 3.0966966 | BX17: 2.3872795 | BY17: 1.5456048 | BZ17: 2.8172954 | CA17: 3.3282282 | CB17: 4.2348462
A18: Construction | B18: 1.9431525 | C18: 7.2975247 | D18: 11.723721 | E18: 7.6005846 | L18: #DIV/0! | M18: #DIV/0! | N18: 44.71781 | O18: 25.525464 | P18: 43.45619 | Q18: -29.255466 | R18: -9.8134064 | S18: 5.4440954 | T18: 35.774416 | U18: 34.890853 | V18: 19.300791 | W18: 5.6888596 | X18: -6.944307 | Y18: 0.61700084 | Z18: 7.84074 | AA18: 16.418834 | AB18: 15.037148 | AC18: -20.557977 | AD18: 8.2998262 | AE18: 2.8466924 | AF18: 1.2242127 | AG18: 46.165913 | AH18: -1.6452512 | AI18: 2.027972 | AJ18: 2.0593874 | AK18: 5.1926902 | AL18: 7.8942269 | AM18: 9.932505 | AN18: 15.153041 | AO18: -2.6291625 | AP18: 11.799601 | AQ18: 13.793986 | AR18: 6.8802813 | AS18: 14.4937 | AT18: 2.9974711 | AU18: 0.27423972 | AV18: 11.334893 | AW18: 16.159827 | AX18: 15.56265 | AY18: 16.406974 | AZ18: 13.141968 | BA18: 11.970939 | BB18: 6.9938076 | BC18: 5.6023043 | BD18: 7.8036239 | BE18: -4.5742311 | BF18: -13.844274 | BG18: 4.0347404 | BH18: 6.2656775 | BI18: 17.641804 | BJ18: 35.586342 | BK18: 3.2452976 | BL18: -5.8444526 | BM18: -4.4513951 | BN18: -0.44535847 | BO18: -0.090876627 | BP18: 9.8392089 | BQ18: 10.672643 | BR18: 2.2440482 | BS18: 4.160566 | BT18: 11.406002 | BU18: 10.941339 | BV18: 9.2645718 | BW18: 7.9062767 | BX18: 14.00141 | BY18: 13.029297 | BZ18: 11.659361 | CA18: 19.416736 | CB18: 7.2391745
A19: SERVICES | B19: 5.7252602 | C19: 4.9685517 | D19: 0.10803461 | E19: 8.516257 | L19: #DIV/0! | M19: #DIV/0! | N19: 20.374508 | O19: 22.213773 | P19: 26.306818 | Q19: 22.211881 | R19: 19.162203 | S19: 14.759592 | T19: 8.6587584 | U19: 0.010149722 | V19: 1.1068078 | W19: -0.01394228 | X19: 0.034092216 | Y19: 10.452351 | Z19: 7.8643215 | AA19: 6.1727909 | AB19: 0.46720325 | AC19: 0.94096569 | AD19: -4.8960841 | AE19: 0.93185245 | AF19: 9.7402359 | AG19: 13.724574 | AH19: 7.3375093 | AI19: 11.073626 | AJ19: 5.1283416 | AK19: 0.19552666 | AL19: 12.275885 | AM19: 7.7511857 | AN19: 0.40701708 | AO19: -0.16135333 | AP19: -2.4907341 | AQ19: -3.736009 | AR19: 2.5175007 | AS19: 4.5088343 | AT19: 7.7450719 | AU19: 10.715277 | AV19: 9.1042744 | AW19: 6.5993997 | AX19: 6.9344151 | AY19: 4.3196164 | AZ19: 6.1470326 | BA19: 5.9465301 | BB19: 6.576558 | BC19: 7.4738828 | BD19: 1.5205013 | BE19: -5.5218535 | BF19: -3.6793477 | BG19: -2.042432 | BH19: 5.2788271 | BI19: 12.807022 | BJ19: 2.9730667 | BK19: 5.8856353 | BL19: 3.9715352 | BM19: 3.3469497 | BN19: 8.6703688 | BO19: 4.7269825 | BP19: 1.5420013 | BQ19: 8.9260995 | BR19: 2.6713069 | BS19: 8.3223194 | BT19: 8.0640636 | BU19: 6.505087 | BV19: 5.9861799 | BW19: 2.2328288 | BX19: 8.7021833 | BY19: 4.9505378 | BZ19: 5.6881024 | CA19: 6.2357551 | CB19: 5.8655812
A20: Trade & Repairs | B20: 3.1570185 | C20: 3.4791905 | D20: -1.2533622 | E20: 7.473792 | L20: #DIV/0! | M20: #DIV/0! | N20: 20.268383 | O20: 10.380386 | P20: -9.1627306 | Q20: -10.581326 | R20: -7.5509079 | S20: 9.2568999 | T20: 41.782641 | U20: -1.9789563 | V20: 17.61156 | W20: -2.263554 | X20: -21.039462 | Y20: 16.157395 | Z20: 7.2486169 | AA20: 6.3085471 | AB20: -1.5791911 | AC20: -1.1073486 | AD20: -9.3763106 | AE20: -2.0957992 | AF20: 2.401113 | AG20: 3.1364556 | AH20: 2.0151967 | AI20: 8.2903567 | AJ20: 2.826001 | AK20: 0.066508127 | AL20: 11.372985 | AM20: 9.5930443 | AN20: -4.7396736 | AO20: -2.763918 | AP20: -8.1649603 | AQ20: -7.382122 | AR20: 8.045278 | AS20: 4.9308722 | AT20: 5.6911985 | AU20: 11.579986 | AV20: 7.5561948 | AW20: 5.3211438 | AX20: 7.5541307 | AY20: 3.2159309 | AZ20: 6.1121135 | BA20: 2.8317832 | BB20: 4.3666528 | BC20: 5.0990698 | BD20: -3.1770575 | BE20: -12.062973 | BF20: -2.7632329 | BG20: -7.1751541 | BH20: -2.8962622 | BI20: 12.701759 | BJ20: -5.4382054 | BK20: 4.2343219 | BL20: 9.1541843 | BM20: 6.8821159 | BN20: 5.9899292 | BO20: 2.2153883 | BP20: -0.69557446 | BQ20: 7.7560919 | BR20: 12.084538 | BS20: 8.5197677 | BT20: 9.5936596 | BU20: 7.1958738 | BV20: 10.270053 | BW20: 7.4696605 | BX20: 11.354877 | BY20: 7.0089552 | BZ20: 6.1769751 | CA20: 4.8980027 | CB20: 5.466652
A21: Transportation & Storage | B21: 6.5628816 | C21: 8.154303 | D21: 2.3370666 | E21: 11.254778 | L21: #DIV/0! | M21: #DIV/0! | N21: 10.544353 | O21: 12.490829 | P21: 6.6263228 | Q21: 5.1662475 | R21: 2.8650279 | S21: 6.8221045 | T21: 21.844549 | U21: 6.8087879 | V21: 19.100671 | W21: 9.0068343 | X21: -3.0398189 | Y21: 7.6086893 | Z21: 2.9996533 | AA21: 6.0510768 | AB21: 4.0109169 | AC21: 6.5859376 | AD21: 2.1780939 | AE21: 6.0730267 | AF21: 9.2002037 | AG21: 6.9615343 | AH21: 6.0290353 | AI21: 5.8599945 | AJ21: 6.0527963 | AK21: 8.2575189 | AL21: 10.144508 | AM21: 15.554801 | AN21: 4.4986419 | AO21: 2.8959227 | AP21: 0.51489418 | AQ21: -4.1751833 | AR21: 5.516088 | AS21: 7.8892464 | AT21: 11.035093 | AU21: 11.993096 | AV21: 12.34121 | AW21: 9.7370847 | AX21: 3.0913646 | AY21: 0.40709826 | AZ21: 0.45822365 | BA21: -0.51614336 | BB21: 4.0784379 | BC21: 1.8562484 | BD21: -2.3113101 | BE21: -10.31746 | BF21: -7.2732658 | BG21: -2.6775396 | BH21: 1.4133737 | BI21: 8.4136611 | BJ21: -8.6920748 | BK21: -2.1481696 | BL21: 3.1876391 | BM21: -7.7795877 | BN21: -6.7600285 | BO21: -2.3159242 | BP21: -9.5641621 | BQ21: -2.4768772 | BR21: 6.0987949 | BS21: 6.4178496 | BT21: 12.48134 | BU21: 16.241652 | BV21: 14.167627 | BW21: 9.7856021 | BX21: 13.148343 | BY21: 11.964916 | BZ21: 7.5558844 | CA21: 11.907258 | CB21: 4.9681758
A22: Accommodation & Food Service | B22: -0.45644771 | C22: 5.7212564 | D22: 19.677317 | E22: 10.667801 | L22: #DIV/0! | M22: #DIV/0! | N22: -1.776025 | O22: 21.371315 | P22: 22.938235 | Q22: 23.691114 | R22: 3.229702 | S22: -1.3763632 | T22: 13.813138 | U22: 11.823792 | V22: 21.848179 | W22: 12.641349 | X22: 2.0492841 | Y22: 2.1248052 | Z22: 8.9607702 | AA22: -2.1842637 | AB22: 7.5221553 | AC22: 5.7316891 | AD22: 0.32799937 | AE22: 9.2670717 | AF22: 17.674864 | AG22: 8.6710084 | AH22: 5.3730573 | AI22: 2.9781611 | AJ22: -7.2829481 | AK22: -2.1149579 | AL22: -1.3616365 | AM22: 6.5607916 | AN22: 12.732639 | AO22: 5.4675606 | AP22: 18.569913 | AQ22: 22.009302 | AR22: 10.226658 | AS22: 28.965844 | AT22: 18.805725 | AU22: 11.842225 | AV22: 8.6554234 | AW22: 3.7948276 | AX22: 0.0097587292 | AY22: -0.36429117 | AZ22: -0.89765327 | BA22: 3.1574909 | BB22: 5.1291927 | BC22: 9.2486383 | BD22: -2.7444655 | BE22: -45.465491 | BF22: -24.632909 | BG22: -18.671665 | BH22: 2.6817194 | BI22: 77.34925 | BJ22: 1.451578 | BK22: 15.497312 | BL22: -19.397604 | BM22: -5.1180401 | BN22: 0.67308436 | BO22: -0.4582821 | BP22: 14.372517 | BQ22: 35.226802 | BR22: 22.874902 | BS22: -1.8573779 | BT22: 13.915446 | BU22: 18.838061 | BV22: 12.978553 | BW22: 17.288332 | BX22: 14.459729 | BY22: -17.655807 | BZ22: 17.134519 | CA22: 15.894795 | CB22: 3.815186
A23: Information & Communication | B23: -1.7587397 | C23: 14.070284 | D23: 19.002555 | E23: 10.414437 | L23: #DIV/0! | M23: #DIV/0! | N23: #DIV/0! | O23: #DIV/0! | P23: #DIV/0! | Q23: #DIV/0! | R23: 53.48028 | S23: 8.8624041 | T23: 8.3163886 | U23: 23.42768 | V23: 11.285075 | W23: 21.447572 | X23: 30.807698 | Y23: 11.285441 | Z23: 18.688885 | AA23: 15.324429 | AB23: 16.671211 | AC23: 21.365158 | AD23: 25.919988 | AE23: 19.076377 | AF23: 5.8331639 | AG23: 8.4851333 | AH23: -6.4268093 | AI23: -2.5969511 | AJ23: 2.3692639 | AK23: -0.039846473 | AL23: 13.132878 | AM23: 12.834932 | AN23: 2.7876395 | AO23: 27.671485 | AP23: 14.672895 | AQ23: 18.612605 | AR23: 35.864433 | AS23: 9.4178929 | AT23: 14.522214 | AU23: 10.766162 | AV23: 10.180792 | AW23: 6.5568626 | AX23: -2.5380986 | AY23: -9.3444254 | AZ23: -11.275812 | BA23: -3.7987845 | BB23: 20.384568 | BC23: 30.248183 | BD23: 20.246897 | BE23: 7.9589769 | BF23: 1.0803687 | BG23: 1.2448219 | BH23: 16.61957 | BI23: 30.792038 | BJ23: 14.373045 | BK23: 9.5718175 | BL23: 4.8930805 | BM23: 1.732853 | BN23: 5.4128749 | BO23: 5.1811211 | BP23: 12.126266 | BQ23: 18.248584 | BR23: 26.710251 | BS23: 17.569141 | BT23: 1.079037 | BU23: -17.72262 | BV23: 0.99376708 | BW23: -1.7658146 | BX23: 16.94567 | BY23: 13.240867 | BZ23: -5.2668292 | CA23: 4.2112695 | CB23: 15.717119
A24: Financial & Insurance | B24: 10.894163 | C24: 9.6069865 | D24: -4.1440916 | E24: 2.3140214 | L24: #DIV/0! | M24: #DIV/0! | N24: -6.1609466 | O24: -5.2972818 | P24: 2.2528894 | Q24: 13.036218 | R24: 60.710204 | S24: 8.189724 | T24: -7.1575803 | U24: 10.007787 | V24: -11.981267 | W24: -0.17037812 | X24: 18.822457 | Y24: -5.1512803 | Z24: 6.1222567 | AA24: 9.0480935 | AB24: 6.2953719 | AC24: 11.050906 | AD24: 7.9239359 | AE24: 12.838971 | AF24: 25.024072 | AG24: 25.65776 | AH24: 13.274047 | AI24: 25.209166 | AJ24: 5.372986 | AK24: 1.6879622 | AL24: 20.530126 | AM24: 2.0587598 | AN24: 10.851678 | AO24: 5.9712261 | AP24: -8.3042828 | AQ24: -8.9860086 | AR24: -1.1196075 | AS24: 2.2443905 | AT24: 4.0745545 | AU24: 9.1260548 | AV24: -4.577274 | AW24: 1.2949706 | AX24: 4.1027252 | AY24: 6.2305067 | AZ24: 18.775487 | BA24: 15.473417 | BB24: 19.678301 | BC24: 18.308975 | BD24: 9.5479128 | BE24: -7.4284076 | BF24: 2.3717188 | BG24: -1.6956533 | BH24: 10.162069 | BI24: 23.46424 | BJ24: -0.29319417 | BK24: 3.1738879 | BL24: 6.4294172 | BM24: 8.4185047 | BN24: 2.2213559 | BO24: 14.737178 | BP24: -19.167856 | BQ24: 6.7280304 | BR24: 1.6795706 | BS24: -0.95144996 | BT24: 5.7580672 | BU24: 1.724074 | BV24: 11.211623 | BW24: 1.8307038 | BX24: 6.2436121 | BY24: 1.1396386 | BZ24: 7.7896357 | CA24: 7.6683532 | CB24: 5.5863164
A25: Real Estate Activities | B25: 6.5071083 | C25: 6.0845539 | D25: 1.6345732 | E25: 11.601503 | L25: #DIV/0! | M25: #DIV/0! | N25: -1.7674183 | O25: 1.8462789 | P25: 8.5218908 | Q25: 10.645227 | R25: 13.054438 | S25: 0.55735508 | T25: 3.7717852 | U25: -4.6063576 | V25: -4.1168123 | W25: 3.8253167 | X25: 2.5775421 | Y25: 16.015035 | Z25: 10.566779 | AA25: 5.9402659 | AB25: 5.8104537 | AC25: -2.3240131 | AD25: 3.6808342 | AE25: 8.3892093 | AF25: 6.5617141 | AG25: 6.5398893 | AH25: 5.7979199 | AI25: 5.2559152 | AJ25: 5.5733026 | AK25: 9.3513774 | AL25: 10.127071 | AM25: 6.5923715 | AN25: 6.0036594 | AO25: 1.8974154 | AP25: -1.7230917 | AQ25: 0.73379323 | AR25: 2.1718462 | AS25: 5.3882714 | AT25: 9.3972089 | AU25: 13.557523 | AV25: 12.418162 | AW25: 11.03855 | AX25: 14.027303 | AY25: 10.445247 | AZ25: 10.535944 | BA25: 5.8611513 | BB25: 4.543804 | BC25: 1.2798496 | BD25: 6.0740613 | BE25: 8.6572743 | BF25: 3.768928 | BG25: 6.3400693 | BH25: 1.5407817 | BI25: 4.0334258 | BJ25: 6.8490858 | BK25: 9.7074885 | BL25: 9.866474 | BM25: 9.4492467 | BN25: 8.592257 | BO25: 7.086855 | BP25: 6.3720562 | BQ25: 7.678154 | BR25: 7.3009523 | BS25: 8.3316668 | BT25: 8.602977 | BU25: 5.4873943 | BV25: 3.421172 | BW25: 3.0092439 | BX25: 6.8301652 | BY25: 6.215573 | BZ25: 8.1754148 | CA25: 6.1405573 | CB25: 6.8774668
A26: Professional, Scientific & Technical | B26: -5.6009944 | C26: -0.3236218 | D26: -18.493969 | E26: 7.4953876 | L26: #DIV/0! | M26: #DIV/0! | N26: #DIV/0! | O26: #DIV/0! | P26: #DIV/0! | Q26: #DIV/0! | R26: 274.62943 | S26: 156.92634 | T26: -48.754155 | U26: -36.007504 | V26: -43.400367 | W26: -25.105025 | X26: 58.904035 | Y26: 27.285671 | Z26: 27.85514 | AA26: 19.667821 | AB26: -30.372443 | AC26: -5.2895996 | AD26: -23.987612 | AE26: -4.724785 | AF26: 35.227297 | AG26: 7.1458234 | AH26: 18.63699 | AI26: -4.1822118 | AJ26: -14.105069 | AK26: -17.486475 | AL26: -2.7782062 | AM26: 10.488906 | AN26: -6.7671977 | AO26: -3.0051179 | AP26: -5.8708965 | AQ26: -24.399645 | AR26: -24.899575 | AS26: -18.798684 | AT26: -4.2126658 | AU26: 4.0827688 | AV26: 16.766199 | AW26: 18.330501 | AX26: 3.0607992 | AY26: -4.7467743 | AZ26: 10.075611 | BA26: 18.465091 | BB26: 29.831525 | BC26: 27.534304 | BD26: -25.613841 | BE26: -18.782577 | BF26: -30.314921 | BG26: -7.3763702 | BH26: 57.673377 | BI26: 19.519426 | BJ26: 28.212585 | BK26: 5.4580855 | BL26: -10.599431 | BM26: -6.7668666 | BN26: 47.718782 | BO26: 17.35866 | BP26: 30.689972 | BQ26: 16.932477 | BR26: -43.532556 | BS26: 44.815642 | BT26: 12.418639 | BU26: 16.537219 | BV26: 7.2477354 | BW26: -24.524773 | BX26: 15.363915 | BY26: 20.202672 | BZ26: 8.1598601 | CA26: -19.721994 | CB26: 7.9954858
A27: Administrative & Support Service | B27: 25.496412 | C27: -13.86055 | D27: -2.2301177 | E27: 5.1735301 | L27: #DIV/0! | M27: #DIV/0! | N27: #DIV/0! | O27: #DIV/0! | P27: #DIV/0! | Q27: #DIV/0! | R27: 31.753838 | S27: 45.907636 | T27: 27.170571 | U27: 23.937603 | V27: 12.918506 | W27: -3.203906 | X27: -7.6236837 | Y27: -14.658524 | Z27: -13.520434 | AA27: -14.363936 | AB27: -8.1466152 | AC27: -8.6989892 | AD27: -5.3875748 | AE27: 2.3748319 | AF27: 10.923796 | AG27: 25.931366 | AH27: 29.22344 | AI27: 34.761434 | AJ27: 28.009828 | AK27: 12.08468 | AL27: -1.1758293 | AM27: -10.65472 | AN27: -24.623745 | AO27: -18.129258 | AP27: -11.066274 | AQ27: -8.7950511 | AR27: 8.0255995 | AS27: 5.5964169 | AT27: 4.0700765 | AU27: 2.4233416 | AV27: 4.5140186 | AW27: 9.5936878 | AX27: 14.198724 | AY27: 17.837804 | AZ27: 18.803643 | BA27: 18.061287 | BB27: 15.310987 | BC27: 15.300059 | BD27: 1.7656868 | BE27: -1.3442291 | BF27: -1.0421944 | BG27: -1.8968784 | BH27: 7.9539484 | BI27: 4.7755762 | BJ27: 2.1815106 | BK27: 2.5299716 | BL27: 2.6927239 | BM27: 6.759602 | BN27: 18.624445 | BO27: 15.204543 | BP27: 20.386012 | BQ27: 16.978639 | BR27: 0.28451944 | BS27: -1.1138003 | BT27: 6.6307932 | BU27: 7.9396548 | BV27: 2.6697438 | BW27: 4.3040065 | BX27: 11.245774 | BY27: -0.075889295 | BZ27: 6.6460219 | CA27: 38.415656 | CB27: 8.1280684
A28: Public Administration | B28: 24.150865 | C28: 8.4113406 | D28: 18.649438 | E28: 9.5462064 | L28: #DIV/0! | M28: #DIV/0! | N28: 22.959825 | O28: 18.70824 | P28: 15.7273 | Q28: -1.9086256 | R28: 42.157697 | S28: 25.564401 | T28: 7.9962748 | U28: -0.57632447 | V28: -10.289294 | W28: -4.2380592 | X28: -4.9094864 | Y28: 4.2811223 | Z28: 3.2643589 | AA28: -2.0398998 | AB28: 3.7133852 | AC28: -4.1249313 | AD28: -10.228045 | AE28: -4.6867706 | AF28: 4.7102685 | AG28: 12.981056 | AH28: 27.535823 | AI28: 37.216899 | AJ28: 20.915255 | AK28: 13.196055 | AL28: 9.0950885 | AM28: 2.443108 | AN28: 3.9619037 | AO28: 18.540998 | AP28: 17.964241 | AQ28: 17.511495 | AR28: 21.546595 | AS28: 17.673423 | AT28: 20.522996 | AU28: 15.434988 | AV28: 8.210705 | AW28: -3.9095177 | AX28: 0.84642754 | AY28: -1.7509283 | AZ28: 5.4540674 | BA28: 13.078352 | BB28: 14.267079 | BC28: 21.617622 | BD28: 16.485418 | BE28: 12.725186 | BF28: 12.227677 | BG28: 11.188967 | BH28: 22.336814 | BI28: 4.4528189 | BJ28: 5.8675551 | BK28: 4.4330242 | BL28: -4.4121082 | BM28: 9.4299671 | BN28: 7.5089015 | BO28: 5.0386013 | BP28: -9.219724 | BQ28: 1.2999141 | BR28: -17.450349 | BS28: 6.6062297 | BT28: 13.264044 | BU28: 26.974222 | BV28: 3.2970129 | BW28: 4.9539411 | BX28: 6.6024955 | BY28: 1.2675267 | BZ28: -4.8207918 | CA28: 8.3384091 | CB28: 4.9478386
A29: Education | B29: 5.1898176 | C29: 7.8466113 | D29: -10.333028 | E29: 6.9267582 | L29: #DIV/0! | M29: #DIV/0! | N29: -0.33892551 | O29: 8.2198887 | P29: 7.4707997 | Q29: -4.5856117 | R29: 15.611785 | S29: 4.5885967 | T29: 5.9633155 | U29: 16.930637 | V29: 2.1490734 | W29: 5.5676304 | X29: 9.0830003 | Y29: 13.635027 | Z29: 12.365984 | AA29: 14.799178 | AB29: 8.6294845 | AC29: -2.4420282 | AD29: -15.861758 | AE29: -14.771682 | AF29: 5.1152098 | AG29: 46.361714 | AH29: 4.7235009 | AI29: 22.602806 | AJ29: 12.463036 | AK29: -11.108071 | AL29: 39.11423 | AM29: 11.600696 | AN29: -1.2930274 | AO29: -9.3545004 | AP29: -9.9388563 | AQ29: -12.667115 | AR29: -12.208823 | AS29: -6.2875495 | AT29: 0.71780029 | AU29: 7.4762323 | AV29: 11.57076 | AW29: 8.4593409 | AX29: 10.938142 | AY29: 12.894567 | AZ29: 8.5698683 | BA29: 4.0791717 | BB29: -7.8670802 | BC29: -5.5843101 | BD29: 0.99207716 | BE29: 4.7305129 | BF29: -12.283379 | BG29: -7.9059071 | BH29: -1.723466 | BI29: 4.4858555 | BJ29: 14.180337 | BK29: -3.1004335 | BL29: 4.5456475 | BM29: -7.6011874 | BN29: 13.405923 | BO29: -0.74293428 | BP29: -8.7536911 | BQ29: 10.740466 | BR29: 10.16384 | BS29: 7.7555088 | BT29: 3.1106209 | BU29: -3.2968824 | BV29: -2.7330343 | BW29: 4.8992189 | BX29: 6.7504518 | BY29: 13.191795 | BZ29: 5.3231919 | CA29: 9.1884059 | CB29: 4.0999939
A30: Human Health & Social Work | B30: 5.4353724 | C30: 3.3767601 | D30: 0.016226632 | E30: 16.846037 | L30: #DIV/0! | M30: #DIV/0! | N30: 8.0762035 | O30: 4.0659732 | P30: 7.4129931 | Q30: 2.5882701 | R30: 4.0720181 | S30: 6.0546777 | T30: 6.4306659 | U30: 1.529805 | V30: 5.9032559 | W30: 2.4845161 | X30: 2.2456231 | Y30: 8.5876853 | Z30: 2.4260824 | AA30: 3.0226266 | AB30: 3.8512277 | AC30: 6.939943 | AD30: -7.7552306 | AE30: -7.3525103 | AF30: 7.6461817 | AG30: 27.314628 | AH30: 3.5383379 | AI30: 19.015898 | AJ30: 10.88906 | AK30: -6.9977349 | AL30: 21.965683 | AM30: 6.1313956 | AN30: -2.5376329 | AO30: -7.7337644 | AP30: -4.4485444 | AQ30: -4.4884766 | AR30: 0.83014489 | AS30: 8.3253781 | AT30: 19.617004 | AU30: 22.692754 | AV30: 18.550392 | AW30: 7.5194997 | AX30: 9.9704382 | AY30: 3.1755782 | AZ30: 1.7645169 | BA30: 6.5746455 | BB30: 1.8466677 | BC30: 6.7697542 | BD30: 2.7307847 | BE30: -7.2914229 | BF30: 8.8043549 | BG30: 5.7588784 | BH30: 1.3043976 | BI30: 12.81764 | BJ30: -4.8643348 | BK30: 17.559177 | BL30: 15.910549 | BM30: 10.512541 | BN30: 11.354252 | BO30: 0.96397589 | BP30: 4.499235 | BQ30: 1.6002764 | BR30: -6.951403 | BS30: -3.2913101 | BT30: 7.3605805 | BU30: 13.177381 | BV30: 7.6829818 | BW30: 6.3708844 | BX30: -0.2597398 | BY30: -5.2503577 | BZ30: 4.2122635 | CA30: 5.3179483 | CB30: 3.8641325
A31: Arts, Entertainment & Recreation | B31: 5.3268488 | C31: -5.0389646 | D31: 29.669926 | E31: 65.707947 | L31: #DIV/0! | M31: #DIV/0! | N31: #DIV/0! | O31: #DIV/0! | P31: #DIV/0! | Q31: #DIV/0! | R31: 46.72677 | S31: 122.36385 | T31: -60.186235 | U31: -53.817372 | V31: -48.829773 | W31: -35.432133 | X31: 250.6371 | Y31: 116.52825 | Z31: 66.655588 | AA31: -0.20094131 | AB31: -36.358825 | AC31: -5.1004276 | AD31: -21.75703 | AE31: 1.3170045 | AF31: 39.433793 | AG31: 14.606026 | AH31: 31.387892 | AI31: -1.8488596 | AJ31: -6.0880452 | AK31: 4.8925744 | AL31: -2.8035524 | AM31: 8.8999843 | AN31: 1.7203723 | AO31: -26.448261 | AP31: -8.2344072 | AQ31: -9.5157976 | AR31: 26.711123 | AS31: 134.33677 | AT31: 81.047491 | AU31: 117.5892 | AV31: 77.484627 | AW31: 22.498751 | AX31: 64.084041 | AY31: 17.417848 | AZ31: 14.150069 | BA31: 4.23429 | BB31: -1.5705449 | BC31: 1.6413162 | BD31: -7.6716318 | BE31: -26.30614 | BF31: -26.051164 | BG31: -22.241978 | BH31: -19.527062 | BI31: 25.991763 | BJ31: 27.334593 | BK31: -3.3078454 | BL31: -12.421508 | BM31: -18.222104 | BN31: -32.128584 | BO31: -2.4413034 | BP31: 31.531404 | BQ31: 34.851999 | BR31: 61.638306 | BS31: -9.3749864 | BT31: 8.0429229 | BU31: -16.471009 | BV31: 3.3350047 | BW31: 11.129547 | BX31: 4.8852735 | BY31: -12.809304 | BZ31: -0.38350465 | CA31: -0.19063188 | CB31: -0.054793256
A32: Other Service Activities | B32: 7.8943433 | C32: 9.2450741 | D32: -3.5309358 | E32: -1.3127541 | L32: #DIV/0! | M32: #DIV/0! | N32: 11.122037 | O32: 9.9004816 | P32: -0.60387659 | Q32: -0.0084756558 | R32: 1.3555989 | S32: 2.4970867 | T32: 3.1140619 | U32: 4.6792555 | V32: 7.3385438 | W32: 7.5932375 | X32: 7.2240977 | Y32: 8.4178041 | Z32: 4.6671141 | AA32: 4.8610259 | AB32: 5.3877605 | AC32: 5.5892347 | AD32: 7.549797 | AE32: 11.898503 | AF32: 15.190551 | AG32: 8.1420195 | AH32: 10.031922 | AI32: 6.9831566 | AJ32: 4.311445 | AK32: 10.489804 | AL32: 10.980113 | AM32: 12.088441 | AN32: 9.021055 | AO32: 5.1087593 | AP32: 0.59627966 | AQ32: -4.6550946 | AR32: -4.5959918 | AS32: -5.388651 | AT32: -4.0421657 | AU32: -1.6094004 | AV32: -0.73952941 | AW32: 1.281162 | AX32: 4.110845 | AY32: 4.8264854 | AZ32: 4.6760247 | BA32: 5.1732115 | BB32: 2.5015481 | BC32: 1.5030344 | BD32: 0.92229905 | BE32: 0.7850375 | BF32: 0.9414597 | BG32: 2.0966427 | BH32: 3.7231534 | BI32: 5.0379402 | BJ32: 5.7216721 | BK32: 5.1949508 | BL32: 4.0428981 | BM32: 4.1944075 | BN32: 3.1217222 | BO32: 2.8070778 | BP32: 2.5234751 | BQ32: 1.239937 | BR32: 2.1083394 | BS32: 16.522672 | BT32: 2.4554742 | BU32: -10.576143 | BV32: 1.5114262 | BW32: -11.048298 | BX32: 0.19000382 | BY32: 16.866167 | BZ32: 2.6261727 | CA32: -9.6482935 | CB32: -0.24092478
A33: Activities of Households | B33: 2.8162666 | C33: 3.3607717 | D33: 2.839093 | E33: 2.8127413 | L33: #DIV/0! | M33: #DIV/0! | N33: 4.2759423 | O33: 4.3374108 | P33: 4.1807364 | Q33: 3.8050368 | R33: 3.2003418 | S33: 2.7003087 | T33: 2.313591 | U33: 2.0396385 | V33: 1.8801607 | W33: 1.7794902 | X33: 1.73738 | Y33: 1.7550303 | Z33: 1.8324203 | AA33: 1.9505441 | AB33: 2.1116637 | AC33: 2.3166001 | AD33: 2.5653309 | AE33: 3.2287643 | AF33: 4.3142927 | AG33: -0.52457145 | AH33: 1.1153794 | AI33: 1.816906 | AJ33: 1.5827113 | AK33: 6.8477433 | AL33: 4.8852482 | AM33: 3.5124962 | AN33: 2.6943059 | AO33: 2.4118507 | AP33: 2.6609965 | AQ33: 2.8320844 | AR33: 2.924144 | AS33: 2.936326 | AT33: 2.8680716 | AU33: 2.818773 | AV33: 2.7883234 | AW33: 2.776886 | AX33: 2.7843704 | AY33: 2.7881906 | AZ33: 2.7883971 | BA33: 2.7846182 | BB33: 2.776885 | BC33: 2.7669055 | BD33: 2.7550021 | BE33: 2.7409598 | BF33: 2.7246889 | BG33: 2.7139813 | BH33: 2.7350163 | BI33: 2.7613682 | BJ33: 2.767027 | BK33: 2.7663441 | BL33: 2.7596131 | BM33: 2.7465927 | BN33: 2.7271632 | BO33: 2.7142034 | BP33: 2.7339014 | BQ33: 2.7598254 | BR33: 2.7659861 | BS33: 2.7659177 | BT33: 2.759914 | BU33: 2.7477363 | BV33: 2.729262 | BW33: 2.7158552 | BX33: 2.7336983 | BY33: 2.7563359 | BZ33: 2.7577825 | CA33: 2.0997339 | CB33: 2.7546326
A35: ADJUSTMENTS
A36: Taxes on products | B36: 9.8801724 | C36: 2.1536066 | D36: 10.904579 | E36: 4.4222697 | L36: #DIV/0! | M36: #DIV/0! | N36: 16.024002 | O36: 18.296005 | P36: -13.335066 | Q36: -8.5764566 | R36: 0.96839961 | S36: 15.080046 | T36: 19.91554 | U36: 12.326273 | V36: 13.06552 | W36: 13.190256 | X36: 16.01425 | Y36: 18.951389 | Z36: 7.8626362 | AA36: -3.3324373 | AB36: -3.5664363 | AC36: 2.4097213 | AD36: 3.5895789 | AE36: 5.9326991 | AF36: 13.001319 | AG36: 7.1171898 | AH36: 7.0267161 | AI36: 15.020728 | AJ36: 4.576532 | AK36: 13.288031 | AL36: 7.6587553 | AM36: 4.9697145 | AN36: -3.4420658 | AO36: 0.11789288 | AP36: 10.604422 | AQ36: 4.5985732 | AR36: 17.953651 | AS36: 10.804192 | AT36: 7.14843 | AU36: 10.453864 | AV36: -0.66306097 | AW36: 1.3702884 | AX36: -0.61078727 | AY36: 3.2552983 | AZ36: 10.00324 | BA36: 5.0444829 | BB36: 11.026391 | BC36: 9.535794 | BD36: -0.67574802 | BE36: -24.997721 | BF36: -3.3582876 | BG36: -4.5905031 | BH36: -3.5545582 | BI36: 47.741356 | BJ36: -1.7056382 | BK36: 8.453615 | BL36: 21.819967 | BM36: 2.6241571 | BN36: 17.806552 | BO36: 5.1403958 | BP36: 4.1100754 | BQ36: 11.125298 | BR36: 13.913662 | BS36: 6.9502737 | BT36: 6.8429801 | BU36: 3.7987589 | BV36: 10.556979 | BW36: 9.3531628 | BX36: 5.4594994 | BY36: 7.9766044 | BZ36: 3.3485178 | CA36: 7.1416697 | CB36: 14.109321
A37: Source: Uganda Bureau of Statistics
Y38: 8.5

Sheet Original_IPD
A1: Table 5: ORIGINAL UNADJUSTED Value Added by activity at constant 2016/17 prices, IMPLICIT PRICE DEFLATORS, 2016/17-2025/26
I2: 2008Q1 | J2: 2008Q2 | K2: 2008Q3 | L2: 2008Q4 | M2: 2009Q1 | N2: 2009Q2 | O2: 2009Q3 | P2: 2009Q4 | Q2: 2010Q1 | R2: 2010Q2 | S2: 2010Q3 | T2: 2010Q4 | U2: 2011Q1 | V2: 2011Q2 | W2: 2011Q3 | X2: 2011Q4 | Y2: 2012Q1 | Z2: 2012Q2 | AA2: 2012Q3 | AB2: 2012Q4 | AC2: 2013Q1 | AD2: 2013Q2 | AE2: 2013Q3 | AF2: 2013Q4 | AG2: 2014Q1 | AH2: 2014Q2 | AI2: 2014Q3 | AJ2: 2014Q4 | AK2: 2015Q1 | AL2: 2015Q2 | AM2: 2015Q3
I3: 2007/08 | K3: 2008/09 | O3: 2009/10 | S3: 2010/11 | W3: 2011/12 | AA3: 2012/13 | AE3: 2013/14 | AF3: 2013/14 | AH3: 2013/14 | AI3: 2014/15 | AJ3: 2014/15 | AK3: 2014/15 | AM3: 2015/16 | AQ3: 2016/17 | AU3: 2017/18 | AY3: 2018/19 | BC3: 2019/20 | BG3: 2020/21 | BK3: 2021/22 | BO3: 2022/23 | BS3: 2023/24 | BW3: 2024/25 | CA3: 2025/26 | CB3: 2025/26 | CC3: 2025/26
B4: 2008/09 | C4: 2009/10 | D4: 2010/11 | E4: 2011/12 | F4: 2012/13 | G4: 2013/14 | I4: Q3 | J4: Q4 | K4: Q1 | L4: Q2 | M4: Q3 | N4: Q4 | O4: Q1 | P4: Q2 | Q4: Q3 | R4: Q4 | S4: Q1 | T4: Q2 | U4: Q3 | V4: Q4 | W4: Q1 | X4: Q2 | Y4: Q3 | Z4: Q4 | AA4: Q1 | AB4: Q2 | AC4: Q3 | AD4: Q4 | AE4: Q1 | AF4: Q2 | AG4: Q3 | AH4: Q4 | AI4: Q1 | AJ4: Q2 | AK4: Q3 | AL4: Q4 | AM4: Q1 | AN4: Q2 | AO4: Q3 | AP4: Q4 | AQ4: Q1 | AR4: Q2 | AS4: Q3 | AT4: Q4 | AU4: Q1 | AV4: Q2 | AW4: Q3 | AX4: Q4 | AY4: Q1 | AZ4: Q2 | BA4: Q3 | BB4: Q4 | BC4: Q1 | BD4: Q2 | BE4: Q3 | BF4: Q4 | BG4: Q1 | BH4: Q2 | BI4: Q3 | BJ4: Q4 | BK4: Q1 | BL4: Q2 | BM4: Q3 | BN4: Q4 | BO4: Q1 | BP4: Q2 | BQ4: Q3 | BR4: Q4 | BS4: Q1 | BT4: Q2 | BU4: Q3 | BV4: Q4 | BW4: Q1 | BX4: Q2 | BY4: Q3 | BZ4: Q4 | CA4: Q1 | CB4: Q2 | CC4: Q3
A5: GDP AT MARKET PRICES | I5: #DIV/0! | J5: #DIV/0! | K5: 169.51822 | L5: 197.11356 | M5: 224.42093 | N5: 177.6833 | O5: 139.62945 | P5: 162.92921 | Q5: 174.26137 | R5: 155.48923 | S5: 138.96649 | T5: 156.17021 | U5: 178.66024 | V5: 171.68489 | W5: 137.37736 | X5: 147.25817 | Y5: 181.45588 | Z5: 165.70977 | AA5: 134.91219 | AB5: 167.85981 | AC5: 190.65712 | AD5: 183.01912 | AE5: 153.73014 | AF5: 188.93798 | AG5: 210.33593 | AH5: 179.71996 | AI5: 159.35423 | AJ5: 192.86199 | AK5: 221.66389 | AL5: 193.72831 | AM5: 166.32398 | AN5: 198.02434 | AO5: 243.06945 | AP5: 215.88943 | AQ5: 191.52156 | AR5: 219.13215 | AS5: 240.68923 | AT5: 228.87248 | AU5: 102.26658 | AV5: 100.32084 | AW5: 106.43321 | AX5: 108.94625 | AY5: 105.17889 | AZ5: 107.41318 | BA5: 108.25572 | BB5: 109.62404 | BC5: 108.59653 | BD5: 112.11937 | BE5: 111.87089 | BF5: 109.5713 | BG5: 111.82212 | BH5: 113.61348 | BI5: 113.49602 | BJ5: 114.44594 | BK5: 115.62811 | BL5: 117.15355 | BM5: 120.01326 | BN5: 122.9211 | BO5: 124.85856 | BP5: 124.95116 | BQ5: 125.78235 | BR5: 132.05512 | BS5: 131.47915 | BT5: 132.18512 | BU5: 133.38067 | BV5: 135.88897 | BW5: 137.02477 | BX5: 139.24051 | BY5: 141.32309 | BZ5: 143.22198 | CA5: 138.14266 | CB5: 144.51503 | CC5: 145.71406
A6: AGRICULTURE,FORESTRY&FISHING | I6: #DIV/0! | J6: #DIV/0! | K6: 83.342758 | L6: 120.87091 | M6: 202.80696 | N6: 106.14355 | O6: 88.710091 | P6: 139.69058 | Q6: 203.52773 | R6: 125.87609 | S6: 95.087448 | T6: 146.40762 | U6: 217.80864 | V6: 152.00117 | W6: 86.745156 | X6: 150.06801 | Y6: 256.26113 | Z6: 172.93861 | AA6: 80.725496 | AB6: 163.15282 | AC6: 269.73046 | AD6: 192.52693 | AE6: 91.718037 | AF6: 185.26044 | AG6: 307.33581 | AH6: 200.70082 | AI6: 108.82361 | AJ6: 184.96144 | AK6: 317.94992 | AL6: 208.38443 | AM6: 126.42866 | AN6: 222.62764 | AO6: 338.68558 | AP6: 249.28893 | AQ6: 159.95336 | AR6: 241.10907 | AS6: 343.40822 | AT6: 266.07811 | AU6: 102.1439 | AV6: 94.090336 | AW6: 110.99282 | AX6: 116.61139 | AY6: 100.941 | AZ6: 106.60955 | BA6: 112.26615 | BB6: 116.33675 | BC6: 109.1623 | BD6: 119.14168 | BE6: 116.5524 | BF6: 113.09197 | BG6: 111.07647 | BH6: 116.78887 | BI6: 113.6891 | BJ6: 122.17879 | BK6: 116.82433 | BL6: 125.01551 | BM6: 124.38791 | BN6: 126.69709 | BO6: 126.59109 | BP6: 130.35175 | BQ6: 131.35429 | BR6: 143.44983 | BS6: 131.11885 | BT6: 138.64887 | BU6: 149.15102 | BV6: 157.02214 | BW6: 144.17741 | BX6: 155.68757 | BY6: 173.07676 | BZ6: 169.67014 | CA6: 143.3403 | CB6: 162.07072 | CC6: 177.23066
A7: Cash crops | I7: #DIV/0! | J7: #DIV/0! | K7: 188.75098 | L7: 85.682327 | M7: 113.6501 | N7: 138.82568 | O7: 182.90172 | P7: 92.121385 | Q7: 155.69019 | R7: 138.33058 | S7: 190.59495 | T7: 97.273236 | U7: 103.51039 | V7: 179.80918 | W7: 175.80395 | X7: 81.364644 | Y7: 113.94219 | Z7: 175.98228 | AA7: 207.26857 | AB7: 123.49691 | AC7: 151.93879 | AD7: 286.6594 | AE7: 262.34473 | AF7: 151.24632 | AG7: 202.7473 | AH7: 294.6564 | AI7: 261.05837 | AJ7: 184.63948 | AK7: 225.84258 | AL7: 375.5341 | AM7: 384.63381 | AN7: 280.53702 | AO7: 325.02717 | AP7: 596.41281 | AQ7: 676.7807 | AR7: 410.50228 | AS7: 353.47983 | AT7: 579.58829 | AU7: 105.81673 | AV7: 98.947391 | AW7: 96.083137 | AX7: 99.648116 | AY7: 99.414196 | AZ7: 92.198663 | BA7: 90.70354 | BB7: 85.10956 | BC7: 87.523435 | BD7: 91.094534 | BE7: 95.195841 | BF7: 83.117495 | BG7: 83.505324 | BH7: 82.513386 | BI7: 91.362991 | BJ7: 99.879413 | BK7: 99.838741 | BL7: 129.30518 | BM7: 134.38613 | BN7: 130.05358 | BO7: 121.6165 | BP7: 125.5794 | BQ7: 122.30837 | BR7: 145.71874 | BS7: 144.7037 | BT7: 161.22797 | BU7: 185.19618 | BV7: 226.19909 | BW7: 182.82839 | BX7: 228.75904 | BY7: 251.20239 | BZ7: 369.9672 | CA7: 208.08641 | CB7: 236.95391 | CC7: 252.5777
A8: Food crops | I8: #DIV/0! | J8: #DIV/0! | K8: 50.841526 | L8: 120.38749 | M8: 297.308 | N8: 105.29359 | O8: 54.533938 | P8: 128.42355 | Q8: 275.44703 | R8: 108.00354 | S8: 55.770906 | T8: 139.49117 | U8: 294.27381 | V8: 117.06988 | W8: 46.683065 | X8: 137.74931 | Y8: 384.19466 | Z8: 142.16314 | AA8: 35.584736 | AB8: 171.70204 | AC8: 438.52378 | AD8: 165.37768 | AE8: 38.63512 | AF8: 199.79895 | AG8: 489.07812 | AH8: 185.20504 | AI8: 44.309057 | AJ8: 168.46923 | AK8: 486.17317 | AL8: 183.49723 | AM8: 48.076509 | AN8: 189.4443 | AO8: 518.84158 | AP8: 209.36775 | AQ8: 53.372853 | AR8: 181.37904 | AS8: 450.11691 | AT8: 218.39817 | AU8: 104.09123 | AV8: 95.676742 | AW8: 104.08751 | AX8: 107.29512 | AY8: 98.31158 | AZ8: 101.05843 | BA8: 103.59143 | BB8: 111.69825 | BC8: 103.71697 | BD8: 105.27323 | BE8: 105.65049 | BF8: 105.10924 | BG8: 105.48664 | BH8: 99.341063 | BI8: 100.55751 | BJ8: 115.43198 | BK8: 110.68597 | BL8: 112.24303 | BM8: 101.0998 | BN8: 116.94817 | BO8: 122.99657 | BP8: 122.02214 | BQ8: 109.09079 | BR8: 137.56287 | BS8: 123.11563 | BT8: 123.66148 | BU8: 111.28913 | BV8: 139.30163 | BW8: 132.83579 | BX8: 133.07466 | BY8: 121.68379 | BZ8: 125.97285 | CA8: 123.03799 | CB8: 137.14503 | CC8: 127.35645
A9: Livestock | I9: #DIV/0! | J9: #DIV/0! | K9: 130.76968 | L9: 134.20484 | M9: 144.43202 | N9: 145.28883 | O9: 151.76604 | P9: 151.77007 | Q9: 158.28378 | R9: 163.93532 | S9: 171.41229 | T9: 174.37104 | U9: 181.28688 | V9: 188.26582 | W9: 196.6984 | X9: 201.1304 | Y9: 203.3042 | Z9: 206.99056 | AA9: 208.40678 | AB9: 222.19708 | AC9: 215.74147 | AD9: 222.07773 | AE9: 220.11841 | AF9: 224.68342 | AG9: 237.87199 | AH9: 245.88618 | AI9: 258.70232 | AJ9: 263.54157 | AK9: 266.59329 | AL9: 274.34836 | AM9: 285.58332 | AN9: 294.23471 | AO9: 304.53564 | AP9: 309.1567 | AQ9: 321.46019 | AR9: 326.70858 | AS9: 328.77584 | AT9: 334.09695 | AU9: 107.75111 | AV9: 108.3424 | AW9: 110.46133 | AX9: 110.66984 | AY9: 114.35907 | AZ9: 116.52011 | BA9: 120.52753 | BB9: 120.41222 | BC9: 123.28849 | BD9: 126.6288 | BE9: 130.8191 | BF9: 132.20314 | BG9: 131.72258 | BH9: 132.04385 | BI9: 129.43381 | BJ9: 134.16454 | BK9: 135.70079 | BL9: 136.93406 | BM9: 133.02029 | BN9: 133.21037 | BO9: 136.95174 | BP9: 139.33305 | BQ9: 145.36231 | BR9: 147.65167 | BS9: 147.94711 | BT9: 149.34967 | BU9: 152.95487 | BV9: 155.18396 | BW9: 159.4172 | BX9: 161.84656 | BY9: 166.66257 | BZ9: 169.94579 | CA9: 170.1319 | CB9: 171.44877 | CC9: 175.17965
A10: Agriculture Support Services | I10: #DIV/0! | J10: #DIV/0! | K10: 53.215736 | L10: 157.2135 | M10: 272.953 | N10: 77.870411 | O10: 45.437683 | P10: 145.64471 | Q10: 281.86569 | R10: 89.21107 | S10: 54.053162 | T10: 180.49539 | U10: 343.0019 | V10: 109.55484 | W10: 65.992757 | X10: 188.74253 | Y10: 368.26131 | Z10: 115.39321 | AA10: 74.771506 | AB10: 197.1082 | AC10: 375.21608 | AD10: 115.08782 | AE10: 76.911122 | AF10: 204.84796 | AG10: 390.27676 | AH10: 111.36537 | AI10: 70.292199 | AJ10: 179.66795 | AK10: 347.92743 | AL10: 104.02943 | AM10: 75.937239 | AN10: 204.05652 | AO10: 405.48102 | AP10: 113.41298 | AQ10: 72.24441 | AR10: 206.33063 | AS10: 347.43639 | AT10: 111.63366 | AU10: 77.401398 | AV10: 90.847301 | AW10: 118.76132 | AX10: 87.647031 | AY10: 85.864393 | AZ10: 108.2144 | BA10: 144.61752 | BB10: 101.51429 | BC10: 87.121766 | BD10: 102.08232 | BE10: 154.0771 | BF10: 104.68774 | BG10: 85.635646 | BH10: 108.84554 | BI10: 144.37767 | BJ10: 103.79515 | BK10: 89.094779 | BL10: 115.16745 | BM10: 141.56272 | BN10: 102.45637 | BO10: 88.338806 | BP10: 113.10301 | BQ10: 153.24617 | BR10: 107.70576 | BS10: 88.644334 | BT10: 111.42295 | BU10: 151.44526 | BV10: 105.2623 | BW10: 90.506313 | BX10: 117.73876 | BY10: 147.83692 | BZ10: 95.903419 | CA10: 92.280156 | CB10: 121.6039 | CC10: 147.87385
A11: Forestry | I11: #DIV/0! | J11: #DIV/0! | K11: 172.48556 | L11: 180.15667 | M11: 140.1448 | N11: 72.472644 | O11: 213.69996 | P11: 257.56531 | Q11: 140.51515 | R11: 152.12084 | S11: 174.20684 | T11: 178.63966 | U11: 180.98575 | V11: 233.70651 | W11: 118.98346 | X11: 228.7699 | Y11: 179.3214 | Z11: 258.1076 | AA11: 179.63195 | AB11: 143.32399 | AC11: 159.10856 | AD11: 196.87004 | AE11: 187.87471 | AF11: 161.48511 | AG11: 187.87617 | AH11: 190.43046 | AI11: 184.74602 | AJ11: 191.06266 | AK11: 196.81688 | AL11: 192.48057 | AM11: 208.19721 | AN11: 249.49465 | AO11: 172.77978 | AP11: 217.37223 | AQ11: 226.8412 | AR11: 224.55686 | AS11: 225.90701 | AT11: 216.56875 | AU11: 80.820459 | AV11: 63.400907 | AW11: 136.99288 | AX11: 155.29977 | AY11: 93.706838 | AZ11: 114.53052 | BA11: 128.10361 | BB11: 133.24456 | BC11: 126.97269 | BD11: 154.59371 | BE11: 120.23834 | BF11: 118.04491 | BG11: 118.82764 | BH11: 168.29651 | BI11: 122.08634 | BJ11: 125.67034 | BK11: 131.22554 | BL11: 135.19181 | BM11: 134.93645 | BN11: 134.4754 | BO11: 136.47611 | BP11: 143.52795 | BQ11: 137.40431 | BR11: 139.18001 | BS11: 145.52087 | BT11: 149.79949 | BU11: 155.3167 | BV11: 158.3514 | BW11: 158.95804 | BX11: 161.29439 | BY11: 172.31061 | BZ11: 163.61483 | CA11: 164.09121 | CB11: 164.17629 | CC11: 165.13225
A12: Fishing | I12: #DIV/0! | J12: #DIV/0! | K12: 102.2323 | L12: 88.024265 | M12: 90.422947 | N12: 87.562416 | O12: 78.219 | P12: 88.953369 | Q12: 107.91241 | R12: 125.1505 | S12: 155.74474 | T12: 141.28912 | U12: 145.0206 | V12: 170.2832 | W12: 167.08965 | X12: 140.05491 | Y12: 147.90219 | Z12: 157.77864 | AA12: 139.36041 | AB12: 131.75205 | AC12: 140.09851 | AD12: 190.76443 | AE12: 146.96463 | AF12: 151.60414 | AG12: 85.32471 | AH12: 167.34652 | AI12: 228.45524 | AJ12: 162.4134 | AK12: 98.628873 | AL12: 136.4581 | AM12: 208.8011 | AN12: 202.68916 | AO12: 93.343727 | AP12: 148.17265 | AQ12: 328.37856 | AR12: 233.61253 | AS12: 133.61598 | AT12: 206.50471 | AU12: 109.02746 | AV12: 118.10552 | AW12: 114.85298 | AX12: 120.64649 | AY12: 124.91048 | AZ12: 125.78344 | BA12: 134.32268 | BB12: 133.37373 | BC12: 134.66077 | BD12: 159.26676 | BE12: 161.02638 | BF12: 154.14502 | BG12: 165.97843 | BH12: 154.40058 | BI12: 157.37526 | BJ12: 167.96606 | BK12: 155.77262 | BL12: 156.93254 | BM12: 155.18709 | BN12: 165.05811 | BO12: 148.42394 | BP12: 153.00882 | BQ12: 171.04625 | BR12: 182.57639 | BS12: 153.10927 | BT12: 162.22542 | BU12: 187.788 | BV12: 193.58219 | BW12: 159.24947 | BX12: 156.65071 | BY12: 195.58469 | BZ12: 212.04481 | CA12: 165.62424 | CB12: 169.65202 | CC12: 209.69178
A13: INDUSTRY | I13: #DIV/0! | J13: #DIV/0! | K13: 515.68608 | L13: 504.5936 | M13: 600.65559 | N13: 409.77988 | O13: 165.83618 | P13: 174.41876 | Q13: 169.60909 | R13: 172.90292 | S13: 170.37573 | T13: 158.26313 | U13: 171.5379 | V13: 179.80541 | W13: 174.33203 | X13: 154.59283 | Y13: 167.04354 | Z13: 176.73506 | AA13: 179.66887 | AB13: 181.73289 | AC13: 173.06441 | AD13: 198.24473 | AE13: 200.12898 | AF13: 206.28541 | AG13: 195.09872 | AH13: 181.51731 | AI13: 185.275 | AJ13: 200.3095 | AK13: 204.17645 | AL13: 185.79604 | AM13: 180.80158 | AN13: 185.06998 | AO13: 219.73323 | AP13: 206.5451 | AQ13: 202.81686 | AR13: 200.42953 | AS13: 203.49866 | AT13: 215.64397 | AU13: 105.6728 | AV13: 105.27361 | AW13: 106.50997 | AX13: 109.34371 | AY13: 111.4677 | AZ13: 108.46498 | BA13: 108.24198 | BB13: 107.49894 | BC13: 108.76951 | BD13: 110.34755 | BE13: 112.08224 | BF13: 113.05143 | BG13: 115.37585 | BH13: 115.57812 | BI13: 118.03021 | BJ13: 117.83228 | BK13: 119.16088 | BL13: 113.40245 | BM13: 123.02174 | BN13: 124.90641 | BO13: 125.63705 | BP13: 122.83105 | BQ13: 123.6165 | BR13: 127.37306 | BS13: 128.91093 | BT13: 129.29454 | BU13: 125.21425 | BV13: 125.63411 | BW13: 127.18904 | BX13: 130.46511 | BY13: 129.99549 | BZ13: 132.3054 | CA13: 129.18592 | CB13: 130.95823 | CC13: 137.83167
A14: Mining & quarrying | I14: #DIV/0! | J14: #DIV/0! | K14: 202.835 | L14: 343.70207 | M14: 352.67445 | N14: 276.55754 | O14: 415.71509 | P14: 526.1942 | Q14: 410.68731 | R14: 249.15441 | S14: 315.91979 | T14: 343.96059 | U14: 293.77991 | V14: 473.82636 | W14: 656.8912 | X14: 715.51489 | Y14: 425.60663 | Z14: 248.06826 | AA14: 272.59029 | AB14: 508.07775 | AC14: 201.56858 | AD14: 266.26146 | AE14: 453.38436 | AF14: 854.47482 | AG14: 205.14686 | AH14: 138.04494 | AI14: 251.69291 | AJ14: 842.75128 | AK14: 458.3782 | AL14: 225.08752 | AM14: 148.27353 | AN14: 121.52565 | AO14: 295.96193 | AP14: 382.54034 | AQ14: 186.35533 | AR14: 142.41237 | AS14: 206.04307 | AT14: 233.61935 | AU14: 104.96698 | AV14: 119.47703 | AW14: 116.27097 | AX14: 134.457 | AY14: 160.28022 | AZ14: 161.90769 | BA14: 142.78991 | BB14: 140.90341 | BC14: 124.32963 | BD14: 127.32376 | BE14: 122.89787 | BF14: 147.92699 | BG14: 133.97547 | BH14: 148.69934 | BI14: 168.11232 | BJ14: 154.30862 | BK14: 136.13166 | BL14: 65.561307 | BM14: 135.17824 | BN14: 106.99265 | BO14: 106.19465 | BP14: 95.016501 | BQ14: 106.70185 | BR14: 129.24527 | BS14: 121.77041 | BT14: 94.269127 | BU14: 97.415384 | BV14: 103.83744 | BW14: 80.447827 | BX14: 127.0965 | BY14: 121.72326 | BZ14: 107.74948 | CA14: 89.35853 | CB14: 101.56045 | CC14: 125.91506
A15: Manufacturing | I15: #DIV/0! | J15: #DIV/0! | K15: #DIV/0! | L15: #DIV/0! | M15: #DIV/0! | N15: #DIV/0! | O15: 155.01702 | P15: 156.63584 | Q15: 142.68941 | R15: 152.64327 | S15: 149.43972 | T15: 135.91335 | U15: 163.12775 | V15: 170.37357 | W15: 156.69605 | X15: 134.82602 | Y15: 155.97227 | Z15: 172.46618 | AA15: 175.58422 | AB15: 174.79037 | AC15: 164.1497 | AD15: 186.60414 | AE15: 204.25322 | AF15: 206.53556 | AG15: 195.10288 | AH15: 187.27599 | AI15: 182.2258 | AJ15: 176.31743 | AK15: 187.56712 | AL15: 180.04789 | AM15: 178.10122 | AN15: 185.16564 | AO15: 229.87316 | AP15: 193.10876 | AQ15: 203.10193 | AR15: 200.19636 | AS15: 201.48938 | AT15: 214.77629 | AU15: 107.72909 | AV15: 106.10424 | AW15: 107.58899 | AX15: 110.07518 | AY15: 109.69786 | AZ15: 106.73219 | BA15: 106.95549 | BB15: 107.23689 | BC15: 110.58499 | BD15: 113.17243 | BE15: 117.42755 | BF15: 119.10495 | BG15: 121.0688 | BH15: 122.57135 | BI15: 126.09668 | BJ15: 126.63247 | BK15: 128.66391 | BL15: 123.97294 | BM15: 131.54376 | BN15: 138.2961 | BO15: 137.59516 | BP15: 133.69207 | BQ15: 135.76712 | BR15: 137.6228 | BS15: 139.22407 | BT15: 141.2314 | BU15: 139.82766 | BV15: 138.91915 | BW15: 143.36815 | BX15: 136.02035 | BY15: 142.78295 | BZ15: 144.93102 | CA15: 143.72909 | CB15: 142.40218 | CC15: 152.64705
A16: Electricity | I16: #DIV/0! | J16: #DIV/0! | K16: 222.21898 | L16: 203.83318 | M16: 195.85478 | N16: 186.84308 | O16: 189.43548 | P16: 185.03279 | Q16: 196.49289 | R16: 186.49601 | S16: 187.97373 | T16: 190.46194 | U16: 198.91817 | V16: 204.10342 | W16: 217.04442 | X16: 195.45048 | Y16: 187.91118 | Z16: 190.82708 | AA16: 191.60602 | AB16: 189.60038 | AC16: 195.64513 | AD16: 192.53844 | AE16: 195.03374 | AF16: 197.00312 | AG16: 204.62548 | AH16: 179.98249 | AI16: 176.64895 | AJ16: 179.83782 | AK16: 182.10177 | AL16: 179.59217 | AM16: 176.45447 | AN16: 180.20352 | AO16: 183.26289 | AP16: 184.01394 | AQ16: 184.94666 | AR16: 180.69336 | AS16: 191.85434 | AT16: 177.91464 | AU16: 104.30515 | AV16: 103.92619 | AW16: 108.92026 | AX16: 108.37647 | AY16: 117.52897 | AZ16: 116.87987 | BA16: 117.06797 | BB16: 116.43945 | BC16: 116.69465 | BD16: 116.89553 | BE16: 117.14703 | BF16: 116.93719 | BG16: 116.58566 | BH16: 115.8339 | BI16: 115.37569 | BJ16: 115.1067 | BK16: 114.12435 | BL16: 114.15975 | BM16: 114.65458 | BN16: 115.49627 | BO16: 116.6274 | BP16: 104.34724 | BQ16: 102.59173 | BR16: 101.18212 | BS16: 99.281847 | BT16: 98.003931 | BU16: 96.41854 | BV16: 98.464028 | BW16: 97.075129 | BX16: 96.721012 | BY16: 94.577707 | BZ16: 92.401641 | CA16: 92.180405 | CB16: 92.000705 | CC16: 91.878382
A17: Water | I17: #DIV/0! | J17: #DIV/0! | K17: 165.31755 | L17: 171.13792 | M17: 173.18371 | N17: 175.07543 | O17: 173.36106 | P17: 177.61659 | Q17: 176.09264 | R17: 172.01148 | S17: 167.97293 | T17: 165.5075 | U17: 167.03831 | V17: 168.63939 | W17: 167.54205 | X17: 167.18667 | Y17: 166.7374 | Z17: 164.9495 | AA17: 162.73308 | AB17: 164.55717 | AC17: 166.41204 | AD17: 167.16087 | AE17: 165.63304 | AF17: 165.92966 | AG17: 173.98038 | AH17: 174.52568 | AI17: 175.41461 | AJ17: 173.0748 | AK17: 181.89798 | AL17: 181.39813 | AM17: 179.63687 | AN17: 183.36781 | AO17: 186.23736 | AP17: 194.70684 | AQ17: 195.13968 | AR17: 195.6378 | AS17: 196.60305 | AT17: 195.66226 | AU17: 105.9027 | AV17: 107.57449 | AW17: 107.05861 | AX17: 109.85286 | AY17: 109.00104 | AZ17: 107.59978 | BA17: 104.93842 | BB17: 103.63962 | BC17: 105.16967 | BD17: 107.70156 | BE17: 106.98108 | BF17: 106.89521 | BG17: 106.54524 | BH17: 106.3669 | BI17: 106.42658 | BJ17: 106.09 | BK17: 106.68091 | BL17: 107.20591 | BM17: 107.16761 | BN17: 107.35467 | BO17: 113.48759 | BP17: 114.94803 | BQ17: 115.66573 | BR17: 113.81493 | BS17: 119.84481 | BT17: 120.40286 | BU17: 120.17809 | BV17: 121.8228 | BW17: 125.90244 | BX17: 132.6939 | BY17: 134.70795 | BZ17: 135.64668 | CA17: 136.02915 | CB17: 136.11704 | CC17: 143.30198
A18: Construction | I18: #DIV/0! | J18: #DIV/0! | K18: 218.41744 | L18: 205.25775 | M18: 273.10036 | N18: 138.81031 | O18: 167.81173 | P18: 191.06077 | Q18: 229.75491 | R18: 236.50432 | S18: 214.29161 | T18: 201.83249 | U18: 172.43032 | V18: 175.25272 | W18: 183.8499 | X18: 172.4331 | Y18: 151.31715 | Z18: 174.0507 | AA18: 176.94014 | AB18: 176.91608 | AC18: 193.65726 | AD18: 251.13267 | AE18: 171.11326 | AF18: 180.7302 | AG18: 200.20029 | AH18: 175.5607 | AI18: 191.95817 | AJ18: 211.0231 | AK18: 218.35027 | AL18: 198.55891 | AM18: 198.1058 | AN18: 196.32526 | AO18: 201.40356 | AP18: 226.23222 | AQ18: 212.45114 | AR18: 217.03964 | AS18: 214.68444 | AT18: 230.4863 | AU18: 100.30599 | AV18: 100.37418 | AW18: 100.80951 | AX18: 101.8725 | AY18: 104.75414 | AZ18: 103.93295 | BA18: 102.61305 | BB18: 101.34293 | BC18: 99.765253 | BD18: 98.375748 | BE18: 97.42509 | BF18: 95.892924 | BG18: 94.561124 | BH18: 94.491346 | BI18: 95.153248 | BJ18: 97.363191 | BK18: 102.67871 | BL18: 104.9058 | BM18: 105.84315 | BN18: 107.05925 | BO18: 107.92802 | BP18: 107.2913 | BQ18: 106.32213 | BR18: 115.23978 | BS18: 117.50009 | BT18: 122.54874 | BU18: 106.26833 | BV18: 106.23835 | BW18: 114.22144 | BX18: 125.99581 | BY18: 111.76241 | BZ18: 118.2422 | CA18: 116.54228 | CB18: 123.07311 | CC18: 119.08781
A19: SERVICES | I19: #DIV/0! | J19: #DIV/0! | K19: 173.52299 | L19: 183.4863 | M19: 182.99625 | N19: 171.68364 | O19: 158.88113 | P19: 164.08821 | Q19: 157.13383 | R19: 154.18311 | S19: 144.51166 | T19: 155.1547 | U19: 161.69735 | V19: 172.37019 | W19: 148.90705 | X19: 145.93754 | Y19: 158.35822 | Z19: 152.68954 | AA19: 146.1676 | AB19: 157.6812 | AC19: 164.52739 | AD19: 165.74581 | AE19: 168.99062 | AF19: 176.42649 | AG19: 179.66037 | AH19: 166.21806 | AI19: 170.87195 | AJ19: 185.65593 | AK19: 192.09648 | AL19: 189.83987 | AM19: 176.09214 | AN19: 188.91507 | AO19: 210.65479 | AP19: 202.79553 | AQ19: 201.45823 | AR19: 212.58705 | AS19: 220.93414 | AT19: 218.68455 | AU19: 100.98822 | AV19: 99.579724 | AW19: 102.94705 | AX19: 104.43643 | AY19: 102.42537 | AZ19: 104.76742 | BA19: 105.11753 | BB19: 106.96503 | BC19: 107.45925 | BD19: 108.99153 | BE19: 107.87335 | BF19: 106.47606 | BG19: 109.29748 | BH19: 108.86213 | BI19: 108.48927 | BJ19: 108.27844 | BK19: 110.79199 | BL19: 112.65242 | BM19: 114.73138 | BN19: 118.31954 | BO19: 122.17355 | BP19: 122.67947 | BQ19: 122.62985 | BR19: 126.96397 | BS19: 133.75655 | BT19: 129.60194 | BU19: 131.30177 | BV19: 130.70433 | BW19: 138.95745 | BX19: 135.20438 | BY19: 134.74828 | BZ19: 134.90851 | CA19: 141.36608 | CB19: 143.42761 | CC19: 137.3364
A20: Trade & Repairs | I20: #DIV/0! | J20: #DIV/0! | K20: 128.85198 | L20: 147.90255 | M20: 126.19146 | N20: 104.64113 | O20: 118.66682 | P20: 149.87882 | Q20: 145.11264 | R20: 137.38851 | S20: 131.50303 | T20: 131.26005 | U20: 109.34771 | V20: 150.80728 | W20: 112.98905 | X20: 129.14486 | Y20: 136.611 | Z20: 123.14229 | AA20: 104.68398 | AB20: 130.5759 | AC20: 137.31426 | AD20: 133.70012 | AE20: 143.14134 | AF20: 181.38278 | AG20: 185.56299 | AH20: 157.14405 | AI20: 157.51093 | AJ20: 202.56673 | AK20: 238.26106 | AL20: 189.10576 | AM20: 159.42104 | AN20: 179.87539 | AO20: 276.87421 | AP20: 221.63643 | AQ20: 199.48988 | AR20: 224.04494 | AS20: 268.40878 | AT20: 258.17723 | AU20: 101.52129 | AV20: 92.612758 | AW20: 108.48733 | AX20: 111.25957 | AY20: 98.598289 | AZ20: 105.34169 | BA20: 104.74255 | BB20: 103.52642 | BC20: 100.93345 | BD20: 107.84317 | BE20: 109.31896 | BF20: 113.20888 | BG20: 102.39782 | BH20: 110.19456 | BI20: 111.86523 | BJ20: 107.9702 | BK20: 107.12526 | BL20: 113.51102 | BM20: 126.99344 | BN20: 137.38307 | BO20: 139.86456 | BP20: 134.61705 | BQ20: 143.55661 | BR20: 154.18894 | BS20: 164.75046 | BT20: 149.37806 | BU20: 147.6565 | BV20: 139.97864 | BW20: 165.39049 | BX20: 158.40349 | BY20: 152.37965 | BZ20: 150.9037 | CA20: 163.15493 | CB20: 184.57701 | CC20: 157.02497
A21: Transportation & Storage | I21: #DIV/0! | J21: #DIV/0! | K21: 169.54502 | L21: 186.05012 | M21: 189.00773 | N21: 176.48126 | O21: 174.0392 | P21: 184.56807 | Q21: 194.43259 | R21: 183.14238 | S21: 182.8472 | T21: 194.47517 | U21: 188.81091 | V21: 196.32671 | W21: 158.90302 | X21: 158.99123 | Y21: 197.14715 | Z21: 176.00072 | AA21: 147.97738 | AB21: 162.3706 | AC21: 168.36617 | AD21: 183.51326 | AE21: 171.90562 | AF21: 178.05658 | AG21: 182.29623 | AH21: 213.55582 | AI21: 212.03407 | AJ21: 211.77596 | AK21: 202.62032 | AL21: 222.20711 | AM21: 223.9725 | AN21: 221.22073 | AO21: 233.37145 | AP21: 246.61815 | AQ21: 255.92633 | AR21: 252.12221 | AS21: 229.73421 | AT21: 245.65961 | AU21: 102.09514 | AV21: 102.57427 | AW21: 102.00251 | AX21: 101.61239 | AY21: 108.62672 | AZ21: 111.49122 | BA21: 109.73227 | BB21: 114.96424 | BC21: 123.49235 | BD21: 125.32869 | BE21: 116.26476 | BF21: 114.23985 | BG21: 134.83167 | BH21: 124.22809 | BI21: 109.96433 | BJ21: 114.12556 | BK21: 131.16764 | BL21: 141.09245 | BM21: 126.49597 | BN21: 143.94993 | BO21: 166.33011 | BP21: 179.78423 | BQ21: 182.92645 | BR21: 185.84649 | BS21: 184.79399 | BT21: 190.30128 | BU21: 189.21167 | BV21: 192.98774 | BW21: 194.81404 | BX21: 197.95277 | BY21: 192.06597 | BZ21: 188.23963 | CA21: 188.14068 | CB21: 190.10354 | CC21: 192.76413
A22: Accommodation & Food Service | I22: #DIV/0! | J22: #DIV/0! | K22: 168.89849 | L22: 216.68622 | M22: 257.82777 | N22: 229.40399 | O22: 188.01143 | P22: 185.36531 | Q22: 213.40084 | R22: 189.74989 | S22: 188.81309 | T22: 206.11267 | U22: 209.46595 | V22: 197.54833 | W22: 158.37798 | X22: 96.197502 | Y22: 149.92424 | Z22: 150.29049 | AA22: 144.60367 | AB22: 182.93892 | AC22: 144.36987 | AD22: 172.68387 | AE22: 121.19372 | AF22: 165.12767 | AG22: 126.16311 | AH22: 156.6465 | AI22: 129.14964 | AJ22: 215.27503 | AK22: 168.70944 | AL22: 159.7709 | AM22: 156.52368 | AN22: 256.60505 | AO22: 181.01934 | AP22: 193.06056 | AQ22: 162.74868 | AR22: 182.09924 | AS22: 203.91774 | AT22: 182.54257 | AU22: 103.94581 | AV22: 103.27584 | AW22: 102.42012 | AX22: 103.25332 | AY22: 105.75917 | AZ22: 106.04807 | BA22: 107.14055 | BB22: 109.76415 | BC22: 112.38398 | BD22: 113.00893 | BE22: 112.59556 | BF22: 105.81471 | BG22: 108.91584 | BH22: 107.95936 | BI22: 109.08946 | BJ22: 110.98588 | BK22: 111.15651 | BL22: 113.55698 | BM22: 113.80408 | BN22: 115.36847 | BO22: 113.54318 | BP22: 112.45826 | BQ22: 111.73232 | BR22: 114.53634 | BS22: 114.5683 | BT22: 114.40025 | BU22: 117.25434 | BV22: 122.42122 | BW22: 122.66022 | BX22: 124.30453 | BY22: 126.29556 | BZ22: 128.72402 | CA22: 130.02759 | CB22: 130.78814 | CC22: 132.53752
A23: Information & Communication | I23: #DIV/0! | J23: #DIV/0! | K23: #DIV/0! | L23: #DIV/0! | M23: #DIV/0! | N23: #DIV/0! | O23: 310.76905 | P23: 229.88932 | Q23: 258.40335 | R23: 281.58271 | S23: 246.96423 | T23: 248.46049 | U23: 285.25089 | V23: 262.39899 | W23: 224.11626 | X23: 187.71472 | Y23: 198.22965 | Z23: 221.55675 | AA23: 213.57364 | AB23: 204.62686 | AC23: 187.63822 | AD23: 195.25676 | AE23: 170.15769 | AF23: 160.98351 | AG23: 163.83765 | AH23: 164.41319 | AI23: 184.84043 | AJ23: 209.61939 | AK23: 282.30085 | AL23: 306.21138 | AM23: 263.47649 | AN23: 214.8211 | AO23: 303.73036 | AP23: 219.54861 | AQ23: 237.84426 | AR23: 183.69692 | AS23: 202.58815 | AT23: 209.33491 | AU23: 81.396685 | AV23: 79.725346 | AW23: 82.135634 | AX23: 91.1499 | AY23: 102.57683 | AZ23: 111.04539 | BA23: 112.91158 | BB23: 111.47875 | BC23: 101.88295 | BD23: 98.061292 | BE23: 94.828923 | BF23: 94.746496 | BG23: 91.624071 | BH23: 91.009341 | BI23: 91.971595 | BJ23: 91.068353 | BK23: 88.471277 | BL23: 88.838705 | BM23: 87.964106 | BN23: 83.85918 | BO23: 77.557326 | BP23: 77.155205 | BQ23: 79.743437 | BR23: 89.945052 | BS23: 107.96404 | BT23: 122.17531 | BU23: 127.22358 | BV23: 126.4113 | BW23: 118.22287 | BX23: 113.84766 | BY23: 112.61468 | BZ23: 113.224 | CA23: 113.09177 | CB23: 113.97477 | CC23: 113.48063
A24: Financial & Insurance | I24: #DIV/0! | J24: #DIV/0! | K24: 198.18839 | L24: 163.57328 | M24: 180.70096 | N24: 192.03121 | O24: 209.22259 | P24: 176.58431 | Q24: 177.987 | R24: 176.29405 | S24: 155.58958 | T24: 207.81003 | U24: 268.09614 | V24: 211.77529 | W24: 192.45979 | X24: 146.85788 | Y24: 232.43109 | Z24: 202.29905 | AA24: 197.9791 | AB24: 186.22944 | AC24: 223.08073 | AD24: 205.63775 | AE24: 216.42557 | AF24: 202.52583 | AG24: 209.99918 | AH24: 226.19506 | AI24: 141.27014 | AJ24: 185.50342 | AK24: 207.84968 | AL24: 213.11973 | AM24: 171.55372 | AN24: 183.37582 | AO24: 210.35137 | AP24: 208.33918 | AQ24: 203.71095 | AR24: 216.93954 | AS24: 235.58064 | AT24: 228.53238 | AU24: 103.60409 | AV24: 105.38867 | AW24: 104.63273 | AX24: 103.85216 | AY24: 100.23473 | AZ24: 102.95043 | BA24: 105.28248 | BB24: 114.50749 | BC24: 117.12552 | BD24: 114.99303 | BE24: 104.63732 | BF24: 87.266257 | BG24: 117.86198 | BH24: 105.98608 | BI24: 103.69083 | BJ24: 97.740446 | BK24: 120.5955 | BL24: 115.96052 | BM24: 114.94383 | BN24: 110.62724 | BO24: 138.84769 | BP24: 139.69329 | BQ24: 105.14141 | BR24: 118.87519 | BS24: 142.41837 | BT24: 135.12557 | BU24: 145.51429 | BV24: 117.8984 | BW24: 143.66603 | BX24: 137.4656 | BY24: 149.13037 | BZ24: 125.51375 | CA24: 147.59835 | CB24: 143.19315 | CC24: 154.94923
A25: Real Estate Activities | I25: #DIV/0! | J25: #DIV/0! | K25: 144.04864 | L25: 146.54228 | M25: 161.53559 | N25: 163.44538 | O25: 167.85462 | P25: 163.28415 | Q25: 171.22891 | R25: 165.32108 | S25: 166.16134 | T25: 175.75448 | U25: 177.00981 | V25: 181.04511 | W25: 187.59733 | X25: 185.52519 | Y25: 180.24297 | Z25: 165.65511 | AA25: 172.6776 | AB25: 182.48091 | AC25: 183.05192 | AD25: 187.55032 | AE25: 185.28036 | AF25: 187.25049 | AG25: 190.76466 | AH25: 193.07789 | AI25: 190.61931 | AJ25: 194.65147 | AK25: 195.87405 | AL25: 192.70288 | AM25: 189.43707 | AN25: 195.44438 | AO25: 195.15791 | AP25: 198.83669 | AQ25: 208.53834 | AR25: 208.88028 | AS25: 207.21049 | AT25: 200.54323 | AU25: 101.55468 | AV25: 101.52594 | AW25: 102.44672 | AX25: 102.82336 | AY25: 102.45126 | AZ25: 102.87699 | BA25: 103.72389 | BB25: 105.13115 | BC25: 105.12803 | BD25: 106.11412 | BE25: 105.85436 | BF25: 106.04064 | BG25: 105.81921 | BH25: 105.92746 | BI25: 106.09679 | BJ25: 106.21236 | BK25: 106.42366 | BL25: 106.77586 | BM25: 107.43083 | BN25: 107.9329 | BO25: 108.83389 | BP25: 109.36135 | BQ25: 109.92995 | BR25: 109.67496 | BS25: 109.94961 | BT25: 110.17635 | BU25: 110.7813 | BV25: 111.27524 | BW25: 112.28309 | BX25: 112.45627 | BY25: 112.18763 | BZ25: 112.7872 | CA25: 112.60109 | CB25: 112.61755 | CC25: 111.70249
A26: Professional, Scientific & Technical | I26: #DIV/0! | J26: #DIV/0! | K26: #DIV/0! | L26: #DIV/0! | M26: #DIV/0! | N26: #DIV/0! | O26: 190.30817 | P26: 182.63734 | Q26: 66.001879 | R26: 64.981782 | S26: 55.438199 | T26: 84.254393 | U26: 171.31737 | V26: 133.47805 | W26: 75.284792 | X26: 93.8991 | Y26: 76.096004 | Z26: 97.079143 | AA26: 92.702366 | AB26: 92.343921 | AC26: 139.88538 | AD26: 110.28423 | AE26: 113.15318 | AF26: 94.838452 | AG26: 163.55229 | AH26: 130.44451 | AI26: 131.70734 | AJ26: 120.96637 | AK26: 111.45898 | AL26: 234.06655 | AM26: 155.66176 | AN26: 130.67468 | AO26: 130.2963 | AP26: 184.35874 | AQ26: 194.80391 | AR26: 214.51563 | AS26: 192.74976 | AT26: 186.64403 | AU26: 103.33676 | AV26: 103.17806 | AW26: 103.24203 | AX26: 104.74434 | AY26: 102.30455 | AZ26: 102.39283 | BA26: 102.35734 | BB26: 104.79772 | BC26: 104.81382 | BD26: 105.53338 | BE26: 105.76418 | BF26: 107.7021 | BG26: 106.16324 | BH26: 105.47843 | BI26: 105.60439 | BJ26: 106.04982 | BK26: 105.98273 | BL26: 107.61403 | BM26: 109.59785 | BN26: 111.30015 | BO26: 113.43526 | BP26: 116.20944 | BQ26: 115.80388 | BR26: 116.32871 | BS26: 117.59149 | BT26: 118.81318 | BU26: 118.3642 | BV26: 119.14279 | BW26: 119.50155 | BX26: 120.26337 | BY26: 120.86207 | BZ26: 123.01128 | CA26: 122.74719 | CB26: 123.15449 | CC26: 123.52443
A27: Administrative & Support Service | I27: #DIV/0! | J27: #DIV/0! | K27: #DIV/0! | L27: #DIV/0! | M27: #DIV/0! | N27: #DIV/0! | O27: 146.20977 | P27: 151.69182 | Q27: 149.21581 | R27: 142.33758 | S27: 133.91527 | T27: 124.26249 | U27: 136.95576 | V27: 132.19169 | W27: 121.9099 | X27: 127.46373 | Y27: 153.64932 | Z27: 162.69923 | AA27: 162.8841 | AB27: 174.5942 | AC27: 186.45134 | AD27: 199.39315 | AE27: 189.99493 | AF27: 190.10633 | AG27: 201.76719 | AH27: 183.82715 | AI27: 178.41747 | AJ27: 171.84979 | AK27: 170.08632 | AL27: 180.10025 | AM27: 197.85371 | AN27: 206.34586 | AO27: 232.53932 | AP27: 220.4651 | AQ27: 232.10231 | AR27: 246.64562 | AS27: 227.1594 | AT27: 280.3573 | AU27: 101.21034 | AV27: 101.13596 | AW27: 100.39168 | AX27: 99.766431 | AY27: 101.43764 | AZ27: 102.11508 | BA27: 101.97294 | BB27: 101.00266 | BC27: 102.67873 | BD27: 101.9408 | BE27: 103.00483 | BF27: 101.65172 | BG27: 107.53292 | BH27: 109.14572 | BI27: 110.24839 | BJ27: 113.80322 | BK27: 117.30031 | BL27: 119.11218 | BM27: 118.47973 | BN27: 118.82493 | BO27: 118.69562 | BP27: 120.03832 | BQ27: 119.4276 | BR27: 123.74255 | BS27: 127.72119 | BT27: 133.30153 | BU27: 122.74168 | BV27: 122.98621 | BW27: 128.19824 | BX27: 128.08209 | BY27: 115.10927 | BZ27: 134.17826 | CA27: 126.85231 | CB27: 124.25801 | CC27: 115.64137
A28: Public Administration | I28: #DIV/0! | J28: #DIV/0! | K28: 258.53456 | L28: 247.95465 | M28: 225.84351 | N28: 188.40748 | O28: 236.81361 | P28: 206.85861 | Q28: 203.45505 | R28: 192.4874 | S28: 179.27437 | T28: 190.22257 | U28: 219.80979 | V28: 240.32198 | W28: 238.16222 | X28: 229.06254 | Y28: 266.81339 | Z28: 263.72662 | AA28: 286.67928 | AB28: 250.13816 | AC28: 276.51575 | AD28: 293.73115 | AE28: 319.01526 | AF28: 304.64181 | AG28: 310.29868 | AH28: 301.17455 | AI28: 247.2227 | AJ28: 240.65746 | AK28: 225.21537 | AL28: 286.97875 | AM28: 262.21865 | AN28: 307.07579 | AO28: 224.02898 | AP28: 265.62595 | AQ28: 247.68087 | AR28: 275.56891 | AS28: 183.40987 | AT28: 254.37465 | AU28: 102.56327 | AV28: 104.11337 | AW28: 104.49241 | AX28: 104.6162 | AY28: 106.02981 | AZ28: 106.19719 | BA28: 106.63588 | BB28: 106.82538 | BC28: 108.26653 | BD28: 108.39207 | BE28: 109.1015 | BF28: 109.27943 | BG28: 111.35046 | BH28: 111.55833 | BI28: 110.853 | BJ28: 111.91631 | BK28: 113.05147 | BL28: 114.06854 | BM28: 115.85116 | BN28: 118.71889 | BO28: 123.56091 | BP28: 125.80295 | BQ28: 126.12988 | BR28: 127.0364 | BS28: 131.36058 | BT28: 127.28318 | BU28: 128.8565 | BV28: 130.78009 | BW28: 131.50967 | BX28: 133.06431 | BY28: 134.68469 | BZ28: 136.18724 | CA28: 137.49183 | CB28: 138.40789 | CC28: 140.32747
A29: Education | I29: #DIV/0! | J29: #DIV/0! | K29: 136.94806 | L29: 147.18969 | M29: 151.73737 | N29: 152.06539 | O29: 156.60624 | P29: 148.92417 | Q29: 159.08688 | R29: 179.40283 | S29: 146.66775 | T29: 150.56397 | U29: 147.04938 | V29: 152.07021 | W29: 147.25291 | X29: 139.27846 | Y29: 119.95757 | Z29: 118.24714 | AA29: 127.70316 | AB29: 135.2607 | AC29: 125.72102 | AD29: 123.71747 | AE29: 162.04423 | AF29: 157.07076 | AG29: 147.67017 | AH29: 90.689781 | AI29: 161.80685 | AJ29: 156.95265 | AK29: 159.84059 | AL29: 104.91961 | AM29: 130.38967 | AN29: 144.37051 | AO29: 166.46168 | AP29: 133.50866 | AQ29: 158.53647 | AR29: 191.33091 | AS29: 229.59274 | AT29: 180.74564 | AU29: 100.20902 | AV29: 103.35524 | AW29: 104.20661 | AX29: 106.52467 | AY29: 101.77902 | AZ29: 103.05576 | BA29: 103.92347 | BB29: 108.22475 | BC29: 108.20013 | BD29: 108.18605 | BE29: 105.53342 | BF29: 100.91298 | BG29: 109.7659 | BH29: 103.8002 | BI29: 104.64363 | BJ29: 107.67527 | BK29: 109.44705 | BL29: 109.34011 | BM29: 106.86419 | BN29: 115.33396 | BO29: 119.15678 | BP29: 118.18787 | BQ29: 122.4685 | BR29: 127.59234 | BS29: 131.66907 | BT29: 112.7961 | BU29: 133.14928 | BV29: 135.44434 | BW29: 139.15329 | BX29: 124.02831 | BY29: 136.58171 | BZ29: 138.49381 | CA29: 159.97945 | CB29: 144.11195 | CC29: 138.43114
A30: Human Health & Social Work | I30: #DIV/0! | J30: #DIV/0! | K30: 142.22631 | L30: 146.0782 | M30: 165.32079 | N30: 161.30138 | O30: 161.1849 | P30: 157.23822 | Q30: 178.08148 | R30: 168.57795 | S30: 161.77889 | T30: 158.79797 | U30: 172.18935 | V30: 180.58697 | W30: 163.22194 | X30: 150.87836 | Y30: 190.39524 | Z30: 183.84754 | AA30: 171.49674 | AB30: 177.52415 | AC30: 186.24151 | AD30: 212.90388 | AE30: 222.22159 | AF30: 213.70881 | AG30: 196.86862 | AH30: 173.28166 | AI30: 226.24185 | AJ30: 187.75077 | AK30: 168.63677 | AL30: 187.40359 | AM30: 190.17562 | AN30: 215.58206 | AO30: 196.17088 | AP30: 217.84886 | AQ30: 216.91166 | AR30: 207.18979 | AS30: 204.17296 | AT30: 218.70039 | AU30: 101.11535 | AV30: 102.24093 | AW30: 103.86577 | AX30: 104.96624 | AY30: 106.38717 | AZ30: 106.24495 | BA30: 106.61235 | BB30: 105.49026 | BC30: 107.4971 | BD30: 108.2279 | BE30: 110.88503 | BF30: 110.79821 | BG30: 111.6979 | BH30: 113.12912 | BI30: 117.79654 | BJ30: 119.04711 | BK30: 119.27067 | BL30: 119.17456 | BM30: 121.47354 | BN30: 120.14506 | BO30: 121.87805 | BP30: 122.31069 | BQ30: 122.53395 | BR30: 123.64464 | BS30: 124.41712 | BT30: 127.20898 | BU30: 117.0122 | BV30: 133.13444 | BW30: 130.99427 | BX30: 128.26708 | BY30: 127.85744 | BZ30: 128.98059 | CA30: 131.91298 | CB30: 132.44552 | CC30: 133.98415
A31: Arts, Entertainment & Recreation | I31: #DIV/0! | J31: #DIV/0! | K31: #DIV/0! | L31: #DIV/0! | M31: #DIV/0! | N31: #DIV/0! | O31: 293.85547 | P31: 321.77827 | Q31: 285.14485 | R31: 245.70889 | S31: 217.0819 | T31: 146.89985 | U31: 779.35826 | V31: 598.99843 | W31: 433.36853 | X31: 178.67751 | Y31: 170.31443 | Z31: 227.18209 | AA31: 219.68609 | AB31: 242.92771 | AC31: 360.21849 | AD31: 238.56344 | AE31: 252.22395 | AF31: 208.7188 | AG31: 186.09846 | AH31: 222.07651 | AI31: 277.16964 | AJ31: 305.15773 | AK31: 340.19717 | AL31: 208.69723 | AM31: 349.05194 | AN31: 271.23507 | AO31: 392.63454 | AP31: 349.53442 | AQ31: 437.38404 | AR31: 285.55499 | AS31: 308.46965 | AT31: 148.8219 | AU31: 98.617524 | AV31: 98.08364 | AW31: 98.457574 | AX31: 98.111286 | AY31: 93.823617 | AZ31: 93.26681 | BA31: 93.491501 | BB31: 95.551425 | BC31: 103.72703 | BD31: 103.30951 | BE31: 103.4399 | BF31: 101.82885 | BG31: 107.48127 | BH31: 109.10837 | BI31: 108.59337 | BJ31: 109.66355 | BK31: 113.6159 | BL31: 112.45037 | BM31: 111.3871 | BN31: 116.73289 | BO31: 120.58604 | BP31: 122.97054 | BQ31: 122.27006 | BR31: 124.2207 | BS31: 128.07416 | BT31: 133.75555 | BU31: 138.52196 | BV31: 143.94813 | BW31: 145.50564 | BX31: 148.26835 | BY31: 151.8647 | BZ31: 157.27242 | CA31: 145.40764 | CB31: 148.2158 | CC31: 151.84776
A32: Other Service Activities | I32: #DIV/0! | J32: #DIV/0! | K32: 167.51618 | L32: 157.27534 | M32: 145.61662 | N32: 147.16464 | O32: 143.18843 | P32: 144.67073 | Q32: 149.14132 | R32: 150.36115 | S32: 149.88451 | T32: 157.69918 | U32: 162.78737 | V32: 163.00557 | W32: 156.62764 | X32: 154.35544 | Y32: 160.74708 | Z32: 158.16611 | AA32: 160.3081 | AB32: 158.46923 | AC32: 153.18317 | AD32: 142.72678 | AE32: 147.79066 | AF32: 140.79764 | AG32: 133.03551 | AH32: 137.25608 | AI32: 130.58388 | AJ32: 129.6695 | AK32: 142.6442 | AL32: 159.24 | AM32: 136.49963 | AN32: 120.74731 | AO32: 150.88963 | AP32: 152.88962 | AQ32: 150.0913 | AR32: 157.13464 | AS32: 169.39582 | AT32: 156.53135 | AU32: 101.69819 | AV32: 101.88672 | AW32: 98.851691 | AX32: 99.548056 | AY32: 99.442888 | AZ32: 99.298325 | BA32: 100.19209 | BB32: 105.75184 | BC32: 109.19027 | BD32: 111.01721 | BE32: 111.35601 | BF32: 110.5018 | BG32: 114.5326 | BH32: 114.39063 | BI32: 115.00991 | BJ32: 113.25575 | BK32: 108.79858 | BL32: 103.61133 | BM32: 109.60338 | BN32: 108.06637 | BO32: 105.54714 | BP32: 104.8105 | BQ32: 103.93502 | BR32: 105.17113 | BS32: 115.61222 | BT32: 115.30209 | BU32: 117.68301 | BV32: 122.75625 | BW32: 131.34226 | BX32: 130.81201 | BY32: 129.92579 | BZ32: 130.33072 | CA32: 137.07436 | CB32: 140.24192 | CC32: 130.25236
A33: Activities of Households | I33: #DIV/0! | J33: #DIV/0! | K33: 127.70454 | L33: 129.56501 | M33: 129.22466 | N33: 129.92659 | O33: 129.75836 | P33: 130.67328 | Q33: 131.36193 | R33: 131.82043 | S33: 132.11812 | T33: 133.4387 | U33: 134.09835 | V33: 135.31906 | W33: 136.4014 | X33: 138.3621 | Y33: 139.19139 | Z33: 140.05653 | AA33: 140.64637 | AB33: 142.17532 | AC33: 142.9961 | AD33: 144.24872 | AE33: 145.66041 | AF33: 150.20517 | AG33: 153.68148 | AH33: 164.82868 | AI33: 162.29369 | AJ33: 161.34068 | AK33: 160.63272 | AL33: 162.46325 | AM33: 163.89561 | AN33: 165.74002 | AO33: 166.2363 | AP33: 167.88692 | AQ33: 169.80927 | AR33: 171.80147 | AS33: 172.32973 | AT33: 171.90403 | AU33: 102.765 | AV33: 103.72044 | AW33: 104.06692 | AX33: 105.14766 | AY33: 105.88385 | AZ33: 106.27333 | BA33: 106.38412 | BB33: 107.28481 | BC33: 107.60228 | BD33: 108.32187 | BE33: 108.89799 | BF33: 110.20219 | BG33: 110.61554 | BH33: 111.06746 | BI33: 111.30051 | BJ33: 112.34583 | BK33: 112.91445 | BL33: 113.89133 | BM33: 115.05044 | BN33: 119.24795 | BO33: 123.22687 | BP33: 126.03663 | BQ33: 126.16875 | BR33: 126.9131 | BS33: 127.31756 | BT33: 129.16219 | BU33: 130.04935 | BV33: 131.34408 | BW33: 131.71412 | BX33: 133.0791 | BY33: 134.64642 | BZ33: 136.24796 | CA33: 136.76319 | CB33: 137.37987 | CC33: 138.61095
A35: ADJUSTMENTS
A36: Taxes on products | I36: #DIV/0! | J36: #DIV/0! | K36: 203.14672 | L36: 222.56056 | M36: 158.08568 | N36: 179.12987 | O36: 196.47715 | P36: 212.80244 | Q36: 217.88418 | R36: 233.97645 | S36: 215.78973 | T36: 195.85594 | U36: 191.96371 | V36: 217.9476 | W36: 200.77445 | X36: 117.25914 | Y36: 167.1203 | Z36: 187.02245 | AA36: 186.91462 | AB36: 203.21492 | AC36: 186.06 | AD36: 214.88475 | AE36: 221.46834 | AF36: 221.9767 | AG36: 197.37629 | AH36: 200.15749 | AI36: 228.93643 | AJ36: 241.20296 | AK36: 211.63583 | AL36: 202.83086 | AM36: 224.5136 | AN36: 227.89379 | AO36: 247.46311 | AP36: 229.12833 | AQ36: 222.65597 | AR36: 260.05117 | AS36: 215.47992 | AT36: 225.82304 | AU36: 98.860365 | AV36: 106.25056 | AW36: 116.03619 | AX36: 112.94704 | AY36: 118.81179 | AZ36: 122.87996 | BA36: 116.97476 | BB36: 113.88375 | BC36: 113.05824 | BD36: 117.37788 | BE36: 123.89242 | BF36: 102.89785 | BG36: 118.15688 | BH36: 125.57577 | BI36: 128.99381 | BJ36: 116.67932 | BK36: 129.05725 | BL36: 136.24321 | BM36: 129.96752 | BN36: 131.56069 | BO36: 131.32229 | BP36: 129.29171 | BQ36: 138.11395 | BR36: 147.96689 | BS36: 129.26802 | BT36: 138.78259 | BU36: 136.47988 | BV36: 141.37944 | BW36: 132.01223 | BX36: 143.53575 | BY36: 141.95384 | BZ36: 156.2819 | CA36: 131.19511 | CB36: 146.30101 | CC36: 148.15003
A37: Source: Uganda Bureau of Statistics
Z38: 8.5

Sheet Deseason_VA
A1: Table 6: SEASONALLY ADJUSTED Value Added at constant 2016/17 prices, BILLION SHILLINGS, 2016/17-2025/26
B2: 2008Q1 | C2: 2008Q2 | D2: 2008Q3 | E2: 2008Q4 | F2: 2009Q1 | G2: 2009Q2 | H2: 2009Q3 | I2: 2009Q4 | J2: 2010Q1 | K2: 2010Q2 | L2: 2010Q3 | M2: 2010Q4 | N2: 2011Q1 | O2: 2011Q2 | P2: 2011Q3 | Q2: 2011Q4 | R2: 2012Q1 | S2: 2012Q2 | T2: 2012Q3 | U2: 2012Q4 | V2: 2013Q1 | W2: 2013Q2 | X2: 2013Q3 | Y2: 2013Q4 | Z2: 2014Q1 | AA2: 2014Q2 | AB2: 2014Q3 | AC2: 2014Q4 | AD2: 2015Q1 | AE2: 2015Q2 | AF2: 2015Q3
H3: 2009/10 | L3: 2010/11 | P3: 2011/12 | R3: 2011/12 | T3: 2012/13 | X3: 2013/14 | Y3: 2013/14 | AA3: 2013/14 | AB3: 2014/15 | AD3: 2014/15 | AE3: 2014/15 | AF3: 2015/16 | AJ3: 2016/17 | AN3: 2017/18 | AR3: 2018/19 | AV3: 2019/20 | AZ3: 2020/21 | BD3: 2021/22 | BH3: 2022/23 | BL3: 2023/24 | BP3: 2024/25 | BT3: 2025/26
H4: Q1 | I4: Q2 | J4: Q3 | K4: Q4 | L4: Q1 | M4: Q2 | N4: Q3 | O4: Q4 | P4: Q1 | Q4: Q2 | R4: Q3 | S4: Q4 | T4: Q1 | U4: Q2 | V4: Q3 | W4: Q4 | X4: Q1 | Y4: Q2 | Z4: Q3 | AA4: Q4 | AB4: Q1 | AC4: Q2 | AD4: Q3 | AE4: Q4 | AF4: Q1 | AG4: Q2 | AH4: Q3 | AI4: Q4 | AJ4: Q1 | AK4: Q2 | AL4: Q3 | AM4: Q4 | AN4: Q1 | AO4: Q2 | AP4: Q3 | AQ4: Q4 | AR4: Q1 | AS4: Q2 | AT4: Q3 | AU4: Q4 | AV4: Q1 | AW4: Q2 | AX4: Q3 | AY4: Q4 | AZ4: Q1 | BA4: Q2 | BB4: Q3 | BC4: Q4 | BD4: Q1 | BE4: Q2 | BF4: Q3 | BG4: Q4 | BH4: Q1 | BI4: Q2 | BJ4: Q3 | BK4: Q4 | BL4: Q1 | BM4: Q2 | BN4: Q3 | BO4: Q4 | BP4: Q1 | BQ4: Q2 | BR4: Q3 | BS4: Q4 | BT4: Q1 | BU4: Q2 | BV4: Q3
A5: GDP AT MARKET PRICES | H5: 19281.409 | I5: 19536.769 | J5: 20670.65 | K5: 21088.659 | L5: 21342.53 | M5: 21896.853 | N5: 22390.232 | O5: 21682.915 | P5: 22486.721 | Q5: 21911.014 | R5: 22517.31 | S5: 22741.164 | T5: 23670.651 | U5: 22632.373 | V5: 22653.884 | W5: 22266.491 | X5: 23206.646 | Y5: 22781.855 | Z5: 24142.298 | AA5: 25208.001 | AB5: 24323.405 | AC5: 25323.803 | AD5: 25570.867 | AE5: 26198.304 | AF5: 26581.324 | AG5: 26727.381 | AH5: 25866.214 | AI5: 26198.378 | AJ5: 26416.451 | AK5: 26812.127 | AL5: 27622.085 | AM5: 27889.914 | AN5: 28283.055 | AO5: 28554.154 | AP5: 29229.258 | AQ5: 29445.35 | AR5: 29941.017 | AS5: 30143.981 | AT5: 31566.283 | AU5: 31403.382 | AV5: 32277.506 | AW5: 32675.789 | AX5: 31950.55 | AY5: 29675.735 | AZ5: 31890.177 | BA5: 32666.766 | BB5: 32921.015 | BC5: 33306.169 | BD5: 32640.319 | BE5: 34251.442 | BF5: 35011.57 | BG5: 35145.427 | BH5: 35487.513 | BI5: 35824.548 | BJ5: 35816.891 | BK5: 36991.392 | BL5: 37471.979 | BM5: 37983.243 | BN5: 38376.532 | BO5: 39004.919 | BP5: 39841.908 | BQ5: 40048.472 | BR5: 41537.216 | BS5: 41152.31 | BT5: 41956.657 | BU5: 43451.338 | BV5: 43978.861
A6: AGRICULTURE,FORESTRY&FISHING | H6: 5418.8793 | I6: 5379.0102 | J6: 5427.2084 | K6: 5738.8634 | L6: 5490.5743 | M6: 5532.3699 | N6: 5851.2593 | O6: 5835.9554 | P6: 6128.9977 | Q6: 5564.0629 | R6: 5419.9699 | S6: 5502.7141 | T6: 6154.724 | U6: 5509.1535 | V6: 5589.387 | W6: 5236.6888 | X6: 6195.7516 | Y6: 5535.5894 | Z6: 5643.2176 | AA6: 5850.6262 | AB6: 5919.8009 | AC6: 6130.1701 | AD6: 5947.1034 | AE6: 6098.914 | AF6: 6058.9851 | AG6: 6151.8418 | AH6: 6459.6385 | AI6: 6172.2801 | AJ6: 6113.4118 | AK6: 6365.2952 | AL6: 6582.8786 | AM6: 6545.6275 | AN6: 6624.1464 | AO6: 6533.1995 | AP6: 6887.5132 | AQ6: 6659.0806 | AR6: 6777.8345 | AS6: 6778.2824 | AT6: 7531.2265 | AU6: 7188.48 | AV6: 7180.5444 | AW6: 7289.088 | AX6: 7451.5711 | AY6: 7595.3947 | AZ6: 7565.5859 | BA6: 7818.2609 | BB6: 7524.9016 | BC6: 7643.6427 | BD6: 7912.3918 | BE6: 7634.5177 | BF6: 8038.7603 | BG6: 8456.0785 | BH6: 8143.4333 | BI6: 8514.0709 | BJ6: 8384.5547 | BK6: 8258.2818 | BL6: 8594.2364 | BM6: 8663.2015 | BN6: 8847.9762 | BO6: 9132.1583 | BP6: 9180.715 | BQ6: 9290.6771 | BR6: 9645.6266 | BS6: 9451.6369 | BT6: 9588.3204 | BU6: 10082.951 | BV6: 9947.8206
A7: Cash crops | H7: 494.58272 | I7: 483.63677 | J7: 365.78297 | K7: 572.76168 | L7: 449.31213 | M7: 446.51707 | N7: 524.32521 | O7: 498.13035 | P7: 558.42661 | Q7: 528.73263 | R7: 487.19815 | S7: 521.39465 | T7: 497.51564 | U7: 511.6843 | V7: 546.36115 | W7: 539.23503 | X7: 537.11765 | Y7: 552.2808 | Z7: 493.08552 | AA7: 503.84528 | AB7: 517.8232 | AC7: 504.22703 | AD7: 564.81305 | AE7: 583.15387 | AF7: 604.2055 | AG7: 573.24311 | AH7: 576.08968 | AI7: 586.49967 | AJ7: 503.30611 | AK7: 710.83122 | AL7: 654.64494 | AM7: 690.02128 | AN7: 709.64797 | AO7: 670.80291 | AP7: 664.73906 | AQ7: 663.55759 | AR7: 709.13985 | AS7: 706.25186 | AT7: 675.46613 | AU7: 746.04683 | AV7: 727.01261 | AW7: 768.48116 | AX7: 801.68146 | AY7: 764.05392 | AZ7: 774.6919 | BA7: 864.71597 | BB7: 898.46825 | BC7: 906.0144 | BD7: 939.95052 | BE7: 921.42453 | BF7: 849.2307 | BG7: 927.14783 | BH7: 924.89569 | BI7: 884.41858 | BJ7: 914.97792 | BK7: 934.86632 | BL7: 975.81339 | BM7: 1034.6492 | BN7: 1077.4858 | BO7: 1017.1926 | BP7: 1140.7186 | BQ7: 1139.7589 | BR7: 1182.3411 | BS7: 1104.6496 | BT7: 1224.5715 | BU7: 1284.9475 | BV7: 1280.0869
A8: Food crops | H8: 3034.2316 | I8: 3055.2466 | J8: 3107.8952 | K8: 3120.2414 | L8: 3018.1074 | M8: 3070.5057 | N8: 3290.864 | O8: 3331.5542 | P8: 3183.6719 | Q8: 3281.8672 | R8: 2920.821 | S8: 2922.8504 | T8: 3564.9335 | U8: 2769.5856 | V8: 2781.5976 | W8: 2730.0321 | X8: 3459.1796 | Y8: 2733.9919 | Z8: 2998.9316 | AA8: 3157.9864 | AB8: 3149.7083 | AC8: 3432.7295 | AD8: 3156.3732 | AE8: 3223.423 | AF8: 3198.9919 | AG8: 3374.4569 | AH8: 3335.9939 | AI8: 3265.8907 | AJ8: 3247.5948 | AK8: 3276.5139 | AL8: 3540.1029 | AM8: 3485.1384 | AN8: 3588.423 | AO8: 3582.1012 | AP8: 3913.4612 | AQ8: 3586.8933 | AR8: 3585.2693 | AS8: 3511.1158 | AT8: 4220.7531 | AU8: 3744.7385 | AV8: 3722.0179 | AW8: 3791.1797 | AX8: 3961.6441 | AY8: 4159.402 | AZ8: 4085.0858 | BA8: 4118.4374 | BB8: 3866.8169 | BC8: 3972.5093 | BD8: 4101.5879 | BE8: 3882.1265 | BF8: 4274.1488 | BG8: 4567.22 | BH8: 4382.6023 | BI8: 4556.7513 | BJ8: 4230.7677 | BK8: 4250.8675 | BL8: 4563.4329 | BM8: 4508.0169 | BN8: 4607.7433 | BO8: 4710.2146 | BP8: 4809.2737 | BQ8: 4771.6128 | BR8: 4804.536 | BS8: 4826.7163 | BT8: 4781.9883 | BU8: 5122.2452 | BV8: 5071.8453
A9: Livestock | H9: 651.25748 | I9: 661.30305 | J9: 668.35498 | K9: 670.05398 | L9: 673.42238 | M9: 676.54203 | N9: 678.53033 | O9: 684.10473 | P9: 689.29439 | Q9: 693.03527 | R9: 695.44502 | S9: 698.17106 | T9: 693.14899 | U9: 689.28531 | V9: 731.81651 | W9: 730.64191 | X9: 729.65303 | Y9: 733.51584 | Z9: 728.4371 | AA9: 731.53217 | AB9: 743.1344 | AC9: 749.52344 | AD9: 756.56446 | AE9: 759.74505 | AF9: 759.6708 | AG9: 765.08309 | AH9: 773.95909 | AI9: 793.79165 | AJ9: 802.21639 | AK9: 821.04978 | AL9: 836.02265 | AM9: 849.95021 | AN9: 867.88295 | AO9: 875.60982 | AP9: 894.96226 | AQ9: 906.56287 | AR9: 925.0041 | AS9: 942.9044 | AT9: 958.01291 | AU9: 979.44584 | AV9: 997.40606 | AW9: 1017.1696 | AX9: 1037.1697 | AY9: 1053.956 | AZ9: 1072.9143 | BA9: 1094.2988 | BB9: 1117.2587 | BC9: 1141.0169 | BD9: 1162.998 | BE9: 1184.4083 | BF9: 1208.8954 | BG9: 1236.7746 | BH9: 1265.043 | BI9: 1289.7119 | BJ9: 1324.3172 | BK9: 1337.6113 | BL9: 1363.5616 | BM9: 1393.1748 | BN9: 1420.6494 | BO9: 1450.6894 | BP9: 1479.1427 | BQ9: 1512.8058 | BR9: 1550.046 | BS9: 1578.7005 | BT9: 1616.3423 | BU9: 1652.1881 | BV9: 1651.7377
A10: Agriculture Support Services | H10: 3.458254 | I10: 3.5872757 | J10: 3.8063551 | K10: 3.8088649 | L10: 3.8443027 | M10: 3.8071824 | N10: 3.7534744 | O10: 3.5686132 | P10: 3.3079595 | Q10: 3.2083797 | R10: 3.2196759 | S10: 3.2767978 | T10: 3.4666229 | U10: 3.543893 | V10: 3.5748165 | W10: 3.5505585 | X10: 3.4238125 | Y10: 3.4462372 | Z10: 3.5428412 | AA10: 3.751852 | AB10: 4.0654065 | AC10: 4.1793674 | AD10: 4.2471311 | AE10: 4.2271004 | AF10: 4.0246167 | AG10: 3.9164621 | AH10: 3.9030523 | AI10: 3.9632534 | AJ10: 4.0849238 | AK10: 4.1195036 | AL10: 4.1046289 | AM10: 4.1826671 | AN10: 4.080421 | AO10: 4.0524008 | AP10: 4.0066184 | AQ10: 4.2514383 | AR10: 4.2560685 | AS10: 4.4280605 | AT10: 4.3047044 | AU10: 4.903745 | AV10: 4.9802162 | AW10: 5.4007219 | AX10: 4.1661829 | AY10: 4.2595187 | AZ10: 4.6143019 | BA10: 4.8909107 | BB10: 5.161198 | BC10: 5.0129288 | BD10: 4.9659581 | BE10: 4.9954512 | BF10: 5.2479787 | BG10: 5.1583725 | BH10: 5.1212278 | BI10: 5.2043512 | BJ10: 5.1874484 | BK10: 5.2169583 | BL10: 5.418092 | BM10: 5.5909201 | BN10: 5.5525524 | BO10: 5.6653951 | BP10: 5.6665599 | BQ10: 5.4307381 | BR10: 5.445814 | BS10: 6.6022628 | BT10: 5.0099065 | BU10: 5.4526283 | BV10: 6.0190996
A11: Forestry | H11: 669.17402 | I11: 615.35691 | J11: 725.72598 | K11: 807.03055 | L11: 793.26242 | M11: 775.75988 | N11: 794.1895 | O11: 757.26282 | P11: 1140.13 | Q11: 502.41784 | R11: 732.3354 | S11: 785.5689 | T11: 811.40242 | U11: 944.8895 | V11: 946.44984 | W11: 805.64972 | X11: 899.4812 | Y11: 954.49036 | Z11: 864.49325 | AA11: 908.34081 | AB11: 952.82886 | AC11: 863.3509 | AD11: 918.57771 | AE11: 948.14998 | AF11: 898.47987 | AG11: 852.93342 | AH11: 1169.7543 | AI11: 935.21617 | AJ11: 984.87035 | AK11: 981.16311 | AL11: 1007.0887 | AM11: 1019.6408 | AN11: 1020.7128 | AO11: 1005.019 | AP11: 1038.1886 | AQ11: 1066.2567 | AR11: 1064.0749 | AS11: 1065.3328 | AT11: 1057.8687 | AU11: 1093.8645 | AV11: 1111.03 | AW11: 1124.2163 | AX11: 1099.7801 | AY11: 1086.4959 | AZ11: 1085.2099 | BA11: 1172.5878 | BB11: 1153.8928 | BC11: 1142.0541 | BD11: 1137.0846 | BE11: 1144.4129 | BF11: 1213.7544 | BG11: 1205.0595 | BH11: 1179.378 | BI11: 1190.2229 | BJ11: 1249.6263 | BK11: 1229.7822 | BL11: 1237.5108 | BM11: 1220.9748 | BN11: 1182.4863 | BO11: 1358.4572 | BP11: 1278.5858 | BQ11: 1279.31 | BR11: 1278.7627 | BS11: 1327.4418 | BT11: 1398.3821 | BU11: 1381.0345 | BV11: 1222.1881
A12: Fishing | H12: 566.1753 | I12: 559.87965 | J12: 555.64295 | K12: 564.96698 | L12: 552.62572 | M12: 559.23804 | N12: 559.59676 | O12: 561.33467 | P12: 554.16682 | Q12: 554.80159 | R12: 580.95066 | S12: 571.45227 | T12: 584.25684 | U12: 590.16483 | V12: 579.58718 | W12: 427.57953 | X12: 566.89633 | Y12: 557.86426 | Z12: 554.72721 | AA12: 545.16966 | AB12: 552.24076 | AC12: 576.15987 | AD12: 546.52785 | AE12: 580.21503 | AF12: 593.61244 | AG12: 582.20881 | AH12: 599.93857 | AI12: 586.91866 | AJ12: 571.33924 | AK12: 571.61767 | AL12: 540.91479 | AM12: 496.69419 | AN12: 433.39921 | AO12: 395.61421 | AP12: 372.15539 | AQ12: 431.55871 | AR12: 490.09035 | AS12: 548.24949 | AT12: 614.82102 | AU12: 619.4806 | AV12: 618.09759 | AW12: 582.6405 | AX12: 547.12957 | AY12: 527.22734 | AZ12: 543.06968 | BA12: 563.33007 | BB12: 483.30383 | BC12: 477.03506 | BD12: 565.80479 | BE12: 497.14993 | BF12: 487.48307 | BG12: 514.71819 | BH12: 386.39304 | BI12: 587.7619 | BJ12: 659.67815 | BK12: 499.93754 | BL12: 448.49966 | BM12: 500.79486 | BN12: 554.05884 | BO12: 589.93913 | BP12: 467.32768 | BQ12: 581.75888 | BR12: 824.49501 | BS12: 607.5264 | BT12: 562.02632 | BU12: 637.08343 | BV12: 715.94347
A13: INDUSTRY | H13: 4827.2019 | I13: 4837.9511 | J13: 5045.4056 | K13: 5080.7289 | L13: 5229.2668 | M13: 5654.5394 | N13: 5352.2274 | O13: 5467.2134 | P13: 5473.1409 | Q13: 5450.86 | R13: 5705.4645 | S13: 5710.1066 | T13: 5726.984 | U13: 5683.649 | V13: 5688.4441 | W13: 5393.8722 | X13: 5672.9448 | Y13: 5639.6677 | Z13: 5982.8773 | AA13: 6234.6007 | AB13: 6197.9643 | AC13: 6294.5185 | AD13: 6463.6108 | AE13: 6717.3836 | AF13: 6859.1499 | AG13: 6774.5135 | AH13: 6234.723 | AI13: 6603.0191 | AJ13: 6810.0732 | AK13: 7061.3088 | AL13: 7254.6058 | AM13: 7145.5964 | AN13: 7163.8099 | AO13: 7221.6637 | AP13: 7504.2004 | AQ13: 7734.8304 | AR13: 7795.0484 | AS13: 7955.7257 | AT13: 8235.0954 | AU13: 8306.1266 | AV13: 8565.2873 | AW13: 8788.3075 | AX13: 8519.1181 | AY13: 7489.7614 | AZ13: 8331.28 | BA13: 8659.1468 | BB13: 8751.579 | BC13: 8758.2813 | BD13: 8306.2219 | BE13: 9394.8316 | BF13: 9294.8048 | BG13: 9341.6653 | BH13: 9255.5267 | BI13: 9203.2318 | BJ13: 9383.2862 | BK13: 9914.2813 | BL13: 10037.899 | BM13: 9663.0934 | BN13: 10040.641 | BO13: 10001.922 | BP13: 10540.582 | BQ13: 10422.667 | BR13: 10795.036 | BS13: 10752.744 | BT13: 11182.707 | BU13: 11713.264 | BV13: 11447.732
A14: Mining & quarrying | H14: 91.308043 | I14: 138.90811 | J14: 139.51889 | K14: 157.3128 | L14: 198.69682 | M14: 219.475 | N14: 170.27062 | O14: 113.04098 | P14: 92.93527 | Q14: 93.586667 | R14: 176.68682 | S14: 248.78738 | T14: 239.2539 | U14: 161.12354 | V14: 163.78259 | W14: 153.00742 | X14: 164.63567 | Y14: 120.22633 | Z14: 238.00721 | AA14: 207.81024 | AB14: 177.13132 | AC14: 216.37325 | AD14: 246.52964 | AE14: 250.54539 | AF14: 285.51679 | AG14: 281.90024 | AH14: 233.30234 | AI14: 222.93526 | AJ14: 279.59398 | AK14: 345.37619 | AL14: 338.28963 | AM14: 382.37404 | AN14: 309.03786 | AO14: 272.05236 | AP14: 310.86787 | AQ14: 390.69718 | AR14: 378.1464 | AS14: 313.78305 | AT14: 432.62458 | AU14: 379.09663 | AV14: 424.83812 | AW14: 529.38902 | AX14: 509.15039 | AY14: 312.28085 | AZ14: 594.00242 | BA14: 501.28894 | BB14: 422.07019 | BC14: 364.33897 | BD14: 249.29083 | BE14: 728.54994 | BF14: 642.14745 | BG14: 678.17167 | BH14: 452.93392 | BI14: 339.34337 | BJ14: 525.35146 | BK14: 1051.5305 | BL14: 858.28183 | BM14: 656.70257 | BN14: 581.91063 | BO14: 259.84656 | BP14: 759.8817 | BQ14: 709.86326 | BR14: 604.55722 | BS14: 377.64552 | BT14: 666.03865 | BU14: 906.24227 | BV14: 693.32289
A15: Manufacturing | H15: 3156.4575 | I15: 3156.6514 | J15: 3396.0412 | K15: 3420.0423 | L15: 3493.89 | M15: 3787.4651 | N15: 3340.3165 | O15: 3530.4011 | P15: 3624.9157 | Q15: 3634.9498 | R15: 3701.6916 | S15: 3575.6261 | T15: 3554.582 | U15: 3545.6698 | V15: 3518.6719 | W15: 3564.1428 | X15: 3439.2133 | Y15: 3485.5335 | Z15: 3678.5863 | AA15: 3892.0265 | AB15: 3914.026 | AC15: 3971.6393 | AD15: 4071.6862 | AE15: 4226.7593 | AF15: 4321.6762 | AG15: 4208.2348 | AH15: 3630.9619 | AI15: 4124.6688 | AJ15: 4065.5686 | AK15: 4165.1067 | AL15: 4380.2623 | AM15: 4252.5124 | AN15: 4278.4004 | AO15: 4335.8924 | AP15: 4464.8889 | AQ15: 4557.1442 | AR15: 4574.2961 | AS15: 4722.8603 | AT15: 4821.1652 | AU15: 4867.6986 | AV15: 5105.9868 | AW15: 5135.2683 | AX15: 4791.3177 | AY15: 4193.7812 | AZ15: 4901.9303 | BA15: 4859.8598 | BB15: 4922.4368 | BC15: 4964.6704 | BD15: 4581.0999 | BE15: 5210.6015 | BF15: 5317.8361 | BG15: 5293.5171 | BH15: 5269.7376 | BI15: 5313.5074 | BJ15: 5259.9398 | BK15: 5196.8965 | BL15: 5490.4047 | BM15: 5255.2844 | BN15: 5528.9115 | BO15: 5752.1072 | BP15: 5809.2342 | BQ15: 5684.5112 | BR15: 5827.3528 | BS15: 5942.2013 | BT15: 6073.0876 | BU15: 6209.068 | BV15: 6107.1018
A16: Electricity | H16: 210.09724 | I16: 211.96724 | J16: 218.0015 | K16: 226.35119 | L16: 232.30361 | M16: 239.22727 | N16: 240.27549 | O16: 239.33957 | P16: 235.40375 | Q16: 232.04045 | R16: 276.647 | S16: 276.74444 | T16: 281.79193 | U16: 288.00407 | V16: 273.4508 | W16: 279.6724 | X16: 280.67773 | Y16: 283.78719 | Z16: 283.45138 | AA16: 295.83973 | AB16: 302.01578 | AC16: 301.01526 | AD16: 303.31869 | AE16: 302.44612 | AF16: 308.92215 | AG16: 311.79822 | AH16: 313.38205 | AI16: 322.86065 | AJ16: 327.91498 | AK16: 340.55763 | AL16: 358.50832 | AM16: 352.86624 | AN16: 363.25028 | AO16: 366.34645 | AP16: 364.71642 | AQ16: 359.46671 | AR16: 363.54782 | AS16: 365.02813 | AT16: 372.04884 | AU16: 389.35399 | AV16: 408.67985 | AW16: 421.5971 | AX16: 435.15871 | AY16: 386.45771 | AZ16: 444.83565 | BA16: 459.06751 | BB16: 467.38043 | BC16: 473.30484 | BD16: 467.51348 | BE16: 473.98323 | BF16: 477.42361 | BG16: 483.42849 | BH16: 495.89613 | BI16: 511.91349 | BJ16: 520.12669 | BK16: 535.34558 | BL16: 554.57949 | BM16: 554.92391 | BN16: 565.65713 | BO16: 571.99004 | BP16: 589.7736 | BQ16: 613.90571 | BR16: 641.28925 | BS16: 668.89279 | BT16: 744.31133 | BU16: 680.69555 | BV16: 691.002
... A33: Activities of Households | H33: 184.38635 | I33: 186.23645 | J33: 187.86271 | K33: 189.19623 | L33: 190.28869 | M33: 191.27152 | N33: 192.20315 | O33: 193.05537 | P33: 193.86499 | Q33: 194.68072 | R33: 195.5394 | S33: 196.44486 | T33: 197.41247 | U33: 198.4816 | V33: 199.6697 | W33: 200.99742 | X33: 202.47136 | Y33: 204.89096 | Z33: 208.28762 | AA33: 199.94347 | AB33: 204.72613 | AC33: 208.61299 | AD33: 211.5876 | AE33: 213.63487 | AF33: 214.72469 | AG33: 215.94028 | AH33: 217.2918 | AI33: 218.78757 | AJ33: 220.43609 | AK33: 222.05519 | AL33: 223.64753 | AM33: 225.21189 | AN33: 226.7569 | AO33: 228.3159 | AP33: 229.88392 | AQ33: 231.46453 | AR33: 233.06941 | AS33: 234.68577 | AT33: 236.29344 | AU33: 237.90493 | AV33: 239.5413 | AW33: 241.1871 | AX33: 242.80279 | AY33: 244.41723 | AZ33: 246.06776 | BA33: 247.74361 | BB33: 249.44329 | BC33: 251.15482 | BD33: 252.87683 | BE33: 254.60923 | BF33: 256.32636 | BG33: 258.04108 | BH33: 259.77367 | BI33: 261.53159 | BJ33: 263.33315 | BK33: 265.15222 | BL33: 266.96014 | BM33: 268.77375 | BN33: 270.59934 | BO33: 272.43202 | BP33: 274.24732 | BQ33: 276.07735 | BR33: 277.99562 | BS33: 279.93921 | BT33: 281.81126 | BU33: 281.87483 | BV33: 285.65257
A35: ADJUSTMENTS
A36: Taxes on products | H36: 1157.5288 | I36: 1085.765 | J36: 1043.4713 | K36: 1101.1745 | L36: 1170.5976 | M36: 1250.9646 | N36: 1257.9697 | O36: 1230.0517 | P36: 1324.8941 | Q36: 1416.7483 | R36: 1467.3473 | S36: 1452.5626 | T36: 1433.5429 | U36: 1367.9814 | V36: 1421.8904 | W36: 1476.618 | X36: 1487.0784 | Y36: 1446.8034 | Z36: 1621.3135 | AA36: 1572.1188 | AB36: 1590.6884 | AC36: 1657.9254 | AD36: 1710.4486 | AE36: 1777.0318 | AF36: 1708.2415 | AG36: 1734.9093 | AH36: 1661.7743 | AI36: 1779.5609 | AJ36: 1883.3454 | AK36: 1804.9623 | AL36: 1969.2047 | AM36: 1978.5694 | AN36: 2011.4652 | AO36: 1988.817 | AP36: 1960.1566 | AQ36: 2012.8766 | AR36: 1994.9247 | AS36: 2050.9008 | AT36: 2153.4128 | AU36: 2121.679 | AV36: 2208.4692 | AW36: 2252.1386 | AX36: 2133.4244 | AY36: 1595.2892 | AZ36: 2124.4659 | BA36: 2157.3696 | BB36: 2054.5485 | BC36: 2366.9671 | BD36: 2068.4292 | BE36: 2358.206 | BF36: 2497.8923 | BG36: 2435.561 | BH36: 2412.4606 | BI36: 2502.2327 | BJ36: 2599.5892 | BK36: 2710.1798 | BL36: 2728.5676 | BM36: 2693.9058 | BN36: 2779.159 | BO36: 2814.7584 | BP36: 3003.6741 | BQ36: 2955.3878 | BR36: 2933.2265 | BS36: 3037.9213 | BT36: 3096.8718 | BU36: 3168.0954 | BV36: 3347.8984
A37: Source: Uganda Bureau of Statistics

Sheet Deseason_Growth
A1: Table 7: SEASONALLY ADJUSTED Value Added at constant 2016/17 prices,PERCENTAGE CHANGE, 2016/17-2025/26
B2: 2008Q1 | C2: 2008Q2 | D2: 2008Q3 | E2: 2008Q4 | F2: 2009Q1 | G2: 2009Q2 | H2: 2009Q3 | I2: 2009Q4 | J2: 2010Q1 | K2: 2010Q2 | L2: 2010Q3 | M2: 2010Q4 | N2: 2011Q1 | O2: 2011Q2 | P2: 2011Q3 | Q2: 2011Q4 | R2: 2012Q1 | S2: 2012Q2 | T2: 2012Q3 | U2: 2012Q4 | V2: 2013Q1 | W2: 2013Q2 | X2: 2013Q3 | Y2: 2013Q4 | Z2: 2014Q1 | AA2: 2014Q2 | AB2: 2014Q3 | AC2: 2014Q4 | AD2: 2015Q1 | AE2: 2015Q2 | AF2: 2015Q3
B3: 2007/08 | D3: 2008/09 | H3: 2009/10 | N3: 2010/11 | P3: 2011/12 | T3: 2012/13 | X3: 2013/14 | Y3: 2013/14 | AA3: 2013/14 | AB3: 2014/15 | AC3: 2014/15 | AF3: 2015/16 | AJ3: 2016/17 | AN3: 2017/18 | AR3: 2018/19 | AV3: 2019/20 | AZ3: 2020/21 | BD3: 2021/22 | BH3: 2022/23 | BL3: 2023/24 | BP3: 2024/25 | BT3: 2025/26
B4: Q3 | C4: Q4 | D4: Q1 | E4: Q2 | F4: Q3 | G4: Q4 | H4: Q1 | I4: Q2 | J4: Q3 | K4: Q4 | L4: Q1 | M4: Q2 | N4: Q3 | O4: Q4 | P4: Q1 | Q4: Q2 | R4: Q3 | S4: Q4 | T4: Q1 | U4: Q2 | V4: Q3 | W4: Q4 | X4: Q1 | Y4: Q2 | Z4: Q3 | AA4: Q4 | AB4: Q1 | AC4: Q2 | AD4: Q3 | AE4: Q4 | AF4: Q1 | AG4: Q2 | AH4: Q3 | AI4: Q4 | AJ4: Q1 | AK4: Q2 | AL4: Q3 | AM4: Q4 | AN4: Q1 | AO4: Q2 | AP4: Q3 | AQ4: Q4 | AR4: Q1 | AS4: Q2 | AT4: Q3 | AU4: Q4 | AV4: Q1 | AW4: Q2 | AX4: Q3 | AY4: Q4 | AZ4: Q1 | BA4: Q2 | BB4: Q3 | BC4: Q4 | BD4: Q1 | BE4: Q2 | BF4: Q3 | BG4: Q4 | BH4: Q1 | BI4: Q2 | BJ4: Q3 | BK4: Q4 | BL4: Q1 | BM4: Q2 | BN4: Q3 | BO4: Q4 | BP4: Q1 | BQ4: Q2 | BR4: Q3 | BS4: Q4 | BT4: Q1 | BU4: Q2 | BV4: Q3
A5: GDP AT MARKET PRICES | E5: #DIV/0! | F5: #DIV/0! | G5: #DIV/0! | H5: #DIV/0! | I5: 1.3243858 | J5: 5.8038312 | K5: 2.0222336 | L5: 1.2038283 | M5: 2.5972695 | N5: 2.2531977 | O5: -3.1590458 | P5: 3.7070942 | Q5: -2.5602057 | R5: 2.7670824 | S5: 0.99414176 | T5: 4.087245 | U5: -4.3863552 | V5: 0.095047173 | W5: -1.7100512 | X5: 4.2222874 | Y5: -1.8304732 | Z5: 5.9716097 | AA5: 4.4142547 | AB5: -3.5091846 | AC5: 4.1129018 | AD5: 0.97561912 | AE5: 2.4537186 | AF5: 1.4620019 | AG5: 0.5494736 | AH5: -3.2220419 | AI5: 1.2841621 | AJ5: 0.83239308 | AK5: 1.4978379 | AL5: 3.0208624 | AM5: 0.96962078 | AN5: 1.4096175 | AO5: 0.95852186 | AP5: 2.3642921 | AQ5: 0.73929905 | AR5: 1.6833459 | AS5: 0.67788171 | AT5: 4.7183604 | AU5: -0.51606042 | AV5: 2.7835341 | AW5: 1.233933 | AX5: -2.2194993 | AY5: -7.1197978 | AZ5: 7.4621281 | BA5: 2.4351986 | BB5: 0.77831284 | BC5: 1.1699338 | BD5: -1.9991802 | BE5: 4.9359917 | BF5: 2.2192565 | BG5: 0.3823237 | BH5: 0.97334385 | BI5: 0.94972824 | BJ5: -0.021375292 | BK5: 3.2791842 | BL5: 1.2991837 | BM5: 1.3643908 | BN5: 1.0354276 | BO5: 1.6374267 | BP5: 2.1458546 | BQ5: 0.51845912 | BR5: 3.7173548 | BS5: -0.92665304 | BT5: 1.954561 | BU5: 3.5624392 | BV5: 1.2140564
A6: AGRICULTURE,FORESTRY&FISHING | C6: #DIV/0! | D6: #DIV/0! | E6: #DIV/0! | F6: #DIV/0! | G6: #DIV/0! | H6: #DIV/0! | I6: -0.73574461 | J6: 0.89604237 | K6: 5.7424551 | L6: -4.326451 | M6: 0.76122511 | N6: 5.764064 | O6: -0.26154903 | P6: 5.0213261 | Q6: -9.2174101 | R6: -2.5897083 | S6: 1.5266548 | T6: 11.848879 | U6: -10.489025 | V6: 1.4563684 | W6: -6.3101413 | X6: 18.314298 | Y6: -10.655078 | Z6: 1.9442937 | AA6: 3.6753608 | AB6: 1.1823483 | AC6: 3.553653 | AD6: -2.9863239 | AE6: 2.5526819 | AF6: -0.65468886 | AG6: 1.5325457 | AH6: 5.0033258 | AI6: -4.4485212 | AJ6: -0.95375315 | AK6: 4.1201765 | AL6: 3.4182772 | AM6: -0.56587876 | AN6: 1.1995622 | AO6: -1.3729598 | AP6: 5.4232797 | AQ6: -3.3166197 | AR6: 1.7833388 | AS6: 0.0066075237 | AT6: 11.108185 | AU6: -4.5510055 | AV6: -0.11039391 | AW6: 1.5116347 | AX6: 2.229128 | AY6: 1.9301113 | AZ6: -0.39245801 | BA6: 3.3397942 | BB6: -3.7522327 | BC6: 1.5779749 | BD6: 3.5159819 | BE6: -3.5118845 | BF6: 5.2949332 | BG6: 5.1913246 | BH6: -3.6972832 | BI6: 4.5513684 | BJ6: -1.5212018 | BK6: -1.5060182 | BL6: 4.0680935 | BM6: 0.80245658 | BN6: 2.1328688 | BO6: 3.2118319 | BP6: 0.53171097 | BQ6: 1.1977514 | BR6: 3.8204911 | BS6: -2.0111679 | BT6: 1.4461358 | BU6: 5.158682 | BV6: -1.3401906
A7: Cash crops | C7: #DIV/0! | D7: #DIV/0! | E7: #DIV/0! | F7: #DIV/0! | G7: #DIV/0! | H7: #DIV/0! | I7: -2.2131688 | J7: -24.368246 | K7: 56.585114 | L7: -21.553389 | M7: -0.6220751 | N7: 17.42557 | O7: -4.9959192 | P7: 12.104515 | Q7: -5.3174366 | R7: -7.8554784 | S7: 7.0190128 | T7: -4.5798348 | U7: 2.8478837 | V7: 6.7769997 | W7: -1.3042878 | X7: -0.39266241 | Y7: 2.8230586 | Z7: -10.71833 | AA7: 2.1821287 | AB7: 2.7742474 | AC7: -2.625638 | AD7: 12.015622 | AE7: 3.2472373 | AF7: 3.6099614 | AG7: -5.1244802 | AH7: 0.49657437 | AI7: 1.8070079 | AJ7: -14.184758 | AK7: 41.232385 | AL7: -7.9043074 | AM7: 5.4038969 | AN7: 2.84436 | AO7: -5.4738493 | AP7: -0.90396809 | AQ7: -0.17773491 | AR7: 6.8693752 | AS7: -0.40725211 | AT7: -4.3590301 | AU7: 10.449184 | AV7: -2.5513443 | AW7: 5.7039666 | AX7: 4.3202486 | AY7: -4.6935775 | AZ7: 1.3923078 | BA7: 11.620628 | BB7: 3.9032796 | BC7: 0.83989083 | BD7: 3.7456493 | BE7: -1.9709545 | BF7: -7.8350229 | BG7: 9.1750242 | BH7: -0.24291063 | BI7: -4.3763972 | BJ7: 3.4553032 | BK7: 2.1736485 | BL7: 4.3799916 | BM7: 6.0294121 | BN7: 4.1402069 | BO7: -5.5957312 | BP7: 12.143813 | BQ7: -0.084128531 | BR7: 3.7360729 | BS7: -6.5709921 | BT7: 10.856102 | BU7: 4.9303843 | BV7: -0.37827649
A8: Food crops | C8: #DIV/0! | D8: #DIV/0! | E8: #DIV/0! | F8: #DIV/0! | G8: #DIV/0! | H8: #DIV/0! | I8: 0.69259714 | J8: 1.7232202 | K8: 0.39725219 | L8: -3.2732723 | M8: 1.7361334 | N8: 7.1766114 | O8: 1.2364593 | P8: -4.4388378 | Q8: 3.0843396 | R8: -11.001243 | S8: 0.069482411 | T8: 21.967702 | U8: -22.310314 | V8: 0.43370814 | W8: -1.853808 | X8: 26.708386 | Y8: -20.964151 | Z8: 9.6905804 | AA8: 5.3037139 | AB8: -0.26213134 | AC8: 8.9856319 | AD8: -8.050629 | AE8: 2.1242678 | AF8: -0.75792468 | AG8: 5.4850107 | AH8: -1.1398302 | AI8: -2.1014168 | AJ8: -0.56021264 | AK8: 0.89047718 | AL8: 8.0448017 | AM8: -1.5526259 | AN8: 2.9635742 | AO8: -0.17617354 | AP8: 9.2504384 | AQ8: -8.3447354 | AR8: -0.045275196 | AS8: -2.0682827 | AT8: 20.211161 | AU8: -11.277953 | AV8: -0.6067333 | AW8: 1.8581796 | AX8: 4.4963414 | AY8: 4.9918138 | AZ8: -1.7867035 | BA8: 0.81642241 | BB8: -6.109611 | BC8: 2.7333182 | BD8: 3.2492973 | BE8: -5.3506448 | BF8: 10.098134 | BG8: 6.8568305 | BH8: -4.0422329 | BI8: 3.9736438 | BJ8: -7.1538592 | BK8: 0.47508611 | BL8: 7.3529794 | BM8: -1.2143493 | BN8: 2.2122011 | BO8: 2.2238931 | BP8: 2.1030701 | BQ8: -0.78309027 | BR8: 0.68998054 | BS8: 0.46165376 | BT8: -0.92667516 | BU8: 7.1153851 | BV8: -0.98394116
A9: Livestock | C9: #DIV/0! | D9: #DIV/0! | E9: #DIV/0! | F9: #DIV/0! | G9: #DIV/0! | H9: #DIV/0! | I9: 1.5424881 | J9: 1.0663697 | K9: 0.25420629 | L9: 0.50270551 | M9: 0.46325262 | N9: 0.29389166 | O9: 0.82154069 | P9: 0.75860583 | Q9: 0.54271162 | R9: 0.34770906 | S9: 0.39198511 | T9: -0.71931715 | U9: -0.55741001 | V9: 6.1703331 | W9: -0.16050471 | X9: -0.13534472 | Y9: 0.52940429 | Z9: -0.69238336 | AA9: 0.4248916 | AB9: 1.5860185 | AC9: 0.85974169 | AD9: 0.93939952 | AE9: 0.42039862 | AF9: -0.0097730117 | AG9: 0.71245234 | AH9: 1.1601361 | AI9: 2.562481 | AJ9: 1.0613293 | AK9: 2.3476691 | AL9: 1.8236257 | AM9: 1.6659304 | AN9: 2.1098584 | AO9: 0.89031241 | AP9: 2.2101671 | AQ9: 1.2962114 | AR9: 2.0341927 | AS9: 1.9351591 | AT9: 1.6023373 | AU9: 2.2372272 | AV9: 1.8337122 | AW9: 1.9814959 | AX9: 1.9662441 | AY9: 1.6184803 | AZ9: 1.7987748 | BA9: 1.9931195 | BB9: 2.0981395 | BC9: 2.1264715 | BD9: 1.9264502 | BE9: 1.840959 | BF9: 2.0674488 | BG9: 2.3061764 | BH9: 2.285653 | BI9: 1.9500463 | BJ9: 2.683177 | BK9: 1.003847 | BL9: 1.9400468 | BM9: 2.1717508 | BN9: 1.9720867 | BO9: 2.1145283 | BP9: 1.9613604 | BQ9: 2.2758571 | BR9: 2.4616633 | BS9: 1.848624 | BT9: 2.3843483 | BU9: 2.2177126 | BV9: -0.027257772
A10: Agriculture Support Services | C10: #DIV/0! | D10: #DIV/0! | E10: #DIV/0! | F10: #DIV/0! | G10: #DIV/0! | H10: #DIV/0! | I10: 3.7308332 | J10: 6.1071255 | K10: 0.06593823 | L10: 0.93040231 | M10: -0.96559212 | N10: -1.4107034 | O10: -4.925069 | P10: -7.3040595 | Q10: -3.0103089 | R10: 0.35208397 | S10: 1.7741492 | T10: 5.7930053 | U10: 2.228975 | V10: 0.8725837 | W10: -0.67857882 | X10: -3.5697489 | Y10: 0.65496314 | Z10: 2.8031743 | AA10: 5.8995244 | AB10: 8.3573254 | AC10: 2.8031853 | AD10: 1.6213878 | AE10: -0.47162915 | AF10: -4.7901321 | AG10: -2.6873278 | AH10: -0.34239431 | AI10: 1.54241 | AJ10: 3.0699637 | AK10: 0.84652162 | AL10: -0.36107938 | AM10: 1.9012232 | AN10: -2.4445179 | AO10: -0.68669884 | AP10: -1.1297612 | AQ10: 6.1103874 | AR10: 0.10890951 | AS10: 4.0411009 | AT10: -2.7857823 | AU10: 13.915952 | AV10: 1.5594453 | AW10: 8.4435221 | AX10: -22.858777 | AY10: 2.240319 | AZ10: 8.3291857 | BA10: 5.9945982 | BB10: 5.5263176 | BC10: -2.8727677 | BD10: -0.9369916 | BE10: 0.59390745 | BF10: 5.0551474 | BG10: -1.7074415 | BH10: -0.72008516 | BI10: 1.6231149 | BJ10: -0.32478364 | BK10: 0.56887233 | BL10: 3.8553814 | BM10: 3.1898346 | BN10: -0.68625163 | BO10: 2.0322674 | BP10: 0.020561023 | BQ10: -4.1616408 | BR10: 0.27760397 | BS10: 21.235554 | BT10: -24.118341 | BU10: 8.8369275 | BV10: 10.388958
A11: Forestry | C11: #DIV/0! | D11: #DIV/0! | E11: #DIV/0! | F11: #DIV/0! | G11: #DIV/0! | H11: #DIV/0! | I11: -8.0423188 | J11: 17.935781 | K11: 11.203206 | L11: -1.7060239 | M11: -2.2063992 | N11: 2.3756862 | O11: -4.6496066 | P11: 50.559358 | Q11: -55.933286 | R11: 45.762221 | S11: 7.2690047 | T11: 3.2885113 | U11: 16.451402 | V11: 0.16513456 | W11: -14.87666 | X11: 11.646685 | Y11: 6.1156544 | Z11: -9.4288128 | AA11: 5.0720534 | AB11: 4.8977267 | AC11: -9.3907687 | AD11: 6.3967976 | AE11: 3.2193534 | AF11: -5.2386337 | AG11: -5.0692788 | AH11: 37.14485 | AI11: -20.050202 | AJ11: 5.3093799 | AK11: -0.3764199 | AL11: 2.6423288 | AM11: 1.246376 | AN11: 0.10513613 | AO11: -1.5375342 | AP11: 3.3003979 | AQ11: 2.7035643 | AR11: -0.20462469 | AS11: 0.11821608 | AT11: -0.70063121 | AU11: 3.4026691 | AV11: 1.5692513 | AW11: 1.1868524 | AX11: -2.1736163 | AY11: -1.2078988 | AZ11: -0.11835861 | BA11: 8.0517065 | BB11: -1.5943442 | BC11: -1.0259754 | BD11: -0.43514058 | BE11: 0.64448896 | BF11: 6.0591249 | BG11: -0.71636313 | BH11: -2.1311351 | BI11: 0.91953992 | BJ11: 4.9909501 | BK11: -1.5880048 | BL11: 0.62845352 | BM11: -1.3362288 | BN11: -3.1522773 | BO11: 14.881431 | BP11: -5.8795637 | BQ11: 0.056642036 | BR11: -0.042782793 | BS11: 3.8067353 | BT11: 5.3441374 | BU11: -1.240552 | BV11: -11.501986
A12: Fishing | C12: #DIV/0! | D12: #DIV/0! | E12: #DIV/0! | F12: #DIV/0! | G12: #DIV/0! | H12: #DIV/0! | I12: -1.1119607 | J12: -0.75671602 | K12: 1.6780611 | L12: -2.184422 | M12: 1.1965292 | N12: 0.064144123 | O12: 0.31056391 | P12: -1.2769292 | Q12: 0.11454435 | R12: 4.7132288 | S12: -1.6349727 | T12: 2.240706 | U12: 1.0111983 | V12: -1.7923224 | W12: -26.226881 | X12: 32.582662 | Y12: -1.5932497 | Z12: -0.5623319 | AA12: -1.7229268 | AB12: 1.2970454 | AC12: 4.3312834 | AD12: -5.1430212 | AE12: 6.1638535 | AF12: 2.3090432 | AG12: -1.9210559 | AH12: 3.0452564 | AI12: -2.1702067 | AJ12: -2.6544423 | AK12: 0.048733129 | AL12: -5.3712265 | AM12: -8.1751506 | AN12: -12.743251 | AO12: -8.7182888 | AP12: -5.9297214 | AQ12: 15.961966 | AR12: 13.562846 | AS12: 11.867024 | AT12: 12.142561 | AU12: 0.75787681 | AV12: -0.22325415 | AW12: -5.7364868 | AX12: -6.094827 | AY12: -3.637572 | AZ12: 3.0048412 | BA12: 3.7307152 | BB12: -14.205924 | BC12: -1.2970646 | BD12: 18.608637 | BE12: -12.134019 | BF12: -1.9444559 | BG12: 5.586885 | BH12: -24.931146 | BI12: 52.115032 | BJ12: 12.23561 | BK12: -24.214932 | BL12: -10.288862 | BM12: 11.660033 | BN12: 10.635886 | BO12: 6.4758995 | BP12: -20.783746 | BQ12: 24.486288 | BR12: 41.724525 | BS12: -26.315333 | BT12: -7.4893994 | BU12: 13.354732 | BV12: 12.378291
A13: INDUSTRY | C13: #DIV/0! | D13: #DIV/0! | E13: #DIV/0! | F13: #DIV/0! | G13: #DIV/0! | H13: #DIV/0! | I13: 0.22267979 | J13: 4.2880642 | K13: 0.70010748 | L13: 2.9235553 | M13: 8.1325471 | N13: -5.3463594 | O13: 2.1483782 | P13: 0.10841875 | Q13: -0.40709601 | R13: 4.6709058 | S13: 0.081361935 | T13: 0.2955701 | U13: -0.75668137 | V13: 0.084367622 | W13: -5.1784273 | X13: 5.1738829 | Y13: -0.58659302 | Z13: 6.0856356 | AA13: 4.2073961 | AB13: -0.58762935 | AC13: 1.5578362 | AD13: 2.686343 | AE13: 3.9261773 | AF13: 2.1104392 | AG13: -1.2339204 | AH13: -7.9679594 | AI13: 5.907176 | AJ13: 3.1357491 | AK13: 3.6891767 | AL13: 2.7374102 | AM13: -1.5026234 | AN13: 0.25489153 | AO13: 0.80758429 | AP13: 3.9123497 | AQ13: 3.0733444 | AR13: 0.77853025 | AS13: 2.0612748 | AT13: 3.5115546 | AU13: 0.86254315 | AV13: 3.1201146 | AW13: 2.6037675 | AX13: -3.0630401 | AY13: -12.082902 | AZ13: 11.235586 | BA13: 3.9353722 | BB13: 1.0674508 | BC13: 0.076583894 | BD13: -5.1615079 | BE13: 13.105955 | BF13: -1.0647003 | BG13: 0.50415779 | BH13: -0.92209023 | BI13: -0.56501245 | BJ13: 1.9564256 | BK13: 5.6589466 | BL13: 1.2468676 | BM13: -3.7339074 | BN13: 3.9071072 | BO13: -0.38562384 | BP13: 5.3855654 | BQ13: -1.118672 | BR13: 3.5726787 | BS13: -0.39176552 | BT13: 3.9986269 | BU13: 4.7444492 | BV13: -2.266936
A14: Mining & quarrying | C14: #DIV/0! | D14: #DIV/0! | E14: #DIV/0! | F14: #DIV/0! | G14: #DIV/0! | H14: #DIV/0! | I14: 52.131297 | J14: 0.43970272 | K14: 12.753765 | L14: 26.306834 | M14: 10.457226 | N14: -22.419128 | O14: -33.61099 | P14: -17.786213 | Q14: 0.70091469 | R14: 88.794867 | S14: 40.806981 | T14: -3.8319782 | U14: -32.655836 | V14: 1.650319 | W14: -6.5789503 | X14: 7.5997978 | Y14: -26.974311 | Z14: 97.965953 | AA14: -12.687419 | AB14: -14.762947 | AC14: 22.154143 | AD14: 13.93721 | AE14: 1.6289095 | AF14: 13.958109 | AG14: -1.2666681 | AH14: -17.239397 | AI14: -4.4436251 | AJ14: 25.41488 | AK14: 23.527763 | AL14: -2.0518389 | AM14: 13.031558 | AN14: -19.179173 | AO14: -11.967951 | AP14: 14.267663 | AQ14: 25.679498 | AR14: -3.2124056 | AS14: -17.020749 | AT14: 37.873788 | AU14: -12.37284 | AV14: 12.065917 | AW14: 24.609586 | AX14: -3.8230163 | AY14: -38.666285 | AZ14: 90.214166 | BA14: -15.608265 | BB14: -15.803013 | BC14: -13.678108 | BD14: -31.577226 | BE14: 192.24899 | BF14: -11.859515 | BG14: 5.6099609 | BH14: -33.212498 | BI14: -25.078834 | BJ14: 54.814121 | BK14: 100.15753 | BL14: -18.377847 | BM14: -23.486372 | BN14: -11.389013 | BO14: -55.345967 | BP14: 192.43477 | BQ14: -6.5823977 | BR14: -14.834694 | BS14: -37.533535 | BT14: 76.366092 | BU14: 36.064517 | BV14: -23.494753
A15: Manufacturing | C15: #DIV/0! | D15: #DIV/0! | E15: #DIV/0! | F15: #DIV/0! | G15: #DIV/0! | H15: #DIV/0! | I15: 0.006145154 | J15: 7.5836617 | K15: 0.70673668 | L15: 2.1592647 | M15: 8.4025267 | N15: -11.806013 | O15: 5.6906183 | P15: 2.6771642 | Q15: 0.27680656 | R15: 1.836114 | S15: -3.4056172 | T15: -0.5885441 | U15: -0.25072353 | V15: -0.7614349 | W15: 1.2922758 | X15: -3.5051754 | Y15: 1.3468254 | Z15: 5.5386854 | AA15: 5.8022347 | AB15: 0.56524451 | AC15: 1.4719714 | AD15: 2.5190343 | AE15: 3.8085705 | AF15: 2.2456197 | AG15: -2.62494 | AH15: -13.717696 | AI15: 13.597137 | AJ15: -1.4328467 | AK15: 2.4483193 | AL15: 5.1656679 | AM15: -2.9164909 | AN15: 0.6087703 | AO15: 1.3437736 | AP15: 2.9750846 | AQ15: 2.0662406 | AR15: 0.37637197 | AS15: 3.2478059 | AT15: 2.0814699 | AU15: 0.9651888 | AV15: 4.8952946 | AW15: 0.57347377 | AX15: -6.6978109 | AY15: -12.471235 | AZ15: 16.885695 | BA15: -0.85824343 | BB15: 1.2876298 | BC15: 0.85798108 | BD15: -7.7259996 | BE15: 13.741276 | BF15: 2.0580079 | BG15: -0.4573103 | BH15: -0.44921868 | BI15: 0.83058806 | BJ15: -1.0081402 | BK15: -1.1985568 | BL15: 5.6477593 | BM15: -4.2823842 | BN15: 5.2067022 | BO15: 4.0368831 | BP15: 0.99314982 | BQ15: -2.1469782 | BR15: 2.5128216 | BS15: 1.970851 | BT15: 2.2026578 | BU15: 2.2390649 | BV15: -1.6422135
A16: Electricity | C16: #DIV/0! | D16: #DIV/0! | E16: #DIV/0! | F16: #DIV/0! | G16: #DIV/0! | H16: #DIV/0! | I16: 0.89006597 | J16: 2.8467863 | K16: 3.8301093 | L16: 2.6297253 | M16: 2.9804371 | N16: 0.43816816 | O16: -0.38952095 | P16: -1.6444476 | Q16: -1.4287359 | R16: 19.223609 | S16: 0.0352189 | T16: 1.823883 | U16: 2.2045134 | V16: -5.053148 | W16: 2.2752183 | X16: 0.35946508 | Y16: 1.1078419 | Z16: -0.11833362 | AA16: 4.3705378 | AB16: 2.0876354 | AC16: -0.33127949 | AD16: 0.76521736 | AE16: -0.28767357 | AF16: 2.1412176 | AG16: 0.93100318 | AH16: 0.50796609 | AI16: 3.0246134 | AJ16: 1.5654851 | AK16: 3.8554638 | AL16: 5.2709704 | AM16: -1.5737645 | AN16: 2.9427684 | AO16: 0.85235285 | AP16: -0.44494311 | AQ16: -1.4393956 | AR16: 1.1353257 | AS16: 0.4071836 | AT16: 1.9233329 | AU16: 4.6513132 | AV16: 4.9635693 | AW16: 3.1607251 | AX16: 3.2167243 | AY16: -11.19155 | AZ16: 15.105908 | BA16: 3.199351 | BB16: 1.8108267 | BC16: 1.2675791 | BD16: -1.2236015 | BE16: 1.3838655 | BF16: 0.72584332 | BG16: 1.2577671 | BH16: 2.5790048 | BI16: 3.2299823 | BJ16: 1.6044118 | BK16: 2.9259968 | BL16: 3.5928032 | BM16: 0.062104796 | BN16: 1.9341782 | BO16: 1.1195669 | BP16: 3.1090676 | BQ16: 4.0917585 | BR16: 4.4605451 | BS16: 4.3043818 | BT16: 11.275132 | BU16: -8.5469322 | BV16: 1.5141054
A17: Water | C17: #DIV/0! | D17: #DIV/0! | E17: #DIV/0! | F17: #DIV/0! | G17: #DIV/0! | H17: #DIV/0! | I17: 1.5067917 | J17: 1.5536805 | K17: 1.9002982 | L17: 0.92054136 | M17: 1.6575147 | N17: 1.5140113 | O17: 1.8956066 | P17: 1.2523166 | Q17: 1.3456254 | R17: 1.4527028 | S17: 1.6987427 | T17: 2.3957689 | U17: 0.35860487 | V17: 1.64255 | W17: 1.3112678 | X17: 2.0079753 | Y17: 1.5379016 | Z17: 1.5095367 | AA17: 1.5202016 | AB17: 1.1957028 | AC17: 1.5762158 | AD17: 1.9041494 | AE17: 1.4037577 | AF17: 1.6806669 | AG17: 1.274464 | AH17: 1.7001503 | AI17: 1.0744828 | AJ17: 1.4976333 | AK17: 1.5453328 | AL17: 1.0425819 | AM17: 1.2789156 | AN17: 0.61833994 | AO17: 0.97497533 | AP17: 0.93257932 | AQ17: 1.1431275 | AR17: 1.3230359 | AS17: 1.2605434 | AT17: 1.0540861 | AU17: 1.1376796 | AV17: 0.77569284 | AW17: 0.89177011 | AX17: 1.3632389 | AY17: 0.86751216 | AZ17: 1.2892233 | BA17: 1.2338704 | BB17: 1.1256787 | BC17: 1.3910144 | BD17: 1.9993346 | BE17: 1.7160831 | BF17: 1.3356547 | BG17: 1.0742688 | BH17: 0.48569452 | BI17: 0.96761974 | BJ17: 1.3457749 | BK17: 1.3414323 | BL17: 1.5274644 | BM17: 1.0862784 | BN17: 1.1337338 | BO17: 1.4908643 | BP17: -0.27446739 | BQ17: 0.74237612 | BR17: 0.41899374 | BS17: 0.64096862 | BT17: 0.98059758 | BU17: 1.2592055 | BV17: 1.291143
... A33: Activities of Households | C33: #DIV/0! | D33: #DIV/0! | E33: #DIV/0! | F33: #DIV/0! | G33: #DIV/0! | H33: #DIV/0! | I33: 1.0033807 | J33: 0.87322243 | K33: 0.70983984 | L33: 0.57742398 | M33: 0.51649108 | N33: 0.48707489 | O33: 0.44339373 | P33: 0.4193696 | Q33: 0.42077297 | R33: 0.44107297 | S33: 0.46305695 | T33: 0.4925617 | U33: 0.54157068 | V33: 0.59859642 | W33: 0.66495399 | X33: 0.73331309 | Y33: 1.1950375 | Z33: 1.6577884 | AA33: -4.0060719 | AB33: 2.3920033 | AC33: 1.8985655 | AD33: 1.4259005 | AE33: 0.96757397 | AF33: 0.51013502 | AG33: 0.56611586 | AH33: 0.62587436 | AI33: 0.68837232 | AJ33: 0.75347741 | AK33: 0.73449972 | AL33: 0.71709349 | AM33: 0.69947546 | AN33: 0.68602446 | AO33: 0.68751858 | AP33: 0.68677825 | AQ33: 0.68756619 | AR33: 0.693362 | AS33: 0.69351051 | AT33: 0.68502717 | AU33: 0.6819874 | AV33: 0.68782738 | AW33: 0.68705993 | AX33: 0.66989351 | AY33: 0.66491834 | AZ33: 0.67529148 | BA33: 0.68105303 | BB33: 0.68606276 | BC33: 0.68614036 | BD33: 0.68563518 | BE33: 0.68507774 | BF33: 0.67441614 | BG33: 0.66896273 | BH33: 0.67143897 | BI33: 0.67671106 | BJ33: 0.6888493 | BK33: 0.690789 | BL33: 0.68184083 | BM33: 0.67935506 | BN33: 0.67923175 | BO33: 0.67726513 | BP33: 0.66633129 | BQ33: 0.6672928 | BR33: 0.69483024 | BS33: 0.69914394 | BT33: 0.66873424 | BU33: 0.022558681 | BV33: 1.340217
A35: ADJUSTMENT
